Workbook

Sheet Read me
A1: Policy gaps — Transport & Industry
A2: The transport- and industry-tagged findings of the 2024 ESABCC progress report, re-assessed against the legislation adopted since; plus candidate additional gaps and the per-subsector gap landscape.
A3: Background document for the Summer Prep · Policy Gap 2.0 Report module (Note 3) · prepared 27 July 2026. Re-assessment vintage: Provisional read, mid-2026.
A5: What is in this workbook
A6: Re-assessed gaps | B6: The 10 transport/industry gaps the report tagged, each with its verbatim report quote and page, its assigned subsector, and a provisional mid-2026 read of whether it still exists — with the sources behind that read.
A7: Candidate gaps | B7: 10 issues that look like policy, ambition or implementation gaps but are not (yet) tagged as such in the report. Each carries the test that would confirm or refute it. These are proposals for the sector lead, not findings.
A8: Gap landscape | B8: Gaps per sector and subsector — report gaps by live status, and candidates — with the landscape figure. Counts are COUNTIFS formulas over the “Landscape data” sheet.
A9: Landscape data | B9: The same gaps in long format, one row per gap × subsector. A gap that bears on two subsectors appears once per subsector, so no subsector row is silently empty. This is the sheet the landscape counts read from.
A10: Legend | B10: Gap types, live statuses and the subsector taxonomy.
A12: How to read it — and what it is not
A13: • The base facts are the Board's: that the report tagged the gap, its verbatim quote, and its page. Those columns are unchanged from the report and should not be edited.
A14: • The re-assessment status and note, the candidate gaps, and the assignment of each gap to a subsector are AI-compiled working material for this prep cycle and are PENDING VERIFICATION. Nothing here is a Board position — it is a prompt for the sector lead's own judgement.
A15: • Where a re-assessment leans on something that happened after the report, the source URLs are in the “Sources” column. Check those first when you take a row forward.
A16: • Candidate gaps are deliberately falsifiable: each has a “Test to confirm / refute”. Work the test, then accept the candidate into the tracker or drop it — and record which.
A17: • The live version is in the Method Hub (Summer Prep › Policy Gap 2.0 Report › Policy Gaps — Transport & Industry).
A19: Source
A20: Report | B20: European Scientific Advisory Board on Climate Change (2024) “Towards EU climate neutrality: Progress, policy gaps and opportunities”, January 2024.
A21: Report URL | B21: https://climate-advisory-board.europa.eu/reports-and-publications/towards-eu-climate-neutrality-progress-policy-gaps-and-opportunities
A22: Data source | B22: src/data/summer-prep-sector-gaps.ts, joined to src/data/policy-gaps.ts, in the ESABCC Method Hub repository.
A23: Vintage | B23: Provisional read, mid-2026

Sheet Re-assessed gaps
A1: # | B1: Sector | C1: Subsector | D1: Gap type | E1: Finding | F1: What the Board found | G1: Main EU instrument(s) | H1: Verbatim quote from the report | I1: Report reference | J1: Status mid-2026 (provisional) | K1: Re-assessment — what has changed since January 2024 | L1: Also bears on | M1: Sources for the re-assessment | N1: ID
A2: 1 | B2: Industry | C2: Cross-cutting | D2: Policy gap | E2: Circular-economy policy focuses on recycling, not prevention | F2: The 2015 Circular Economy Action Plan (CEAP 1) and the strategy on plastics mainly targeted recycling, with little focus on solutions upstream in the waste hierarchy. | G2: Circular Economy Action Plan, Plastics Strategy | H2: “The 2015 circular economy action plan (CEAP 1) and the strategy on plastics mainly targeted recycling, with little focus on solutions upstream in the waste hierarchy (policy gap).” | I2: Ch. 5 Industry, p. 82, line 16 | J2: Partially addressed | K2: The Ecodesign for Sustainable Products Regulation (ESPR, 2024) and the CEAP-2 workstream push design, durability and reuse upstream of recycling for the first time — but the prevention/waste-hierarchy tilt is still early and product-group delegated acts are pending, so the gap is narrowed, not closed. | L2: — | M2: — | N2: industry-ceap-upstream
A3: 2 | B3: Industry | C3: Cross-cutting | D3: Policy gap | E3: Ecodesign circularity scope remained limited | F3: The Ecodesign Directive has been mainly focused on energy efficiency; product circularity has been added only in recent years, and its scope remained limited to energy products. | G3: Ecodesign Directive | H3: “the Ecodesign Directive has been mainly focused on energy efficiency and, whereas product circularity has been added in recent years, its scope remained limited to energy products (policy gap).” | I3: Ch. 5 Industry, p. 82, line 18 | J3: Addressed | K3: Largely closed: the ESPR (Reg. (EU) 2024/1781) replaces the old energy-only Ecodesign Directive and extends the framework to almost all physical product groups. Effect now depends on the pace of delegated acts (implementation risk remains). | L3: — | M3: — | N3: industry-ecodesign-scope
A4: 3 | B4: Industry | C4: Cross-cutting | D4: Policy gap | E4: Missing support for early deployment / lead markets | F4: Past EU policies have mainly focused on basic R&D (e.g. Horizon Europe), pilots and demonstration (NER 300 and the Innovation Fund) and large-scale diffusion of mature technologies (the EU ETS), but dedicated policies to support early deployment / market formation have been largely absent. | G4: Innovation Fund, EU ETS, (future) lead-market instruments | H4: “Past EU policies have been mainly focused on supporting basic R & D (e.g. Horizon Europe), pilots and demonstration (NER 300 and the Innovation Fund) and the large-scale diffusion of mature technologies (the EU ETS), but dedicated policies to support early deployment / market formation have been largely absent (policy gap).” | I4: Ch. 5 Industry, p. 83, line 17 | J4: Partially addressed | K4: The Net-Zero Industry Act (2024) and the 2025 Clean Industrial Deal add lead-market and demand-side tools (e.g. non-price criteria in public procurement and auctions, planned resilience/green-content requirements). Coverage of early deployment / market formation is improving but still thin versus the R&D and diffusion ends. | L4: — | M4: — | N4: industry-early-deployment
A5: 4 | B5: Transport | C5: Road passenger | D5: Ambition gap | E5: CO₂ standards do not reward vehicle efficiency | F5: While CO₂ emission performance standards for cars and vans effectively accelerate ZEV uptake, they do not incentivise efficiency (smaller, more efficient vehicles) within the ZEV segment, and might even incentivise the uptake of larger, less-efficient ZEVs. | G5: CO₂ emission standards for cars and vans | H5: “Whereas these policies can effectively accelerate the uptake of ZEVs, they currently do not incentivise efficiency (smaller, more efficient vehicles) within the segment of ZEVs (ambition gap), and might even incentivise the uptake of larger, less-efficient ZEVs (policy inconsistency), increasing pressure on the already constrained availability of critical resources.” | I5: Ch. 6 Transport, p. 103, line 41 | J5: Still open | K5: CO₂ standards for cars and vans still reward zero-tailpipe rather than vehicle efficiency; the 2025/2026 review of the standards is the moment to close it, but nothing is adopted. Assessed unchanged. | L5: — | M5: — | N5: transport-zev-efficiency
A6: 5 | B6: Transport | C6: Road freight | D6: Ambition gap | E6: Weak framework for rail/intermodal freight shift | F6: EU policies to support a modal shift (the Combined Transport Directive, the Rail Freight Corridors Regulation and the TEN-T regulation) have so far had little success owing to lack of ambition: outdated provisions in the Combined Transport Directive that prevent digitalised workflows, lack of adequate delivery mechanisms in the Rail Freight Corridors Regulation, and lack of an overview of current and future required capacities of intermodal terminals under the TEN-T regulation. | G6: Combined Transport Directive, Rail Freight Corridors Regulation, TEN-T | H6: “Furthermore, EU policies to support a modal shift (the Combined Transport Directive, the Rail Freight Corridors Regulation, the Trans-European Transport Network (TEN-T) regulation) have so far had little success owing to lack of ambition (e.g. outdated provisions in the Combined Transport directive that prevent digitalised workflows, lack of adequate delivery mechanisms in the Rail Freights Corridors Regulation, lack of an overview of current and future required capacities of intermodal terminals under the TEN-T regulation) (ambition gap)” | I6: Ch. 6 Transport, p. 103, line 12 | J6: Partially addressed | K6: The TEN-T recast (Reg. (EU) 2024/1679) is in force and addresses some ambition weaknesses, but the Combined Transport Directive recast came close to being withdrawn by the Commission in late 2025, was kept alive only after Parliament rejected the withdrawal (Jan 2026), and remains stalled in Council with no agreed text as of mid-2026 — the ambition gap is unresolved and the file’s survival itself is in question. | L6: — | M6: https://www.railwaygazette.com/freight/2026/06/04/rail-association-throw-last-hail-mary-to-save-combined-transport-directive/ https://www.cer.be/cer-press-releases/council-faces-stalemate-as-combined-transport-directive-loses-momentum | N6: transport-modal-shift-freight
A7: 6 | B7: Transport | C7: Road freight | D7: Implementation gap | E7: Heterogeneous Member-State freight-shift implementation | F7: Implementation of the modal-shift measures (notably the Rail Freight Corridor Regulation and the Combined Transport Directive) has been incomplete and heterogeneous across Member States. | G7: Rail Freight Corridors Regulation, Combined Transport Directive | H7: “EU policies to support a modal shift (the Combined Transport Directive, the Rail Freight Corridors Regulation, the Trans-European Transport Network (TEN-T) regulation) have so far had little success owing to lack of ambition (e.g. outdated provisions in the Combined Transport directive that prevent digitalised workflows, lack of adequate delivery mechanisms in the Rail Freights Corridors Regulation, lack of an overview of current and future required capacities of intermodal terminals under the TEN-T regulation) (ambition gap) and incomplete and heterogeneous implementation at the Member State level (implementation gap).” | I7: Ch. 6 Transport, p. 103, line 12 | J7: Still open | K7: Implementation across Member States remains heterogeneous; the new TEN-T deadlines are not yet in force. Assessed unchanged. | L7: — | M7: — | N7: transport-modal-shift-implementation
A8: 7 | B8: Transport | C8: Aviation | D8: Policy gap | E8: Extra-EU aviation and maritime largely exempt from ETS | F8: Extra-EU aviation and half of extra-EU maritime transport remain exempt from the EU ETS. | G8: EU ETS (aviation & maritime) | H8: “Furthermore, extra-EU aviation and half of extra-EU maritime transport remains exempt from the EU ETS (policy gap).” | I8: Ch. 6 Transport, p. 105, line 5 | J8: Still open | K8: Extra-EU aviation still sits under CORSIA rather than the ETS, and half of extra-EU maritime remains outside the ETS; the review clauses have not changed the scope. Assessed unchanged (also applies to Maritime). | L8: Maritime | M8: — | N8: transport-extra-eu-exemption
A9: 8 | B9: Transport | C9: Cross-cutting | D9: Policy gap | E9: Transport demand moderation not an EU policy option | F9: Moderation of overall transport demand is not considered as an option in the EU's Sustainable and Smart Mobility Strategy. | G9: Sustainable and Smart Mobility Strategy | H9: “Moderation of overall transport demand is not considered as an option in the EU's Sustainable and Smart Mobility Strategy (policy gap).” | I9: Ch. 6 Transport, p. 103, line 11 | J9: Still open | K9: No sign that overall transport-demand moderation has entered EU mobility strategy since the report; the "avoid" tier remains largely absent. Assessed unchanged. | L9: — | M9: — | N9: transport-demand-moderation
A10: 9 | B10: Transport | C10: Cross-cutting | D10: Ambition gap | E10: Policies still promote high-indirect-effect biofuels | F10: The RED III, ReFuelEU Aviation and FuelEU Maritime continue to promote some biofuels with potentially high indirect effects, such as fuels made from food and feed crops (up to 7 %), intermediate crops and specific types of animal fats ('category 3 animal fats'). | G10: RED III, ReFuelEU Aviation, FuelEU Maritime | H10: “Nevertheless, concerns remain, as these policies continue to promote some biofuels with potentially high indirect effects, such as fuels made from food and feed crops (up to 7 %), intermediate crops and specific types of animal fats (so-called “category 3 animal fats”) (ambition gap).” | I10: Ch. 6 Transport, p. 104, line 14 | J10: Still open | K10: The aviation and maritime instruments now largely shut out crop biofuels (ReFuelEU Aviation Art. 4(5) excludes food/feed crops from the SAF mandate; FuelEU Maritime assigns them fossil-equivalent emission factors), but RED III still admits food/feed-crop biofuels within Member-State caps for road transport and indirect land-use-change effects remain unpriced. Assessed still open, narrowed at the edges. | L10: — | M10: — | N10: transport-biofuels-indirect
A11: 10 | B11: Transport | C11: Cross-cutting | D11: Implementation gap | E11: Suspected fraud in biofuel sustainability labelling | F11: There are well-founded suspicions of fraud in the labelling of transport biofuels as sustainable under RED III. | G11: RED III | H11: “Furthermore, there are well-founded suspicions of fraud in the labelling of biofuels as sustainable (implementation gap).” | I11: Ch. 6 Transport, p. 104, line 17 | J11: Partially addressed | K11: The Union Database for Biofuels has been operational since January 2024 and stricter voluntary-scheme oversight tightens traceability, but the delegated act setting a binding mandatory-use/sanctions date is still pending agreement with Member States as of 2025–2026 — enforcement teeth are not yet in place, so the implementation gap is narrowed, not resolved. | L11: — | M11: https://vespertool.com/blog/the-udb-will-be-mandatory/ https://energy.ec.europa.eu/news/eu-database-biofuels-becomes-operational-2024-01-15_en | N11: transport-biofuel-fraud
A13: Notes: columns A–I are the report's own findings (unchanged). Columns J–M are a provisional mid-2026 re-assessment compiled for this prep cycle and pending verification — not a Board position.
A14: Source: ESABCC (2024) “Towards EU climate neutrality: Progress, policy gaps and opportunities”, January 2024; re-assessment Provisional read, mid-2026.

Sheet Candidate gaps
A1: # | B1: Sector | C1: Subsector | D1: Proposed gap type | E1: Candidate gap | F1: Why this may be a gap | G1: Instrument(s) concerned | H1: Test to confirm / refute | I1: Sources | J1: Lead's decision | K1: ID
A2: 1 | B2: Industry | C2: Iron & steel | D2: Policy gap | E2: No binding demand signal for near-zero steel | F2: Near-zero primary steel carries a green premium that no EU instrument yet guarantees demand for. Without mandatory lead-market quotas (e.g. green public procurement or a minimum near-zero content in cars/construction), first-mover H₂-DRI plants lack an offtake floor — a market-formation gap the report flags generically but not for steel specifically. | G2: Public procurement, Clean Industrial Deal lead-market measures, product standards, Industrial Accelerator Act | H2: A draft Industrial Accelerator Act (renamed from "Industrial Decarbonisation Accelerator Act" in von der Leyen’s Sept-2025 State of the Union address) was tabled 4 March 2026 with "Made in EU" / low-carbon procurement content among its core measures — the gap is now "policy proposed, not yet enacted", not a purely hypothetical future test. Confirmed if the Act is adopted without binding near-zero-steel content/procurement quotas, or stalls before adoption; refuted if the adopted Act sets enforceable near-zero-steel demand. | I2: https://www.sidley.com/en/insights/newsupdates/2026/04/industrial-accelerator-act https://single-market-economy.ec.europa.eu/publications/industrial-accelerator-act_en | K2: cand-steel-lead-market
A3: 2 | B3: Industry | C3: Cement & lime | D3: Implementation gap | E3: CO₂ transport & storage lags cement CCS needs | F3: Cement’s process emissions are unavoidable without CCS, yet permitted CO₂ storage capacity and shared transport infrastructure are being built far more slowly than the Net-Zero Industry Act 2030 injection target implies, leaving abatement plans without somewhere to send the CO₂ — an implementation gap specific to hard-to-abate process industry. | G3: Net-Zero Industry Act (CO₂ storage target), CCS Directive, CEF / TEN-E | H3: Confirmed if operational/committed storage & transport capacity stays below the trajectory needed for cement process emissions; refuted if storage FIDs and CO₂ networks scale to meet the 50 Mt/yr target on time. | I3: — | K3: cand-cement-co2-storage
A4: 3 | B4: Industry | C4: Chemicals & petrochemicals | D4: Policy gap | E4: No incentive to decarbonise chemical feedstock (defossilisation) | F4: EU policy prices energy-related CO₂ but barely touches the fossil carbon embedded as feedstock in plastics and chemicals; there is no clear framework (or CCU/recycled-carbon accounting) to steer feedstock away from virgin fossil, so the largest part of the sector’s carbon is unaddressed. | G4: EU ETS scope, ESPR, Packaging & Plastics rules, a possible recycled-carbon standard | H4: Confirmed if no instrument sets a feedstock-defossilisation signal or CCU/recycled-carbon accounting rule; refuted if such a framework is proposed. | I4: — | K4: cand-chem-feedstock
A5: 4 | B5: Industry | C5: Cross-cutting | D5: Implementation gap | E5: Grid-connection and price barriers stall industrial electrification | F5: Electrification is the backbone of industrial mitigation, but multi-year grid-connection queues and the EU’s industrial-electricity price gap are not treated as a decarbonisation barrier in their own right, so plants electrify slower than the abatement pathway needs — an enabling-conditions implementation gap. | G5: Electricity Market Design, grid planning, Clean Industrial Deal affordability measures | H5: Confirmed if connection lead-times and industrial power prices remain binding constraints without a targeted instrument; refuted if the Affordable Energy / grid package resolves them. | I5: — | K5: cand-ind-electrification-enabling
A6: 5 | B6: Industry | C6: Cross-cutting | D6: Policy gap | E6: Decarbonisation siting ignores water-stress (mitigation–adaptation blind spot) | F6: Green-hydrogen and CCS support is allocated without a systematic water-availability screen, so water-intensive abatement can be steered toward drought-prone regions — a maladaptation risk that no industrial-decarbonisation instrument currently guards against. | G6: Net-Zero Industry Act, Hydrogen Bank auctions, State-aid / IPCEI conditions | H6: Confirmed if support instruments carry no water-stress conditionality; refuted if a water screen is added to siting/funding criteria. | I6: — | K6: cand-ind-water-siting
A7: 6 | B7: Transport | C7: Road passenger | D7: Policy gap | E7: No EU steer on road pricing & company-car tax to moderate demand | F7: Company-car taxation and the near-absence of distance/CO₂-based road pricing entrench car use and inefficient fleets, but demand- and fiscal-side levers sit almost entirely with Member States with no EU framework — reinforcing the report’s demand-moderation gap on the passenger side. | G7: Energy Taxation Directive revision, Eurovignette, Member-State fiscal coordination | H7: Confirmed if no EU instrument steers company-car/road-pricing reform; refuted if the ETD recast or a pricing framework does. | I7: — | K7: cand-road-pricing
A8: 7 | B8: Transport | C8: Road freight | D8: Implementation gap | E8: Heavy-duty charging/refuelling rollout trails the HDV CO₂ targets | F8: The 2024 HDV CO₂ standards assume a fast zero-emission truck ramp-up, but AFIR megawatt-charging and hydrogen-refuelling deployment at logistics hubs — and the grid capacity behind them — are lagging, risking an infrastructure implementation gap that could stall the mitigation the standards require. | G8: AFIR, TEN-T, grid connection at freight hubs | H8: Confirmed if MCS/H₂ corridor coverage stays below the truck-fleet trajectory; refuted if AFIR delivery keeps pace. | I8: — | K8: cand-hdv-charging
A9: 8 | B9: Transport | C9: Rail | D9: Policy gap | E9: Rail electrification not paired with mandatory climate-proofing | F9: EU funding accelerates rail electrification (a mitigation asset) without requiring the heat-/flood-proofing that keeps the network reliable in extremes, so the low-carbon backbone the modal-shift strategy depends on is left exposed — a joint mitigation–adaptation gap. | G9: TEN-T climate-proofing requirements, CEF Transport, Rail Freight rules | H9: Confirmed if electrification funding carries no binding adaptation/climate-proofing condition; refuted if TEN-T climate-proofing is enforced on rail works. | I9: — | K9: cand-rail-adaptation
A10: 9 | B10: Transport | C10: Aviation | D10: Policy gap | E10: Non-CO₂ aviation effects still unregulated | F10: Contrails and NOx account for roughly two-thirds of aviation’s effective warming (Lee et al. 2021, Atmospheric Environment 244:117834: non-CO₂ terms are ~66% of aviation’s net effective radiative forcing), yet only an MRV step exists — there is no instrument that prices or operationally mitigates non-CO₂ effects, leaving most of aviation’s climate impact outside policy. | G10: EU ETS aviation (non-CO₂ MRV), air-traffic-management measures | H10: Confirmed if non-CO₂ effects remain only monitored, not acted on, after the MRV review; refuted if a mitigation/pricing measure is introduced. | I10: — | K10: cand-aviation-nonco2
A11: 10 | B11: Transport | C11: Maritime | D11: Implementation gap | E11: FuelEU Maritime compliance conditions not yet in place | F11: FuelEU Maritime's declining GHG-intensity limit (in force since 1 January 2025) assumes fuel and infrastructure conditions that are still open questions rather than settled facts: RFNBO/biofuel supply may not scale fast enough (a conditional 2% RFNBO sub-target only bites from 2034, and only if uptake stays below 1% through 2031), well-to-wake lifecycle accounting leaves commercial/contractual practicalities unresolved between charterers, pool members and owners, and shore-side (OPS) port infrastructure was only ~20% contracted/installed by May 2025 against the 1 January 2030 AFIR deadline for major container/passenger ports — leaving the sector's own gap landscape with no tagged Maritime-specific risk despite these open questions. | G11: FuelEU Maritime (Reg. (EU) 2023/1805), AFIR onshore power supply requirements, RED III RFNBO sub-target mechanism | H11: Confirmed if RFNBO uptake stays below 1% of maritime fuel use through 2031 (triggering the conditional 2034 sub-target) and/or OPS installation at major EU ports continues to lag the 1 January 2030 AFIR deadline; refuted if RFNBO/biofuel supply and port electrification scale to meet the FuelEU trajectory on schedule. | I11: https://transport.ec.europa.eu/transport-modes/maritime/decarbonising-maritime-transport-fueleu-maritime/questions-and-answers-regulation-eu-20231805-use-renewable-and-low-carbon-fuels-maritime-transport_en https://www.sustainable-ships.org/stories/2025/eu-shore-power-demand-2030 | K11: cand-maritime-fueleu-conditions
A13: Notes: “Lead's decision” (shaded) is the column to fill in — accept into the gap tracker, reject, or park with a reason. Every candidate is AI-compiled working material pending verification; none is a Board finding.

Sheet Landscape data
A1: Sector | B1: Subsector | C1: Origin | D1: Live status | E1: Gap type | F1: Finding | G1: ID
A2: Industry | B2: Cross-cutting | C2: Report gap | D2: Partially addressed | E2: Policy gap | F2: Circular-economy policy focuses on recycling, not prevention | G2: industry-ceap-upstream
A3: Industry | B3: Cross-cutting | C3: Report gap | D3: Addressed | E3: Policy gap | F3: Ecodesign circularity scope remained limited | G3: industry-ecodesign-scope
A4: Industry | B4: Cross-cutting | C4: Report gap | D4: Partially addressed | E4: Policy gap | F4: Missing support for early deployment / lead markets | G4: industry-early-deployment
A5: Transport | B5: Road passenger | C5: Report gap | D5: Still open | E5: Ambition gap | F5: CO₂ standards do not reward vehicle efficiency | G5: transport-zev-efficiency
A6: Transport | B6: Road freight | C6: Report gap | D6: Partially addressed | E6: Ambition gap | F6: Weak framework for rail/intermodal freight shift | G6: transport-modal-shift-freight
A7: Transport | B7: Road freight | C7: Report gap | D7: Still open | E7: Implementation gap | F7: Heterogeneous Member-State freight-shift implementation | G7: transport-modal-shift-implementation
A8: Transport | B8: Aviation | C8: Report gap | D8: Still open | E8: Policy gap | F8: Extra-EU aviation and maritime largely exempt from ETS | G8: transport-extra-eu-exemption
A9: Transport | B9: Maritime | C9: Report gap | D9: Still open | E9: Policy gap | F9: Extra-EU aviation and maritime largely exempt from ETS | G9: transport-extra-eu-exemption
A10: Transport | B10: Cross-cutting | C10: Report gap | D10: Still open | E10: Policy gap | F10: Transport demand moderation not an EU policy option | G10: transport-demand-moderation
A11: Transport | B11: Cross-cutting | C11: Report gap | D11: Still open | E11: Ambition gap | F11: Policies still promote high-indirect-effect biofuels | G11: transport-biofuels-indirect
A12: Transport | B12: Cross-cutting | C12: Report gap | D12: Partially addressed | E12: Implementation gap | F12: Suspected fraud in biofuel sustainability labelling | G12: transport-biofuel-fraud
... A22: Transport | B22: Maritime | C22: Candidate | D22: Candidate — to test | E22: Implementation gap | F22: FuelEU Maritime compliance conditions not yet in place | G22: cand-maritime-fueleu-conditions
A24: One row per gap × subsector: a gap flagged as bearing on a second subsector appears twice, so the landscape counts do not leave that subsector empty. Row totals here are therefore larger than the number of distinct gaps.

Sheet Gap landscape
A1: The gap landscape, subsector by subsector
A2: How the transport and industry gaps distribute across the report-aligned subsectors: report gaps by their provisional mid-2026 status, and the candidate gaps proposed on top. Counts are COUNTIFS formulas over the “Landscape data” sheet.
A4: Industry
A5: Subsector | B5: Still open | C5: Partially addressed | D5: Addressed | E5: Candidate — to test | F5: Total
A6: Iron & steel | B6: =COUNTIFS('Landscape data'!$A$2:$A$200,"Industry",'Landscape data'!$B$2:$B$200,$A6,'Landscape data'!$D$2:$D$200,B$5) | C6: =COUNTIFS('Landscape data'!$A$2:$A$200,"Industry",'Landscape data'!$B$2:$B$200,$A6,'Landscape data'!$D$2:$D$200,C$5) | D6: =COUNTIFS('Landscape data'!$A$2:$A$200,"Industry",'Landscape data'!$B$2:$B$200,$A6,'Landscape data'!$D$2:$D$200,D$5) | E6: =COUNTIFS('Landscape data'!$A$2:$A$200,"Industry",'Landscape data'!$B$2:$B$200,$A6,'Landscape data'!$D$2:$D$200,E$5) | F6: =SUM(B6:E6)
A7: Cement & lime | B7: =COUNTIFS('Landscape data'!$A$2:$A$200,"Industry",'Landscape data'!$B$2:$B$200,$A7,'Landscape data'!$D$2:$D$200,B$5) | C7: =COUNTIFS('Landscape data'!$A$2:$A$200,"Industry",'Landscape data'!$B$2:$B$200,$A7,'Landscape data'!$D$2:$D$200,C$5) | D7: =COUNTIFS('Landscape data'!$A$2:$A$200,"Industry",'Landscape data'!$B$2:$B$200,$A7,'Landscape data'!$D$2:$D$200,D$5) | E7: =COUNTIFS('Landscape data'!$A$2:$A$200,"Industry",'Landscape data'!$B$2:$B$200,$A7,'Landscape data'!$D$2:$D$200,E$5) | F7: =SUM(B7:E7)
A8: Chemicals & petrochemicals | B8: =COUNTIFS('Landscape data'!$A$2:$A$200,"Industry",'Landscape data'!$B$2:$B$200,$A8,'Landscape data'!$D$2:$D$200,B$5) | C8: =COUNTIFS('Landscape data'!$A$2:$A$200,"Industry",'Landscape data'!$B$2:$B$200,$A8,'Landscape data'!$D$2:$D$200,C$5) | D8: =COUNTIFS('Landscape data'!$A$2:$A$200,"Industry",'Landscape data'!$B$2:$B$200,$A8,'Landscape data'!$D$2:$D$200,D$5) | E8: =COUNTIFS('Landscape data'!$A$2:$A$200,"Industry",'Landscape data'!$B$2:$B$200,$A8,'Landscape data'!$D$2:$D$200,E$5) | F8: =SUM(B8:E8)
A9: Cross-cutting | B9: =COUNTIFS('Landscape data'!$A$2:$A$200,"Industry",'Landscape data'!$B$2:$B$200,$A9,'Landscape data'!$D$2:$D$200,B$5) | C9: =COUNTIFS('Landscape data'!$A$2:$A$200,"Industry",'Landscape data'!$B$2:$B$200,$A9,'Landscape data'!$D$2:$D$200,C$5) | D9: =COUNTIFS('Landscape data'!$A$2:$A$200,"Industry",'Landscape data'!$B$2:$B$200,$A9,'Landscape data'!$D$2:$D$200,D$5) | E9: =COUNTIFS('Landscape data'!$A$2:$A$200,"Industry",'Landscape data'!$B$2:$B$200,$A9,'Landscape data'!$D$2:$D$200,E$5) | F9: =SUM(B9:E9)
A10: All industry | B10: =SUM(B6:B9) | C10: =SUM(C6:C9) | D10: =SUM(D6:D9) | E10: =SUM(E6:E9) | F10: =SUM(F6:F9)
A13: Transport
A14: Subsector | B14: Still open | C14: Partially addressed | D14: Addressed | E14: Candidate — to test | F14: Total
A15: Road passenger | B15: =COUNTIFS('Landscape data'!$A$2:$A$200,"Transport",'Landscape data'!$B$2:$B$200,$A15,'Landscape data'!$D$2:$D$200,B$14) | C15: =COUNTIFS('Landscape data'!$A$2:$A$200,"Transport",'Landscape data'!$B$2:$B$200,$A15,'Landscape data'!$D$2:$D$200,C$14) | D15: =COUNTIFS('Landscape data'!$A$2:$A$200,"Transport",'Landscape data'!$B$2:$B$200,$A15,'Landscape data'!$D$2:$D$200,D$14) | E15: =COUNTIFS('Landscape data'!$A$2:$A$200,"Transport",'Landscape data'!$B$2:$B$200,$A15,'Landscape data'!$D$2:$D$200,E$14) | F15: =SUM(B15:E15)
A16: Road freight | B16: =COUNTIFS('Landscape data'!$A$2:$A$200,"Transport",'Landscape data'!$B$2:$B$200,$A16,'Landscape data'!$D$2:$D$200,B$14) | C16: =COUNTIFS('Landscape data'!$A$2:$A$200,"Transport",'Landscape data'!$B$2:$B$200,$A16,'Landscape data'!$D$2:$D$200,C$14) | D16: =COUNTIFS('Landscape data'!$A$2:$A$200,"Transport",'Landscape data'!$B$2:$B$200,$A16,'Landscape data'!$D$2:$D$200,D$14) | E16: =COUNTIFS('Landscape data'!$A$2:$A$200,"Transport",'Landscape data'!$B$2:$B$200,$A16,'Landscape data'!$D$2:$D$200,E$14) | F16: =SUM(B16:E16)
A17: Rail | B17: =COUNTIFS('Landscape data'!$A$2:$A$200,"Transport",'Landscape data'!$B$2:$B$200,$A17,'Landscape data'!$D$2:$D$200,B$14) | C17: =COUNTIFS('Landscape data'!$A$2:$A$200,"Transport",'Landscape data'!$B$2:$B$200,$A17,'Landscape data'!$D$2:$D$200,C$14) | D17: =COUNTIFS('Landscape data'!$A$2:$A$200,"Transport",'Landscape data'!$B$2:$B$200,$A17,'Landscape data'!$D$2:$D$200,D$14) | E17: =COUNTIFS('Landscape data'!$A$2:$A$200,"Transport",'Landscape data'!$B$2:$B$200,$A17,'Landscape data'!$D$2:$D$200,E$14) | F17: =SUM(B17:E17)
A18: Aviation | B18: =COUNTIFS('Landscape data'!$A$2:$A$200,"Transport",'Landscape data'!$B$2:$B$200,$A18,'Landscape data'!$D$2:$D$200,B$14) | C18: =COUNTIFS('Landscape data'!$A$2:$A$200,"Transport",'Landscape data'!$B$2:$B$200,$A18,'Landscape data'!$D$2:$D$200,C$14) | D18: =COUNTIFS('Landscape data'!$A$2:$A$200,"Transport",'Landscape data'!$B$2:$B$200,$A18,'Landscape data'!$D$2:$D$200,D$14) | E18: =COUNTIFS('Landscape data'!$A$2:$A$200,"Transport",'Landscape data'!$B$2:$B$200,$A18,'Landscape data'!$D$2:$D$200,E$14) | F18: =SUM(B18:E18)
A19: Maritime | B19: =COUNTIFS('Landscape data'!$A$2:$A$200,"Transport",'Landscape data'!$B$2:$B$200,$A19,'Landscape data'!$D$2:$D$200,B$14) | C19: =COUNTIFS('Landscape data'!$A$2:$A$200,"Transport",'Landscape data'!$B$2:$B$200,$A19,'Landscape data'!$D$2:$D$200,C$14) | D19: =COUNTIFS('Landscape data'!$A$2:$A$200,"Transport",'Landscape data'!$B$2:$B$200,$A19,'Landscape data'!$D$2:$D$200,D$14) | E19: =COUNTIFS('Landscape data'!$A$2:$A$200,"Transport",'Landscape data'!$B$2:$B$200,$A19,'Landscape data'!$D$2:$D$200,E$14) | F19: =SUM(B19:E19)
A20: Cross-cutting | B20: =COUNTIFS('Landscape data'!$A$2:$A$200,"Transport",'Landscape data'!$B$2:$B$200,$A20,'Landscape data'!$D$2:$D$200,B$14) | C20: =COUNTIFS('Landscape data'!$A$2:$A$200,"Transport",'Landscape data'!$B$2:$B$200,$A20,'Landscape data'!$D$2:$D$200,C$14) | D20: =COUNTIFS('Landscape data'!$A$2:$A$200,"Transport",'Landscape data'!$B$2:$B$200,$A20,'Landscape data'!$D$2:$D$200,D$14) | E20: =COUNTIFS('Landscape data'!$A$2:$A$200,"Transport",'Landscape data'!$B$2:$B$200,$A20,'Landscape data'!$D$2:$D$200,E$14) | F20: =SUM(B20:E20)
A21: All transport | B21: =SUM(B15:B20) | C21: =SUM(C15:C20) | D21: =SUM(D15:D20) | E21: =SUM(E15:E20) | F21: =SUM(F15:F20)
A24: Notes: a gap that bears on more than one subsector is counted in each — the totals are therefore assignments, not distinct gaps. “Candidate — to test” rows are proposals, not Board findings.
A25: Source: ESABCC (2024) “Towards EU climate neutrality: Progress, policy gaps and opportunities”; re-assessment Provisional read, mid-2026.

Sheet Legend
A1: Legend
A2: The report's gap classification, the status vocabulary used in the re-assessment, and the subsector taxonomy.
A4: Gap type | B4: What it means (report methodology) | C4: Colour
A5: Policy gap | B5: No policy in place to address the required change.
A6: Ambition gap | B6: Policies exist but are not ambitious enough to deliver the change.
A7: Implementation gap | B7: Policies are not implemented adequately.
A8: Inconsistency | B8: Policies provide counter-productive incentives.
A11: Status (mid-2026 re-assessment) | B11: What it means here | C11: Colour
A12: Still open | B12: Nothing adopted since the report changes the finding — assessed unchanged.
A13: Partially addressed | B13: Legislation since the report narrows the gap but does not close it.
A14: Addressed | B14: An adopted instrument closes the gap; any residual risk is named in the note.
A15: To review | B15: Not yet re-assessed.
A16: Candidate — to test | B16: Proposed additional gap, not tagged in the report. Work the test in the “Candidate gaps” sheet, then accept or reject.
A19: Sector | B19: Subsectors (report-aligned taxonomy)
A20: Industry | B20: Iron & steel · Cement & lime · Chemicals & petrochemicals · Cross-cutting
A21: Transport | B21: Road passenger · Road freight · Rail · Aviation · Maritime · Cross-cutting
