Workbook

Sheet Read me
A1: Policy Gap Tracker — ESABCC 2024 progress report
A2: Every policy, ambition and implementation gap and inconsistency the Board identified across the 12 chapters of “Towards EU climate neutrality: Progress, policy gaps and opportunities” (January 2024), with the verbatim report sentence and page behind each finding.
A3: Background document for the Summer Prep · Policy Gap 2.0 Report module · prepared 27 July 2026.
A5: What is in this workbook
A6: Sheet | B6: What it holds
A7: Gap tracker | B7: All 66 findings, one row each: sector/chapter, gap type, the finding, the EU instrument(s) concerned, the verbatim report quote, the page reference, and two status columns to maintain (see below). Filter with the arrows in row 1.
A8: Summary | B8: Counts by chapter × gap type and by live status, with the two overview figures. Every number is a COUNTIFS formula over the tracker — it updates by itself when you edit, add or delete rows there.
A9: Legend | B9: What the four gap types and the four live statuses mean, in the report's own words.
A11: How to use it
A12: • The two columns to maintain are “Live status” and “Status note”. Everything to their left is the January-2024 report baseline and should not be overwritten — if a finding changes, record it in the note.
A13: • “Live status” has a drop-down (Still open / Partially addressed / Addressed / To review). All 66 rows are seeded to the report baseline “Still open”, so nothing is silently claimed to be solved.
A14: • Rows you add at the bottom are picked up by the Summary sheet automatically (the formulas run to row 400). Mark them “Custom” in the Origin column so they stay distinguishable from Board findings.
A15: • The same list lives in the Method Hub (Summer Prep › Policy Gap 2.0 Report › Policy Gap Tracker), where it is filterable and editable in the browser. This workbook is the offline copy — if both are edited, the Hub is the one to reconcile against.
A17: Source
A18: Report | B18: European Scientific Advisory Board on Climate Change (ESABCC) (2024) “Towards EU climate neutrality: Progress, policy gaps and opportunities”, January 2024.
A19: Report URL | B19: https://climate-advisory-board.europa.eu/reports-and-publications/towards-eu-climate-neutrality-progress-policy-gaps-and-opportunities
A20: Data source | B20: src/data/policy-gaps.ts in the ESABCC Method Hub repository — every quote was checked line-by-line against the report text, and each page reference points at the page carrying the tagged finding.
A21: Status of the content | B21: The findings and quotes are the Board's own, from the published report. The live status columns are a working tool for the Secretariat, not a Board position.

Sheet Gap tracker
A1: # | B1: Sector / report chapter | C1: Gap type | D1: Finding | E1: What the Board found | F1: Main EU instrument(s) | G1: Verbatim quote from the report | H1: Report reference | I1: Status in the report (Jan 2024) | J1: Live status | K1: Status note (what changed since) | L1: Origin | M1: ID
A2: 1 | B2: Energy supply | C2: Policy gap | D2: Hydrogen support ignores techno-economic limits | E2: The EU's massive policy support to the hydrogen value chain does not sufficiently reflect the techno-economic limits of hydrogen and its role in the integrated and decarbonised energy systems. | F2: Hydrogen & Decarbonised Gas package, RED III, IPCEIs | G2: “The EU's massive policy support to the hydrogen value chain does not sufficiently reflect the techno-economic limits of hydrogen and its role in the integrated and decarbonised energy systems (policy gap).” | H2: Ch. 4 Energy supply, p. 50, line 14 | I2: Open | J2: Still open | L2: Report | M2: energy-hydrogen-support
A3: 2 | B3: Energy supply | C3: Policy gap | D3: Imported upstream methane emissions not priced | E3: The Methane Regulation does not put a price on leaking upstream emissions and does not align with similar international initiatives. | F3: EU Methane Regulation | G3: “The regulation does not put a price on leaking upstream emissions and does not align with similar international initiatives (policy gap).” | H3: Ch. 4 Energy supply, p. 51, line 38 | I3: Open | J3: Still open | L3: Report | M3: energy-methane-upstream
A4: 3 | B4: Energy supply | C4: Policy gap | D4: No EU definition of legitimate CCS applications | E4: Residual emissions (e.g. in agriculture or industry) that motivate the use of carbon capture and storage (CCS) are currently not defined at EU or Member State level. | F4: Net-Zero Industry Act, TEN-E Regulation, Innovation Fund (State-aid rules) | G4: “Residual emissions (e.g. in agriculture or industry) that motivate the use of carbon capture and storage (CCS) are currently not defined at the EU or Member State level (policy gap).” | H4: Ch. 4 Energy supply, p. 50, line 31 | I4: Open | J4: Still open | L4: Report | M4: energy-ccs-scope
A5: 4 | B5: Energy supply | C5: Policy gap | D5: Renewables value-chain reinforcement still under negotiation | E5: The RED III (including the newly adopted target of a 42.5% renewable energy share in final energy consumption) and the electricity market reform are mostly in place, but the RES value-chain reinforcement is still under negotiation. | F5: RED III, Electricity Market Design reform, Net-Zero Industry Act | G5: “The RED III, including the newly adopted target of a 42.5 % renewable energy share in final energy consumption and the electricity market reform are mostly in place, the RES value chain reinforcement is still under negotiation (policy gap).” | H5: Ch. 4 Energy supply, p. 49, line 15 | I5: Open | J5: Still open | L5: Report | M5: energy-res-value-chain
A6: 5 | B6: Energy supply | C6: Ambition gap | D6: EED cost-benefit threshold exempts most projects | E6: While the EED aims to reinforce the application of the energy-efficiency-first principle, it sets a very high investment value (EUR 100 million) threshold, which means that many relevant projects will be exempted from assessment of energy efficiency solutions, including demand-side resources and system flexibilities. | F6: Energy Efficiency Directive (EED) | G6: “While the EED aims to reinforce the application of the energy efficiency first principle, it sets a very high investment value (EUR 100 million) threshold, which means that many relevant projects will be exempted from assessment of energy efficiency solutions, including demand-side resources and system flexibilities (ambition gap).” | H6: Ch. 4 Energy supply, p. 48, line 35 | I6: Open | J6: Still open | L6: Report | M6: energy-eed-threshold
A7: 6 | B7: Energy supply | C7: Implementation gap | D7: Energy system not planned and operated as a whole | E7: Despite the European Commission's endorsement of system integration as a strategic direction in 2020, the EU still does not plan and operate the energy system as a whole. | F7: EU Energy System Integration Strategy, TEN-E | G7: “Despite the endorsement of the system integration as a strategic direction by the European Commission in 2020, the EU still does not plan and operate the energy system as a whole (implementation gap).” | H7: Ch. 4 Energy supply, p. 50, line 2 | I7: Open | J7: Still open | L7: Report | M7: energy-system-integration
A8: 7 | B8: Energy supply | C8: Implementation gap | D8: Energy-efficiency-first principle not operationalised | E8: Understanding issues have led to insufficient operationalisation of the energy-efficiency-first principle so far. | F8: Energy Efficiency Directive (EED), Governance Regulation | G8: “Understanding issues also led to insufficient operationalisation of the energy efficiency first principle so far (implementation gap).” | H8: Ch. 4 Energy supply, p. 48, line 33 | I8: Open | J8: Still open | L8: Report | M8: energy-eef-operationalisation
A9: 8 | B9: Industry | C9: Policy gap | D9: Circular-economy policy focuses on recycling, not prevention | E9: The 2015 Circular Economy Action Plan (CEAP 1) and the strategy on plastics mainly targeted recycling, with little focus on solutions upstream in the waste hierarchy. | F9: Circular Economy Action Plan, Plastics Strategy | G9: “The 2015 circular economy action plan (CEAP 1) and the strategy on plastics mainly targeted recycling, with little focus on solutions upstream in the waste hierarchy (policy gap).” | H9: Ch. 5 Industry, p. 82, line 16 | I9: Open | J9: Still open | L9: Report | M9: industry-ceap-upstream
A10: 9 | B10: Industry | C10: Policy gap | D10: Ecodesign circularity scope remained limited | E10: The Ecodesign Directive has been mainly focused on energy efficiency; product circularity has been added only in recent years, and its scope remained limited to energy products. | F10: Ecodesign Directive | G10: “the Ecodesign Directive has been mainly focused on energy efficiency and, whereas product circularity has been added in recent years, its scope remained limited to energy products (policy gap).” | H10: Ch. 5 Industry, p. 82, line 18 | I10: Open | J10: Still open | L10: Report | M10: industry-ecodesign-scope
A11: 10 | B11: Industry | C11: Policy gap | D11: Missing support for early deployment / lead markets | E11: Past EU policies have mainly focused on basic R&D (e.g. Horizon Europe), pilots and demonstration (NER 300 and the Innovation Fund) and large-scale diffusion of mature technologies (the EU ETS), but dedicated policies to support early deployment / market formation have been largely absent. | F11: Innovation Fund, EU ETS, (future) lead-market instruments | G11: “Past EU policies have been mainly focused on supporting basic R & D (e.g. Horizon Europe), pilots and demonstration (NER 300 and the Innovation Fund) and the large-scale diffusion of mature technologies (the EU ETS), but dedicated policies to support early deployment / market formation have been largely absent (policy gap).” | H11: Ch. 5 Industry, p. 83, line 17 | I11: Open | J11: Still open | L11: Report | M11: industry-early-deployment
A12: 11 | B12: Transport | C12: Policy gap | D12: Extra-EU aviation and maritime largely exempt from ETS | E12: Extra-EU aviation and half of extra-EU maritime transport remain exempt from the EU ETS. | F12: EU ETS (aviation & maritime) | G12: “Furthermore, extra-EU aviation and half of extra-EU maritime transport remains exempt from the EU ETS (policy gap).” | H12: Ch. 6 Transport, p. 105, line 5 | I12: Open | J12: Still open | L12: Report | M12: transport-extra-eu-exemption
A13: 12 | B13: Transport | C13: Policy gap | D13: Transport demand moderation not an EU policy option | E13: Moderation of overall transport demand is not considered as an option in the EU's Sustainable and Smart Mobility Strategy. | F13: Sustainable and Smart Mobility Strategy | G13: “Moderation of overall transport demand is not considered as an option in the EU's Sustainable and Smart Mobility Strategy (policy gap).” | H13: Ch. 6 Transport, p. 103, line 11 | I13: Open | J13: Still open | L13: Report | M13: transport-demand-moderation
... A67: 66 | B67: Labour & skills | C67: Implementation gap | D67: Weak upskilling in key transition sectors | E67: Low participation in training in some key sectors (e.g. buildings, agriculture) limits the opportunities to upskill and enhance knowledge exchange relevant to the transition. | F67: Vocational training provision (Member-State competence) | G67: “Low participation in training in some key sectors (e.g. buildings, agriculture) also limits the opportunities to upskill and enhance knowledge exchange relevant to the transition (implementation gap).” | H67: Ch. 15 Labour, skills and capacity building, p. 278, line 21 | I67: Open | J67: Still open | L67: Report | M67: labour-sector-upskilling

Sheet Summary
A1: Where the gaps sit
A2: Findings per report chapter and gap type, and the live status of the list. All counts are COUNTIFS formulas over the “Gap tracker” sheet (rows 2–400), so they follow your edits.
A4: Sector / report chapter | B4: Policy gap | C4: Ambition gap | D4: Implementation gap | E4: Inconsistency | F4: Total
A5: Energy supply | B5: =COUNTIFS('Gap tracker'!$B$2:$B$400,$A5,'Gap tracker'!$C$2:$C$400,B$4) | C5: =COUNTIFS('Gap tracker'!$B$2:$B$400,$A5,'Gap tracker'!$C$2:$C$400,C$4) | D5: =COUNTIFS('Gap tracker'!$B$2:$B$400,$A5,'Gap tracker'!$C$2:$C$400,D$4) | E5: =COUNTIFS('Gap tracker'!$B$2:$B$400,$A5,'Gap tracker'!$C$2:$C$400,E$4) | F5: =SUM(B5:E5)
A6: Industry | B6: =COUNTIFS('Gap tracker'!$B$2:$B$400,$A6,'Gap tracker'!$C$2:$C$400,B$4) | C6: =COUNTIFS('Gap tracker'!$B$2:$B$400,$A6,'Gap tracker'!$C$2:$C$400,C$4) | D6: =COUNTIFS('Gap tracker'!$B$2:$B$400,$A6,'Gap tracker'!$C$2:$C$400,D$4) | E6: =COUNTIFS('Gap tracker'!$B$2:$B$400,$A6,'Gap tracker'!$C$2:$C$400,E$4) | F6: =SUM(B6:E6)
A7: Transport | B7: =COUNTIFS('Gap tracker'!$B$2:$B$400,$A7,'Gap tracker'!$C$2:$C$400,B$4) | C7: =COUNTIFS('Gap tracker'!$B$2:$B$400,$A7,'Gap tracker'!$C$2:$C$400,C$4) | D7: =COUNTIFS('Gap tracker'!$B$2:$B$400,$A7,'Gap tracker'!$C$2:$C$400,D$4) | E7: =COUNTIFS('Gap tracker'!$B$2:$B$400,$A7,'Gap tracker'!$C$2:$C$400,E$4) | F7: =SUM(B7:E7)
A8: Buildings | B8: =COUNTIFS('Gap tracker'!$B$2:$B$400,$A8,'Gap tracker'!$C$2:$C$400,B$4) | C8: =COUNTIFS('Gap tracker'!$B$2:$B$400,$A8,'Gap tracker'!$C$2:$C$400,C$4) | D8: =COUNTIFS('Gap tracker'!$B$2:$B$400,$A8,'Gap tracker'!$C$2:$C$400,D$4) | E8: =COUNTIFS('Gap tracker'!$B$2:$B$400,$A8,'Gap tracker'!$C$2:$C$400,E$4) | F8: =SUM(B8:E8)
A9: Agriculture | B9: =COUNTIFS('Gap tracker'!$B$2:$B$400,$A9,'Gap tracker'!$C$2:$C$400,B$4) | C9: =COUNTIFS('Gap tracker'!$B$2:$B$400,$A9,'Gap tracker'!$C$2:$C$400,C$4) | D9: =COUNTIFS('Gap tracker'!$B$2:$B$400,$A9,'Gap tracker'!$C$2:$C$400,D$4) | E9: =COUNTIFS('Gap tracker'!$B$2:$B$400,$A9,'Gap tracker'!$C$2:$C$400,E$4) | F9: =SUM(B9:E9)
A10: LULUCF | B10: =COUNTIFS('Gap tracker'!$B$2:$B$400,$A10,'Gap tracker'!$C$2:$C$400,B$4) | C10: =COUNTIFS('Gap tracker'!$B$2:$B$400,$A10,'Gap tracker'!$C$2:$C$400,C$4) | D10: =COUNTIFS('Gap tracker'!$B$2:$B$400,$A10,'Gap tracker'!$C$2:$C$400,D$4) | E10: =COUNTIFS('Gap tracker'!$B$2:$B$400,$A10,'Gap tracker'!$C$2:$C$400,E$4) | F10: =SUM(B10:E10)
A11: Carbon pricing | B11: =COUNTIFS('Gap tracker'!$B$2:$B$400,$A11,'Gap tracker'!$C$2:$C$400,B$4) | C11: =COUNTIFS('Gap tracker'!$B$2:$B$400,$A11,'Gap tracker'!$C$2:$C$400,C$4) | D11: =COUNTIFS('Gap tracker'!$B$2:$B$400,$A11,'Gap tracker'!$C$2:$C$400,D$4) | E11: =COUNTIFS('Gap tracker'!$B$2:$B$400,$A11,'Gap tracker'!$C$2:$C$400,E$4) | F11: =SUM(B11:E11)
A12: Whole-of-society | B12: =COUNTIFS('Gap tracker'!$B$2:$B$400,$A12,'Gap tracker'!$C$2:$C$400,B$4) | C12: =COUNTIFS('Gap tracker'!$B$2:$B$400,$A12,'Gap tracker'!$C$2:$C$400,C$4) | D12: =COUNTIFS('Gap tracker'!$B$2:$B$400,$A12,'Gap tracker'!$C$2:$C$400,D$4) | E12: =COUNTIFS('Gap tracker'!$B$2:$B$400,$A12,'Gap tracker'!$C$2:$C$400,E$4) | F12: =SUM(B12:E12)
A13: Finance & investment | B13: =COUNTIFS('Gap tracker'!$B$2:$B$400,$A13,'Gap tracker'!$C$2:$C$400,B$4) | C13: =COUNTIFS('Gap tracker'!$B$2:$B$400,$A13,'Gap tracker'!$C$2:$C$400,C$4) | D13: =COUNTIFS('Gap tracker'!$B$2:$B$400,$A13,'Gap tracker'!$C$2:$C$400,D$4) | E13: =COUNTIFS('Gap tracker'!$B$2:$B$400,$A13,'Gap tracker'!$C$2:$C$400,E$4) | F13: =SUM(B13:E13)
A14: Innovation | B14: =COUNTIFS('Gap tracker'!$B$2:$B$400,$A14,'Gap tracker'!$C$2:$C$400,B$4) | C14: =COUNTIFS('Gap tracker'!$B$2:$B$400,$A14,'Gap tracker'!$C$2:$C$400,C$4) | D14: =COUNTIFS('Gap tracker'!$B$2:$B$400,$A14,'Gap tracker'!$C$2:$C$400,D$4) | E14: =COUNTIFS('Gap tracker'!$B$2:$B$400,$A14,'Gap tracker'!$C$2:$C$400,E$4) | F14: =SUM(B14:E14)
A15: Climate governance | B15: =COUNTIFS('Gap tracker'!$B$2:$B$400,$A15,'Gap tracker'!$C$2:$C$400,B$4) | C15: =COUNTIFS('Gap tracker'!$B$2:$B$400,$A15,'Gap tracker'!$C$2:$C$400,C$4) | D15: =COUNTIFS('Gap tracker'!$B$2:$B$400,$A15,'Gap tracker'!$C$2:$C$400,D$4) | E15: =COUNTIFS('Gap tracker'!$B$2:$B$400,$A15,'Gap tracker'!$C$2:$C$400,E$4) | F15: =SUM(B15:E15)
A16: Labour & skills | B16: =COUNTIFS('Gap tracker'!$B$2:$B$400,$A16,'Gap tracker'!$C$2:$C$400,B$4) | C16: =COUNTIFS('Gap tracker'!$B$2:$B$400,$A16,'Gap tracker'!$C$2:$C$400,C$4) | D16: =COUNTIFS('Gap tracker'!$B$2:$B$400,$A16,'Gap tracker'!$C$2:$C$400,D$4) | E16: =COUNTIFS('Gap tracker'!$B$2:$B$400,$A16,'Gap tracker'!$C$2:$C$400,E$4) | F16: =SUM(B16:E16)
A17: All chapters | B17: =SUM(B5:B16) | C17: =SUM(C5:C16) | D17: =SUM(D5:D16) | E17: =SUM(E5:E16) | F17: =SUM(F5:F16)
A20: Live status of the list
A21: Live status | B21: Findings
A22: Still open | B22: =COUNTIF('Gap tracker'!$J$2:$J$400,$A22)
A23: Partially addressed | B23: =COUNTIF('Gap tracker'!$J$2:$J$400,$A23)
A24: Addressed | B24: =COUNTIF('Gap tracker'!$J$2:$J$400,$A24)
A25: To review | B25: =COUNTIF('Gap tracker'!$J$2:$J$400,$A25)
A27: Note: all rows are seeded to the report's January-2024 baseline (“Still open”). A count against any other status means someone has reassessed that row — the reason should be in its “Status note”.
A28: Source: European Scientific Advisory Board on Climate Change (ESABCC) (2024) “Towards EU climate neutrality: Progress, policy gaps and opportunities”, January 2024; Method Hub Policy Gap Tracker.

Sheet Legend
A1: Legend
A2: The report's own classification (Ch. 2, methodology) and the live-status vocabulary used in the tracker.
A4: Gap type | B4: What it means (report methodology) | C4: Colour
A5: Policy gap | B5: No policy in place to address the required change.
A6: Ambition gap | B6: Policies exist but are not ambitious enough to deliver the change.
A7: Implementation gap | B7: Policies are not implemented adequately.
A8: Inconsistency | B8: Policies provide counter-productive incentives.
A11: Live status | B11: When to use it | C11: Colour
A12: Still open | B12: Nothing adopted since January 2024 changes the finding — the report's baseline for every row.
A13: Partially addressed | B13: Legislation or implementation since the report narrows the gap but does not close it. Say which instrument, and what is still missing, in the status note.
A14: Addressed | B14: The gap is closed by an adopted instrument that is in force. Name the instrument in the note.
A15: To review | B15: Needs a look — the row was flagged but not yet reassessed.
A18: Colours follow the ESABCC template palette (teal #4D7E83 with the template's accent colours), so this workbook sits alongside the Board's Word documents.
