Workbook
Name Mtoe_to_TWh: 'conversion factor'!$B$10

Sheet conversion factor
A1: https://www.iea.org/data-and-statistics/data-tools/unit-converter
B3: Kwh | C3: Mwh | D3: Gwh | E3: Twh
A4: 1 toe | B4: =C4*1000 -> 11630 | C4: 11.63 | D4: =C4*0.001 -> 0.01163 | E4: =D4*0.001 -> 1.163e-05
A5: 1 ktoe | B5: =B4*1000 -> 11630000 | C5: =C4*1000 -> 11630 | D5: =D4*1000 -> 11.63 | E5: =E4*1000 -> 0.01163
A6: 1 Mtoe | B6: =B4*1000000 -> 11630000000 | C6: =C4*1000000 -> 11630000 | D6: =D4*1000000 -> 11630 | E6: =E4*1000000 -> 11.63
A10: Mtoe to TWh | B10: 11.63

Sheet Colour palette
S1: 2020 | T1: 2021 | U1: 2022 | V1: 2023 | W1: 2024 | X1: 2025 | Y1: 2026 | Z1: 2027 | AA1: 2028 | AB1: 2029 | AC1: 2030 | AD1: 2031 | AE1: 2032 | AF1: 2033 | AG1: 2034 | AH1: 2035 | AI1: 2036 | AJ1: 2037 | AK1: 2038 | AL1: 2039 | AM1: 2040 | AN1: 2041 | AO1: 2042 | AP1: 2043 | AQ1: 2044 | AR1: 2045 | AS1: 2046 | AT1: 2047 | AU1: 2048 | AV1: 2049 | AW1: 2050
Q2: Demand-side Focus Pathway | R2: 1 | S2: 1 | T2: 0.98 | U2: 0.96 | V2: 0.94 | W2: 0.92 | X2: 0.9 | Y2: 0.88 | Z2: 0.86 | AA2: 0.85 | AB2: 0.83 | AC2: 0.81 | AD2: 0.79 | AE2: 0.77 | AF2: 0.75 | AG2: 0.73 | AH2: 0.71 | AI2: 0.69 | AJ2: 0.67 | AK2: 0.65 | AL2: 0.63 | AM2: 0.61 | AN2: 0.6 | AO2: 0.58 | AP2: 0.57 | AQ2: 0.56 | AR2: 0.54 | AS2: 0.53 | AT2: 0.52 | AU2: 0.51 | AV2: 0.5 | AW2: 0.49
Q3: High Renewable Energy Pathway | R3: 1 | S3: 1 | T3: 0.99 | U3: 0.99 | V3: 0.98 | W3: 0.97 | X3: 0.96 | Y3: 0.94 | Z3: 0.92 | AA3: 0.89 | AB3: 0.87 | AC3: 0.85 | AD3: 0.83 | AE3: 0.8 | AF3: 0.78 | AG3: 0.75 | AH3: 0.73 | AI3: 0.71 | AJ3: 0.69 | AK3: 0.67 | AL3: 0.64 | AM3: 0.62 | AN3: 0.61 | AO3: 0.6 | AP3: 0.59 | AQ3: 0.58 | AR3: 0.56 | AS3: 0.56 | AT3: 0.55 | AU3: 0.55 | AV3: 0.55 | AW3: 0.54
B4: Font and colours: | E4: Half page width: | Q4: Mixed Options Pathway | R4: 1 | S4: 1.01 | T4: 0.99 | U4: 0.98 | V4: 0.96 | W4: 0.95 | X4: 0.93 | Y4: 0.92 | Z4: 0.9 | AA4: 0.89 | AB4: 0.88 | AC4: 0.86 | AD4: 0.85 | AE4: 0.83 | AF4: 0.82 | AG4: 0.8 | AH4: 0.79 | AI4: 0.78 | AJ4: 0.77 | AK4: 0.77 | AL4: 0.76 | AM4: 0.76 | AN4: 0.76 | AO4: 0.76 | AP4: 0.76 | AQ4: 0.76 | AR4: 0.76 | AS4: 0.76 | AT4: 0.76 | AU4: 0.77 | AV4: 0.77 | AW4: 0.77
Q5: #REF! | R5: 1 | S5: 1 | T5: 0.99 | U5: 0.97 | V5: 0.95 | W5: 0.93 | X5: 0.91 | Y5: 0.9 | Z5: 0.88 | AA5: 0.86 | AB5: 0.84 | AC5: 0.83 | AD5: 0.81 | AE5: 0.79 | AF5: 0.77 | AG5: 0.76 | AH5: 0.74 | AI5: 0.73 | AJ5: 0.72 | AK5: 0.72 | AL5: 0.71 | AM5: 0.7 | AN5: 0.7 | AO5: 0.7 | AP5: 0.7 | AQ5: 0.7 | AR5: 0.7 | AS5: 0.7 | AT5: 0.71 | AU5: 0.71 | AV5: 0.71 | AW5: 0.71
A6: Font: | B6: Segoe UI, size 8 | Q6: #REF! | R6: 1 | S6: 1 | T6: 0.99 | U6: 0.97 | V6: 0.96 | W6: 0.95 | X6: 0.94 | Y6: 0.93 | Z6: 0.91 | AA6: 0.9 | AB6: 0.88 | AC6: 0.87 | AD6: 0.85 | AE6: 0.83 | AF6: 0.81 | AG6: 0.79 | AH6: 0.77 | AI6: 0.76 | AJ6: 0.74 | AK6: 0.72 | AL6: 0.71 | AM6: 0.69 | AN6: 0.69 | AO6: 0.68 | AP6: 0.68 | AQ6: 0.68 | AR6: 0.67 | AS6: 0.67 | AT6: 0.67 | AU6: 0.66 | AV6: 0.66 | AW6: 0.66
B7: Signature colour | Q7: #REF! | R7: 1 | S7: 1 | T7: 0.98 | U7: 0.96 | V7: 0.94 | W7: 0.92 | X7: 0.9 | Y7: 0.88 | Z7: 0.86 | AA7: 0.84 | AB7: 0.83 | AC7: 0.81 | AD7: 0.79 | AE7: 0.77 | AF7: 0.75 | AG7: 0.73 | AH7: 0.71 | AI7: 0.7 | AJ7: 0.7 | AK7: 0.69 | AL7: 0.68 | AM7: 0.68 | AN7: 0.68 | AO7: 0.69 | AP7: 0.69 | AQ7: 0.7 | AR7: 0.7 | AS7: 0.71 | AT7: 0.71 | AU7: 0.71 | AV7: 0.71 | AW7: 0.71
Q8: #REF! | R8: 1 | S8: 1 | T8: 0.99 | U8: 0.99 | V8: 0.98 | W8: 0.97 | X8: 0.96 | Y8: 0.94 | Z8: 0.92 | AA8: 0.89 | AB8: 0.87 | AC8: 0.85 | AD8: 0.83 | AE8: 0.8 | AF8: 0.78 | AG8: 0.76 | AH8: 0.73 | AI8: 0.71 | AJ8: 0.69 | AK8: 0.67 | AL8: 0.65 | AM8: 0.63 | AN8: 0.62 | AO8: 0.6 | AP8: 0.59 | AQ8: 0.58 | AR8: 0.57 | AS8: 0.56 | AT8: 0.56 | AU8: 0.55 | AV8: 0.55 | AW8: 0.54
A9: Gridlines: | B9: Signature colour | Q9: #REF! | R9: 1 | S9: 1 | T9: 0.99 | U9: 0.99 | V9: 0.98 | W9: 0.97 | X9: 0.96 | Y9: 0.94 | Z9: 0.92 | AA9: 0.89 | AB9: 0.87 | AC9: 0.85 | AD9: 0.83 | AE9: 0.8 | AF9: 0.78 | AG9: 0.76 | AH9: 0.73 | AI9: 0.71 | AJ9: 0.69 | AK9: 0.67 | AL9: 0.65 | AM9: 0.63 | AN9: 0.62 | AO9: 0.6 | AP9: 0.59 | AQ9: 0.58 | AR9: 0.57 | AS9: 0.56 | AT9: 0.56 | AU9: 0.55 | AV9: 0.55 | AW9: 0.54
B10: Transparency: 90% | Q10: #REF! | R10: 1 | S10: 1 | T10: 0.99 | U10: 0.99 | V10: 0.98 | W10: 0.97 | X10: 0.96 | Y10: 0.94 | Z10: 0.92 | AA10: 0.89 | AB10: 0.87 | AC10: 0.85 | AD10: 0.82 | AE10: 0.8 | AF10: 0.77 | AG10: 0.75 | AH10: 0.73 | AI10: 0.7 | AJ10: 0.68 | AK10: 0.66 | AL10: 0.64 | AM10: 0.61 | AN10: 0.6 | AO10: 0.59 | AP10: 0.58 | AQ10: 0.57 | AR10: 0.56 | AS10: 0.56 | AT10: 0.56 | AU10: 0.55 | AV10: 0.55 | AW10: 0.55
Q11: #REF! | R11: 1 | S11: 1 | T11: 0.99 | U11: 0.99 | V11: 0.98 | W11: 0.97 | X11: 0.96 | Y11: 0.94 | Z11: 0.92 | AA11: 0.89 | AB11: 0.87 | AC11: 0.85 | AD11: 0.82 | AE11: 0.8 | AF11: 0.77 | AG11: 0.75 | AH11: 0.73 | AI11: 0.7 | AJ11: 0.68 | AK11: 0.66 | AL11: 0.64 | AM11: 0.62 | AN11: 0.6 | AO11: 0.59 | AP11: 0.58 | AQ11: 0.57 | AR11: 0.56 | AS11: 0.56 | AT11: 0.56 | AU11: 0.55 | AV11: 0.55 | AW11: 0.55
A12: Lines: | B12: High width: 2.25 pt | Q12: #REF! | R12: #N/A | S12: #N/A | T12: #N/A | U12: #N/A | V12: #N/A | W12: #N/A | X12: #N/A | Y12: #N/A | Z12: #N/A | AA12: #N/A | AB12: #N/A | AC12: #N/A | AD12: #N/A | AE12: #N/A | AF12: #N/A | AG12: #N/A | AH12: #N/A | AI12: #N/A | AJ12: #N/A | AK12: #N/A | AL12: #N/A | AM12: #N/A | AN12: #N/A | AO12: #N/A | AP12: #N/A | AQ12: #N/A | AR12: #N/A | AS12: #N/A | AT12: #N/A | AU12: #N/A | AV12: #N/A | AW12: #N/A
B13: Low width: 0.25 pt | Q13: #REF! | R13: #N/A | S13: #N/A | T13: #N/A | U13: #N/A | V13: #N/A | W13: #N/A | X13: #N/A | Y13: #N/A | Z13: #N/A | AA13: #N/A | AB13: #N/A | AC13: #N/A | AD13: #N/A | AE13: #N/A | AF13: #N/A | AG13: #N/A | AH13: #N/A | AI13: #N/A | AJ13: #N/A | AK13: #N/A | AL13: #N/A | AM13: #N/A | AN13: #N/A | AO13: #N/A | AP13: #N/A | AQ13: #N/A | AR13: #N/A | AS13: #N/A | AT13: #N/A | AU13: #N/A | AV13: #N/A | AW13: #N/A
Q14: #REF! | R14: 1 | S14: 1 | T14: 0.99 | U14: 0.99 | V14: 0.98 | W14: 0.97 | X14: 0.96 | Y14: 0.94 | Z14: 0.92 | AA14: 0.89 | AB14: 0.87 | AC14: 0.85 | AD14: 0.82 | AE14: 0.8 | AF14: 0.78 | AG14: 0.75 | AH14: 0.73 | AI14: 0.71 | AJ14: 0.68 | AK14: 0.66 | AL14: 0.64 | AM14: 0.62 | AN14: 0.61 | AO14: 0.59 | AP14: 0.58 | AQ14: 0.57 | AR14: 0.56 | AS14: 0.56 | AT14: 0.55 | AU14: 0.55 | AV14: 0.55 | AW14: 0.54
A15: Colours: | B15: Primary colour palette | Q15: #REF! | R15: 1 | S15: 1 | T15: 0.99 | U15: 0.99 | V15: 0.98 | W15: 0.97 | X15: 0.96 | Y15: 0.94 | Z15: 0.92 | AA15: 0.89 | AB15: 0.87 | AC15: 0.85 | AD15: 0.82 | AE15: 0.79 | AF15: 0.77 | AG15: 0.74 | AH15: 0.71 | AI15: 0.69 | AJ15: 0.67 | AK15: 0.65 | AL15: 0.62 | AM15: 0.6 | AN15: 0.59 | AO15: 0.58 | AP15: 0.58 | AQ15: 0.57 | AR15: 0.56 | AS15: 0.56 | AT15: 0.55 | AU15: 0.55 | AV15: 0.55 | AW15: 0.55
Q16: #REF! | R16: 1 | S16: 1.01 | T16: 0.99 | U16: 0.98 | V16: 0.97 | W16: 0.95 | X16: 0.94 | Y16: 0.93 | Z16: 0.91 | AA16: 0.9 | AB16: 0.89 | AC16: 0.87 | AD16: 0.86 | AE16: 0.85 | AF16: 0.83 | AG16: 0.82 | AH16: 0.8 | AI16: 0.79 | AJ16: 0.78 | AK16: 0.77 | AL16: 0.76 | AM16: 0.75 | AN16: 0.75 | AO16: 0.75 | AP16: 0.75 | AQ16: 0.75 | AR16: 0.75 | AS16: 0.76 | AT16: 0.76 | AU16: 0.76 | AV16: 0.76 | AW16: 0.77
Q17: #REF! | R17: #N/A | S17: #N/A | T17: #N/A | U17: #N/A | V17: #N/A | W17: #N/A | X17: #N/A | Y17: #N/A | Z17: #N/A | AA17: #N/A | AB17: #N/A | AC17: #N/A | AD17: #N/A | AE17: #N/A | AF17: #N/A | AG17: #N/A | AH17: #N/A | AI17: #N/A | AJ17: #N/A | AK17: #N/A | AL17: #N/A | AM17: #N/A | AN17: #N/A | AO17: #N/A | AP17: #N/A | AQ17: #N/A | AR17: #N/A | AS17: #N/A | AT17: #N/A | AU17: #N/A | AV17: #N/A | AW17: #N/A
Q18: #REF! | R18: 1 | S18: 1 | T18: 0.99 | U18: 0.99 | V18: 0.98 | W18: 0.97 | X18: 0.96 | Y18: 0.94 | Z18: 0.92 | AA18: 0.89 | AB18: 0.87 | AC18: 0.85 | AD18: 0.82 | AE18: 0.8 | AF18: 0.77 | AG18: 0.75 | AH18: 0.72 | AI18: 0.7 | AJ18: 0.68 | AK18: 0.66 | AL18: 0.64 | AM18: 0.61 | AN18: 0.6 | AO18: 0.59 | AP18: 0.58 | AQ18: 0.57 | AR18: 0.56 | AS18: 0.56 | AT18: 0.55 | AU18: 0.55 | AV18: 0.55 | AW18: 0.54
B19: Primary colour palette | Q19: #REF! | R19: 1 | S19: 1 | T19: 0.99 | U19: 0.99 | V19: 0.98 | W19: 0.97 | X19: 0.96 | Y19: 0.94 | Z19: 0.92 | AA19: 0.89 | AB19: 0.87 | AC19: 0.85 | AD19: 0.82 | AE19: 0.8 | AF19: 0.77 | AG19: 0.75 | AH19: 0.72 | AI19: 0.7 | AJ19: 0.68 | AK19: 0.66 | AL19: 0.64 | AM19: 0.61 | AN19: 0.6 | AO19: 0.59 | AP19: 0.58 | AQ19: 0.57 | AR19: 0.56 | AS19: 0.56 | AT19: 0.56 | AU19: 0.55 | AV19: 0.55 | AW19: 0.54
Q20: #REF! | R20: #N/A | S20: #N/A | T20: #N/A | U20: #N/A | V20: #N/A | W20: #N/A | X20: #N/A | Y20: #N/A | Z20: #N/A | AA20: #N/A | AB20: #N/A | AC20: #N/A | AD20: #N/A | AE20: #N/A | AF20: #N/A | AG20: #N/A | AH20: #N/A | AI20: #N/A | AJ20: #N/A | AK20: #N/A | AL20: #N/A | AM20: #N/A | AN20: #N/A | AO20: #N/A | AP20: #N/A | AQ20: #N/A | AR20: #N/A | AS20: #N/A | AT20: #N/A | AU20: #N/A | AV20: #N/A | AW20: #N/A
B21: Primary colour palette | Q21: #REF! | R21: #N/A | S21: #N/A | T21: #N/A | U21: #N/A | V21: #N/A | W21: #N/A | X21: #N/A | Y21: #N/A | Z21: #N/A | AA21: #N/A | AB21: #N/A | AC21: #N/A | AD21: #N/A | AE21: #N/A | AF21: #N/A | AG21: #N/A | AH21: #N/A | AI21: #N/A | AJ21: #N/A | AK21: #N/A | AL21: #N/A | AM21: #N/A | AN21: #N/A | AO21: #N/A | AP21: #N/A | AQ21: #N/A | AR21: #N/A | AS21: #N/A | AT21: #N/A | AU21: #N/A | AV21: #N/A | AW21: #N/A
Q22: #REF! | R22: 1 | S22: 1 | T22: 0.99 | U22: 0.98 | V22: 0.98 | W22: 0.97 | X22: 0.96 | Y22: 0.94 | Z22: 0.92 | AA22: 0.89 | AB22: 0.87 | AC22: 0.85 | AD22: 0.82 | AE22: 0.8 | AF22: 0.77 | AG22: 0.75 | AH22: 0.73 | AI22: 0.7 | AJ22: 0.68 | AK22: 0.66 | AL22: 0.64 | AM22: 0.62 | AN22: 0.6 | AO22: 0.59 | AP22: 0.58 | AQ22: 0.57 | AR22: 0.56 | AS22: 0.56 | AT22: 0.55 | AU22: 0.55 | AV22: 0.54 | AW22: 0.54
Q23: #REF! | R23: 1 | S23: 1 | T23: 0.99 | U23: 0.99 | V23: 0.98 | W23: 0.97 | X23: 0.96 | Y23: 0.94 | Z23: 0.92 | AA23: 0.89 | AB23: 0.87 | AC23: 0.84 | AD23: 0.82 | AE23: 0.79 | AF23: 0.77 | AG23: 0.74 | AH23: 0.71 | AI23: 0.69 | AJ23: 0.67 | AK23: 0.65 | AL23: 0.63 | AM23: 0.6 | AN23: 0.6 | AO23: 0.59 | AP23: 0.58 | AQ23: 0.57 | AR23: 0.56 | AS23: 0.56 | AT23: 0.56 | AU23: 0.55 | AV23: 0.55 | AW23: 0.55
B24: Primary colour palette | Q24: #REF! | R24: #N/A | S24: #N/A | T24: #N/A | U24: #N/A | V24: #N/A | W24: #N/A | X24: #N/A | Y24: #N/A | Z24: #N/A | AA24: #N/A | AB24: #N/A | AC24: #N/A | AD24: #N/A | AE24: #N/A | AF24: #N/A | AG24: #N/A | AH24: #N/A | AI24: #N/A | AJ24: #N/A | AK24: #N/A | AL24: #N/A | AM24: #N/A | AN24: #N/A | AO24: #N/A | AP24: #N/A | AQ24: #N/A | AR24: #N/A | AS24: #N/A | AT24: #N/A | AU24: #N/A | AV24: #N/A | AW24: #N/A
Q25: #REF! | R25: 1 | S25: 1 | T25: 0.99 | U25: 0.99 | V25: 0.98 | W25: 0.97 | X25: 0.96 | Y25: 0.94 | Z25: 0.92 | AA25: 0.89 | AB25: 0.87 | AC25: 0.85 | AD25: 0.83 | AE25: 0.81 | AF25: 0.8 | AG25: 0.78 | AH25: 0.76 | AI25: 0.74 | AJ25: 0.72 | AK25: 0.7 | AL25: 0.68 | AM25: 0.66 | AN25: 0.65 | AO25: 0.64 | AP25: 0.63 | AQ25: 0.62 | AR25: 0.61 | AS25: 0.61 | AT25: 0.61 | AU25: 0.61 | AV25: 0.61 | AW25: 0.6
E26: Full page width: | Q26: #REF! | R26: 1 | S26: 1 | T26: 0.99 | U26: 0.99 | V26: 0.98 | W26: 0.97 | X26: 0.96 | Y26: 0.94 | Z26: 0.92 | AA26: 0.89 | AB26: 0.87 | AC26: 0.85 | AD26: 0.83 | AE26: 0.81 | AF26: 0.8 | AG26: 0.78 | AH26: 0.76 | AI26: 0.74 | AJ26: 0.72 | AK26: 0.7 | AL26: 0.68 | AM26: 0.66 | AN26: 0.65 | AO26: 0.64 | AP26: 0.63 | AQ26: 0.62 | AR26: 0.61 | AS26: 0.61 | AT26: 0.61 | AU26: 0.61 | AV26: 0.61 | AW26: 0.6
Q27: #REF! | R27: 1 | S27: 1.01 | T27: 0.99 | U27: 0.98 | V27: 0.96 | W27: 0.95 | X27: 0.94 | Y27: 0.92 | Z27: 0.91 | AA27: 0.89 | AB27: 0.88 | AC27: 0.87 | AD27: 0.85 | AE27: 0.84 | AF27: 0.82 | AG27: 0.81 | AH27: 0.79 | AI27: 0.78 | AJ27: 0.78 | AK27: 0.77 | AL27: 0.76 | AM27: 0.75 | AN27: 0.75 | AO27: 0.75 | AP27: 0.75 | AQ27: 0.75 | AR27: 0.75 | AS27: 0.75 | AT27: 0.75 | AU27: 0.76 | AV27: 0.76 | AW27: 0.76
Q28: #REF! | R28: #N/A | S28: #N/A | T28: #N/A | U28: #N/A | V28: #N/A | W28: #N/A | X28: #N/A | Y28: #N/A | Z28: #N/A | AA28: #N/A | AB28: #N/A | AC28: #N/A | AD28: #N/A | AE28: #N/A | AF28: #N/A | AG28: #N/A | AH28: #N/A | AI28: #N/A | AJ28: #N/A | AK28: #N/A | AL28: #N/A | AM28: #N/A | AN28: #N/A | AO28: #N/A | AP28: #N/A | AQ28: #N/A | AR28: #N/A | AS28: #N/A | AT28: #N/A | AU28: #N/A | AV28: #N/A | AW28: #N/A
Q29: #REF! | R29: #N/A | S29: #N/A | T29: #N/A | U29: #N/A | V29: #N/A | W29: #N/A | X29: #N/A | Y29: #N/A | Z29: #N/A | AA29: #N/A | AB29: #N/A | AC29: #N/A | AD29: #N/A | AE29: #N/A | AF29: #N/A | AG29: #N/A | AH29: #N/A | AI29: #N/A | AJ29: #N/A | AK29: #N/A | AL29: #N/A | AM29: #N/A | AN29: #N/A | AO29: #N/A | AP29: #N/A | AQ29: #N/A | AR29: #N/A | AS29: #N/A | AT29: #N/A | AU29: #N/A | AV29: #N/A | AW29: #N/A
Q30: #REF! | R30: 1 | S30: 1 | T30: 0.99 | U30: 0.99 | V30: 0.98 | W30: 0.97 | X30: 0.96 | Y30: 0.94 | Z30: 0.92 | AA30: 0.89 | AB30: 0.87 | AC30: 0.85 | AD30: 0.83 | AE30: 0.81 | AF30: 0.8 | AG30: 0.78 | AH30: 0.76 | AI30: 0.74 | AJ30: 0.72 | AK30: 0.7 | AL30: 0.68 | AM30: 0.65 | AN30: 0.65 | AO30: 0.64 | AP30: 0.63 | AQ30: 0.62 | AR30: 0.61 | AS30: 0.61 | AT30: 0.6 | AU30: 0.6 | AV30: 0.6 | AW30: 0.59
A31: Title and | B31: In Word document | Q31: #REF! | R31: 1 | S31: 1 | T31: 0.99 | U31: 0.99 | V31: 0.98 | W31: 0.97 | X31: 0.96 | Y31: 0.94 | Z31: 0.92 | AA31: 0.89 | AB31: 0.87 | AC31: 0.85 | AD31: 0.83 | AE31: 0.8 | AF31: 0.78 | AG31: 0.76 | AH31: 0.73 | AI31: 0.71 | AJ31: 0.69 | AK31: 0.66 | AL31: 0.64 | AM31: 0.62 | AN31: 0.61 | AO31: 0.6 | AP31: 0.6 | AQ31: 0.59 | AR31: 0.59 | AS31: 0.58 | AT31: 0.58 | AU31: 0.58 | AV31: 0.58 | AW31: 0.58
A32: source: | B32: (only unit on chart) | Q32: #REF! | R32: 1 | S32: 1 | T32: 0.99 | U32: 0.99 | V32: 0.98 | W32: 0.97 | X32: 0.96 | Y32: 0.94 | Z32: 0.92 | AA32: 0.89 | AB32: 0.87 | AC32: 0.85 | AD32: 0.82 | AE32: 0.79 | AF32: 0.76 | AG32: 0.73 | AH32: 0.7 | AI32: 0.68 | AJ32: 0.66 | AK32: 0.64 | AL32: 0.62 | AM32: 0.6 | AN32: 0.6 | AO32: 0.6 | AP32: 0.59 | AQ32: 0.59 | AR32: 0.59 | AS32: 0.59 | AT32: 0.59 | AU32: 0.6 | AV32: 0.6 | AW32: 0.6
Q33: #REF! | R33: 1 | S33: 1 | T33: 0.99 | U33: 0.99 | V33: 0.98 | W33: 0.97 | X33: 0.97 | Y33: 0.96 | Z33: 0.95 | AA33: 0.94 | AB33: 0.94 | AC33: 0.93 | AD33: 0.92 | AE33: 0.9 | AF33: 0.89 | AG33: 0.88 | AH33: 0.87 | AI33: 0.85 | AJ33: 0.83 | AK33: 0.81 | AL33: 0.8 | AM33: 0.78 | AN33: 0.77 | AO33: 0.76 | AP33: 0.76 | AQ33: 0.75 | AR33: 0.74 | AS33: 0.74 | AT33: 0.73 | AU33: 0.72 | AV33: 0.72 | AW33: 0.71
Q34: #REF! | R34: 1 | S34: 1 | T34: 0.99 | U34: 0.99 | V34: 0.98 | W34: 0.98 | X34: 0.97 | Y34: 0.96 | Z34: 0.95 | AA34: 0.95 | AB34: 0.94 | AC34: 0.93 | AD34: 0.92 | AE34: 0.91 | AF34: 0.9 | AG34: 0.89 | AH34: 0.87 | AI34: 0.86 | AJ34: 0.84 | AK34: 0.82 | AL34: 0.8 | AM34: 0.78 | AN34: 0.78 | AO34: 0.77 | AP34: 0.76 | AQ34: 0.76 | AR34: 0.75 | AS34: 0.74 | AT34: 0.74 | AU34: 0.73 | AV34: 0.72 | AW34: 0.71
Q35: #REF! | R35: 1 | S35: 1 | T35: 0.99 | U35: 0.99 | V35: 0.98 | W35: 0.98 | X35: 0.97 | Y35: 0.97 | Z35: 0.96 | AA35: 0.95 | AB35: 0.95 | AC35: 0.94 | AD35: 0.93 | AE35: 0.92 | AF35: 0.9 | AG35: 0.89 | AH35: 0.88 | AI35: 0.86 | AJ35: 0.85 | AK35: 0.83 | AL35: 0.81 | AM35: 0.79 | AN35: 0.78 | AO35: 0.78 | AP35: 0.77 | AQ35: 0.76 | AR35: 0.75 | AS35: 0.75 | AT35: 0.74 | AU35: 0.73 | AV35: 0.72 | AW35: 0.71
Q36: #REF! | R36: 1 | S36: 1 | T36: 0.99 | U36: 0.99 | V36: 0.98 | W36: 0.97 | X36: 0.97 | Y36: 0.96 | Z36: 0.95 | AA36: 0.94 | AB36: 0.93 | AC36: 0.92 | AD36: 0.91 | AE36: 0.9 | AF36: 0.89 | AG36: 0.88 | AH36: 0.86 | AI36: 0.85 | AJ36: 0.83 | AK36: 0.81 | AL36: 0.79 | AM36: 0.77 | AN36: 0.77 | AO36: 0.76 | AP36: 0.75 | AQ36: 0.75 | AR36: 0.74 | AS36: 0.73 | AT36: 0.73 | AU36: 0.72 | AV36: 0.71 | AW36: 0.71
Q37: #REF! | R37: 1 | S37: 1 | T37: 0.98 | U37: 0.96 | V37: 0.95 | W37: 0.93 | X37: 0.91 | Y37: 0.9 | Z37: 0.89 | AA37: 0.88 | AB37: 0.87 | AC37: 0.86 | AD37: 0.84 | AE37: 0.83 | AF37: 0.82 | AG37: 0.8 | AH37: 0.79 | AI37: 0.77 | AJ37: 0.75 | AK37: 0.72 | AL37: 0.7 | AM37: 0.68 | AN37: 0.67 | AO37: 0.66 | AP37: 0.65 | AQ37: 0.64 | AR37: 0.63 | AS37: 0.63 | AT37: 0.62 | AU37: 0.61 | AV37: 0.61 | AW37: 0.6
Q38: #REF! | R38: 1 | S38: 1 | T38: 0.99 | U38: 0.98 | V38: 0.96 | W38: 0.95 | X38: 0.94 | Y38: 0.92 | Z38: 0.91 | AA38: 0.89 | AB38: 0.88 | AC38: 0.86 | AD38: 0.85 | AE38: 0.83 | AF38: 0.81 | AG38: 0.8 | AH38: 0.78 | AI38: 0.78 | AJ38: 0.77 | AK38: 0.76 | AL38: 0.76 | AM38: 0.75 | AN38: 0.75 | AO38: 0.75 | AP38: 0.75 | AQ38: 0.75 | AR38: 0.75 | AS38: 0.75 | AT38: 0.75 | AU38: 0.75 | AV38: 0.75 | AW38: 0.76
Q39: #REF! | R39: 1 | S39: 0.99 | T39: 0.97 | U39: 0.95 | V39: 0.93 | W39: 0.91 | X39: 0.89 | Y39: 0.88 | Z39: 0.87 | AA39: 0.85 | AB39: 0.84 | AC39: 0.83 | AD39: 0.81 | AE39: 0.79 | AF39: 0.77 | AG39: 0.76 | AH39: 0.74 | AI39: 0.72 | AJ39: 0.71 | AK39: 0.69 | AL39: 0.68 | AM39: 0.66 | AN39: 0.65 | AO39: 0.64 | AP39: 0.64 | AQ39: 0.63 | AR39: 0.62 | AS39: 0.62 | AT39: 0.61 | AU39: 0.61 | AV39: 0.6 | AW39: 0.6
Q40: #REF! | R40: 1 | S40: 1 | T40: 0.99 | U40: 0.97 | V40: 0.96 | W40: 0.95 | X40: 0.94 | Y40: 0.93 | Z40: 0.91 | AA40: 0.9 | AB40: 0.88 | AC40: 0.87 | AD40: 0.85 | AE40: 0.83 | AF40: 0.81 | AG40: 0.79 | AH40: 0.77 | AI40: 0.76 | AJ40: 0.74 | AK40: 0.73 | AL40: 0.71 | AM40: 0.69 | AN40: 0.69 | AO40: 0.68 | AP40: 0.68 | AQ40: 0.68 | AR40: 0.67 | AS40: 0.67 | AT40: 0.67 | AU40: 0.66 | AV40: 0.66 | AW40: 0.66
Q41: #REF! | R41: 1 | S41: 1 | T41: 0.98 | U41: 0.97 | V41: 0.95 | W41: 0.94 | X41: 0.93 | Y41: 0.91 | Z41: 0.88 | AA41: 0.86 | AB41: 0.84 | AC41: 0.82 | AD41: 0.8 | AE41: 0.78 | AF41: 0.75 | AG41: 0.73 | AH41: 0.7 | AI41: 0.68 | AJ41: 0.65 | AK41: 0.63 | AL41: 0.61 | AM41: 0.58 | AN41: 0.57 | AO41: 0.56 | AP41: 0.55 | AQ41: 0.54 | AR41: 0.52 | AS41: 0.52 | AT41: 0.51 | AU41: 0.5 | AV41: 0.49 | AW41: 0.48
Q42: #REF! | R42: 1 | S42: 1 | T42: 0.99 | U42: 0.98 | V42: 0.96 | W42: 0.95 | X42: 0.94 | Y42: 0.93 | Z42: 0.91 | AA42: 0.9 | AB42: 0.88 | AC42: 0.87 | AD42: 0.85 | AE42: 0.83 | AF42: 0.82 | AG42: 0.8 | AH42: 0.78 | AI42: 0.76 | AJ42: 0.75 | AK42: 0.73 | AL42: 0.72 | AM42: 0.7 | AN42: 0.7 | AO42: 0.7 | AP42: 0.69 | AQ42: 0.69 | AR42: 0.68 | AS42: 0.68 | AT42: 0.68 | AU42: 0.68 | AV42: 0.67 | AW42: 0.67
Q43: #REF! | R43: 1 | S43: 1 | T43: 0.99 | U43: 0.97 | V43: 0.96 | W43: 0.95 | X43: 0.94 | Y43: 0.93 | Z43: 0.91 | AA43: 0.9 | AB43: 0.88 | AC43: 0.87 | AD43: 0.85 | AE43: 0.83 | AF43: 0.81 | AG43: 0.8 | AH43: 0.78 | AI43: 0.76 | AJ43: 0.75 | AK43: 0.74 | AL43: 0.73 | AM43: 0.71 | AN43: 0.72 | AO43: 0.72 | AP43: 0.72 | AQ43: 0.72 | AR43: 0.72 | AS43: 0.72 | AT43: 0.72 | AU43: 0.72 | AV43: 0.72 | AW43: 0.72
Q44: #REF! | R44: 1 | S44: 1 | T44: 0.99 | U44: 0.97 | V44: 0.96 | W44: 0.95 | X44: 0.94 | Y44: 0.93 | Z44: 0.91 | AA44: 0.9 | AB44: 0.88 | AC44: 0.87 | AD44: 0.85 | AE44: 0.83 | AF44: 0.81 | AG44: 0.79 | AH44: 0.78 | AI44: 0.76 | AJ44: 0.75 | AK44: 0.73 | AL44: 0.72 | AM44: 0.7 | AN44: 0.7 | AO44: 0.69 | AP44: 0.69 | AQ44: 0.69 | AR44: 0.68 | AS44: 0.68 | AT44: 0.68 | AU44: 0.68 | AV44: 0.68 | AW44: 0.68

Sheet I1. GHG emissions
A1: Graph feed
B2: Source | C2: Unit | D2: 2005 | I2: 2010 | N2: 2015 | S2: 2020 | X2: 2025 | AC2: 2030 | AH2: 2035 | AM2: 2040 | AR2: 2045 | AW2: 2050
A3: Total | B3: EEA GHG data viewer | C3: Mt CO2e | D3: =(D46+D54)/1000 -> 981.27376 | E3: =(E46+E54)/1000 -> 973.78646 | F3: =(F46+F54)/1000 -> 995.61813 | G3: =(G46+G54)/1000 -> 952.33845 | H3: =(H46+H54)/1000 -> 789.42831 | I3: =(I46+I54)/1000 -> 838.81444 | J3: =(J46+J54)/1000 -> 826.15345 | K3: =(K46+K54)/1000 -> 795.67043 | ... U3: =(U46+U54)/1000 -> 691.32881
A4: Total (CO2 only) | B4: EEA GHG data viewer | C4: Mt CO2e | D4: =(D104+D105)/1000 -> 846.23154 | E4: =(E104+E105)/1000 -> 841.93794 | F4: =(F104+F105)/1000 -> 858.35254 | G4: =(G104+G105)/1000 -> 819.45573 | H4: =(H104+H105)/1000 -> 664.81233 | I4: =(I104+I105)/1000 -> 719.5554 | J4: =(J104+J105)/1000 -> 707.40423 | K4: =(K104+K105)/1000 -> 676.08116 | ... U4: =(U104+U105)/1000 -> 605.55116
A5: Iron and steel | B5: EEA GHG data viewer | C5: Mt CO2e | D5: =(D47+D72)/1000 -> 193.15413 | E5: =(E47+E72)/1000 -> 198.50066 | F5: =(F47+F72)/1000 -> 201.86984 | G5: =(G47+G72)/1000 -> 186.83828 | H5: =(H47+H72)/1000 -> 129.57684 | I5: =(I47+I72)/1000 -> 162.13319 | J5: =(J47+J72)/1000 -> 158.78095 | K5: =(K47+K72)/1000 -> 149.00264 | ... T5: =(T47+T72)/1000 -> 147.01485
A6: Chemicals | B6: EEA GHG data viewer | C6: Mt CO2e | D6: =(D49+D60)/1000 -> 194.703 | E6: =(E49+E60)/1000 -> 181.20545 | F6: =(F49+F60)/1000 -> 182.77373 | G6: =(G49+G60)/1000 -> 171.13872 | H6: =(H49+H60)/1000 -> 144.65984 | I6: =(I49+I60)/1000 -> 144.54893 | J6: =(J49+J60)/1000 -> 140.6777 | K6: =(K49+K60)/1000 -> 134.88674 | ... T6: =(T49+T60)/1000 -> 123.86514
A7: Cement | B7: EEA EU ETS data viewer | C7: Mt CO2e | D7: =(D99)/1000 -> 143.41195 | E7: =(E99)/1000 -> 147.15261 | F7: =(F99)/1000 -> 163.11498 | G7: =(G99)/1000 -> 150.48991 | H7: =(H99)/1000 -> 121.31189 | I7: =(I99)/1000 -> 119.34112 | J7: =(J99)/1000 -> 116.97662 | K7: =(K99)/1000 -> 109.89505 | ... T7: =(T99)/1000 -> 110.22327
A8: Other sub-sectors | B8: EEA GHG data viewer | C8: Mt CO2e | D8: =D3-D5-D6-D7 -> 450.00469 | E8: =E3-E5-E6-E7 -> 446.92775 | F8: =F3-F5-F6-F7 -> 447.85958 | G8: =G3-G5-G6-G7 -> 443.87155 | H8: =H3-H5-H6-H7 -> 393.87974 | I8: =I3-I5-I6-I7 -> 412.7912 | J8: =J3-J5-J6-J7 -> 409.71817 | K8: =K3-K5-K6-K7 -> 401.886 | ... T8: =T3-T5-T6-T7 -> 376.37083
A9: linear trajector to benchmarks | B9: linear trajectory | C9: Mt CO2e | U9: 691.32881 | V9: 666.9647 | W9: 642.60059 | X9: 618.23647 | Y9: 593.87236 | Z9: 569.50824 | AA9: 545.14413 | AB9: 520.78002 | AC9: 496.4159 | AD9: 475.47011 | AE9: 454.52431 | AF9: 433.57852 | AG9: 412.63272 | AH9: 391.68693 | AI9: 370.74113 | AJ9: 349.79534 | AK9: 328.84954 | AL9: 307.90375 | AM9: 286.95795 | AN9: 266.01216 | AO9: 245.06636 | AP9: 224.12057 | AQ9: 203.17477 | AR9: 182.22898 | AS9: 161.28318 | AT9: 140.33739 | AU9: 119.39159 | AV9: 98.445795 | AW9: 77.5
A10: linear trajector to benchmarks 2 | B10: linear trajectory | C10: Mt CO2e | U10: 605.55116 | V10: 589.0982 | W10: 572.64524 | X10: 556.19229 | Y10: 539.73933 | Z10: 523.28637 | AA10: 506.83341 | AB10: 490.38045 | AC10: 473.92749 | AD10: 453.60612 | AE10: 433.28474 | AF10: 412.96337 | AG10: 392.64199 | AH10: 372.32062 | AI10: 351.99924 | AJ10: 331.67787 | AK10: 311.35649 | AL10: 291.03512 | AM10: 270.71375 | AN10: 250.39237 | AO10: 230.071 | AP10: 209.74962 | AQ10: 189.42825 | AR10: 169.10687 | AS10: 148.7855 | AT10: 128.46412 | AU10: 108.14275 | AV10: 87.821375 | AW10: 67.5
A11: 2030 benchmark | B11: FF55 MIX | C11: Mt CO2e | AC11: =SUM(AC109:AC113) -> 496.4159
A12: 2030 benchmark (CO2 only) | B12: FF55 MIX | AC12: =AC109+AC110 -> 473.92749
A13: 2050 benchmark | B13: CTP | C13: Mt CO2e | AW13: =E121 -> 77.5
A14: 2050 benchmark (CO2 only) | B14: CTP | C14: Mt CO2e | AW14: =E119+E118 -> 67.5
A15: 2040 advice scenarios (CO2 only) | C15: Mt CO2e | AM15: 129 | AW15: =AW138 -> 21.7077
A16: 2040 advice min | C16: Mt CO2e | AM16: 89 | AW16: =AW137 -> 5.2357
A17: Gross value added (2005=100) | C17: % of 2005 | D17: 100 | E17: 101.541 | F17: 103.794 | G17: 106.502 | H17: 107.121 | I17: 106.463 | J17: 107.861 | K17: 109.731 | L17: 110.792 | M17: 110.972 | N17: 114.084 | O17: 114.141 | P17: 114.224 | Q17: 115.075 | R17: 117.21 | S17: 118.66 | T17: 121.182 | U17: 133.059
A19: Average 2005-2022 | B19: calculated | C19: Mt CO2e | D19: =(U3-D3)/17 -> -17.055585
A20: Average 2017-2021 | B20: calculated | C20: Mt CO2e | D20: =(T3-P3)/4 -> -8.3905015 | G20: Indicator I1
A21: Average 2018-2022 | B21: calculated | C21: Mt CO2e | D21: =AVERAGE(U3-Q3)/4 -> -23.486949
A22: Average 2022-2030 | B22: calculated | C22: Mt CO2e | D22: =(AC9-T3)/9 -> -29.006466
A23: Average 2023-2030 | B23: calculated | C23: Mt CO2e | D23: =(AC9-U3)/8 -> -24.364114
A24: Average 2031-2050 | B24: calculated | C24: Mt CO2e | D24: =AE9-AD9 -> -20.945795
A26: Average 2005-2022 (CO2 only) | B26: calculated | C26: Mt CO2e | D26: =(U4-D4)/17 -> -14.15767
D27: 2005-2021
A28: Iron and steel | D28: =T5/D5-1 -> -0.23887283
A29: chemicals | D29: =T6/D6-1 -> -0.36382521
A30: cement | D30: =T7/D7-1 -> -0.23142196
A31: other subsectors | D31: =T8/D8-1 -> -0.16362909
D40: 473.92749
A43: Historical data
A44: All GHGs
A45: Sector | B45: Source | C45: Unit | D45: 2005 | E45: 2006 | F45: 2007 | G45: 2008 | H45: 2009 | I45: 2010 | J45: 2011 | K45: 2012 | L45: 2013 | M45: 2014 | N45: 2015 | O45: 2016 | P45: 2017 | Q45: 2018 | R45: 2019 | S45: 2020 | T45: 2021 | U45: 2022 (proxy)
A46: 1.A.2 - Manufacturing Industries and Construction | B46: EEA GHG data viewer | C46: kt CO2e | D46: 556523.8 | E46: 546025.34 | F46: 558821.74 | G46: 539298.56 | H46: 447681.17 | I46: 480724.97 | J46: 468688.84 | K46: 450892.56 | L46: 432830.47 | M46: 419987.2 | N46: 428994.7 | O46: 434138.47 | P46: 441345.55 | Q46: 442369.92 | R46: 428579.9 | S46: 412771.88 | T46: 439540.13 | U46: 398202.32
A47: 1.A.2.a - Iron and Steel | B47: EEA GHG data viewer | C47: kt CO2e | D47: 105195.78 | E47: 105786.76 | F47: 113121.87 | G47: 105942.33 | H47: 74338.594 | I47: 93329.779 | J47: 92651.345 | K47: 86978.152 | L47: 81983.505 | M47: 80583.691 | N47: 85620.562 | O47: 82270.658 | P47: 82921.438 | Q47: 82741.115 | R47: 78548.167 | S47: 69669.793 | T47: 79592.435
A48: 1.A.2.b - Non-Ferrous Metals | B48: EEA GHG data viewer | C48: kt CO2e | D48: 11481.897 | E48: 11507.632 | F48: 11589.219 | G48: 11099.26 | H48: 10078.701 | I48: 11058.486 | J48: 10185.994 | K48: 9248.4225 | L48: 8994.9345 | M48: 8471.8817 | N48: 8610.4113 | O48: 8720.0899 | P48: 8900.5287 | Q48: 8614.4304 | R48: 8881.1903 | S48: 8387.0876 | T48: 9496.5356
A49: 1.A.2.c - Chemicals | B49: EEA GHG data viewer | C49: kt CO2e | D49: 84642.992 | E49: 83294.121 | F49: 83946.663 | G49: 83378.025 | H49: 72400.56 | I49: 76266.277 | J49: 74843.112 | K49: 73217.125 | L49: 69690.367 | M49: 64414.16 | N49: 63994.164 | O49: 65140.923 | P49: 67504.683 | Q49: 69772.981 | R49: 65596.111 | S49: 66957.922 | T49: 71819.845
A50: 1.A.2.d - Pulp, Paper and Print | B50: EEA GHG data viewer | C50: kt CO2e | D50: 30831.444 | E50: 30433.125 | F50: 29562.723 | G50: 28226.145 | H50: 26485.725 | I50: 27205.072 | J50: 26138.148 | K50: 25422.207 | L50: 24910.829 | M50: 23365.407 | N50: 23589.919 | O50: 23974.439 | P50: 24024.492 | Q50: 23951.275 | R50: 24727.018 | S50: 22486.315 | T50: 23774.576
A51: 1.A.2.e - Food Processing, Beverages and Tobacco | B51: EEA GHG data viewer | C51: kt CO2e | D51: 45384.168 | E51: 41185.079 | F51: 40457.017 | G51: 38587.184 | H51: 35153.199 | I51: 36444.619 | J51: 34739.926 | K51: 34662.808 | L51: 34953.81 | M51: 34746.389 | N51: 35459.476 | O51: 36002.584 | P51: 36579.36 | Q51: 36786.972 | R51: 36263.172 | S51: 34896.666 | T51: 36843.585
A52: 1.A.2.f - Non-metallic minerals | B52: EEA GHG data viewer | C52: kt CO2e | D52: 125162.75 | E52: 123512.02 | F52: 126165.9 | G52: 121291 | H52: 98848.969 | I52: 99975.673 | J52: 98054.619 | K52: 93107.541 | L52: 83163.865 | M52: 84427.301 | N52: 84249.262 | O52: 86503.771 | P52: 86737.503 | Q52: 88766.998 | R52: 85877.742 | S52: 81701.413 | T52: 84372.779 | AH52: 0
A53: 1.A.2.g - Other Manufacturing Industries and Constructions | B53: EEA GHG data viewer | C53: kt CO2e | D53: 153824.77 | E53: 150306.6 | F53: 153978.35 | G53: 150774.62 | H53: 130375.42 | I53: 136445.06 | J53: 132075.7 | K53: 128256.31 | L53: 129133.16 | M53: 123978.36 | N53: 127470.91 | O53: 131526 | P53: 134677.54 | Q53: 131736.15 | R53: 128686.5 | S53: 128672.68 | T53: 133640.38
A54: 2 - Industrial Processes and Product Use | B54: EEA GHG data viewer | C54: kt CO2e | D54: 424749.96 | E54: 427761.12 | F54: 436796.4 | G54: 413039.89 | H54: 341747.14 | I54: 358089.48 | J54: 357464.61 | K54: 344777.87 | L54: 342701.87 | M54: 349178.2 | N54: 339854.34 | O54: 342081.2 | P54: 349690.55 | Q54: 342906.69 | R54: 331548.23 | S54: 306828.45 | T54: 317933.96 | U54: 293126.49
A55: 2.A - Mineral Industry | B55: EEA GHG data viewer | C55: kt CO2e | D55: 134942.18 | E55: 138917.96 | F55: 143961.06 | G55: 134868.85 | H55: 109190.15 | I55: 110165.24 | J55: 110550.55 | K55: 103993.85 | L55: 99752.675 | M55: 103209.19 | N55: 102195.85 | O55: 101919.32 | P55: 104919.16 | Q55: 106586.53 | R55: 105196.89 | S55: 99134.603 | T55: 104085.64
A56: 2.A.1 - Cement Production | B56: EEA GHG data viewer | C56: kt CO2e | D56: 96018.7 | E56: 98794.539 | F56: 103243.79 | G56: 96063.326 | H56: 78538.56 | I56: 76952.116 | J56: 75694.639 | K56: 71334.584 | L56: 67609.412 | M56: 70798.265 | N56: 70178.383 | O56: 70151.659 | P56: 72298.226 | Q56: 73607.949 | R56: 73556.1 | S56: 70408.308 | T56: 72419.613
A57: 2.A.2 - Lime Production | B57: EEA GHG data viewer | C57: kt CO2e | D57: 21081.137 | E57: 21973.194 | F57: 22578.333 | G57: 21769.583 | H57: 16933.148 | I57: 18809.296 | J57: 19500.991 | K57: 18094.518 | L57: 18227.305 | M57: 18652.193 | N57: 18116.405 | O57: 17813.765 | P57: 18393.393 | Q57: 18587.158 | R57: 17703.413 | S57: 15994.819 | T57: 17728.138
A58: 2.A.3 - Glass production | B58: EEA GHG data viewer | C58: kt CO2e | D58: 4343.1797 | E58: 4406.5475 | F58: 4464.0945 | G58: 4254.7387 | H58: 3671.9851 | I58: 3809.2691 | J58: 3896.171 | K58: 3775.7107 | L58: 3729.2083 | M58: 3786.459 | N58: 3847.0024 | O58: 3848.3739 | P58: 3898.9917 | Q58: 3960.8537 | R58: 3969.1735 | S58: 3771.9716 | T58: 4064.7184
A59: 2.A.4 - Other Process Uses of Carbonates | B59: EEA GHG data viewer | C59: kt CO2e | D59: 13499.166 | E59: 13743.677 | F59: 13674.842 | G59: 12781.202 | H59: 10046.456 | I59: 10594.563 | J59: 11458.749 | K59: 10789.036 | L59: 10186.75 | M59: 9972.2733 | N59: 10054.063 | O59: 10105.526 | P59: 10328.549 | Q59: 10430.574 | R59: 9968.2025 | S59: 8959.5039 | T59: 9873.1652
A60: 2.B - Chemical Industry | B60: EEA GHG data viewer | C60: kt CO2e | D60: 110060 | E60: 97911.331 | F60: 98827.07 | G60: 87760.691 | H60: 72259.282 | I60: 68282.65 | J60: 65834.59 | K60: 61669.619 | L60: 60116.404 | M60: 59311.457 | N60: 58314.234 | O60: 56840.887 | P60: 59945.4 | Q60: 58104.699 | R60: 55714.869 | S60: 53934.677 | T60: 52045.293
A61: 2.B.1 - Ammonia Production | B61: EEA GHG data viewer | C61: kt CO2e | D61: 27471.936 | E61: 24908.708 | F61: 26633.296 | G61: 25609.08 | H61: 20621.732 | I61: 23820.677 | J61: 25570.252 | K61: 24798.435 | L61: 23726.772 | M61: 22178.659 | N61: 21162.754 | O61: 20925.222 | P61: 22124.758 | Q61: 20696.223 | R61: 19943.801 | S61: 20849.998 | T61: 19301.46
A62: 2.B.2 - Nitric Acid Production | B62: EEA GHG data viewer | C62: kt CO2e | D62: 34582.136 | E62: 31334.927 | F62: 29343.94 | G62: 20742.589 | H62: 11308.697 | I62: 9512.9889 | J62: 6857.4486 | K62: 5874.4669 | L62: 4119.8249 | M62: 4110.6006 | N62: 3886.9347 | O62: 3483.7211 | P62: 3192.5253 | Q62: 3009.827 | R62: 2745.454 | S62: 2457.2711 | T62: 2397.6389
A63: 2.B.3 - Adipic Acid Production | B63: EEA GHG data viewer | C63: kt CO2e | D63: 9329.9108 | E63: 5138.2169 | F63: 6857.251 | G63: 6593.3702 | H63: 9205.9403 | I63: 1390.8576 | J63: 686.75533 | K63: 483.44435 | L63: 562.10771 | M63: 389.68569 | N63: 412.5286 | O63: 333.60392 | P63: 966.10455 | Q63: 371.43855 | R63: 283.23687 | S63: 262.60018 | T63: 143.74206
A64: 2.B.4 - Caprolactam, Glyoxal and Glyoxylic Acid Production | B64: EEA GHG data viewer | C64: kt CO2e | D64: 1896.2951 | E64: 1975.5529 | F64: 1893.9514 | G64: 1731.9042 | H64: 1936.3605 | I64: 2055.8253 | J64: 2210.6922 | K64: 2159.0709 | L64: 2019.2773 | M64: 1996.3453 | N64: 1973.2975 | O64: 1727.5531 | P64: 1768.9282 | Q64: 1703.0476 | R64: 1508.0092 | S64: 1267.7138 | T64: 1035.4031
A65: 2.B.5 - Carbide Production | B65: EEA GHG data viewer | C65: kt CO2e | D65: 588.02817 | E65: 567.9231 | F65: 504.82963 | G65: 504.65647 | H65: 414.59987 | I65: 419.17384 | J65: 480.24454 | K65: 374.73799 | L65: 317.22513 | M65: 286.64351 | N65: 254.99888 | O65: 272.04351 | P65: 255.45715 | Q65: 276.95636 | R65: 270.93929 | S65: 220.54927 | T65: 262.11689
A66: 2.B.6 - Titanium Dioxide Production | B66: EEA GHG data viewer | C66: kt CO2e | D66: 40.254924 | E66: 49.921532 | F66: 53.497999 | G66: 50.855124 | H66: 48.290878 | I66: 53.464553 | J66: 55.197428 | K66: 42.108178 | L66: 120.29777 | M66: 122.83436 | N66: 124.7171 | O66: 131.2227 | P66: 136.86152 | Q66: 120.46015 | R66: 120.09837 | S66: 116.57946 | T66: 123.50909
... A84: 2.E.1 - Integrated Circuit or Semiconductor | B84: EEA GHG data viewer | C84: kt CO2e | D84: 1986.168 | E84: 1821.6981 | F84: 1643.0777 | G84: 1477.6182 | H84: 901.95677 | I84: 1038.5999 | J84: 962.50876 | K84: 830.66385 | L84: 740.45248 | M84: 759.27733 | N84: 738.95745 | O84: 778.68894 | P84: 789.17745 | Q84: 760.16238 | R84: 769.11721 | S84: 683.45275 | T84: 742.20341
A85: 2.E.2 - TFT Flat Panel Display | B85: EEA GHG data viewer | C85: kt CO2e
A86: 2.E.3 - Photovoltaics | B86: EEA GHG data viewer | C86: kt CO2e | D86: 22.177697 | E86: 26.118384 | F86: 46.005362 | G86: 96.601282 | H86: 62.317138 | I86: 104.36772 | J86: 63.708661 | K86: 31.321302 | L86: 7.540325 | M86: 5.424734 | N86: 0.240856 | O86: 0.187726 | P86: 0.0109641 | Q86: 0.0255829
A87: 2.E.4 - Heat Transfer Fluid | B87: EEA GHG data viewer | C87: kt CO2e | D87: 24.428297 | E87: 24.471159 | F87: 24.471159 | G87: 24.471159 | H87: 24.471159 | I87: 24.471159 | J87: 24.471159 | K87: 24.471159 | L87: 24.471159 | M87: 24.481008 | N87: 24.430952 | O87: 24.428297 | P87: 24.470113 | Q87: 22.84402 | R87: 23.292115 | S87: 22.505505 | T87: 25.47048
A88: 2.E.5 - Other electronics industry | B88: EEA GHG data viewer | C88: kt CO2e | E88: 4.57076 | F88: 8.1972 | G88: 5.54304 | H88: 9.6558 | I88: 11.1438 | J88: 9.606 | K88: 4.5894 | L88: 3.315 | M88: 4.1744 | P88: 0.97461 | R88: 0.98787
A89: 2.F - Product Uses as Substitutes for ODS | B89: EEA GHG data viewer | C89: kt CO2e | D89: 57702.925 | E89: 65502.762 | F89: 72594.372 | G89: 78356.892 | H89: 80202.468 | I89: 83675.711 | J89: 87589.565 | K89: 90512.53 | L89: 92620.633 | M89: 94592.855 | N89: 86468.982 | O89: 87365.483 | P89: 85767.314 | Q89: 81803.508 | R89: 78104.078 | S89: 73359.015 | T89: 70842.225
A90: 2.F.1 - Refrigeration and Air conditioning | B90: EEA GHG data viewer | C90: kt CO2e | D90: 48762.26 | E90: 56137.874 | F90: 62765.883 | G90: 68857.931 | H90: 71738.814 | I90: 75219.145 | J90: 78831.414 | K90: 81989.114 | L90: 84313.328 | M90: 86276.61 | N90: 78089.99 | O90: 78967.526 | P90: 77266.904 | Q90: 74572.903 | R90: 71756.135 | S90: 67350.967 | T90: 65043.871
A91: 2.F.2 - Foam Blowing Agents | B91: EEA GHG data viewer | C91: kt CO2e | D91: 3560.1018 | E91: 3497.291 | F91: 3810.9305 | G91: 3482.6374 | H91: 2595.4621 | I91: 2555.0921 | J91: 2571.9538 | K91: 2418.0547 | L91: 2269.6099 | M91: 2357.1877 | N91: 2399.9145 | O91: 2435.1399 | P91: 2497.392 | Q91: 2068.2701 | R91: 1828.9243 | S91: 1668.3349 | T91: 1634.5317
A92: 2.F.3 - Fire Protection | B92: EEA GHG data viewer | C92: kt CO2e | D92: 1042.6966 | E92: 1213.3143 | F92: 1372.415 | G92: 1513.5356 | H92: 1719.6052 | I92: 1874.2417 | J92: 2017.1755 | K92: 2121.621 | L92: 2212.7141 | M92: 2268.322 | N92: 2317.4336 | O92: 2357.5221 | P92: 2410.501 | Q92: 2420.1702 | R92: 2403.7241 | S92: 2370.8465 | T92: 2383.2847
A93: 2.F.4 - Aerosols | B93: EEA GHG data viewer | C93: kt CO2e | D93: 4052.0204 | E93: 4365.6026 | F93: 4213.2311 | G93: 4032.4645 | H93: 3756.6236 | I93: 3683.5892 | J93: 3647.0127 | K93: 3462.9274 | L93: 3368.4106 | M93: 3321.9732 | N93: 3329.2983 | O93: 3340.1997 | P93: 3320.9229 | Q93: 2561.007 | R93: 1948.0514 | S93: 1802.4273 | T93: 1619.8323
A94: 2.F.5 - Solvents | B94: EEA GHG data viewer | C94: kt CO2e | D94: 144.86959 | E94: 128.65623 | F94: 209.74634 | G94: 227.85465 | H94: 181.53472 | I94: 152.3628 | J94: 249.00156 | K94: 308.24311 | L94: 275.25643 | M94: 196.576 | N94: 144.23303 | O94: 66.287338 | P94: 64.78476 | Q94: 45.547339 | R94: 33.560718 | S94: 34.607837 | T94: 30.52255
A95: 2.F.6 - Other Applications | B95: EEA GHG data viewer | C95: kt CO2e | D95: 140.97573 | E95: 160.02366 | F95: 222.16653 | G95: 242.4695 | H95: 210.42886 | I95: 191.27989 | J95: 273.00767 | K95: 212.56983 | L95: 181.3139 | M95: 172.18612 | N95: 188.1134 | O95: 198.80805 | P95: 206.8092 | Q95: 135.61034 | R95: 133.68282 | S95: 131.8317 | T95: 130.18244
A96: 2.G - Other Product Manufacture and Use | B96: EEA GHG data viewer | C96: kt CO2e | D96: 8540.8784 | E96: 8676.5483 | F96: 8573.5008 | G96: 8654.6412 | H96: 8571.1884 | I96: 8407.918 | J96: 8385.7355 | K96: 8501.3396 | L96: 8305.266 | M96: 7991.528 | N96: 8262.4102 | O96: 8546.9962 | P96: 8822.9682 | Q96: 9078.3062 | R96: 9224.8452 | S96: 8144.0543 | T96: 7473.034
A97: 2.H - Other Industrial Process and Product Use | B97: EEA GHG data viewer | C97: kt CO2e | D97: 602.18685 | E97: 665.14962 | F97: 617.61549 | G97: 590.07388 | H97: 533.57462 | I97: 507.30221 | J97: 422.65504 | K97: 454.19515 | L97: 461.77676 | M97: 384.90183 | N97: 378.04745 | O97: 316.94268 | P97: 354.15011 | Q97: 351.92001 | R97: 373.68444 | S97: 303.43289 | T97: 332.67855
A99: Cement | B99: EEA EU ETS data viewer | C99: kt CO2e | D99: ='[1]Sheet 1'!C4/1000 -> 143411.95 | E99: ='[1]Sheet 1'!D4/1000 -> 147152.61 | F99: ='[1]Sheet 1'!E4/1000 -> 163114.98 | G99: ='[1]Sheet 1'!F4/1000 -> 150489.91 | H99: ='[1]Sheet 1'!G4/1000 -> 121311.89 | I99: ='[1]Sheet 1'!H4/1000 -> 119341.12 | J99: ='[1]Sheet 1'!I4/1000 -> 116976.62 | K99: ='[1]Sheet 1'!J4/1000 -> 109895.05 | ... U99: ='[1]Sheet 1'!T4/1000 -> 102239.74
A100: Lime | B100: EEA EU ETS data viewer | C100: kt CO2e | D100: ='[1]Sheet 1'!U4/1000 -> 31876.89 | E100: ='[1]Sheet 1'!V4/1000 -> 31567.279 | F100: ='[1]Sheet 1'!W4/1000 -> 33124.661 | G100: ='[1]Sheet 1'!X4/1000 -> 32120.333 | H100: ='[1]Sheet 1'!Y4/1000 -> 25718.958 | I100: ='[1]Sheet 1'!Z4/1000 -> 28450.774 | J100: ='[1]Sheet 1'!AA4/1000 -> 29433.932 | K100: ='[1]Sheet 1'!AB4/1000 -> 27603.986 | ... U100: ='[1]Sheet 1'!AL4/1000 -> 25196.237
A102: CO2 only
A103: Sector | B103: Source | C103: Unit | D103: 2005 | E103: 2006 | F103: 2007 | G103: 2008 | H103: 2009 | I103: 2010 | J103: 2011 | K103: 2012 | L103: 2013 | M103: 2014 | N103: 2015 | O103: 2016 | P103: 2017 | Q103: 2018 | R103: 2019 | S103: 2020 | T103: 2021 | U103: 2022 (proxy)
A104: 1.A.2 - Manufacturing Industries and Construction | B104: EEA GHG data viewer | C104: kt CO2 | D104: 550116.01 | E104: 540008.08 | F104: 552705.2 | G104: 533271.35 | H104: 442529.16 | I104: 475272.04 | J104: 463198.32 | K104: 445486.84 | L104: 427419.06 | M104: 414786.88 | N104: 423568.77 | O104: 428740.22 | P104: 435805.45 | Q104: 436657.27 | R104: 422971.59 | S104: 407337.38 | T104: 433739.78 | U104: 392416.82
A105: 2 - Industrial Processes and Product Use | B105: EEA GHG data viewer | C105: kt CO2 | D105: 296115.53 | E105: 301929.86 | F105: 305647.34 | G105: 286184.38 | H105: 222283.17 | I105: 244283.37 | J105: 244205.9 | K105: 230594.32 | L105: 228472.08 | M105: 233750.38 | N105: 232302.01 | O105: 233791.61 | P105: 242545.17 | Q105: 239998.24 | R105: 233662.81 | S105: 216476.79 | T105: 231737.37 | U105: 213134.34
A107: 2030 benchmark
B108: Source | C108: Unit | D108: 2005 | I108: 2010 | N108: 2015 | S108: 2020 | X108: 2025 | AC108: 2030 | AH108: 2035 | AM108: 2040 | AR108: 2045 | AW108: 2050
A109: industry energy CO2 | B109: FF55 MIX | C109: Mt CO2e | AC109: 237.81152
A110: industry other CO2 | B110: FF55 MIX | C110: Mt CO2e | AC110: 236.11597
A111: industry non-CO2 | B111: FF55 MIX | C111: Mt CO2e | AC111: 7.5930223
A112: AC and refrigerator non-CO2 | B112: FF55 MIX | C112: Mt CO2e | AC112: 9.0558653
A113: Other sectors | B113: FF55 MIX | C113: Mt CO2e | AC113: 5.8395234
A116: 2050 benchmarks | K116: 2015 Baseline (for consistency check
D117: CTP REG | E117: CTP MIX | F117: CTP CPRICE | M117: CTP
A118: industry energy CO2 only | B118: CTP IA figure 65 | D118: 40.3 | E118: 38 | F118: 34.4 | G118: CTP IA figure 65 | M118: =SUM('[2]Fig 65'!$B$5:$B$14) -> 453.1117
A119: industry CO2 process | B119: CTP IA figure 65 | D119: 44.5 | E119: 29.5 | F119: 20.1 | G119: CTP IA figure 65 | M119: ='[2]Fig 65'!$B$4 -> 267.75123
A120: industry non-CO2 | B120: CTP IA figure 9 | D120: 10 | E120: 10 | F120: 10 | G120: CTP IA figure 9 | M120: ='[2]Fig 9'!$B$7 -> 36
A121: total | D121: =D120+D119+D118 -> 94.8 | E121: =E120+E119+E118 -> 77.5 | F121: =F120+F119+F118 -> 64.5 | K121: =SUM(K118:K120) -> 0 | L121: =SUM(L118:L120) -> 0 | M121: =SUM(M118:M120) -> 756.86293
D122: =D121/$D$3-1 -> -0.90339087 | E122: =E121/$D$3-1 -> -0.92102102 | F122: =F121/$D$3-1 -> -0.93426911
A124: ACP4A data | D124: 2005 | E124: 2050 1.5LIFE | F124: 2050 1.5TECH
A125: Industry CO2 | B125: In depth analysis figure 90 and 91 | D125: 846 | E125: =99.9*89% -> 88.911 | F125: =109.8*89% -> 97.722
E126: =E125/D125-1 -> -0.89490426 | F126: =F125/D125-1 -> -0.88448936
A128: EU27 share
N129: 2015
A130: EU27 | N130: =N3 -> 768.84905
A131: UK | N131: 87.257
A132: EU28 | N132: =N130+N131 -> 856.10605
A133: EU27 share | N133: =N130/N132 -> 0.89807688
A135: 2040 advice modelling
A136: Minimum and maximum of 2040 range within environmental risk & challenge levels
A137: Min | N137: =[3]Industry!AA$24 -> 760.8829 | S137: =[3]Industry!AF$24 -> 715.6107 | X137: =[3]Industry!AK$24 -> 639.7804 | AC137: =[3]Industry!AP$24 -> 455.4076 | AH137: =[3]Industry!AU$24 -> 239.4605 | AM137: =[3]Industry!AZ$24 -> 88.5697 | AR137: =[3]Industry!BE$24 -> 18.9987 | AW137: =[3]Industry!BJ$24 -> 5.2357
...

Sheet Figure 21. emissions profile
A1: Sector 1 | B1: Source | C1: 2019 (kt CO2e) | D1: 2019 (Mt CO2e) | E1: 2021 (kt CO2e) | F1: 2021 (Mt CO2e) | G1: Sector 2 | H1: Sector 3 | J1: Row Labels | K1: Sum of 2019 (Mt CO2e) | L1: Sum of 2021 (Mt CO2e) | O1: Row Labels | P1: Sum of 2021 (Mt CO2e)
A2: 1.A.2 - Manufacturing Industries and Construction | B2: EEA GHG data viewer | C2: 428579.9 | D2: =C2/1000 -> 428.5799 | E2: 439540.13 | F2: =E2/1000 -> 439.54013 | G2: aggregate | H2: aggregate | J2: cement and lime | K2: 145.17591 | L2: 118.74314 | O2: Iron and steel | P2: 147.01485
A3: 1.A.2.a - Iron and Steel | B3: EEA GHG data viewer | C3: 78548.167 | D3: =C3/1000 -> 78.548167 | E3: 79592.435 | F3: =E3/1000 -> 79.592435 | G3: Iron and steel | H3: iron and steel | J3: Chemicals | K3: 121.31098 | L3: 123.86514 | O3: Chemicals | P3: 123.86514
A4: 1.A.2.b - Non-Ferrous Metals | B4: EEA GHG data viewer | C4: 8881.1903 | D4: =C4/1000 -> 8.8811903 | E4: 9496.5356 | F4: =E4/1000 -> 9.4965356 | G4: other | H4: other ferrous and non-ferrous | J4: Iron and steel | K4: 145.36342 | L4: 147.01485 | O4: Cement | P4: =F57 -> 93.596201
A5: 1.A.2.c - Chemicals | B5: EEA GHG data viewer | C5: 65596.111 | D5: =C5/1000 -> 65.596111 | E5: 71819.845 | F5: =E5/1000 -> 71.819845 | G5: Chemicals | H5: chemicals | J5: other | K5: 348.27782 | L5: 367.85096 | O5: other | P5: =GETPIVOTDATA("Sum of 2021 (Mt CO2e)",$J$1)-P4-P3-P2 -> 392.9979
A6: 1.A.2.d - Pulp, Paper and Print | B6: EEA GHG data viewer | C6: 24727.018 | D6: =C6/1000 -> 24.727018 | E6: 23774.576 | F6: =E6/1000 -> 23.774576 | G6: other | H6: pulp and paper | J6: Grand Total | K6: 760.12813 | L6: 757.47409
A7: 1.A.2.e - Food Processing, Beverages and Tobacco | B7: EEA GHG data viewer | C7: 36263.172 | D7: =C7/1000 -> 36.263172 | E7: 36843.585 | F7: =E7/1000 -> 36.843585 | G7: other | H7: food, beverages and tobacco
A8: 1.A.2.f - Non-metallic minerals | B8: EEA GHG data viewer | C8: 85877.742 | D8: =C8/1000 -> 85.877742 | E8: 84372.779 | F8: =E8/1000 -> 84.372779 | G8: aggregate | H8: aggregate
A9: - of which cement and lime | C9: =C57+C58-C14-C15 -> 53916.4 | D9: =C9/1000 -> 53.9164 | E9: =E57+E58-E14-E15 -> 28595.393 | F9: =E9/1000 -> 28.595393 | G9: cement and lime | H9: cement and lime
A10: - of which other non-metalic minerals | C10: =C8-C9 -> 31961.341 | D10: =C10/1000 -> 31.961341 | E10: =E8-E9 -> 55777.385 | F10: =E10/1000 -> 55.777385 | G10: other | H10: other non-metalic minerals
A11: 1.A.2.g - Other Manufacturing Industries and Constructions | B11: EEA GHG data viewer | C11: 128686.5 | D11: =C11/1000 -> 128.6865 | E11: 133640.38 | F11: =E11/1000 -> 133.64038 | G11: other | H11: other
A12: 2 - Industrial Processes and Product Use | B12: EEA GHG data viewer | C12: 331548.23 | D12: =C12/1000 -> 331.54823 | E12: 317933.96 | F12: =E12/1000 -> 317.93396 | G12: aggregate | H12: aggregate
A13: 2.A - Mineral Industry | B13: EEA GHG data viewer | C13: 105196.89 | D13: =C13/1000 -> 105.19689 | E13: 104085.64 | F13: =E13/1000 -> 104.08564 | G13: aggregate | H13: aggregate
A14: 2.A.1 - Cement Production | B14: EEA GHG data viewer | C14: 73556.1 | D14: =C14/1000 -> 73.5561 | E14: 72419.613 | F14: =E14/1000 -> 72.419613 | G14: cement and lime | H14: cement
A15: 2.A.2 - Lime Production | B15: EEA GHG data viewer | C15: 17703.413 | D15: =C15/1000 -> 17.703413 | E15: 17728.138 | F15: =E15/1000 -> 17.728138 | G15: cement and lime | H15: other non-metalic minerals
A16: 2.A.3 - Glass production | B16: EEA GHG data viewer | C16: 3969.1735 | D16: =C16/1000 -> 3.9691735 | E16: 4064.7184 | F16: =E16/1000 -> 4.0647184 | G16: other | H16: other non-metalic minerals
A17: 2.A.4 - Other Process Uses of Carbonates | B17: EEA GHG data viewer | C17: 9968.2025 | D17: =C17/1000 -> 9.9682025 | E17: 9873.1652 | F17: =E17/1000 -> 9.8731652 | G17: other | H17: other non-metalic minerals
A18: 2.B - Chemical Industry | B18: EEA GHG data viewer | C18: 55714.869 | D18: =C18/1000 -> 55.714869 | E18: 52045.293 | F18: =E18/1000 -> 52.045293 | G18: aggregate | H18: aggregate
A19: 2.B.1 - Ammonia Production | B19: EEA GHG data viewer | C19: 19943.801 | D19: =C19/1000 -> 19.943801 | E19: 19301.46 | F19: =E19/1000 -> 19.30146 | G19: Chemicals | H19: chemicals | K19: industrial GHG emissions in 2021 per sub-sector (in Mt CO2e. and % of total)
A20: 2.B.2 - Nitric Acid Production | B20: EEA GHG data viewer | C20: 2745.454 | D20: =C20/1000 -> 2.745454 | E20: 2397.6389 | F20: =E20/1000 -> 2.3976389 | G20: Chemicals | H20: chemicals
A21: 2.B.3 - Adipic Acid Production | B21: EEA GHG data viewer | C21: 283.23687 | D21: =C21/1000 -> 0.28323687 | E21: 143.74206 | F21: =E21/1000 -> 0.14374206 | G21: Chemicals | H21: chemicals
A22: 2.B.4 - Caprolactam, Glyoxal and Glyoxylic Acid Production | B22: EEA GHG data viewer | C22: 1508.0092 | D22: =C22/1000 -> 1.5080092 | E22: 1035.4031 | F22: =E22/1000 -> 1.0354031 | G22: Chemicals | H22: chemicals
A23: 2.B.5 - Carbide Production | B23: EEA GHG data viewer | C23: 270.93929 | D23: =C23/1000 -> 0.27093929 | E23: 262.11689 | F23: =E23/1000 -> 0.26211689 | G23: Chemicals | H23: chemicals
A24: 2.B.6 - Titanium Dioxide Production | B24: EEA GHG data viewer | C24: 120.09837 | D24: =C24/1000 -> 0.12009837 | E24: 123.50909 | F24: =E24/1000 -> 0.12350909 | G24: Chemicals | H24: chemicals
A25: 2.B.7 - Soda Ash Production | B25: EEA GHG data viewer | C25: 1948.8551 | D25: =C25/1000 -> 1.9488551 | E25: 1832.151 | F25: =E25/1000 -> 1.832151 | G25: Chemicals | H25: chemicals
A26: 2.B.8 - Petrochemical and Carbon Black Production | B26: EEA GHG data viewer | C26: 12895.284 | D26: =C26/1000 -> 12.895284 | E26: 13207.577 | F26: =E26/1000 -> 13.207577 | G26: Chemicals | H26: chemicals
A27: 2.B.9 - Fluorochemical Production | B27: EEA GHG data viewer | C27: 2662.625 | D27: =C27/1000 -> 2.662625 | E27: 1051.1049 | F27: =E27/1000 -> 1.0511049 | G27: Chemicals | H27: chemicals
A28: 2.B.10 - Other chemical industry | B28: EEA GHG data viewer | C28: 13336.567 | D28: =C28/1000 -> 13.336567 | E28: 12690.59 | F28: =E28/1000 -> 12.69059 | G28: Chemicals | H28: chemicals
A29: 2.C - Metal Industry | B29: EEA GHG data viewer | C29: 74906.841 | D29: =C29/1000 -> 74.906841 | E29: 74664.268 | F29: =E29/1000 -> 74.664268 | G29: aggregate | H29: aggregate
A30: 2.C.1 - Iron and Steel Production | B30: EEA GHG data viewer | C30: 66815.25 | D30: =C30/1000 -> 66.81525 | E30: 67422.42 | F30: =E30/1000 -> 67.42242 | G30: Iron and steel | H30: Iron and steel
A31: 2.C.2 - Ferroalloys Production | B31: EEA GHG data viewer | C31: 2609.3178 | D31: =C31/1000 -> 2.6093178 | E31: 2189.1354 | F31: =E31/1000 -> 2.1891354 | G31: other | H31: other ferrous and non-ferrous
... A42: 2.E.1 - Integrated Circuit or Semiconductor | B42: EEA GHG data viewer | C42: 769.11721 | D42: =C42/1000 -> 0.76911721 | E42: 742.20341 | F42: =E42/1000 -> 0.74220341 | G42: other | H42: other
A43: 2.E.2 - TFT Flat Panel Display | B43: EEA GHG data viewer | D43: =C43/1000 -> 0 | F43: =E43/1000 -> 0 | G43: other | H43: other
A44: 2.E.3 - Photovoltaics | B44: EEA GHG data viewer | D44: =C44/1000 -> 0 | F44: =E44/1000 -> 0 | G44: other | H44: other
A45: 2.E.4 - Heat Transfer Fluid | B45: EEA GHG data viewer | C45: 23.292115 | D45: =C45/1000 -> 0.023292115 | E45: 25.47048 | F45: =E45/1000 -> 0.02547048 | G45: other | H45: other
A46: 2.E.5 - Other electronics industry | B46: EEA GHG data viewer | C46: 0.98787 | D46: =C46/1000 -> 0.00098787 | F46: =E46/1000 -> 0 | G46: other | H46: other
A47: 2.F - Product Uses as Substitutes for ODS | B47: EEA GHG data viewer | C47: 78104.078 | D47: =C47/1000 -> 78.104078 | E47: 70842.225 | F47: =E47/1000 -> 70.842225 | G47: aggregate | H47: aggregate
A48: 2.F.1 - Refrigeration and Air conditioning | B48: EEA GHG data viewer | C48: 71756.135 | D48: =C48/1000 -> 71.756135 | E48: 65043.871 | F48: =E48/1000 -> 65.043871 | G48: other | H48: F-gases
A49: 2.F.2 - Foam Blowing Agents | B49: EEA GHG data viewer | C49: 1828.9243 | D49: =C49/1000 -> 1.8289243 | E49: 1634.5317 | F49: =E49/1000 -> 1.6345317 | G49: other | H49: F-gases
A50: 2.F.3 - Fire Protection | B50: EEA GHG data viewer | C50: 2403.7241 | D50: =C50/1000 -> 2.4037241 | E50: 2383.2847 | F50: =E50/1000 -> 2.3832847 | G50: other | H50: F-gases
A51: 2.F.4 - Aerosols | B51: EEA GHG data viewer | C51: 1948.0514 | D51: =C51/1000 -> 1.9480514 | E51: 1619.8323 | F51: =E51/1000 -> 1.6198323 | G51: other | H51: F-gases
A52: 2.F.5 - Solvents | B52: EEA GHG data viewer | C52: 33.560718 | D52: =C52/1000 -> 0.033560718 | E52: 30.52255 | F52: =E52/1000 -> 0.03052255 | G52: other | H52: F-gases
A53: 2.F.6 - Other Applications | B53: EEA GHG data viewer | C53: 133.68282 | D53: =C53/1000 -> 0.13368282 | E53: 130.18244 | F53: =E53/1000 -> 0.13018244 | G53: other | H53: F-gases
A54: 2.G - Other Product Manufacture and Use | B54: EEA GHG data viewer | C54: 9224.8452 | D54: =C54/1000 -> 9.2248452 | E54: 7473.034 | F54: =E54/1000 -> 7.473034 | G54: other | H54: other
A55: 2.H - Other Industrial Process and Product Use | B55: EEA GHG data viewer | C55: 373.68444 | D55: =C55/1000 -> 0.37368444 | E55: 332.67855 | F55: =E55/1000 -> 0.33267855 | G55: other | H55: other
A57: Production of cement clinker | B57: ETS verified emissions (activity code 29) | C57: 117336.48 | D57: =C57/1000 -> 117.33648 | E57: 93596.201 | F57: =E57/1000 -> 93.596201
A58: Production of lime or calcination of dolomite/magnestie | B58: ETS verified emissions (activity code 30) | C58: 27839.431 | D58: =C58/1000 -> 27.839431 | E58: 25146.944 | F58: =E58/1000 -> 25.146944
A59: Manufacture of glass | B59: ETS verified emissions (activity code 31) | C59: 17368.035 | D59: =C59/1000 -> 17.368035 | E59: 13327.251 | F59: =E59/1000 -> 13.327251
A60: manufacture of ceramics | B60: ETS verified emissions (activity code 32) | C60: 13910.4 | D60: =C60/1000 -> 13.9104 | E60: 11817.824 | F60: =E60/1000 -> 11.817824
A61: Manufacture of mineral wool | B61: ETS verified emissions (activity code 33) | C61: 2009.386 | D61: =C61/1000 -> 2.009386 | E61: 1526.293 | F61: =E61/1000 -> 1.526293
A62: Production or processing of gypsum or plasterboard | B62: ETS verified emissions (activity code 34) | C62: 1248.381 | D62: =C62/1000 -> 1.248381 | E62: 922.368 | F62: =E62/1000 -> 0.922368

Sheet I2. Production and consumption
A1: Steel
B2: Source | C2: Unit | D2: 2005 | I2: 2010 | N2: 2015 | S2: 2020
A3: Production | B3: Eurofer Steel in Figures 2022 (crude steel output) | C3: Mt | G3: 185.03224 | H3: 129.26978 | I3: 163.07653 | J3: 168.09782 | K3: 159.00343 | L3: 154.31767 | M3: 157.06496 | N3: 155.12873 | O3: 154.29781 | P3: 160.86903 | Q3: 160.06576 | R3: 150.24445 | S3: 132.21726 | T3: 152.78208
A4: Production | B4: Eurofer Steel in Figures 2022 (finished steel output) | C4: Mt | K4: 145.358 | L4: 142.25 | M4: 144.052 | N4: 142.874 | O4: 143.653 | P4: 147.772 | Q4: 148.478 | R4: 139.199 | S4: 123.664 | T4: 140.65
A5: Use | B5: Eurofer Steel in Figures 2022 | C5: Mt | G5: 173.811 | H5: 113.52 | I5: 139.077 | J5: 147.828 | K5: 132.18 | L5: 132.072 | M5: 135.732 | N5: 142.068 | O5: 146.796 | P5: 148.92 | Q5: 152.712 | R5: 144.768 | S5: 129.288 | T5: 148.956
A6: Difference | B6: calculated | C6: Mt | K6: =K4-K5 -> 13.178 | L6: =L4-L5 -> 10.178 | M6: =M4-M5 -> 8.32 | N6: =N4-N5 -> 0.806 | O6: =O4-O5 -> -3.143 | P6: =P4-P5 -> -1.148 | Q6: =Q4-Q5 -> -4.234 | R6: =R4-R5 -> -5.569 | ... T6: =T4-T5 -> -8.306
A7: Import | B7: Eurostat EU trade since 2002 by CPA 2.1 (DS-059268) | C7: Mt | G7: 48.829396 | H7: 26.530051 | I7: 33.209668 | J7: 39.478382 | K7: 30.440176 | L7: 33.975869 | M7: 36.280126 | N7: 43.016655 | O7: 44.162149 | P7: 44.908824 | Q7: 49.450438 | R7: 44.267942 | S7: 36.525231 | T7: 47.176036
A8: Export | B8: Eurostat EU trade since 2002 by CPA 2.1 (DS-059268) | C8: Mt | G8: 29.806234 | H8: 26.672804 | I8: 30.294907 | J8: 31.05282 | K8: 33.553666 | L8: 30.462541 | M8: 30.850526 | N8: 28.806755 | O8: 27.946372 | P8: 28.482287 | Q8: 26.152524 | R8: 25.760837 | S8: 21.340454 | T8: 21.409915
A9: Trade balance | B9: calculated | C9: Mt | G9: =G8-G7 -> -19.023162 | H9: =H8-H7 -> 0.1427534 | I9: =I8-I7 -> -2.9147615 | J9: =J8-J7 -> -8.4255613 | K9: =K8-K7 -> 3.1134906 | L9: =L8-L7 -> -3.5133284 | M9: =M8-M7 -> -5.4296002 | N9: =N8-N7 -> -14.209899 | ... T9: =T8-T7 -> -25.766121
A11: Average 2017-2021 | D11: =AVERAGE(T5-S5,S5-R5,R5-Q5,Q5-P5) -> 0.009 | M11: =M4/M3 -> 0.9171492 | N11: =N4/N3 -> 0.92100282 | O11: =O4/O3 -> 0.93101126 | P11: =P4/P3 -> 0.91858576 | Q11: =Q4/Q3 -> 0.92760628 | R11: =R4/R3 -> 0.9264835 | S11: =S4/S3 -> 0.93530907 | T11: =T4/T3 -> 0.92059224
A13: Cement
B14: Source | C14: Unit | I14: 2010 | N14: 2015 | S14: 2020
A15: Production | B15: Provided by Cembureau | C15: Mt | D15: 239.527 | E15: 256.169 | F15: 261.812 | G15: 244.355 | H15: 197.892 | I15: 185.623 | J15: 187.216 | K15: 164.687 | L15: 156.994 | M15: 157.525 | N15: 158.108 | O15: 159.874 | P15: 165.694 | Q15: 179.792 | R15: 173.053 | S15: 172.231 | T15: 182.549
A16: Use | B16: Provided by Cembureau | C16: Mt | D16: 232.29 | E16: 250.175 | F16: 254.029 | G16: 235.559 | H16: 189.106 | I16: 176.409 | J16: 178.253 | K16: 151.764 | L16: 142.188 | M16: 140.49 | N16: 141.356 | O16: 142.746 | P16: 147.836 | Q16: 155.342 | R16: 157.444 | S16: 159.215 | T16: 170.472
A17: Difference | B17: calculated | C17: Mt | D17: =D15-D16 -> 7.237 | E17: =E15-E16 -> 5.994 | F17: =F15-F16 -> 7.783 | G17: =G15-G16 -> 8.796 | H17: =H15-H16 -> 8.786 | I17: =I15-I16 -> 9.214 | J17: =J15-J16 -> 8.963 | K17: =K15-K16 -> 12.923 | ... T17: =T15-T16 -> 12.077
A18: Import | B18: Eurostat EU trade since 2002 by CPA 2.1 (DS-059268) | C18: Mt | D18: 15.252737 | E18: 16.010581 | F18: 18.332848 | G18: 10.896095 | H18: 7.6650245 | I18: 5.6254366 | J18: 4.3293103 | K18: 2.944935 | L18: 2.6824019 | M18: 2.5325485 | N18: 2.6133071 | O18: 2.42527 | P18: 3.1882888 | Q18: 3.4076022 | R18: 5.2322343 | S18: 6.3119639 | T18: 9.7064403
A19: Export | B19: Eurostat EU trade since 2002 by CPA 2.1 (DS-059268) | C19: Mt | D19: 12.936851 | E19: 11.454387 | F19: 10.93445 | G19: 13.100721 | H19: 13.892032 | I19: 16.361451 | J19: 13.170613 | K19: 19.953939 | L19: 25.077026 | M19: 27.918478 | N19: 26.820222 | O19: 24.625602 | P19: 22.341496 | Q19: 18.580939 | R19: 14.942994 | S19: 13.219775 | T19: 13.198037
A20: Trade balance | B20: calculated | C20: Mt | D20: =D19-D18 -> -2.3158858 | E20: =E19-E18 -> -4.5561949 | F20: =F19-F18 -> -7.3983985 | G20: =G19-G18 -> 2.2046262 | H20: =H19-H18 -> 6.2270072 | I20: =I19-I18 -> 10.736014 | J20: =J19-J18 -> 8.8413023 | K20: =K19-K18 -> 17.009004 | ... T20: =T19-T18 -> 3.4915972
A22: Average 2017-2021 | D22: =AVERAGE(T16-S16,S16-R16,R16-Q16,Q16-P16) -> 5.659
A24: Chemicals
B25: Source | C25: Unit | I25: 2010 | N25: 2015 | S25: 2020
A26: Production | B26: calculated | C26: Mt | E26: =SUM(E27:E33) -> 33.518075 | F26: =SUM(F27:F33) -> 36.246996 | G26: =SUM(G27:G33) -> 31.117619 | H26: =SUM(H27:H33) -> 28.083484 | I26: =SUM(I27:I33) -> 30.660657 | J26: =SUM(J27:J33) -> 32.080734 | K26: =SUM(K27:K33) -> 31.200394 | L26: =SUM(L27:L33) -> 29.589364 | ... U26: =SUM(U27:U33) -> 26.839574
A27: - of which ethylene | B27: Eurostat sold production, exports and imports (code DS-056120) | C27: Mt | E27: 12.099995 | F27: 14.178715 | G27: 11.868967 | H27: 9.9257453 | I27: 12.156694 | J27: 12.107575 | K27: 11.713151 | L27: 10.34106 | M27: 11.024052 | N27: 10.657337 | O27: 10.860381 | P27: 11.744647 | Q27: 10.690058 | R27: 9.817689 | S27: 9.7353332 | T27: 10 | U27: 9.6064602
A28: - of which propylene | B28: Eurostat sold production, exports and imports (code DS-056120) | C28: Mt | E28: 10.355846 | F28: 11.390539 | G28: 10.41218 | H28: 9.2213145 | I28: 9.6312747 | J28: 9.8828846 | K28: 9.5138379 | L28: 8.9870171 | M28: 9.4741108 | N28: 9.559588 | O28: 9.7137054 | P28: 10.287057 | Q28: 10.044501 | R28: 9.7924461 | S28: 10 | T28: 9.7426019 | U28: 8.9217571
A29: - of which benzene | B29: Eurostat sold production, exports and imports (code DS-056120) | C29: Mt | E29: 5.647354 | F29: 5.68717 | G29: 4.8 | H29: 4.8132951 | I29: 4.9728469 | J29: 6.1928237 | K29: 6.1298411 | L29: 6.3477446 | M29: 6.2895174 | N29: 5.9145912 | O29: 5.979281 | P29: 6.1085583 | Q29: 5.6 | R29: 5.4064826 | S29: 5.2544714 | T29: 6.2944227 | U29: 5.639483
A30: - of which toluene | B30: Eurostat sold production, exports and imports (code DS-056120) | C30: Mt | E30: 1.6957346 | F30: 1.6899812 | G30: 1.5274441 | H30: 1.440881 | I30: 1.317171 | J30: 1.2933429 | K30: 1.2343715 | L30: 1.2791024 | M30: 1.3188164 | N30: 1.3852643 | O30: 1.3139596 | P30: 1.4238731 | Q30: 1.3258779 | R30: 1.2794011 | S30: 1.249507 | T30: 1 | U30: 1.1751407
A31: - of which o-Xylene | B31: Eurostat sold production, exports and imports (code DS-056120) | C31: Mt | E31: 0.56918118 | F31: 0.47680124 | G31: 0.66969656 | H31: 0.70989645 | I31: 0.40345642 | J31: 0.41198505 | K31: 0.3621391 | L31: 0.4446734 | M31: 0.49692034 | N31: 0.49141533 | O31: 0.37896919 | P31: 0.400811 | Q31: 0.22893626 | R31: 0.22955776 | S31: 0.17870472 | T31: 0.18 | U31: 0.14703406
A32: - of which p-Xylene | B32: Eurostat sold production, exports and imports (code DS-056120) | C32: Mt | E32: 2.0085954 | F32: 1.7952467 | G32: 0.91445819 | H32: 1.1052903 | I32: 1.1851053 | J32: 1.3033674 | K32: 1.3780775 | L32: 1.3397637 | M32: 1.102881 | N32: 1.2076284 | O32: 0.97550402 | P32: 1.0452295 | Q32: 0.80931744 | R32: 0.89550441 | S32: 0.73878121 | T32: 0.6 | U32: 0.549699
A33: - of which m-Xylene and mixed xylene isomers | B33: Eurostat sold production, exports and imports (code DS-056120) | C33: Mt | E33: 1.1413691 | F33: 1.0285428 | G33: 0.92487251 | H33: 0.86706092 | I33: 0.99410827 | J33: 0.88875499 | K33: 0.86897587 | L33: 0.85000336 | M33: 0.87164626 | N33: 0.91346055 | O33: 0.91736333 | P33: 0.94612219 | Q33: 0.94155131 | R33: 0.93202882 | S33: 0.85057722 | T33: 0.9 | U33: 0.8
A34: Use | B34: calculated | C34: Mt | E34: =E26-E35 -> 35.991754 | F34: =F26-F35 -> 39.390657 | G34: =G26-G35 -> 33.351163 | H34: =H26-H35 -> 29.562272 | I34: =I26-I35 -> 32.741205 | J34: =J26-J35 -> 33.954248 | K34: =K26-K35 -> 32.582584 | L34: =L26-L35 -> 30.984954 | ... U34: =U26-U35 -> 29.107128
A35: Trade balance | B35: calculated | C35: Mt | E35: =E44-E36 -> -2.4736789 | F35: =F44-F36 -> -3.1436611 | G35: =G44-G36 -> -2.2335448 | H35: =H44-H36 -> -1.478788 | I35: =I44-I36 -> -2.0805481 | J35: =J44-J36 -> -1.8735148 | K35: =K44-K36 -> -1.3821896 | L35: =L44-L36 -> -1.3955899 | ... U35: =U44-U36 -> -2.2675537
A36: Import | B36: calculated | C36: Mt | E36: =SUM(E37:E43) -> 3.6972343 | F36: =SUM(F37:F43) -> 4.4879989 | G36: =SUM(G37:G43) -> 3.4573382 | H36: =SUM(H37:H43) -> 2.8117923 | I36: =SUM(I37:I43) -> 2.9841959 | J36: =SUM(J37:J43) -> 3.1926908 | K36: =SUM(K37:K43) -> 2.7053228 | L36: =SUM(L37:L43) -> 2.7682372 | ... U36: =SUM(U37:U43) -> 3.3315652
A37: - of which ethylene | B37: Eurostat sold production, exports and imports (code DS-056120) | C37: Mt | E37: 1.5486027 | F37: 1.9101667 | G37: 1.4475951 | H37: 1.2290101 | I37: 1.1949306 | J37: 1.1784766 | K37: 1.0051484 | L37: 1.1650942 | M37: 0.8140495 | N37: 1.1288497 | O37: 1.2494755 | P37: 1.3261649 | Q37: 1.376512 | R37: 1.4185796 | S37: 1.2961027 | T37: 0.87732496 | U37: 1.2426082
A38: - of which propylene | B38: Eurostat sold production, exports and imports (code DS-056120) | C38: Mt | E38: 1.0040396 | F38: 1.1494441 | G38: 0.6338235 | H38: 0.558885 | I38: 0.723305 | J38: 0.7494352 | K38: 0.6165615 | L38: 0.5628204 | M38: 0.4350917 | N38: 0.5194684 | O38: 0.6289835 | P38: 0.7030132 | Q38: 0.62616 | R38: 0.8455699 | S38: 0.69313842 | T38: 0.74792151 | U38: 0.50772954
A39: - of which benzene | B39: Eurostat sold production, exports and imports (code DS-056120) | C39: Mt | E39: 0.7478965 | F39: 0.8506079 | G39: 0.9144626 | H39: 0.6868722 | I39: 0.7713624 | J39: 0.9034372 | K39: 0.7524077 | L39: 0.8708824 | M39: 0.9488023 | N39: 0.940197 | O39: 1.0769815 | P39: 1.0521058 | Q39: 1.0495044 | R39: 1.0302582 | S39: 1.0372322 | T39: 1.1247476 | U39: 0.72380394
A40: - of which toluene | B40: Eurostat sold production, exports and imports (code DS-056120) | C40: Mt | E40: 0.0529164 | F40: 0.1483364 | G40: 0.1406226 | H40: 0.070911 | I40: 0.0477936 | J40: 0.0499153 | K40: 0.0491632 | L40: 0.024203 | M40: 0.0381771 | N40: 0.023865 | O40: 0.0365229 | P40: 0.027925 | Q40: 0.0283288 | R40: 0.050491828 | S40: 0.026964021 | T40: 0.014039966 | U40: 0.023749282
A41: - of which o-Xylene | B41: Eurostat sold production, exports and imports (code DS-056120) | C41: Mt | E41: 0.0861513 | F41: 0.1058511 | G41: 0.0912346 | H41: 0.0672676 | I41: 0.089781 | J41: 0.0850444 | K41: 0.0702122 | L41: 0.0584313 | M41: 0.064507 | N41: 0.0855043 | O41: 0.1166635 | P41: 0.0851389 | Q41: 0.1100099 | R41: 0.11357239 | S41: 0.14139793 | T41: 0.15497753 | U41: 0.17563638
A42: - of which p-Xylene | B42: Eurostat sold production, exports and imports (code DS-056120) | C42: Mt | E42: 0.170929 | F42: 0.2273287 | G42: 0.1781055 | H42: 0.1077158 | I42: 0.0896718 | J42: 0.1358516 | K42: 0.1781173 | L42: 0.0840575 | M42: 0.0658065 | N42: 0.1199557 | O42: 0.1347842 | P42: 0.1287653 | Q42: 0.3021161 | R42: 0.46647632 | S42: 0.52157054 | T42: 0.71478314 | U42: 0.63661447
A43: - of which m-Xylene and mixed xylene isomers | B43: Eurostat sold production, exports and imports (code DS-056120) | C43: Mt | E43: 0.0866988 | F43: 0.096264 | G43: 0.0514943 | H43: 0.0911306 | I43: 0.0673515 | J43: 0.0905305 | K43: 0.0337125 | L43: 0.0027484 | M43: 0.0515534 | N43: 0.0328568 | O43: 0.0345136 | P43: 0.0472585 | Q43: 0.0818401 | R43: 0.03767513 | S43: 0.027219623 | T43: 0.015898002 | U43: 0.021423338
A44: Export | B44: calculated | C44: Mt | E44: =SUM(E45:E51) -> 1.2235554 | F44: =SUM(F45:F51) -> 1.3443378 | G44: =SUM(G45:G51) -> 1.2237934 | H44: =SUM(H45:H51) -> 1.3330043 | I44: =SUM(I45:I51) -> 0.9036478 | J44: =SUM(J45:J51) -> 1.319176 | K44: =SUM(K45:K51) -> 1.3231332 | L44: =SUM(L45:L51) -> 1.3726473 | ... U44: =SUM(U45:U51) -> 1.0640115
A45: - of which ethylene | B45: Eurostat sold production, exports and imports (code DS-056120) | C45: Mt | E45: 0.0596733 | F45: 0.071421 | G45: 0.0251298 | H45: 0.0292142 | I45: 0.0862115 | J45: 0.1329833 | K45: 0.3355183 | L45: 0.2092947 | M45: 0.2482584 | N45: 0.1785489 | O45: 0.5123663 | P45: 0.3892257 | Q45: 0.6027401 | R45: 0.28075874 | S45: 0.41958019 | T45: 0.20819405 | U45: 0.130147
A46: - of which propylene | B46: Eurostat sold production, exports and imports (code DS-056120) | C46: Mt | E46: 0.1481002 | F46: 0.2250891 | G46: 0.2300863 | H46: 0.1477694 | I46: 0.1644286 | J46: 0.1924882 | K46: 0.0686223 | L46: 0.0966842 | M46: 0.1186577 | N46: 0.1068684 | O46: 0.1537389 | P46: 0.1463928 | Q46: 0.11674 | R46: 0.12445344 | S46: 0.093275189 | T46: 0.11955574 | U46: 0.19959427
A47: - of which benzene | B47: Eurostat sold production, exports and imports (code DS-056120) | C47: Mt | E47: 0.2139677 | F47: 0.1876518 | G47: 0.1721289 | H47: 0.3375127 | I47: 0.160101 | J47: 0.2931432 | K47: 0.293101 | L47: 0.408498 | M47: 0.373892 | N47: 0.3270322 | O47: 0.2490083 | P47: 0.2460195 | Q47: 0.2017763 | R47: 0.11314431 | S47: 0.27447724 | T47: 0.13632388 | U47: 0.31482187
A48: - of which toluene | B48: Eurostat sold production, exports and imports (code DS-056120) | C48: Mt | E48: 0.5229545 | F48: 0.5505765 | G48: 0.4731736 | H48: 0.4312708 | I48: 0.2171217 | J48: 0.188919 | K48: 0.1815732 | L48: 0.2371832 | M48: 0.2100185 | N48: 0.2309543 | O48: 0.270496 | P48: 0.2871936 | Q48: 0.2898095 | R48: 0.21093157 | S48: 0.34497419 | T48: 0.32253202 | U48: 0.24509784
A49: - of which o-Xylene | B49: Eurostat sold production, exports and imports (code DS-056120) | C49: Mt | E49: 0.0207479 | F49: 0.018587 | G49: 0.0286555 | H49: 0.0767916 | I49: 0.0336999 | J49: 0.0704307 | K49: 0.0480704 | L49: 0.0580519 | M49: 0.0251945 | N49: 0.045424 | O49: 0.0266331 | P49: 0.0137751 | Q49: 0.0173266 | R49: 0.02318284 | S49: 0.026501882 | T49: 0.023381115 | U49: 0.017890036
A50: - of which p-Xylene | B50: Eurostat sold production, exports and imports (code DS-056120) | C50: Mt | E50: 0.1453619 | F50: 0.1814669 | G50: 0.2330825 | H50: 0.2650846 | I50: 0.2030366 | J50: 0.3811252 | K50: 0.3207779 | L50: 0.2302278 | M50: 0.1847238 | N50: 0.4551484 | O50: 0.4339126 | P50: 0.4648047 | Q50: 0.2513989 | R50: 0.36928943 | S50: 0.20272771 | T50: 0.21637198 | U50: 0.15465156
A51: - of which m-Xylene and mixed xylene isomers | B51: Eurostat sold production, exports and imports (code DS-056120) | C51: Mt | E51: 0.1127499 | F51: 0.1095455 | G51: 0.0615368 | H51: 0.045361 | I51: 0.0390485 | J51: 0.0600864 | K51: 0.0754701 | L51: 0.1327075 | M51: 0.0744425 | N51: 0.1005495 | O51: 0.0721022 | P51: 0.0320297 | Q51: 0.0104407 | R51: 0.003284692 | S51: 0.00206478 | T51: 0.004165898 | U51: 0.00180891
A54: Average 2017-2021 | D54: =AVERAGE(T34-S34,S34-R34,R34-Q34,Q34-P34) -> -0.60275891
A58: Indicator I2

Sheet I3. CMUR
A1: CMUR
B2: Source | C2: Unit | D2: 2010 | I2: 2015 | N2: 2020 | S2: 2025 | X2: 2030
A3: Historic | B3: Eurostat SDG_12_41 | C3: % | D3: 0.108 | E3: 0.103 | F3: 0.111 | G3: 0.113 | H3: 0.112 | I3: 0.113 | J3: 0.115 | K3: 0.115 | L3: 0.117 | M3: 0.12 | N3: 0.117 | O3: 0.117
A4: 2030 benchmark | B4: 8th EAP, Circular Economy Action Plan | C4: % | X4: =2*N3 -> 0.234
A5: linear trajectory | C5: % | O5: 0.117 | P5: 0.13 | Q5: 0.143 | R5: 0.156 | S5: 0.169 | T5: 0.182 | U5: 0.195 | V5: 0.208 | W5: 0.221 | X5: 0.234
A7: Average 2017-2021 | D7: =AVERAGE(O3-N3,N3-M3,M3-L3,L3-K3) -> 0.0005
A8: Average 2021-2030 | D8: =P5-O5 -> 0.013
A11: Indicator I3

Sheet I4. GHG intensity products
A1: Steel
B2: Source | C2: Unit | D2: 2005 | I2: 2010 | N2: 2015 | S2: 2020
A3: Production (Mt) | B3: Eurofer data | C3: Mt | G3: ='I2. Production and consumption'!G3 -> 185.03224 | H3: ='I2. Production and consumption'!H3 -> 129.26978 | I3: ='I2. Production and consumption'!I3 -> 163.07653 | J3: ='I2. Production and consumption'!J3 -> 168.09782 | K3: ='I2. Production and consumption'!K3 -> 159.00343 | L3: ='I2. Production and consumption'!L3 -> 154.31767 | M3: ='I2. Production and consumption'!M3 -> 157.06496 | N3: ='I2. Production and consumption'!N3 -> 155.12873 | ... T3: ='I2. Production and consumption'!T3 -> 152.78208 | U3: 136.2
A4: Total emissions (Mt CO2e) | B4: EEA GHG data viewer | C4: Mt CO2e | D4: ='I1. GHG emissions'!D5 -> 193.15413 | E4: ='I1. GHG emissions'!E5 -> 198.50066 | F4: ='I1. GHG emissions'!F5 -> 201.86984 | G4: ='I1. GHG emissions'!G5 -> 186.83828 | H4: ='I1. GHG emissions'!H5 -> 129.57684 | I4: ='I1. GHG emissions'!I5 -> 162.13319 | J4: ='I1. GHG emissions'!J5 -> 158.78095 | K4: ='I1. GHG emissions'!K5 -> 149.00264 | ... T4: ='I1. GHG emissions'!T5 -> 147.01485
A5: Emission intensity (t CO2e/t) | C5: t CO2/t | G5: =G4/G3 -> 1.0097606 | H5: =H4/H3 -> 1.0023753 | I5: =I4/I3 -> 0.99421541 | J5: =J4/J3 -> 0.94457473 | K5: =K4/K3 -> 0.93710327 | L5: =L4/L3 -> 0.94990037 | M5: =M4/M3 -> 0.93782665 | N5: =N4/N3 -> 0.98709755 | ... T5: =T4/T3 -> 0.96225193
A7: Average 2017-2021 | D7: =AVERAGE(T5-S5,S5-R5,R5-Q5,Q5-P5)*1000 -> -0.83306621
A10: Cement
B11: Source | C11: Unit | D11: 2005 | I11: 2010 | N11: 2015 | S11: 2020
A12: Production (Mt) | B12: Cembureau data | C12: Mt | D12: ='I2. Production and consumption'!D15 -> 239.527 | E12: ='I2. Production and consumption'!E15 -> 256.169 | F12: ='I2. Production and consumption'!F15 -> 261.812 | G12: ='I2. Production and consumption'!G15 -> 244.355 | H12: ='I2. Production and consumption'!H15 -> 197.892 | I12: ='I2. Production and consumption'!I15 -> 185.623 | J12: ='I2. Production and consumption'!J15 -> 187.216 | K12: ='I2. Production and consumption'!K15 -> 164.687 | ... T12: ='I2. Production and consumption'!T15 -> 182.549
A13: Total emissions (Mt CO2e) | B13: ETS data | C13: Mt CO2e | D13: ='I1. GHG emissions'!D99/1000 -> 143.41195 | E13: ='I1. GHG emissions'!E99/1000 -> 147.15261 | F13: ='I1. GHG emissions'!F99/1000 -> 163.11498 | G13: ='I1. GHG emissions'!G99/1000 -> 150.48991 | H13: ='I1. GHG emissions'!H99/1000 -> 121.31189 | I13: ='I1. GHG emissions'!I99/1000 -> 119.34112 | J13: ='I1. GHG emissions'!J99/1000 -> 116.97662 | K13: ='I1. GHG emissions'!K99/1000 -> 109.89505 | ... T13: ='I1. GHG emissions'!T99/1000 -> 110.22327 | U13: =T13/D13-1 -> -0.23142196
A14: Emission intensity (t CO2e/t) | C14: t CO2/t | D14: =D13/D12 -> 0.59872977 | E14: =E13/E12 -> 0.57443565 | F14: =F13/F12 -> 0.62302332 | G14: =G13/G12 -> 0.61586588 | H14: =H13/H12 -> 0.61302067 | I14: =I13/I12 -> 0.64292204 | J14: =J13/J12 -> 0.62482173 | K14: =K13/K12 -> 0.66729648 | ... T14: =T13/T12 -> 0.60380102 | U14: =T14/D14-1 -> 0.0084700155
A16: Average 2017-2021 | D16: =AVERAGE(T14-S14,S14-R14,R14-Q14,Q14-P14)*1000 -> -17.835528
A18: Base organic chemicals
B19: Source | C19: Unit | D19: 2005 | I19: 2010 | N19: 2015 | S19: 2020
A20: total production | L20: =L21+L22+L23 -> 41.563355 | M20: =M21+M22+M23 -> 45.623831 | N20: =N21+N22+N23 -> 42.671854 | O20: =O21+O22+O23 -> 44.459177 | P20: =P21+P22+P23 -> 43.648533 | Q20: =Q21+Q22+Q23 -> 42.821067 | R20: =R21+R22+R23 -> 41.648877 | S20: =S21+S22+S23 -> 40.441816 | ... U20: =U21+U22+U23 -> 37.504566
A21: Production - ethylene (Mt) | B21: Eurostat DS-056121 | C21: Mt | L21: 16.096333 | M21: 19.039978 | N21: 17.404166 | O21: 18.037565 | P21: 18 | Q21: 17.439047 | R21: 16.628416 | S21: 16.477749 | T21: 15.649568 | U21: 13.558041
A22: Production - propylene (Mt) | B22: Eurostat DS-056121 | C22: Mt | L22: 12.935621 | M22: 13.387043 | N22: 12.872033 | O22: 12.929714 | P22: 13.128196 | Q22: 12.756553 | R22: 12.435086 | S22: 11.590565 | T22: 12.109004 | U22: 11.168238
A23: Production - aromatics (Mt) | B23: Eurostat DS-056121 | C23: Mt | L23: 12.531402 | M23: 13.196809 | N23: 12.395656 | O23: 13.491898 | P23: 12.520337 | Q23: 12.625467 | R23: 12.585375 | S23: 12.373501 | T23: 11.42717 | U23: 12.778287
A24: Total emissions (Mt CO2e) | B24: EEA EU ETS data viewer (activity code 42) | C24: Mt CO2e | L24: 33.431033 | M24: 33.366782 | N24: 33.600201 | O24: 33.407365 | P24: 34.007494 | Q24: 33.84863 | R24: 31.999661 | S24: 31.866199 | T24: 33.952083 | U24: 28.767537
A25: Emission intensity (t CO2e/t) | C25: t CO2/t | L25: =L24/SUM(L21:L23) -> 0.80433914 | M25: =M24/SUM(M21:M23) -> 0.73134547 | N25: =N24/SUM(N21:N23) -> 0.78740897 | O25: =O24/SUM(O21:O23) -> 0.75141663 | P25: =P24/SUM(P21:P23) -> 0.77912111 | Q25: =Q24/SUM(Q21:Q23) -> 0.79046675 | R25: =R24/SUM(R21:R23) -> 0.76831991 | S25: =S24/SUM(S21:S23) -> 0.78795174 | ... U25: =U24/SUM(U21:U23) -> 0.76704092
A36: Graph feed
D37: 2005 | I37: 2010 | N37: 2015 | S37: 2020
A38: Steel | C38: t CO2/t | G38: =G5 -> 1.0097606 | H38: =H5 -> 1.0023753 | I38: =I5 -> 0.99421541 | J38: =J5 -> 0.94457473 | K38: =K5 -> 0.93710327 | L38: =L5 -> 0.94990037 | M38: =M5 -> 0.93782665 | N38: =N5 -> 0.98709755 | ... T38: =T5 -> 0.96225193
A39: Cement | C39: t CO2/t | D39: =D14 -> 0.59872977 | E39: =E14 -> 0.57443565 | F39: =F14 -> 0.62302332 | G39: =G14 -> 0.61586588 | H39: =H14 -> 0.61302067 | I39: =I14 -> 0.64292204 | J39: =J14 -> 0.62482173 | K39: =K14 -> 0.66729648 | ... T39: =T14 -> 0.60380102
A40: Base organic chemicals | C40: t CO2/t | L40: =L25 -> 0.80433914 | M40: =M25 -> 0.73134547 | N40: =N25 -> 0.78740897 | O40: =O25 -> 0.75141663 | P40: =P25 -> 0.77912111 | Q40: =Q25 -> 0.79046675 | R40: =R25 -> 0.76831991 | S40: =S25 -> 0.78795174 | ... U40: =U25 -> 0.76704092
E42: Indicator I4

Sheet I5. Energy use
A1: Total energy use
B2: Source | C2: Unit | D2: 2005 | I2: 2010 | N2: 2015 | S2: 2020 | X2: 2025 | AC2: 2030 | AH2: 2035 | AM2: 2040 | AR2: 2045 | AW2: 2050
A4: non-energy use | B4: Eurostat energy balances | C4: Mtoe | D4: 99.990623 | E4: 99.997192 | F4: 100.08822 | G4: 97.473406 | H4: 88.569504 | I4: 93.214571 | J4: 91.250167 | K4: 87.860121 | L4: 85.120679 | M4: 87.033583 | N4: 84.302239 | O4: 84.018661 | P4: 90.634032 | Q4: 87.111026 | R4: 86.765967 | S4: 86.237262 | T4: 90.078307
A5: Total | B5: Eurostat energy balances | C5: Mtoe | D5: 275.12525 | E5: 269.57638 | F5: 274.27585 | G5: 265.10807 | H5: 229.18046 | I5: 243.87311 | J5: 244.29556 | K5: 239.7027 | L5: 236.74852 | M5: 233.29777 | N5: 233.50766 | O5: 237.7992 | P5: 240.06351 | Q5: 242.46632 | R5: 239.2396 | S5: 230.92331 | T5: 240.34385
A6: Fossil fuels | B6: Eurostat energy balances | C6: Mtoe | D6: 153.97343 | E6: 147.17088 | F6: 148.63917 | G6: 142.21975 | H6: 119.20615 | I6: 126.45741 | J6: 125.23791 | K6: 122.01803 | L6: 119.61184 | M6: 116.21046 | N6: 115.37357 | O6: 116.90441 | P6: 117.57363 | Q6: 118.72717 | R6: 115.6967 | S6: 112.32517 | T6: 117.67025
A7: electricity | B7: Eurostat energy balances | C7: Mtoe | D7: 87.25259 | E7: 87.202153 | F7: 88.358376 | G7: 86.265145 | H7: 74.300824 | I7: 79.58803 | J7: 80.52822 | K7: 79.129937 | L7: 77.933983 | M7: 78.251377 | N7: 78.580682 | O7: 79.617355 | P7: 81.036995 | Q7: 81.292179 | R7: 80.233557 | S7: 76.037877 | T7: 79.831363
A8: renewables (mainly biomass) | B8: Eurostat energy balances | C8: Mtoe | D8: 17.624981 | E8: 18.387066 | F8: 19.316373 | G8: 18.262628 | H8: 18.020873 | I8: 19.552827 | J8: 19.657035 | K8: 19.04706 | L8: 19.584087 | M8: 19.985262 | N8: 20.803288 | O8: 21.709893 | P8: 22.055517 | Q8: 22.601831 | R8: 23.10638 | S8: 23.181768 | T8: 23.310921
A9: Others (heat and waste) | B9: Eurostat energy balances | C9: Mtoe | D9: 16.207034 | E9: 16.764237 | F9: 17.887465 | G9: 18.290436 | H9: 17.62016 | I9: 18.230786 | J9: 18.820172 | K9: 19.466152 | L9: 19.582331 | M9: 18.816755 | N9: 18.735153 | O9: 19.557802 | P9: 19.377378 | Q9: 19.822711 | R9: 20.183071 | S9: 19.377115 | T9: 19.531317
A10: 2040 min (delete label) | B10: ESABCC database | AC10: 323.02966 | AM10: 239.02752 | AW10: 231.86931
A11: 2040 advice range | B11: ESABCC database | AC11: 1.9513718 | AM11: 12.685111 | AW11: 17.442923
A12: 2030 benchmark (max) | B12: FF55 MIX | C12: Mtoe | AC12: 211.313
A13: 2030 benchmark (min) | B13: Repower EU (SWD) | AC13: 196
A14: 2050 benchmark | B14: CTP MIX | C14: Mtoe | AW14: 218.73423
A15: linear trajectory | C15: Mtoe | T15: 240.34385 | U15: 237.1182 | V15: 233.89255 | W15: 230.6669 | X15: 227.44125 | Y15: 224.2156 | Z15: 220.98995 | AA15: 217.7643 | AB15: 214.53865 | AC15: 211.313 | AD15: 209.85415 | AE15: 208.3953 | AF15: 206.93645 | AG15: 205.4776 | AH15: 204.01874 | AI15: 202.55989 | AJ15: 201.10104 | AK15: 199.64219 | AL15: 198.18334 | AM15: 196.72449 | AN15: 195.26564 | AO15: 193.80679 | AP15: 192.34794 | AQ15: 190.88908 | AR15: 189.43023 | AS15: 187.97138 | AT15: 186.51253 | AU15: 185.05368 | AV15: 183.59483 | AW15: 182.13598
A16: linear trajectory 2 | C16: Mtoe | AC16: 211.313 | AD16: 208.80336 | AE16: 206.29373 | AF16: 203.78409 | AG16: 201.27446 | AH16: 198.76482 | AI16: 196.25519 | AJ16: 193.74555 | AK16: 191.23591 | AL16: 188.72628 | AM16: 186.21664 | AN16: 183.70701 | AO16: 181.19737 | AP16: 178.68774 | AQ16: 176.1781 | AR16: 173.66847 | AS16: 171.15883 | AT16: 168.64919 | AU16: 166.13956 | AV16: 163.62992 | AW16: 161.12029
A18: Average 2017-2021 | D18: 0.07008525
A19: Average 2021-2030 | D19: -3.2256499
A20: Average 2030-2050 min | D20: -1.4588511
A21: Average 2030-2050 max | D21: -2.5096356
A23: non-energy use | B23: Eurostat energy balances | C23: TWh | D23: =D4*'conversion factor'!$E$6 -> 1162.8909 | E23: =E4*'conversion factor'!$E$6 -> 1162.9673 | F23: =F4*'conversion factor'!$E$6 -> 1164.026 | G23: =G4*'conversion factor'!$E$6 -> 1133.6157 | H23: =H4*'conversion factor'!$E$6 -> 1030.0633 | I23: =I4*'conversion factor'!$E$6 -> 1084.0855 | J23: =J4*'conversion factor'!$E$6 -> 1061.2394 | K23: =K4*'conversion factor'!$E$6 -> 1021.8132 | ... T23: =T4*'conversion factor'!$E$6 -> 1047.6107
A24: Total | B24: Eurostat energy balances | C24: TWh | D24: =D5*'conversion factor'!$E$6 -> 3199.7067 | E24: =E5*'conversion factor'!$E$6 -> 3135.1733 | F24: =F5*'conversion factor'!$E$6 -> 3189.8281 | G24: =G5*'conversion factor'!$E$6 -> 3083.2069 | H24: =H5*'conversion factor'!$E$6 -> 2665.3687 | I24: =I5*'conversion factor'!$E$6 -> 2836.2443 | J24: =J5*'conversion factor'!$E$6 -> 2841.1573 | K24: =K5*'conversion factor'!$E$6 -> 2787.7423 | ... T24: =T5*'conversion factor'!$E$6 -> 2795.199
A25: Fossil fuels | B25: Eurostat energy balances | C25: TWh | D25: =D6*'conversion factor'!$E$6 -> 1790.711 | E25: =E6*'conversion factor'!$E$6 -> 1711.5974 | F25: =F6*'conversion factor'!$E$6 -> 1728.6735 | G25: =G6*'conversion factor'!$E$6 -> 1654.0158 | H25: =H6*'conversion factor'!$E$6 -> 1386.3676 | I25: =I6*'conversion factor'!$E$6 -> 1470.6997 | J25: =J6*'conversion factor'!$E$6 -> 1456.5169 | K25: =K6*'conversion factor'!$E$6 -> 1419.0696 | ... T25: =T6*'conversion factor'!$E$6 -> 1368.505
A26: electricity | B26: Eurostat energy balances | C26: TWh | D26: =D7*'conversion factor'!$E$6 -> 1014.7476 | E26: =E7*'conversion factor'!$E$6 -> 1014.161 | F26: =F7*'conversion factor'!$E$6 -> 1027.6079 | G26: =G7*'conversion factor'!$E$6 -> 1003.2636 | H26: =H7*'conversion factor'!$E$6 -> 864.11858 | I26: =I7*'conversion factor'!$E$6 -> 925.60879 | J26: =J7*'conversion factor'!$E$6 -> 936.5432 | K26: =K7*'conversion factor'!$E$6 -> 920.28117 | ... T26: =T7*'conversion factor'!$E$6 -> 928.43875
A27: renewables (mainly biomass) | B27: Eurostat energy balances | C27: TWh | D27: =D8*'conversion factor'!$E$6 -> 204.97853 | E27: =E8*'conversion factor'!$E$6 -> 213.84158 | F27: =F8*'conversion factor'!$E$6 -> 224.64942 | G27: =G8*'conversion factor'!$E$6 -> 212.39436 | H27: =H8*'conversion factor'!$E$6 -> 209.58275 | I27: =I8*'conversion factor'!$E$6 -> 227.39938 | J27: =J8*'conversion factor'!$E$6 -> 228.61132 | K27: =K8*'conversion factor'!$E$6 -> 221.51731 | ... T27: =T8*'conversion factor'!$E$6 -> 271.10601
A28: Others (heat and waste) | B28: Eurostat energy balances | C28: TWh | D28: =D9*'conversion factor'!$E$6 -> 188.48781 | E28: =E9*'conversion factor'!$E$6 -> 194.96808 | F28: =F9*'conversion factor'!$E$6 -> 208.03122 | G28: =G9*'conversion factor'!$E$6 -> 212.71777 | H28: =H9*'conversion factor'!$E$6 -> 204.92246 | I28: =I9*'conversion factor'!$E$6 -> 212.02404 | J28: =J9*'conversion factor'!$E$6 -> 218.8786 | K28: =K9*'conversion factor'!$E$6 -> 226.39135 | ... T28: =T9*'conversion factor'!$E$6 -> 227.14922
A29: 2040 min (delete label) | B29: ESABCC database | C29: TWh | AC29: =AC10*'conversion factor'!$E$6 -> 3756.835 | AM29: =AM10*'conversion factor'!$E$6 -> 2779.8901 | AW29: =AW10*'conversion factor'!$E$6 -> 2696.6401
A30: 2040 advice range | B30: ESABCC database | C30: TWh | AC30: =AC11*'conversion factor'!$E$6 -> 22.694454 | AM30: =AM11*'conversion factor'!$E$6 -> 147.52784 | AW30: =AW11*'conversion factor'!$E$6 -> 202.8612
A31: 2030 benchmark (max) | B31: FF55 MIX | C31: TWh | AC31: =AC12*'conversion factor'!$E$6 -> 2457.5702
A32: 2030 benchmark (min) | B32: Repower EU (SWD) | C32: TWh | AC32: =AC13*'conversion factor'!$E$6 -> 2279.48
A33: 2050 benchmark | B33: CTP MIX | C33: TWh | AW33: =AW14*'conversion factor'!$E$6 -> 2543.8791
A34: linear trajectory | C34: TWh | T34: =T15*'conversion factor'!$E$6 -> 2795.199 | U34: =U15*'conversion factor'!$E$6 -> 2757.6847 | V34: =V15*'conversion factor'!$E$6 -> 2720.1703 | W34: =W15*'conversion factor'!$E$6 -> 2682.656 | X34: =X15*'conversion factor'!$E$6 -> 2645.1417 | Y34: =Y15*'conversion factor'!$E$6 -> 2607.6274 | Z34: =Z15*'conversion factor'!$E$6 -> 2570.1131 | AA34: =AA15*'conversion factor'!$E$6 -> 2532.5988 | ... AW34: =AW15*'conversion factor'!$E$6 -> 2118.2414
A35: linear trajectory 2 | C35: TWh | T35: =T24 -> 2795.199 | U35: =T35-($T35-$AC32)/9 -> 2737.8969 | V35: =U35-($T35-$AC32)/9 -> 2680.5947 | W35: =V35-($T35-$AC32)/9 -> 2623.2926 | X35: =W35-($T35-$AC32)/9 -> 2565.9905 | Y35: =X35-($T35-$AC32)/9 -> 2508.6884 | Z35: =Y35-($T35-$AC32)/9 -> 2451.3863 | AA35: =Z35-($T35-$AC32)/9 -> 2394.0842 | AB35: =AA35-($T35-$AC32)/9 -> 2336.7821 | AC35: =AB35-($T35-$AC32)/9 -> 2279.48 | AD35: =AD16*'conversion factor'!$E$6 -> 2428.3831 | AE35: =AE16*'conversion factor'!$E$6 -> 2399.1961 | AF35: =AF16*'conversion factor'!$E$6 -> 2370.009 | AG35: =AG16*'conversion factor'!$E$6 -> 2340.8219 | AH35: =AH16*'conversion factor'!$E$6 -> 2311.6349 | AI35: =AI16*'conversion factor'!$E$6 -> 2282.4478 | AJ35: =AJ16*'conversion factor'!$E$6 -> 2253.2608 | AK35: =AK16*'conversion factor'!$E$6 -> 2224.0737 | ... AW35: =AW16*'conversion factor'!$E$6 -> 1873.8289
A37: Average 2017-2021 | D37: =(T24-P24)/4 -> 0.81509146
A38: Average 2021-2030 (CTP) | D38: =U34-T34 -> -37.514308
A39: Average 2021-2030 (RePowerEU) | D39: =U35-T35 -> -57.302107
A40: Average 2030-2050 min | D40: =AD34-AC34 -> -16.966439
A41: Average 2030-2050 max | D41: =AD35-AC35 -> 148.90313
G44: Indicator I5
A45: 2040 advice scenarios
A46: REMIND Min | I46: =[3]Industry!V42 -> 403.73572 | N46: =[3]Industry!AA42 -> 397.66187 | S46: =[3]Industry!AF42 -> 389.83966 | X46: =[3]Industry!AK42 -> 383.92345 | AC46: =[3]Industry!AP42 -> 323.02966 | AH46: =[3]Industry!AU42 -> 272.69287 | AM46: =[3]Industry!AZ42 -> 239.02752 | AR46: =[3]Industry!BE42 -> 232.96083 | AW46: =[3]Industry!BJ42 -> 231.86931
A47: REMIND Max | I47: =[3]Industry!V43 -> 403.73572 | N47: =[3]Industry!AA43 -> 397.66187 | S47: =[3]Industry!AF43 -> 389.83966 | X47: =[3]Industry!AK43 -> 384.92183 | AC47: =[3]Industry!AP43 -> 324.98103 | AH47: =[3]Industry!AU43 -> 283.26897 | AM47: =[3]Industry!AZ43 -> 251.71263 | AR47: =[3]Industry!BE43 -> 245.22319 | AW47: =[3]Industry!BJ43 -> 249.31223
A48: NZero_bioLim7p5_withICEPhOP | I48: =[3]Industry!V44 -> 403.73572 | N48: =[3]Industry!AA44 -> 397.66187 | S48: =[3]Industry!AF44 -> 389.83966 | X48: =[3]Industry!AK44 -> 384.28888 | AC48: =[3]Industry!AP44 -> 324.98103 | AH48: =[3]Industry!AU44 -> 283.26897 | AM48: =[3]Industry!AZ44 -> 251.71263 | AR48: =[3]Industry!BE44 -> 238.64776 | AW48: =[3]Industry!BJ44 -> 232.17742
A50: CTP scenarios (IA figure 67, in Mtoe)
C51: Coal | D51: Oil | E51: Natural gas* | F51: e-gas | G51: Hydrogen | H51: Marketed Heat | I51: Bioenergy** | J51: Other RES | K51: Electricity | L51: Total | AC51: 2030 | AH51: 2035 | AM51: 2040 | AR51: 2045 | AW51: 2050
A52: 2030 | B52: MIX-50 | C52: -0.46460532 | D52: -2.7419705 | E52: -2.6467798 | F52: 0 | G52: -1.0885819e-11 | H52: -0.89588186 | I52: -1.1366724 | J52: -0.032022373 | K52: -0.91600736 | L52: =SUM(C52:K52) -> -8.8339396
B53: REG | C53: -0.83911601 | D53: -5.9314095 | E53: -4.2850262 | F53: 0 | G53: -1.088582e-11 | H53: -1.2109013 | I53: 2.490802 | J53: -0.044576458 | K53: -1.6534772 | L53: =SUM(C53:K53) -> -11.473705
B54: MIX | C54: -0.71975987 | D54: -3.7115573 | E54: -5.7192856 | F54: 0 | G54: -1.088582e-11 | H54: -1.0749976 | I54: 0.55993205 | J54: -0.019735228 | K54: -1.1960052 | L54: =SUM(C54:K54) -> -11.881409
B55: CPRICE | C55: -0.66443476 | D55: -4.5853486 | E55: -7.2630603 | F55: 0 | G55: -1.088582e-11 | H55: -1.5026238 | I55: -0.013432973 | J55: 0.027457314 | K55: -0.43178206 | L55: =SUM(C55:K55) -> -14.433225
B56: ALLBNK | C56: -1.2722913 | D56: -6.9868896 | E56: -8.75928 | F56: 0 | G56: -1.088582e-11 | H56: -1.5287941 | I56: 2.6513923 | J56: 0.0072103745 | K56: -1.5722332 | L56: =SUM(C56:K56) -> -17.460885
A57: 2050 | B57: REG | C57: -3.5394769 | D57: -12.168232 | E57: -68.674496 | F57: 18.752902 | G57: 15.877076 | H57: 3.2678196 | I57: 5.4209439 | J57: 0.13400279 | K57: 13.229972 | L57: =SUM(C57:K57) -> -27.699488
B58: MIX | C58: -3.8134269 | D58: -12.093551 | E58: -68.718861 | F58: 19.587625 | G58: 16.679995 | H58: 4.5506454 | I58: 3.9631566 | J58: 0.14939001 | K58: 16.039261 | L58: =SUM(C58:K58) -> -23.655767
B59: CPRICE | C59: -4.0740283 | D59: -12.791707 | E59: -68.80673 | F59: 20.225967 | G59: 18.070085 | H59: 8.7173435 | I59: 3.9626241 | J59: 0.14009417 | K59: 7.7700901 | L59: =SUM(C59:K59) -> -26.786261
B60: ALLBNK | C60: -4.0891529 | D60: -12.806516 | E60: -69.140629 | F60: 17.84456 | G60: 16.215336 | H60: 3.9834466 | I60: 6.147134 | J60: 0.08896419 | K60: 16.183211 | L60: =SUM(C60:K60) -> -25.573646
A61: BSL | B61: 2030 | C61: 9.9605931 | D61: 34.247904 | E61: 73.863305 | F61: 0 | G61: 1.088582e-11 | H61: 18.457363 | I61: 26.300694 | J61: 0.24242325 | K61: 86.226295 | L61: =SUM(C61:K61) -> 249.29858
A62: BSL | B62: 2050 | C62: 4.354041 | D62: 17.66954 | E62: 74.093 | F62: 0 | G62: 0.26257182 | H62: 23.274214 | I62: 27.448187 | J62: 0.61391781 | K62: 94.674528 | L62: =SUM(C62:K62) -> 242.39

Sheet I6. Energy mix
A1: Total energy use per carrier
B2: Source | C2: Unit | D2: 2005 | I2: 2010 | N2: 2015 | S2: 2020 | X2: 2025 | AC2: 2030 | AH2: 2035 | AM2: 2040 | AR2: 2045 | AW2: 2050
A3: Non-energy fossil fuels | B3: Eurostat energy balances | C3: Mtoe | D3: =D133+D134 -> 99.990623 | E3: =E133+E134 -> 99.997192 | F3: =F133+F134 -> 100.08822 | G3: =G133+G134 -> 97.473406 | H3: =H133+H134 -> 88.569504 | I3: =I133+I134 -> 93.214571 | J3: =J133+J134 -> 91.250167 | K3: =K133+K134 -> 87.860121 | ... T3: =T133+T134 -> 90.078307
A4: Total energy use | B4: Eurostat energy balances | C4: Mtoe | D4: =D64 -> 275.12525 | E4: =E64 -> 269.57638 | F4: =F64 -> 274.27585 | G4: =G64 -> 265.10807 | H4: =H64 -> 229.18046 | I4: =I64 -> 243.87311 | J4: =J64 -> 244.29556 | K4: =K64 -> 239.7027 | ... T4: =T64 -> 240.34385
A5: Fossil fuels | B5: Eurostat energy balances | C5: Mtoe | D5: =D65+D76+D81+D85+D86 -> 153.97343 | E5: =E65+E76+E81+E85+E86 -> 147.17088 | F5: =F65+F76+F81+F85+F86 -> 148.63917 | G5: =G65+G76+G81+G85+G86 -> 142.21975 | H5: =H65+H76+H81+H85+H86 -> 119.20615 | I5: =I65+I76+I81+I85+I86 -> 126.45741 | J5: =J65+J76+J81+J85+J86 -> 125.23791 | K5: =K65+K76+K81+K85+K86 -> 122.01803 | ... T5: =T65+T76+T81+T85+T86 -> 117.67025
A6: renewables (mainly biomass) | B6: Eurostat energy balances | C6: Mtoe | D6: =D109 -> 17.624981 | E6: =E109 -> 18.387066 | F6: =F109 -> 19.316373 | G6: =G109 -> 18.262628 | H6: =H109 -> 18.020873 | I6: =I109 -> 19.552827 | J6: =J109 -> 19.657035 | K6: =K109 -> 19.04706 | ... T6: =T109 -> 23.310921
A7: electricity | B7: Eurostat energy balances | C7: Mtoe | D7: =D131 -> 87.25259 | E7: =E131 -> 87.202153 | F7: =F131 -> 88.358376 | G7: =G131 -> 86.265145 | H7: =H131 -> 74.300824 | I7: =I131 -> 79.58803 | J7: =J131 -> 80.52822 | K7: =K131 -> 79.129937 | ... T7: =T131 -> 79.831363
A8: Others (heat and waste) | B8: Eurostat energy balances | C8: Mtoe | D8: =D132+D128 -> 16.207034 | E8: =E132+E128 -> 16.764237 | F8: =F132+F128 -> 17.887465 | G8: =G132+G128 -> 18.290436 | H8: =H132+H128 -> 17.62016 | I8: =I132+I128 -> 18.230786 | J8: =J132+J128 -> 18.820172 | K8: =K132+K128 -> 19.466152 | ... T8: =T132+T128 -> 19.531317
G10: 2005-2021 change
G11: Non-energy fossil fuels | H11: =T3-D3 -> -9.912316
G12: Total energy use | H12: =T4-D4 -> -34.781405
G13: Fossil fuels | H13: =T5-D5 -> -36.303183
G14: renewables (mainly biomass) | H14: =T6-D6 -> 5.68594
G15: electricity | H15: =T7-D7 -> -7.421227
G16: Others (heat and waste) | H16: =T8-D8 -> 3.324283
AE27: =(15-11)/19 -> 0.21052632
A29: Relative energy mix
B30: Source | C30: Unit | D30: 2005 | I30: 2010 | N30: 2015 | S30: 2020 | X30: 2025 | AC30: 2030 | AH30: 2035 | AM30: 2040 | AR30: 2045 | AW30: 2050
A31: % of fossils | B31: Eurostat energy balances | C31: % | D31: =D5/D4 -> 0.55964849 | E31: =E5/E4 -> 0.5459339 | F31: =F5/F4 -> 0.54193313 | G31: =G5/G4 -> 0.53645954 | H31: =H5/H4 -> 0.520141 | I31: =I5/I4 -> 0.51853773 | J31: =J5/J4 -> 0.51264915 | K31: =K5/K4 -> 0.50903902 | ... T31: =T5/T4 -> 0.48959127
A32: % of renewables | B32: Eurostat energy balances | C32: % | D32: =D6/D4 -> 0.064061662 | E32: =E6/E4 -> 0.068207258 | F32: =F6/F4 -> 0.07042681 | G32: =G6/G4 -> 0.068887483 | H32: =H6/H4 -> 0.078631804 | I32: =I6/I4 -> 0.080176231 | J32: =J6/J4 -> 0.080464153 | K32: =K6/K4 -> 0.079461184 | ... T32: =T6/T4 -> 0.09698988
A33: % of electricity | B33: Eurostat energy balances | C33: % | D33: =D7/D4 -> 0.3171377 | E33: =E7/E4 -> 0.32347846 | F33: =F7/F4 -> 0.3221515 | G33: =G7/G4 -> 0.32539614 | H33: =H7/H4 -> 0.32420226 | I33: =I7/I4 -> 0.32635016 | J33: =J7/J4 -> 0.3296344 | K33: =K7/K4 -> 0.33011701 | ... T33: =T7/T4 -> 0.3321548
A34: % of other (incl. hydrogen & marketed heat) | B34: Eurostat energy balances | D34: =D8/D4 -> 0.058907838 | E34: =E8/E4 -> 0.062187336 | F34: =F8/F4 -> 0.065217063 | G34: =G8/G4 -> 0.068992376 | H34: =H8/H4 -> 0.076883343 | I34: =I8/I4 -> 0.074755212 | J34: =J8/J4 -> 0.077038536 | K34: =K8/K4 -> 0.081209567 | ... T34: =T8/T4 -> 0.08126406
A35: benchmark - fossils | B35: CTP - MIX | C35: % | AC35: =AC166/AC165 -> 0.45456358 | AW35: =AW166/AW165 -> 0.05253289
A36: benchmark - renewables | B36: CTP - MIX | C36: % | AC36: =AC174/AC165 -> 0.11407479 | AW36: =AW174/AW165 -> 0.14709472
A37: benchmark - electricity | B37: CTP - MIX | C37: % | AC37: =AC177/AC165 -> 0.35814718 | AW37: =AW177/AW165 -> 0.50615666
A38: benchmark - other | B38: CTP - MIX | AC38: =SUM(AC171:AC173)/(AC165) -> 0.073214443 | AW38: =SUM(AW171:AW173)/(AW165) -> 0.29421573
A39: linear trajectory - fossils | T39: 0.48959127 | U39: 0.4856993 | V39: 0.48180734 | W39: 0.47791537 | X39: 0.47402341 | Y39: 0.47013144 | Z39: 0.46623948 | AA39: 0.46234751 | AB39: 0.45845555 | AC39: 0.45456358 | AD39: 0.43446205 | AE39: 0.41436051 | AF39: 0.39425898 | AG39: 0.37415745 | AH39: 0.35405591 | AI39: 0.33395438 | AJ39: 0.31385284 | AK39: 0.29375131 | AL39: 0.27364977 | AM39: 0.25354824 | AN39: 0.2334467 | AO39: 0.21334517 | AP39: 0.19324363 | AQ39: 0.1731421 | AR39: 0.15304056 | AS39: 0.13293903 | AT39: 0.11283749 | AU39: 0.09273596 | AV39: 0.072634425 | AW39: 0.05253289
A40: linear trajectory - renewables | T40: 0.09698988 | U40: 0.098888203 | V40: 0.10078653 | W40: 0.10268485 | X40: 0.10458317 | Y40: 0.1064815 | Z40: 0.10837982 | AA40: 0.11027814 | AB40: 0.11217647 | AC40: 0.11407479 | AD40: 0.11572579 | AE40: 0.11737678 | AF40: 0.11902778 | AG40: 0.12067878 | AH40: 0.12232977 | AI40: 0.12398077 | AJ40: 0.12563177 | AK40: 0.12728276 | AL40: 0.12893376 | AM40: 0.13058476 | AN40: 0.13223575 | AO40: 0.13388675 | AP40: 0.13553775 | AQ40: 0.13718874 | AR40: 0.13883974 | AS40: 0.14049074 | AT40: 0.14214173 | AU40: 0.14379273 | AV40: 0.14544373 | AW40: 0.14709472
A41: linear trajectory - electricity | T41: 0.3321548 | U41: 0.33504284 | V41: 0.33793088 | W41: 0.34081893 | X41: 0.34370697 | Y41: 0.34659501 | Z41: 0.34948305 | AA41: 0.3523711 | AB41: 0.35525914 | AC41: 0.35814718 | AD41: 0.36554766 | AE41: 0.37294813 | AF41: 0.3803486 | AG41: 0.38774908 | AH41: 0.39514955 | AI41: 0.40255003 | AJ41: 0.4099505 | AK41: 0.41735097 | AL41: 0.42475145 | AM41: 0.43215192 | AN41: 0.4395524 | AO41: 0.44695287 | AP41: 0.45435334 | AQ41: 0.46175382 | AR41: 0.46915429 | AS41: 0.47655477 | AT41: 0.48395524 | AU41: 0.49135571 | AV41: 0.49875619 | AW41: 0.50615666
A42: linear trajectory - other | T42: =T34 -> 0.08126406 | U42: =($AC$42-$T$42)/9+T42 -> 0.080369658 | V42: =($AC$42-$T$42)/9+U42 -> 0.079475256 | W42: =($AC$42-$T$42)/9+V42 -> 0.078580854 | X42: =($AC$42-$T$42)/9+W42 -> 0.077686452 | Y42: =($AC$42-$T$42)/9+X42 -> 0.07679205 | Z42: =($AC$42-$T$42)/9+Y42 -> 0.075897648 | AA42: =($AC$42-$T$42)/9+Z42 -> 0.075003246 | AB42: =($AC$42-$T$42)/9+AA42 -> 0.074108845 | AC42: =AC38 -> 0.073214443 | AD42: =($AW$42-$AC$42)/(2050-2030)+AC42 -> 0.084264507 | AE42: =($AW$42-$AC$42)/(2050-2030)+AD42 -> 0.095314571 | AF42: =($AW$42-$AC$42)/(2050-2030)+AE42 -> 0.10636463 | AG42: =($AW$42-$AC$42)/(2050-2030)+AF42 -> 0.1174147 | AH42: =($AW$42-$AC$42)/(2050-2030)+AG42 -> 0.12846476 | AI42: =($AW$42-$AC$42)/(2050-2030)+AH42 -> 0.13951483 | AJ42: =($AW$42-$AC$42)/(2050-2030)+AI42 -> 0.15056489 | AK42: =($AW$42-$AC$42)/(2050-2030)+AJ42 -> 0.16161496 | ... AV42: =($AW$42-$AC$42)/(2050-2030)+AU42 -> 0.28316566 | AW42: =AW38 -> 0.29421573
A43: 2040 advice scenarios - fossils | B43: fossil | AC43: =[3]Industry!AP219 -> 0.46673361 | AM43: =[3]Industry!AZ219 -> 0.22283393 | AW43: =[3]Industry!BJ219 -> 0.068479246
A44: 2040 advice scenarios - renewables | AC44: =[3]Industry!AP220 -> 0.17078136 | AM44: =[3]Industry!AZ220 -> 0.19769973 | AW44: =[3]Industry!BJ220 -> 0.19428402
A45: 2040 advice scenarios - electricity | AC45: =[3]Industry!AP221 -> 0.29238379 | AM45: =[3]Industry!AZ221 -> 0.42109276 | AW45: =[3]Industry!BJ221 -> 0.47221192
A46: 2040 advice - other | AC46: =[3]Industry!AP222 -> 0.070104923 | AM46: =[3]Industry!AZ222 -> 0.15836866 | AW46: =[3]Industry!BJ222 -> 0.23539492
D48: Average 2017-2021 | E48: Average 2022-2030 | F48: Average 2031-2050
A49: Fossils | D49: =(T31-P31)/4 -> -4.2318495e-05 | E49: =V39-U39 -> -0.0038919649 | F49: =AE39-AD39 -> -0.020101535
A50: renewables | D50: =(T32-P32)/4 -> 0.0012790509 | E50: =V40-U40 -> 0.0018983234 | F50: =AE40-AD40 -> 0.0016509966
A51: electricity | D51: =(T33-P33)/4 -> -0.0013525052 | E51: =V41-U41 -> 0.0028880425 | F51: =AE41-AD41 -> 0.0074004739
Q52: average 2017-2021 | R52: Average 2021-2030 | S52: Average 2031-2050
P53: Fossils | Q53: =AVERAGE(T31-S31,S31-R31,R31-Q31,Q31-P31) -> -4.2318495e-05 | R53: =V39-U39 -> -0.0038919649 | S53: =AF39-AE39 -> -0.020101535
P54: renewables (mainly biomass) | Q54: =AVERAGE(T32-S32,S32-R32,R32-Q32,Q32-P32) -> 0.0012790509 | R54: =V40-U40 -> 0.0018983234 | S54: =AF40-AE40 -> 0.0016509966
P55: electricity | Q55: =AVERAGE(T33-S33,S33-R33,R33-Q33,Q33-P33) -> -0.0013525052 | R55: =V41-U41 -> 0.0028880425 | S55: =AF41-AE41 -> 0.0074004739
L61: Indicator I6
A62: Historic data
B63: Source | C63: Unit | D63: 2005 | I63: 2010 | N63: 2015 | S63: 2020 | X63: 2025 | AC63: 2030 | AH63: 2035 | AM63: 2040 | AR63: 2045 | AW63: 2050
A64: Total | B64: Eurostat energy balances | C64: Mtoe | D64: 275.12525 | E64: 269.57638 | F64: 274.27585 | G64: 265.10807 | H64: 229.18046 | I64: 243.87311 | J64: 244.29556 | K64: 239.7027 | L64: 236.74852 | M64: 233.29777 | N64: 233.50766 | O64: 237.7992 | P64: 240.06351 | Q64: 242.46632 | R64: 239.2396 | S64: 230.92331 | T64: 240.34385
A65: Solid fossil fuels | B65: Eurostat energy balances | C65: Mtoe | D65: 17.369068 | E65: 17.268435 | F65: 17.843435 | G65: 16.476515 | H65: 13.09949 | I65: 13.190286 | J65: 14.710645 | K65: 13.681187 | L65: 12.935438 | M65: 12.60322 | N65: 12.962336 | O65: 12.9894 | P65: 13.193693 | Q65: 12.582302 | R65: 11.667757 | S65: 10.90815 | T65: 11.069728
A66: Anthracite | B66: Eurostat energy balances | C66: Mtoe | D66: 0.617332 | E66: 0.630415 | F66: 0.687536 | G66: 0.689113 | H66: 0.461958 | I66: 0.753637 | J66: 1.483667 | K66: 1.495101 | L66: 1.587228 | M66: 1.234698 | N66: 1.336823 | O66: 1.308475 | P66: 1.345654 | Q66: 1.22452 | R66: 1.101765 | S66: 0.859389 | T66: 1.102354
A67: Coking coal | B67: Eurostat energy balances | C67: Mtoe | D67: 0.199675 | E67: 0.088101 | F67: 0.080863 | G67: 0.033058 | H67: 0.044377 | I67: 0.0439 | J67: 0.087716 | K67: 0.086089 | L67: 0.041517 | M67: 0.017085 | N67: 0.010812 | O67: 0.01526 | P67: 0.021734 | Q67: 0.025126 | R67: 0.010821 | S67: 0.021975 | T67: 0.027931
A68: Other bituminous coal | B68: Eurostat energy balances | C68: Mtoe | D68: 9.292023 | E68: 8.677394 | F68: 10.166059 | G68: 9.43697 | H68: 7.320729 | I68: 7.420761 | J68: 7.515841 | K68: 6.768986 | L68: 6.129545 | M68: 6.456454 | N68: 6.488232 | O68: 6.556074 | P68: 6.769165 | Q68: 6.37802 | R68: 6.035039 | S68: 5.559542 | T68: 5.391819
A69: Sub-bituminous coal | B69: Eurostat energy balances | C69: Mtoe | D69: 0.278039 | E69: 0.355691 | F69: 0.339661 | G69: 0.258956 | H69: 0.151907 | I69: 0.191157 | J69: 0.169955 | K69: 0.279293 | L69: 0.298046 | M69: 0.297026 | N69: 0.352885 | O69: 0.361332 | P69: 0.316952 | Q69: 0.313014 | R69: 0.343321 | S69: 0.308933 | T69: 0.36495
A70: Lignite | B70: Eurostat energy balances | C70: Mtoe | D70: 1.397904 | E70: 1.431262 | F70: 1.0295 | G70: 1.113492 | H70: 1.255037 | I70: 0.719162 | J70: 0.705488 | K70: 0.75195 | L70: 0.679498 | M70: 0.65837 | N70: 0.641574 | O70: 0.566079 | P70: 0.634177 | Q70: 0.644986 | R70: 0.576986 | S70: 0.565326 | T70: 0.578086
A71: Coke oven coke | B71: Eurostat energy balances | C71: Mtoe | D71: 3.950961 | E71: 4.532895 | F71: 3.917512 | G71: 3.283348 | H71: 2.400156 | I71: 2.55506 | J71: 2.926384 | K71: 2.436949 | L71: 2.282627 | M71: 2.099889 | N71: 2.33558 | O71: 2.291137 | P71: 2.242907 | Q71: 2.159557 | R71: 1.946802 | S71: 1.718643 | T71: 1.752178
A72: Gas coke | B72: Eurostat energy balances | C72: Mtoe | D72: 0 | E72: 0 | F72: 0 | G72: 0 | H72: 0 | I72: 0 | J72: 0 | K72: 0 | L72: 0 | M72: 0 | N72: 0 | O72: 0 | P72: 0 | Q72: 0 | R72: 0 | S72: 0 | T72: 0
A73: Patent fuel | B73: Eurostat energy balances | C73: Mtoe | D73: 0.0075 | E73: 0.003554 | F73: 0 | G73: 0.00075 | H73: 0.002167 | I73: 0 | J73: 0.005145 | K73: 0.041833 | L73: 0.017386 | M73: 0 | N73: 0 | O73: 0 | P73: 0.000143 | Q73: 0.019859 | R73: 0.000503 | S73: 0.0007 | T73: 0.000316
A74: Brown coal briquettes | B74: Eurostat energy balances | C74: Mtoe | D74: 1.54434 | E74: 1.503152 | F74: 1.569024 | G74: 1.596563 | H74: 1.350895 | I74: 1.500404 | J74: 1.755976 | K74: 1.763251 | L74: 1.842954 | M74: 1.786076 | N74: 1.741897 | O74: 1.815535 | P74: 1.848104 | Q74: 1.796289 | R74: 1.63788 | S74: 1.869613 | T74: 1.850747
A75: Coal tar | B75: Eurostat energy balances | C75: Mtoe | D75: 0.081302 | E75: 0.045968 | F75: 0.053282 | G75: 0.064264 | H75: 0.112259 | I75: 0.006204 | J75: 0.060474 | K75: 0.057737 | L75: 0.056635 | M75: 0.05362 | N75: 0.054533 | O75: 0.075504 | P75: 0.014857 | Q75: 0.020932 | R75: 0.014643 | S75: 0.004025 | T75: 0.001349
... A88: Natural gas liquids | B88: Eurostat energy balances | C88: Mtoe | D88: 0 | E88: 0 | F88: 0.0477 | G88: 0 | H88: 0.015357 | I88: 0.001181 | J88: 0 | K88: 0.002363 | L88: 0.003544 | M88: 0.004725 | N88: 0.007088 | O88: 0.007088 | P88: 0.006717 | Q88: 0.013246 | R88: 0.02513 | S88: 0.031609 | T88: 0.053245
A89: Refinery feedstocks | B89: Eurostat energy balances | C89: Mtoe | D89: #VALUE! | E89: #VALUE! | F89: #VALUE! | G89: #VALUE! | H89: #VALUE! | I89: #VALUE! | J89: #VALUE! | K89: #VALUE! | L89: #VALUE! | M89: #VALUE! | N89: #VALUE! | O89: #VALUE! | P89: #VALUE! | Q89: #VALUE! | R89: #VALUE! | S89: #VALUE! | T89: #VALUE!
A90: Additives and oxygenates (excluding biofuel portion) | B90: Eurostat energy balances | C90: Mtoe | D90: #VALUE! | E90: #VALUE! | F90: #VALUE! | G90: #VALUE! | H90: #VALUE! | I90: #VALUE! | J90: #VALUE! | K90: #VALUE! | L90: #VALUE! | M90: #VALUE! | N90: #VALUE! | O90: #VALUE! | P90: #VALUE! | Q90: #VALUE! | R90: #VALUE! | S90: #VALUE! | T90: #VALUE!
A91: Other hydrocarbons | B91: Eurostat energy balances | C91: Mtoe | D91: #VALUE! | E91: #VALUE! | F91: #VALUE! | G91: #VALUE! | H91: #VALUE! | I91: #VALUE! | J91: #VALUE! | K91: #VALUE! | L91: #VALUE! | M91: #VALUE! | N91: #VALUE! | O91: #VALUE! | P91: #VALUE! | Q91: #VALUE! | R91: #VALUE! | S91: #VALUE! | T91: #VALUE!
A92: Refinery gas | B92: Eurostat energy balances | C92: Mtoe | D92: 3.43373 | E92: 3.9205 | F92: 4.674245 | G92: 4.111088 | H92: 3.698203 | I92: 3.857791 | J92: 3.397974 | K92: 3.579863 | L92: 3.271802 | M92: 3.369149 | N92: 3.454971 | O92: 3.706369 | P92: 3.687715 | Q92: 3.800047 | R92: 3.87808 | S92: 4.100433 | T92: 3.957252
A93: Ethane | B93: Eurostat energy balances | C93: Mtoe | D93: 0.015515 | E93: 0.004433 | F93: 0.007925 | G93: 0.010189 | H93: 0 | I93: 0 | J93: 0 | K93: 0 | L93: 0 | M93: 0 | N93: 0 | O93: 0 | P93: 0 | Q93: 0 | R93: 0 | S93: 0.000345 | T93: 0.000436
A94: Liquefied petroleum gases | B94: Eurostat energy balances | C94: Mtoe | D94: 3.143031 | E94: 3.330362 | F94: 3.168272 | G94: 2.998649 | H94: 2.745584 | I94: 2.884167 | J94: 2.706623 | K94: 2.658454 | L94: 2.436723 | M94: 2.507556 | N94: 2.429464 | O94: 2.473575 | P94: 2.429163 | Q94: 2.596092 | R94: 2.497823 | S94: 2.328988 | T94: 2.44061
A95: Naphtha | B95: Eurostat energy balances | C95: Mtoe | D95: 0.170045 | E95: 0.032922 | F95: 0.030823 | G95: 0.037175 | H95: 0.937422 | I95: 1.058277 | J95: 1.166858 | K95: 1.20192 | L95: 1.453684 | M95: 1.483374 | N95: 1.507456 | O95: 1.560688 | P95: 1.279519 | Q95: 1.285387 | R95: 1.033269 | S95: 1.152345 | T95: 1.245762
A96: Aviation gasoline | B96: Eurostat energy balances | C96: Mtoe | D96: 0 | E96: 0 | F96: 0 | G96: 0 | H96: 0 | I96: 0 | J96: 0 | K96: 0 | L96: 0 | M96: 0 | N96: 0 | O96: 0 | P96: 1e-06 | Q96: 1e-06 | R96: 1e-06 | S96: 2e-06 | T96: 2.8e-05
A97: Motor gasoline (excluding biofuel portion) | B97: Eurostat energy balances | C97: Mtoe | D97: 0.39062 | E97: 0.360168 | F97: 0.461346 | G97: 0.298845 | H97: 0.300812 | I97: 0.229879 | J97: 0.067549 | K97: 0.52231 | L97: 0.351417 | M97: 0.355514 | N97: 0.05884 | O97: 0.194608 | P97: 0.183732 | Q97: 0.256365 | R97: 0.257 | S97: 0.173537 | T97: 0.147765
A98: Gasoline-type jet fuel | B98: Eurostat energy balances | C98: Mtoe | D98: 0 | E98: 0 | F98: 0 | G98: 0 | H98: 0 | I98: 0 | J98: 0 | K98: 0 | L98: 0 | M98: 0 | N98: 0 | O98: 0 | P98: 0 | Q98: 0 | R98: 0 | S98: 0 | T98: 0
A99: Kerosene-type jet fuel (excluding biofuel portion) | B99: Eurostat energy balances | C99: Mtoe | D99: 0.023924 | E99: 0.026005 | F99: 0.021904 | G99: 0.016459 | H99: 0.014531 | I99: 0.022746 | J99: 0.018613 | K99: 0.013482 | L99: 0.015551 | M99: 0.013485 | N99: 0.006308 | O99: 0.007334 | P99: 0.006029 | Q99: 0.006189 | R99: 0.004656 | S99: 0.0039 | T99: 0.003517
A100: Other kerosene | B100: Eurostat energy balances | C100: Mtoe | D100: 0.052825 | E100: 0.03987 | F100: 0.024832 | G100: 0.020773 | H100: 0.014714 | I100: 0.010928 | J100: 0.010952 | K100: 0.014231 | L100: 0.010588 | M100: 0.0135 | N100: 0.015777 | O100: 0.013369 | P100: 0.012139 | Q100: 0.013668 | R100: 0.012312 | S100: 0.013069 | T100: 0.011688
A101: Gas oil and diesel oil (excluding biofuel portion) | B101: Eurostat energy balances | C101: Mtoe | D101: 10.947236 | E101: 9.721572 | F101: 9.982073 | G101: 9.554908 | H101: 8.417804 | I101: 8.436107 | J101: 8.310537 | K101: 7.731319 | L101: 7.235068 | M101: 6.898489 | N101: 7.138287 | O101: 7.066545 | P101: 7.086339 | Q101: 8.513393 | R101: 8.346198 | S101: 8.188878 | T101: 8.506635
A102: Fuel oil | B102: Eurostat energy balances | C102: Mtoe | D102: 11.645592 | E102: 12.226776 | F102: 11.125154 | G102: 10.276845 | H102: 8.14362 | I102: 6.697258 | J102: 6.068232 | K102: 5.041851 | L102: 4.537052 | M102: 3.988574 | N102: 4.185771 | O102: 3.697676 | P102: 3.137818 | Q102: 3.001106 | R102: 2.567252 | S102: 2.4457 | T102: 2.524427
A103: White spirit and special boiling point industrial spirits | B103: Eurostat energy balances | C103: Mtoe | D103: 0.003319 | E103: 0.003768 | F103: 0.005509 | G103: 0.004434 | H103: 0.004683 | I103: 0.00486 | J103: 0.004818 | K103: 0.004853 | L103: 0.001813 | M103: 0.001504 | N103: 0.001418 | O103: 0.005246 | P103: 0.002926 | Q103: 0.003708 | R103: 0.008531 | S103: 0.005328 | T103: 0.225192
... A109: Renewables and biofuels | B109: Eurostat energy balances | C109: Mtoe | D109: 17.624981 | E109: 18.387066 | F109: 19.316373 | G109: 18.262628 | H109: 18.020873 | I109: 19.552827 | J109: 19.657035 | K109: 19.04706 | L109: 19.584087 | M109: 19.985262 | N109: 20.803288 | O109: 21.709893 | P109: 22.055517 | Q109: 22.601831 | R109: 23.10638 | S109: 23.181768 | T109: 23.310921
A110: Hydro | B110: Eurostat energy balances | C110: Mtoe
A111: Geothermal | B111: Eurostat energy balances | C111: Mtoe | D111: 0.002269 | E111: 0.002006 | F111: 0.001887 | G111: 0.0016 | H111: 0.001313 | I111: 0.006544 | J111: 0.005494 | K111: 0.00406 | L111: 0.003894 | M111: 0.003392 | N111: 0.003583 | O111: 0.006974 | P111: 0.004999 | Q111: 0.003154 | R111: 0.003148 | S111: 0.003445 | T111: 0.00352
A112: Wind | B112: Eurostat energy balances | C112: Mtoe
A113: Solar thermal | B113: Eurostat energy balances | C113: Mtoe | D113: 0.001777 | E113: 0.001975 | F113: 0.002163 | G113: 0.00262 | H113: 0.002958 | I113: 0.009968 | J113: 0.010516 | K113: 0.011612 | L113: 0.012675 | M113: 0.013852 | N113: 0.014639 | O113: 0.01525 | P113: 0.016218 | Q113: 0.01759 | R113: 0.01834 | S113: 0.017272 | T113: 0.018376
A114: Solar photovoltaic | B114: Eurostat energy balances | C114: Mtoe
A115: Tide, wave, ocean | B115: Eurostat energy balances | C115: Mtoe
A116: Ambient heat (heat pumps) | B116: Eurostat energy balances | C116: Mtoe | D116: 0.028471 | E116: 0.031909 | F116: 0.031816 | G116: 0.032834 | H116: 0.036148 | I116: 0.040872 | J116: 0.045355 | K116: 0.049401 | L116: 0.053945 | M116: 0.179428 | N116: 0.199383 | O116: 0.223324 | P116: 0.247903 | Q116: 0.28723 | R116: 0.316822 | S116: 0.346836 | T116: 0.377544
A117: Primary solid biofuels | B117: Eurostat energy balances | C117: Mtoe | D117: 17.140626 | E117: 17.844727 | F117: 18.526306 | G117: 17.810628 | H117: 17.559431 | I117: 18.905488 | J117: 18.884684 | K117: 18.339041 | L117: 18.623963 | M117: 18.844666 | N117: 19.591447 | O117: 20.366671 | P117: 20.478225 | Q117: 20.683293 | R117: 21.073089 | S117: 20.997761 | T117: 21.120484
A118: Charcoal | B118: Eurostat energy balances | C118: Mtoe | D118: 0.014713 | E118: 0.015449 | F118: 0.014713 | G118: 0.037518 | H118: 0.019127 | I118: 0.007356 | J118: 0.007356 | K118: 0.007356 | L118: 0.008324 | M118: 0.00831 | N118: 0.008297 | O118: 0.008287 | P118: 0.008529 | Q118: 0.007698 | R118: 0.007417 | S118: 0.007417 | T118: 0.007417
A119: Pure biogasoline | B119: Eurostat energy balances | C119: Mtoe | D119: 0 | E119: 0 | F119: 0 | G119: 0 | H119: 0 | I119: 3e-06 | J119: 0 | K119: 0.0009 | L119: 0.001104 | M119: 0.001246 | N119: 0.00151 | O119: 0 | P119: 0 | Q119: 0 | R119: 0 | S119: 0 | T119: 0
A120: Blended biogasoline | B120: Eurostat energy balances | C120: Mtoe | D120: 0.000149 | E120: 0.000178 | F120: 0.000212 | G120: 0.000275 | H120: 0.000233 | I120: 0.000252 | J120: 0.000294 | K120: 0.000279 | L120: 0.000261 | M120: 0.000246 | N120: 0.000233 | O120: 0.000202 | P120: 0.000151 | Q120: 0.003549 | R120: 0.003482 | S120: 0.003419 | T120: 0.003482
A121: Pure biodiesels | B121: Eurostat energy balances | C121: Mtoe | D121: 5.9e-05 | E121: 0.000388 | F121: 0.000207 | G121: 0.000212 | H121: 0.000628 | I121: 0.001372 | J121: 0.002937 | K121: 0.001974 | L121: 0.002038 | M121: 0.006391 | N121: 0.007657 | O121: 0.014313 | P121: 0.033611 | Q121: 0.037468 | R121: 0.028828 | S121: 0.028569 | T121: 0.022551
A122: Blended biodiesels | B122: Eurostat energy balances | C122: Mtoe | D122: 0.003616 | E122: 0.015307 | F122: 0.025661 | G122: 0.028326 | H122: 0.03688 | I122: 0.038611 | J122: 0.040002 | K122: 0.065018 | L122: 0.065277 | M122: 0.075487 | N122: 0.090985 | O122: 0.138375 | P122: 0.163621 | Q122: 0.267955 | R122: 0.278352 | S122: 0.268665 | T122: 0.306109
A123: Pure bio jet kerosene | B123: Eurostat energy balances | C123: Mtoe | D123: 0 | E123: 0 | F123: 0 | G123: 0 | H123: 0 | I123: 0 | J123: 0 | K123: 0 | L123: 0 | M123: 0 | N123: 0 | O123: 0 | P123: 0 | Q123: 0 | R123: 0 | S123: 0 | T123: 0
A124: Blended bio jet kerosene | B124: Eurostat energy balances | C124: Mtoe | D124: 0 | E124: 0 | F124: 0 | G124: 0 | H124: 0 | I124: 0 | J124: 0 | K124: 0 | L124: 0 | M124: 0 | N124: 0 | O124: 0 | P124: 0 | Q124: 0 | R124: 0 | S124: 0 | T124: 0
A125: Other liquid biofuels | B125: Eurostat energy balances | C125: Mtoe | D125: 0.019858 | E125: 0.043583 | F125: 0.055098 | G125: 0.107556 | H125: 0.085562 | I125: 0.080881 | J125: 0.043294 | K125: 0.014256 | L125: 0.021874 | M125: 0.038068 | N125: 0.027474 | O125: 0.037782 | P125: 0.03257 | Q125: 0.070562 | R125: 0.072608 | S125: 0.122104 | T125: 0.112137
A126: Biogases | B126: Eurostat energy balances | C126: Mtoe | D126: 0.131561 | E126: 0.11617 | F126: 0.153941 | G126: 0.133464 | H126: 0.16371 | I126: 0.307345 | J126: 0.339633 | K126: 0.226563 | L126: 0.288777 | M126: 0.312061 | N126: 0.308999 | O126: 0.331842 | P126: 0.38566 | Q126: 0.407384 | R126: 0.468843 | S126: 0.521922 | T126: 0.508431
A127: Renewable municipal waste | B127: Eurostat energy balances | C127: Mtoe | D127: 0.281887 | E127: 0.315372 | F127: 0.504371 | G127: 0.1076 | H127: 0.11488 | I127: 0.154136 | J127: 0.277472 | K127: 0.326597 | L127: 0.501954 | M127: 0.502115 | N127: 0.549083 | O127: 0.566873 | P127: 0.684033 | Q127: 0.815953 | R127: 0.835455 | S127: 0.864363 | T127: 0.830871
... A134: non-energy - oil and petroleum products | B134: Eurostat energy balances | C134: Mtoe | D134: 85.898337 | E134: 87.159363 | F134: 86.37785 | G134: 84.168721 | H134: 77.078504 | I134: 80.456029 | J134: 77.777253 | K134: 74.671898 | L134: 71.703445 | M134: 73.096884 | N134: 70.610588 | O134: 70.47865 | P134: 75.890906 | Q134: 72.435507 | R134: 71.494762 | S134: 71.472646 | T134: 75.985965
A136: Benchmark data
A137: Baseline
B138: Source | C138: Unit | D138: 2005 | I138: 2010 | N138: 2015 | S138: 2020 | X138: 2025 | AC138: 2030 | AH138: 2035 | AM138: 2040 | AR138: 2045 | AW138: 2050
A139: Total | B139: CTP IA figure 67 | C139: Mtoe | AC139: =SUM(AC140:AC148) -> 249.29858 | AW139: =SUM(AW140:AW148) -> 242.39
A140: Coal | B140: CTP IA figure 67 | C140: Mtoe | AC140: 9.9605931 | AW140: 4.354041
A141: Oil | B141: CTP IA figure 67 | C141: Mtoe | AC141: 34.247904 | AW141: 17.66954
A142: Natural gas* | B142: CTP IA figure 67 | C142: Mtoe | AC142: 73.863305 | AW142: 74.093
...

Sheet I7a,b&c. Low carbon projects
A1: Steel
A2: Row Labels | B2: DRI | C2: H2 production | D2: EAF | E2: other | F2: CCS/CCU | H2: Indicator I7a
A3: R&D | B3: 2 | C3: 2 | E3: 2
A4: pilot | B4: 3 | C4: 1 | E4: 3 | F4: 1
A5: demo | B5: 3 | C5: 2
A6: full scale | B6: 15 | C6: 7 | D6: 5 | E6: 1 | F6: 1
A13: Green steel tracker data
A14: Company | B14: Project name (if applicable) | C14: Project website | D14: GEM Project ID | E14: 2030 climate target | F14: 2050 climate target | G14: [ref] Climate target | H14: 2021 company production (Mtpa, million tonnes steel p.a.) (source: World Steel in Figures 2022) | I14: Country (in which project/investment is taking place) | J14: Location | K14: Latitude | L14: Longitude | M14: Coordinate accuracy | N14: Continent (in which project/investment is taking place) | O14: [ref] Location | P14: Project scale | Q14: [ref] Project scale | R14: Technology category | S14: technology group | T14: Hydrogen type (if applicable) | U14: Specific technology | V14: [ref] Technology | W14: Year online | X14: [ref] Year online | Y14: Size (m USD) | Z14: [ref] Size | AA14: Steel production capacity (million tonnes per year) | AB14: [ref] Steel production capacity | AC14: Iron production capacity (million tonnes per year) | AD14: [ref] Iron production capacity | AE14: Hydrogen generation capacity (MW) | AF14: [ref] Hydrogen generation capacity | AG14: Carbon capture capacity (million tonnes CO2 per year) | AH14: [ref] Carbon capture capacity | AI14: Partners | AJ14: [ref] Partners | AK14: Comments | AL14: [ref] Comments | AM14: Last update (year-month-day) | AN14: Date of announcement (year-month-day) | AQ14: Count of Project name (if applicable) | AR14: Column Labels
A15: ArcelorMittal | B15: N/A | C15: N/A | D15: SBE00001-1 | E15: 35% reduction in Europe (baseline 2018) | F15: carbon neutrality | G15: https://corporate-media.arcelormittal.com/media/ob3lpdom/car_2.pdf | H15: 79.26 | I15: Belgium | J15: Ghent | K15: 51.169929 | L15: 3.804462 | M15: TBC | N15: Europe | O15: https://corporate.arcelormittal.com/media/press-releases/arcelormittal-signs-letter-of-intent-with-the-governments-of-belgium-and-flanders-supporting-1-1-billion-investment-in-decarbonisation-technologies-at-its-flagship-gent-plant | P15: full scale | Q15: https://corporate.arcelormittal.com/media/press-releases/arcelormittal-signs-letter-of-intent-with-the-governments-of-belgium-and-flanders-supporting-1-1-billion-investment-in-decarbonisation-technologies-at-its-flagship-gent-plant | R15: NG-DR --> H-DR & EAF | S15: DRI | T15: Green electrolytic | U15: NG-DR --> H-DR & EAF | V15: https://corporate.arcelormittal.com/media/press-releases/arcelormittal-signs-letter-of-intent-with-the-governments-of-belgium-and-flanders-supporting-1-1-billion-investment-in-decarbonisation-technologies-at-its-flagship-gent-plant | W15: 2030 | X15: https://corporate.arcelormittal.com/media/press-releases/arcelormittal-signs-letter-of-intent-with-the-governments-of-belgium-and-flanders-supporting-1-1-billion-investment-in-decarbonisation-technologies-at-its-flagship-gent-plant | Y15: 1237 | Z15: https://corporate.arcelormittal.com/media/press-releases/arcelormittal-signs-letter-of-intent-with-the-governments-of-belgium-and-flanders-supporting-1-1-billion-investment-in-decarbonisation-technologies-at-its-flagship-gent-plant | AA15: Not stated | AB15: https://corporate.arcelormittal.com/media/press-releases/arcelormittal-signs-letter-of-intent-with-the-governments-of-belgium-and-flanders-supporting-1-1-billion-investment-in-decarbonisation-technologies-at-its-flagship-gent-plant | AC15: 2.5 | AD15: https://corporate.arcelormittal.com/media/press-releases/arcelormittal-signs-letter-of-intent-with-the-governments-of-belgium-and-flanders-supporting-1-1-billion-investment-in-decarbonisation-technologies-at-its-flagship-gent-plant | AE15: N/A | AF15: https://corporate.arcelormittal.com/media/press-releases/arcelormittal-signs-letter-of-intent-with-the-governments-of-belgium-and-flanders-supporting-1-1-billion-investment-in-decarbonisation-technologies-at-its-flagship-gent-plant | AG15: N/A | AH15: https://corporate.arcelormittal.com/media/press-releases/arcelormittal-signs-letter-of-intent-with-the-governments-of-belgium-and-flanders-supporting-1-1-billion-investment-in-decarbonisation-technologies-at-its-flagship-gent-plant | AI15: N/A | AJ15: https://corporate.arcelormittal.com/media/press-releases/arcelormittal-signs-letter-of-intent-with-the-governments-of-belgium-and-flanders-supporting-1-1-billion-investment-in-decarbonisation-technologies-at-its-flagship-gent-plant | AK15: 2022-10-17 No further comment Letters of intent signed between ArcelorMittal and Belgium and Flanders governments | AL15: https://corporate.arcelormittal.com/media/press-releases/arcelormittal-signs-letter-of-intent-with-the-governments-of-belgium-and-flanders-supporting-1-1-billion-investment-in-decarbonisation-technologies-at-its-flagship-gent-plant | AM15: 44851 | AN15: 44467 | AQ15: Row Labels | AR15: CCS/CCU | AS15: DRI | AT15: EAF | AU15: H2 production | AV15: other | AW15: Grand Total
A16: ArcelorMittal | B16: 3D | C16: https://3d-ccus.com/ | D16: SFR00001 | E16: 35% reduction in Europe (baseline 2018) | F16: carbon neutrality | G16: https://corporate-media.arcelormittal.com/media/ob3lpdom/car_2.pdf | H16: 79.26 | I16: France | J16: Dunkirk | K16: 51.041274 | L16: 2.292948 | M16: exact | N16: Europe | O16: https://flateurope.arcelormittal.com/ourmills/704/dunkerque | P16: pilot | Q16: https://3d-ccus.com/3d-publications/#press | R16: CCS | S16: CCS/CCU | T16: N/A | U16: CCS | V16: https://3d-ccus.com/3d-overview/ | W16: 2021 | X16: https://3d-ccus.com/3d-overview/ | Y16: 22.8 | Z16: https://3d-ccus.com/ | AA16: N/A | AB16: https://3d-ccus.com/3d-overview/ | AC16: N/A | AD16: https://3d-ccus.com/3d-overview/ | AE16: N/A | AF16: https://3d-ccus.com/3d-overview/ | AG16: 0.005 | AH16: https://3d-ccus.com/3d-overview/ | AI16: Axens, Total, Air Products, Brevik Engineering, CMI, DTU, Gassco, RWTH and Uetikon. | AJ16: https://3d-ccus.com/3d-project-partners/ | AK16: 2022-10-17 No further comment // 2022-05-25: No further comment // Horizon 2020 project; aims to scale up to 1MtCO2 by 2025 and 10MtCO2 by 2035. // 02/03: Pilot running. Scheduled to last for 12 to 18 months, is the final stage before the technology’s full-scale deployment. | AL16: https://totalenergies.com/media/news/press-releases/france-start-3d-carbon-capture-pilot-dunkirk | AM16: 44851 | AN16: 43530 | AQ16: demo | AS16: 3 | AU16: 2 | AW16: 5
A17: ArcelorMittal | B17: N/A | C17: N/A | D17: SFR00001 | E17: 35% reduction in Europe (baseline 2018) | F17: carbon neutrality | G17: https://corporate-media.arcelormittal.com/media/ob3lpdom/car_2.pdf | H17: 79.26 | I17: France | J17: Dunkirk | K17: 51.041274 | L17: 2.292948 | M17: exact | N17: Europe | O17: https://flateurope.arcelormittal.com/ourmills/704/dunkerque | P17: full scale | Q17: https://corporate.arcelormittal.com/media/news-articles/air-liquide-and-arcelormittal-join-forces-to-accelerate-the-decarbonisation-of-steel-production-in-the-dunkirk-industrial-basin | R17: H-DR | S17: DRI | T17: Blue | U17: H-DR + EAF & CCS | V17: https://corporate.arcelormittal.com/media/news-articles/air-liquide-and-arcelormittal-join-forces-to-accelerate-the-decarbonisation-of-steel-production-in-the-dunkirk-industrial-basin | W17: 2027 | X17: https://corporate.arcelormittal.com/media/press-releases/arcelormittal-accelerates-its-decarbonisation-with-a-1-7-billion-investment-programme-in-france-supported-by-the-french-government | Y17: Not stated | Z17: https://corporate.arcelormittal.com/media/news-articles/air-liquide-and-arcelormittal-join-forces-to-accelerate-the-decarbonisation-of-steel-production-in-the-dunkirk-industrial-basin | AA17: Not stated | AB17: https://corporate.arcelormittal.com/media/news-articles/air-liquide-and-arcelormittal-join-forces-to-accelerate-the-decarbonisation-of-steel-production-in-the-dunkirk-industrial-basin | AC17: 2.5 | AD17: https://corporate.arcelormittal.com/media/press-releases/arcelormittal-accelerates-its-decarbonisation-with-a-1-7-billion-investment-programme-in-france-supported-by-the-french-government | AE17: N/A | AF17: https://www.steelorbis.com/steel-news/latest-news/arcelormittal-and-air-liquide-join-forces-for-decarbonization-of-steelmaking-in-dunkirk-1191099.htm | AG17: 0.00438 | AH17: https://france.arcelormittal.com/news/2019/dec/arcelormittal-europe-se-fixe-comme-objectif-de-reduire-ses-emissions-de-co2.aspx | AI17: Air Liquide | AJ17: https://corporate.arcelormittal.com/media/news-articles/air-liquide-and-arcelormittal-join-forces-to-accelerate-the-decarbonisation-of-steel-production-in-the-dunkirk-industrial-basin | AK17: 2022-10-17 No further comments // 2022-05-17 No further comments. // 2022-02-04: Support from the French Government for ArcelorMittal’s decarbonization programme in France, which involves a €1.7 billion investment in its Fos-sur-Mer and Dunkirk sites in France. The partnership between ArcelorMittal and the French government for the projects is subject to EU approval, which is anticipated by the second quarter of this year, as well as the availability of economically viable energy infrastructure and supply. https://corporate.arcelormittal.com/media/press-releases/arcelormittal-accelerates-its-decarbonisation-with-a-1-7-billion-investment-programme-in-france-supported-by-the-french-government. Using "low-carbon" hydrogen. MoU signed. Applied for Important Project of Common European Interest (IPCEI). The new industrial facilities will be operational starting in 2027 and will gradually replace 3 out of 5 of ArcelorMittal’s blast furnaces in France by 2030 (2 out of 3 in Dunkirk, 1 out of 2 in Fos). | AL17: https://corporate.arcelormittal.com/media/news-articles/air-liquide-and-arcelormittal-join-forces-to-accelerate-the-decarbonisation-of-steel-production-in-the-dunkirk-industrial-basin // https://corporate.arcelormittal.com/media/press-releases/arcelormittal-accelerates-its-decarbonisation-with-a-1-7-billion-investment-programme-in-france-supported-by-the-french-government# | AM17: 44851 | AN17: 44272 | AQ17: full scale | AR17: 1 | AS17: 15 | AT17: 5 | AU17: 7 | AV17: 1 | AW17: 29
A18: ArcelorMittal | B18: SIDERWIN | C18: https://www.siderwin-spire.eu/content/home | D18: TBD | E18: 35% reduction in Europe (baseline 2018) | F18: carbon neutrality | G18: https://corporate-media.arcelormittal.com/media/ob3lpdom/car_2.pdf | H18: 79.26 | I18: France | J18: Maizières-lès-Metz | K18: 49.200148 | L18: 6.1521338 | M18: exact | N18: Europe | O18: https://www.google.com/maps/place/ArcelorMittal+Maizi%C3%A8res+Research+SA/@49.2001901,6.1498485,1012m/data=!3m2!1e3!4b1!4m5!3m4!1s0x47952763712f4885:0x3c31c2bfb0413f7c!8m2!3d49.2001901!4d6.1520372 | P18: pilot | Q18: https://www.siderwin-spire.eu/content/home | R18: Other | S18: other | T18: N/A | U18: Electrowinning | V18: https://www.siderwin-spire.eu/content/home | W18: 2022 | X18: https://www.siderwin-spire.eu/content/home | Y18: 9 | Z18: https://www.siderwin-spire.eu/sites/siderwin.drupal.pulsartecnalia.com/files/documents/Massive%20production%20of%20primary%20steel_presentation_DECHEMA_23_11_2018.pdf | AA18: 1.825e-05 | AB18: https://zenodo.org/record/4327314#.X9oWA7N7nIU | AC18: N/A | AD18: https://www.siderwin-spire.eu/sites/siderwin.drupal.pulsartecnalia.com/files/documents/Massive%20production%20of%20primary%20steel_presentation_DECHEMA_23_11_2018.pdf | AE18: N/A | AF18: https://www.siderwin-spire.eu/sites/siderwin.drupal.pulsartecnalia.com/files/documents/Massive%20production%20of%20primary%20steel_presentation_DECHEMA_23_11_2018.pdf | AG18: N/A | AH18: https://www.siderwin-spire.eu/sites/siderwin.drupal.pulsartecnalia.com/files/documents/Massive%20production%20of%20primary%20steel_presentation_DECHEMA_23_11_2018.pdf | AI18: JohnCockerill (Belgium), EDF (France), CFD-Numerics (France), QUANTIS (Switzerland), TECNALIA (Spain), UAVR (Portugal), Mytilineos (Greece), NTUA (Greece), N-Side (Belgium), Dynergie (France), NTNU (Norway) | AJ18: https://www.siderwin-spire.eu/content/home | AK18: 2022-10-17 No further comments // 25/05: No further comments // Duration: October 2017 - September 2022 (60 months) 24/03: First trials are expected for middle of April 2022. | AL18: https://www.siderwin-spire.eu/news | AM18: 44851 | AN18: 43009 | AQ18: pilot | AR18: 1 | AS18: 3 | AU18: 1 | AV18: 3 | AW18: 8
A19: ArcelorMittal | B19: HyBit - Hydrogen for Bremen’s industrial transformation | C19: N/A | D19: SDE00006 | E19: 35% reduction in Europe (baseline 2018) | F19: carbon neutrality | G19: https://corporate-media.arcelormittal.com/media/ob3lpdom/car_2.pdf | H19: 79.26 | I19: Germany | J19: Bremen | K19: 53.133305 | L19: 8.688193 | M19: exact | N19: Europe | O19: https://bremen.arcelormittal.com/Ueber-uns/ | P19: full scale | Q19: https://www.ewe.com/de/presse/pressemitteilungen/2020/07/ewe-mit-tochter-swb-und-arcelormittal-kooperieren-bei-grner-stahlerzeugung-ewe-ag | R19: Hydrogen production | S19: H2 production | T19: Green electrolytic | U19: Hydrogen production (green hydrogen) | V19: https://www.ewe.com/de/presse/pressemitteilungen/2020/07/ewe-mit-tochter-swb-und-arcelormittal-kooperieren-bei-grner-stahlerzeugung-ewe-ag | W19: 2024 | X19: https://www.steeltimesint.com/news/largest-industrial-hydrogen-project-in-germany-and-europe-contracted-for-construction | Y19: 19 | Z19: https://www.greencarcongress.com/2022/07/20220711-apex.html | AA19: N/A | AB19: https://www.ewe.com/de/presse/pressemitteilungen/2020/07/ewe-mit-tochter-swb-und-arcelormittal-kooperieren-bei-grner-stahlerzeugung-ewe-ag | AC19: N/A | AD19: https://www.ewe.com/de/presse/pressemitteilungen/2020/07/ewe-mit-tochter-swb-und-arcelormittal-kooperieren-bei-grner-stahlerzeugung-ewe-ag | AE19: 24 | AF19: https://www.ewe.com/de/presse/pressemitteilungen/2020/07/ewe-mit-tochter-swb-und-arcelormittal-kooperieren-bei-grner-stahlerzeugung-ewe-ag | AG19: N/A | AH19: https://www.ewe.com/de/presse/pressemitteilungen/2020/07/ewe-mit-tochter-swb-und-arcelormittal-kooperieren-bei-grner-stahlerzeugung-ewe-ag | AI19: EWE AG | AJ19: https://www.ewe.com/de/presse/pressemitteilungen/2020/07/ewe-mit-tochter-swb-und-arcelormittal-kooperieren-bei-grner-stahlerzeugung-ewe-ag | AK19: 2022-10-17 The electrolyzer is expected to come into operation in 2024 ; The project costs will amount to approximately €20 million, with €10 million coming from the state of Bremen. ; The electrolysis plant capacity will gradually increase up to 300 MW at the later stages // 2022-05-25: No further comments // 2022-01-04: Project received funding of over €10 million from the state of Bremen | AL19: https://www.h2bulletin.com/arcelormittal-bremen-receives-10m-funding-for-hybit-hydrogen-project/ | AM19: 44851 | AN19: 44025 | AQ19: R&D partnership | AS19: 2 | AU19: 2 | AV19: 2 | AW19: 6
A20: ArcelorMittal | B20: Steel4Future | C20: N/A | D20: SDE00006 | E20: 35% reduction in Europe (baseline 2018) | F20: carbon neutrality | G20: https://corporate-media.arcelormittal.com/media/ob3lpdom/car_2.pdf | H20: 79.26 | I20: Germany | J20: Bremen | K20: 53.133305 | L20: 8.688193 | M20: exact | N20: Europe | O20: https://bremen.arcelormittal.com/Ueber-uns/ | P20: full scale | Q20: https://corporate.arcelormittal.com/media/news-articles/arcelormittal-plans-major-investment-in-german-sites-to-accelerate-co2-emissions-reduction-strategy-and-leverage-the-hydrogen-grid | R20: NG-DR --> H-DR | S20: DRI | T20: Green electrolytic | U20: NG-DR --> H-DR | V20: https://corporate.arcelormittal.com/media/news-articles/arcelormittal-plans-major-investment-in-german-sites-to-accelerate-co2-emissions-reduction-strategy-and-leverage-the-hydrogen-grid | W20: 2026 | X20: https://bremen.arcelormittal.com/Nachhaltigkeit/Auf-dem-Weg-zum-gruenen-Stahl/ | Y20: 0.75 | Z20: https://corporate.arcelormittal.com/media/news-articles/arcelormittal-plans-major-investment-in-german-sites-to-accelerate-co2-emissions-reduction-strategy-and-leverage-the-hydrogen-grid | AA20: 1.75 | AB20: https://corporate.arcelormittal.com/media/news-articles/arcelormittal-plans-major-investment-in-german-sites-to-accelerate-co2-emissions-reduction-strategy-and-leverage-the-hydrogen-grid | AC20: Not stated | AD20: https://bremen.arcelormittal.com/Nachhaltigkeit/Auf-dem-Weg-zum-gruenen-Stahl/ | AE20: Not stated | AF20: https://bremen.arcelormittal.com/Nachhaltigkeit/Auf-dem-Weg-zum-gruenen-Stahl/ | AG20: N/A | AH20: https://bremen.arcelormittal.com/Nachhaltigkeit/Auf-dem-Weg-zum-gruenen-Stahl/ | AI20: N/A | AJ20: https://bremen.arcelormittal.com/Nachhaltigkeit/Auf-dem-Weg-zum-gruenen-Stahl/ | AK20: 2022-10-17 No further comments // 2022-05-25: No further comments Using green hydrogen, up to 3.5 million tonnes of steel could be produced by the Bremen and Eisenhuttenstadt sites by 2030, with significantly lower CO2 emissions. The technology conversion requires investments in the range of €1-1.5 billion. In Bremen, ArcelorMittal initially plans to use natural gas for the DRI, and later hydrogen from electrolysis; the hydrogen is to be made available as part of the regional North German Clean Hydrogen Coastline network. https://corporate.arcelormittal.com/media/news-articles/arcelormittal-plans-major-investment-in-german-sites-to-accelerate-co2-emissions-reduction-strategy-and-leverage-the-hydrogen-grid# | AL20: https://bremen.arcelormittal.com/Nachhaltigkeit/Auf-dem-Weg-zum-gruenen-Stahl/ | AM20: 44851 | AN20: 44260 | AQ20: Grand Total | AR20: 2 | AS20: 23 | AT20: 5 | AU20: 12 | AV20: 6 | AW20: 48
A21: ArcelorMittal | B21: Steel4Future | C21: N/A | D21: SDE00005 | E21: 35% reduction in Europe (baseline 2018) | F21: carbon neutrality | G21: https://corporate-media.arcelormittal.com/media/ob3lpdom/car_2.pdf | H21: 79.26 | I21: Germany | J21: Eisenhüttenstadt | K21: 52.168649 | L21: 14.623473 | M21: exact | N21: Europe | O21: https://eisenhuettenstadt.arcelormittal.com/Ueber-uns/ | P21: pilot | Q21: https://bremen.arcelormittal.com/Nachhaltigkeit/Auf-dem-Weg-zum-gruenen-Stahl/ | R21: H-DR | S21: DRI | T21: Green electrolytic | U21: H-DR | V21: https://germany.arcelormittal.com/icc/arcelor/broker.jsp?uMen=b4460b16-d5ab-c671-587e-7e978c4e5e0b&uCon=8ac40a49-e039-f771-f0f6-ded50099481d&uTem=aaaaaaaa-aaaa-aaaa-aaaa-000000000042 | W21: 2026 | X21: https://bremen.arcelormittal.com/Nachhaltigkeit/Auf-dem-Weg-zum-gruenen-Stahl/ | Y21: 0.75 | Z21: https://corporate.arcelormittal.com/media/news-articles/arcelormittal-plans-major-investment-in-german-sites-to-accelerate-co2-emissions-reduction-strategy-and-leverage-the-hydrogen-grid | AA21: 1.75 | AB21: https://corporate.arcelormittal.com/media/news-articles/arcelormittal-plans-major-investment-in-german-sites-to-accelerate-co2-emissions-reduction-strategy-and-leverage-the-hydrogen-grid | AC21: Not stated | AD21: https://corporate.arcelormittal.com/media/news-articles/arcelormittal-plans-major-investment-in-german-sites-to-accelerate-co2-emissions-reduction-strategy-and-leverage-the-hydrogen-grid | AE21: Not stated | AF21: https://corporate.arcelormittal.com/media/news-articles/arcelormittal-plans-major-investment-in-german-sites-to-accelerate-co2-emissions-reduction-strategy-and-leverage-the-hydrogen-grid | AG21: N/A | AH21: https://corporate.arcelormittal.com/media/news-articles/arcelormittal-plans-major-investment-in-german-sites-to-accelerate-co2-emissions-reduction-strategy-and-leverage-the-hydrogen-grid | AI21: N/A | AJ21: https://corporate.arcelormittal.com/media/news-articles/arcelormittal-plans-major-investment-in-german-sites-to-accelerate-co2-emissions-reduction-strategy-and-leverage-the-hydrogen-grid | AK21: 2022-10-17 No further comments // 2022-05-25 No further comments The project will use hydrogen produced from natural gas (pyrolysis), until green hydrogen becomes available in the future. The sponge iron produced in the Bremen DRI unit will initially supply the steelworks in Bremen and Eisenhüttenstadt, until the regional hydrogen cluster in East Brandenburg can also supply the Eisenhüttenstadt site with sufficient hydrogen. | AL21: https://corporate.arcelormittal.com/media/news-articles/arcelormittal-plans-major-investment-in-german-sites-to-accelerate-co2-emissions-reduction-strategy-and-leverage-the-hydrogen-grid | AM21: 44851 | AN21: 44260
A22: ArcelorMittal | B22: Hamburg H2 | C22: https://future.hamburg/en/project-brief-hydrogen-arcelormittal | D22: SDE00007 | E22: 35% reduction in Europe (baseline 2018) | F22: carbon neutrality | G22: https://corporate-media.arcelormittal.com/media/ob3lpdom/car_2.pdf | H22: 79.26 | I22: Germany | J22: Hamburg | K22: 53.522601 | L22: 9.900749 | M22: exact | N22: Europe | O22: https://hamburg.arcelormittal.com/Ueber-uns/ | P22: demo | Q22: https://corporate.arcelormittal.com/media/case-studies/hydrogen-based-steelmaking-to-begin-in-hamburg | R22: H-DR | S22: DRI | T22: Grey | U22: H-DR (waste gas recovery) + Pressure swing adsorption | V22: https://corporate.arcelormittal.com/media/case-studies/hydrogen-based-steelmaking-to-begin-in-hamburg | W22: 2024 | X22: https://corporate.arcelormittal.com/climate-action/decarbonisation-technologies/hamburg-h2-working-towards-the-production-of-zero-carbon-emissions-steel-with-hydrogen / https://www.globenewswire.com/news-release/2021/02/11/2173710/0/en/ArcelorMittal-reports-fourth-quarter-2020-and-twelve-months-2020-results.html | Y22: 122 | Z22: https://corporate.arcelormittal.com/climate-action/decarbonisation-technologies/hamburg-h2-working-towards-the-production-of-zero-carbon-emissions-steel-with-hydrogen | AA22: 0.1 | AB22: https://corporate.arcelormittal.com/media/case-studies/hydrogen-based-steelmaking-to-begin-in-hamburg | AC22: 0.1 | AD22: https://www.midrex.com/press-release/arcelormittal-commissions-midrex-to-design-demonstration-plant-for-hydrogen-steel-production-in-hamburg/ | AE22: N/A | AF22: https://corporate.arcelormittal.com/media/case-studies/hydrogen-based-steelmaking-to-begin-in-hamburg | AG22: Not stated | AH22: https://www.midrex.com/press-release/arcelormittal-commissions-midrex-to-design-demonstration-plant-for-hydrogen-steel-production-in-hamburg/ | AI22: Midrex | AJ22: https://corporate.arcelormittal.com/media/case-studies/hydrogen-based-steelmaking-to-begin-in-hamburg | AK22: 2022-10-17 The project initially will operate with grey hydrogen from natural gas and in a later stage with green hydrogen // 2022-05-25 Plans to now source green hydrogen from Vattenfall and then build up electrolysis capacity of its own https://www.reuters.com/article/us-vattenfall-arcelormittal-germany-excl/exclusive-arcelormittal-vattenfall-form-hydrogen-consortium-with-shell-airbus-others-idUSKBN2CD0X9 2021-09-07: Federal Government has expressed its intention to provide €55 million of funding support towards the construction of the plant, which is half of the €110 million total capital expenditure required. The next step is for the European Commission to approve the Federal Government's intention to provide funding before the installation of the new plant can begin. https://corporate.arcelormittal.com/media/news-articles/german-federal-government-commits-its-intention-to-provide-55-million-of-funding-for-arcelormittal-s-hydrogen-dri-plant | AL22: https://corporate.arcelormittal.com/media/news-articles/german-federal-government-commits-its-intention-to-provide-55-million-of-funding-for-arcelormittal-s-hydrogen-dri-plant https://future.hamburg/en/project-brief-hydrogen-arcelormittal | AM22: 44851 | AN22: 43724
A23: ArcelorMittal | B23: SeaH2Land | C23: https://seah2land.nl/en | D23: SBE00001 | E23: 35% reduction in Europe (baseline 2018) | F23: carbon neutrality | G23: https://corporate-media.arcelormittal.com/media/ob3lpdom/car_2.pdf | H23: 79.26 | I23: Netherlands | J23: North Sea (Dutch region) | K23: 51.961733 | L23: 5.6900411 | M23: approximate (country) | N23: Europe | O23: https://www.rechargenews.com/energy-transition/orsted-in-gigawatt-scale-offshore-wind-to-green-hydrogen-plan-with-steel-giant-arcelormittal/2-1-990058 | P23: full scale | Q23: https://www.rechargenews.com/energy-transition/orsted-in-gigawatt-scale-offshore-wind-to-green-hydrogen-plan-with-steel-giant-arcelormittal/2-1-990058 | R23: Hydrogen production | S23: H2 production | T23: Green electrolytic | U23: Hydrogen production (green hydrogen) | V23: https://www.rechargenews.com/energy-transition/orsted-in-gigawatt-scale-offshore-wind-to-green-hydrogen-plan-with-steel-giant-arcelormittal/2-1-990058 | W23: 2030 | X23: https://www.rechargenews.com/energy-transition/orsted-in-gigawatt-scale-offshore-wind-to-green-hydrogen-plan-with-steel-giant-arcelormittal/2-1-990058 | Y23: Not stated | Z23: https://www.rechargenews.com/energy-transition/orsted-in-gigawatt-scale-offshore-wind-to-green-hydrogen-plan-with-steel-giant-arcelormittal/2-1-990058 | AA23: N/A | AB23: https://www.rechargenews.com/energy-transition/orsted-in-gigawatt-scale-offshore-wind-to-green-hydrogen-plan-with-steel-giant-arcelormittal/2-1-990058 | AC23: N/A | AD23: https://www.rechargenews.com/energy-transition/orsted-in-gigawatt-scale-offshore-wind-to-green-hydrogen-plan-with-steel-giant-arcelormittal/2-1-990058 | AE23: 1000 | AF23: https://www.rechargenews.com/energy-transition/orsted-in-gigawatt-scale-offshore-wind-to-green-hydrogen-plan-with-steel-giant-arcelormittal/2-1-990058 | AG23: N/A | AH23: https://www.rechargenews.com/energy-transition/orsted-in-gigawatt-scale-offshore-wind-to-green-hydrogen-plan-with-steel-giant-arcelormittal/2-1-990058 | AI23: Orsted, Yara, Dow Benelux, Zeeland Refinery, North Sea Port, Smart Delta Resources | AJ23: https://www.rechargenews.com/energy-transition/orsted-in-gigawatt-scale-offshore-wind-to-green-hydrogen-plan-with-steel-giant-arcelormittal/2-1-990058 // https://seah2land.nl/en/who | AK23: 2022-10-17 No further comment // 2022-05-25 No further comment Green H2 to be used by ArcelorMittal, Yara, Dow Benelux and Zeeland refinery | AL23: https://www.rechargenews.com/energy-transition/orsted-in-gigawatt-scale-offshore-wind-to-green-hydrogen-plan-with-steel-giant-arcelormittal/2-1-990058 | AM23: 44851 | AN23: 44286
A24: ArcelorMittal | B24: N/A | C24: N/A | D24: SES00001-1 | E24: 35% reduction in Europe (baseline 2018) | F24: carbon neutrality | G24: https://corporate-media.arcelormittal.com/media/ob3lpdom/car_2.pdf | H24: 79.26 | I24: Spain | J24: Gijon | K24: 43.525092 | L24: -5.731926 | M24: exact | N24: Europe | O24: https://corporate.arcelormittal.com/media/press-releases/arcelormittal-signs-mou-with-the-spanish-government-supporting-1-billion-investment-in-decarbonisation-technologies | P24: full scale | Q24: https://corporate.arcelormittal.com/media/press-releases/arcelormittal-signs-mou-with-the-spanish-government-supporting-1-billion-investment-in-decarbonisation-technologies | R24: H-DR & EAF | S24: DRI | T24: Green electrolytic | U24: H-DR & EAF | V24: https://corporate.arcelormittal.com/media/press-releases/arcelormittal-signs-mou-with-the-spanish-government-supporting-1-billion-investment-in-decarbonisation-technologies | W24: 2025 | X24: https://corporate.arcelormittal.com/media/press-releases/arcelormittal-signs-mou-with-the-spanish-government-supporting-1-billion-investment-in-decarbonisation-technologies | Y24: 1648.8 | Z24: https://corporate.arcelormittal.com/media/press-releases/arcelormittal-signs-mou-with-the-spanish-government-supporting-1-billion-investment-in-decarbonisation-technologies | AA24: 1.1 | AB24: https://corporate.arcelormittal.com/media/press-releases/arcelormittal-signs-mou-with-the-spanish-government-supporting-1-billion-investment-in-decarbonisation-technologies | AC24: N/A | AD24: https://corporate.arcelormittal.com/media/press-releases/arcelormittal-signs-mou-with-the-spanish-government-supporting-1-billion-investment-in-decarbonisation-technologies | AE24: Not stated | AF24: https://corporate.arcelormittal.com/media/press-releases/arcelormittal-signs-mou-with-the-spanish-government-supporting-1-billion-investment-in-decarbonisation-technologies | AG24: N/A | AH24: https://corporate.arcelormittal.com/media/press-releases/arcelormittal-signs-mou-with-the-spanish-government-supporting-1-billion-investment-in-decarbonisation-technologies | AI24: N/A | AJ24: https://corporate.arcelormittal.com/media/press-releases/arcelormittal-signs-mou-with-the-spanish-government-supporting-1-billion-investment-in-decarbonisation-technologies | AK24: 2023-02-20 EU Commission to fund 460 million EUR for this project 2022-10-17 1.1 Mtonne hybrid EAF for steel production // 25/05: No further comment 1) MOU signed with Spanish government for co-funding estimated to 50% 2) "Should green hydrogen not be available at affordable rates at the end of 2025, natural gas would be use to power the DRI furnace" | AL24: https://www.steelorbis.com/steel-news/latest-news/ec-approves-fundings-to-support-arcelormittals-decarbonization-1279571.htm https://corporate.arcelormittal.com/media/press-releases/arcelormittal-signs-mou-with-the-spanish-government-supporting-1-billion-investment-in-decarbonisation-technologies | AM24: 45020 | AN24: 44390
A25: ArcelorMittal | B25: N/A | C25: N/A | D25: SES00002 | E25: 35% reduction in Europe (baseline 2018) | F25: carbon neutrality | G25: https://corporate-media.arcelormittal.com/media/ob3lpdom/car_2.pdf | H25: 79.26 | I25: Spain | J25: Sestao | K25: 43.313144 | L25: -2.998964 | M25: exact | N25: Europe | O25: https://corporate.arcelormittal.com/media/press-releases/arcelormittal-sestao-to-become-the-world-s-first-full-scale-zero-carbon-emissions-steel-plant | P25: full scale | Q25: https://corporate.arcelormittal.com/media/press-releases/arcelormittal-sestao-to-become-the-world-s-first-full-scale-zero-carbon-emissions-steel-plant | R25: Other | S25: other | T25: N/A | U25: Hybrid EAF | V25: https://corporate.arcelormittal.com/media/press-releases/arcelormittal-sestao-to-become-the-world-s-first-full-scale-zero-carbon-emissions-steel-plant | W25: 2025 | X25: https://corporate.arcelormittal.com/media/press-releases/arcelormittal-sestao-to-become-the-world-s-first-full-scale-zero-carbon-emissions-steel-plant | Y25: 58 | Z25: https://corporate.arcelormittal.com/media/press-releases/arcelormittal-sestao-to-become-the-world-s-first-full-scale-zero-carbon-emissions-steel-plant | AA25: 1.6 | AB25: https://corporate.arcelormittal.com/media/press-releases/arcelormittal-sestao-to-become-the-world-s-first-full-scale-zero-carbon-emissions-steel-plant | AC25: N/A | AD25: https://corporate.arcelormittal.com/media/press-releases/arcelormittal-sestao-to-become-the-world-s-first-full-scale-zero-carbon-emissions-steel-plant | AE25: Not stated | AF25: https://corporate.arcelormittal.com/media/press-releases/arcelormittal-sestao-to-become-the-world-s-first-full-scale-zero-carbon-emissions-steel-plant | AG25: N/A | AH25: https://corporate.arcelormittal.com/media/press-releases/arcelormittal-sestao-to-become-the-world-s-first-full-scale-zero-carbon-emissions-steel-plant | AI25: Not stated | AJ25: https://corporate.arcelormittal.com/media/press-releases/arcelormittal-sestao-to-become-the-world-s-first-full-scale-zero-carbon-emissions-steel-plant | AK25: 2022-10-17 No further comments // 2022-05-25 No further comment Central to this development will be the construction of a 2.3 million-tonne green hydrogen DRI unit in Gijón. Around 1 million tonnes of DRI will be transported to Sestao to be used a feedstock for its two EAFs. | AL25: https://corporate.arcelormittal.com/media/press-releases/arcelormittal-sestao-to-become-the-world-s-first-full-scale-zero-carbon-emissions-steel-plant | AM25: 44851 | AN25: 44390
A26: Enagas | B26: Green Crane - Western route (formerly Green Spider, Asturias Hub) | C26: https://www.h2v.eu/hydrogen-valleys/green-crane-western-route | D26: SES00001 | E26: N/A | F26: N/A (carbon neutrality by 2040) | G26: https://www.enagas.es/en/about-us/sustainability/environment/climate-action-energy-efficiency/ | H26: N/A | I26: Spain | J26: Asturias | K26: 43.525092 | L26: -5.731926 | M26: exact | N26: Europe | O26: https://www.h2v.eu/hydrogen-valleys/green-crane-western-route | P26: full scale | Q26: https://www.h2v.eu/hydrogen-valleys/green-crane-western-route | R26: Hydrogen production | S26: H2 production | T26: Green electrolytic | U26: hydrogen production (green hydrogen) | V26: https://www.h2v.eu/hydrogen-valleys/green-crane-western-route | W26: 2024 | X26: https://www.h2v.eu/hydrogen-valleys/green-crane-western-route | Y26: 1745 | Z26: https://www.h2v.eu/hydrogen-valleys/green-crane-western-route | AA26: N/A | AB26: https://www.h2v.eu/hydrogen-valleys/green-crane-western-route | AC26: N/A | AD26: https://www.h2v.eu/hydrogen-valleys/green-crane-western-route | AE26: Not stated | AF26: https://www.h2v.eu/hydrogen-valleys/green-crane-western-route | AG26: N/A | AH26: https://www.h2v.eu/hydrogen-valleys/green-crane-western-route | AI26: Hydrogenious LOHC Technologies, Vopak, Térega, Petronor, Arcelor-Mittal I+D, Bosch, McPhy, Vestas, Falck Renewables, IGNIS Energía, H2V, Gransolar | AJ26: https://www.h2v.eu/hydrogen-valleys/green-crane-western-route | AK26: 2022-10-21 Investment of 1470 million EUR. The projected H2 production volume is 80 ton/day // 2022-05-25 Concrete plan agreed by main stakeholders Green Crane website captures costs and production for whole multinational project - not possible to separate costs and production volumes for steel. Hydrogen hub that will supply Asturias steel plant (likely ArcelorMittal Asturias). Previous link to project no longer live: https://static1.squarespace.com/static/5d3f0387728026000121b2a2/t/5d9f24f459c7f056aca5a74f/1570710781671/4.A+Green+Spider+project.pdf | AL26: https://www.h2v.eu/hydrogen-valleys/green-crane-western-route | AM26: 44855 | AN26: 44043
A27: FerroSilva | B27: FerroSilva | C27: https://www.ferrosilva.com/english/ | D27: N/A | E27: N/A | F27: N/A | G27: https://www.ferrosilva.com/english/ | H27: N/A | I27: Sweden | J27: Not applicable | K27: 62.945386 | L27: 17.186327 | M27: approximate (country) | N27: Europe | O27: https://www.ferrosilva.com/english/ | P27: R&D partnership | Q27: https://www.ferrosilva.com/english/ | R27: Other | S27: other | T27: N/A | U27: Biogenic reduction gas | V27: https://www.ferrosilva.com/english/ | W27: 2022 | X27: https://www.ferrosilva.com/english/ | Y27: Not stated | Z27: https://www.ferrosilva.com/english/ | AA27: N/A | AB27: https://www.ferrosilva.com/english/ | AC27: Not stated | AD27: https://www.ferrosilva.com/english/ | AE27: N/A | AF27: https://www.ferrosilva.com/english/ | AG27: N/A | AH27: https://www.ferrosilva.com/english/ | AI27: Ovako, Sandvik Materials Technology, Uddeholm, Sveaskog and Lantmännen | AJ27: https://www.ferrosilva.com/wp-content/themes/ferrosilva_theme/assets/FerroSilva_Pressrelease_210427.pdf | AK27: 2022-10-21 No further comment The applicant is MMM Advice, which is managing the project together with Kobolde & Partners - R&D project in association with Academia (KTH, Chalmers) | AL27: https://www.ferrosilva.com/wp-content/themes/ferrosilva_theme/assets/FerroSilva_Pressrelease_210427.pdf | AM27: 44855 | AN27: 44313
A28: H2 Green Steel | B28: H2 Green Steel (H2GS) | C28: https://www.h2greensteel.com/ | D28: TBD | E28: N/A | F28: N/A | G28: https://www.h2greensteel.com/ | H28: 0 | I28: Sweden | J28: Svartbyn | K28: 66.258949 | L28: 22.834703 | M28: approximate (city) | N28: Europe | O28: https://www.di.se/nyheter/northvolt-grundare-utmanar-ssab-med-25-miljarder-i-ryggen/ | P28: full scale | Q28: https://www.di.se/nyheter/northvolt-grundare-utmanar-ssab-med-25-miljarder-i-ryggen/ | R28: H-DR | S28: DRI | T28: Green electrolytic | U28: H-DR | V28: https://www.h2greensteel.com/about-us | W28: 2024 | X28: https://www.h2greensteel.com/green-steel | Y28: 3000 | Z28: https://www.di.se/nyheter/northvolt-grundare-utmanar-ssab-med-25-miljarder-i-ryggen/ | AA28: 5 | AB28: https://www.di.se/nyheter/northvolt-grundare-utmanar-ssab-med-25-miljarder-i-ryggen/ | AC28: Not stated | AD28: https://www.di.se/nyheter/northvolt-grundare-utmanar-ssab-med-25-miljarder-i-ryggen/ | AE28: Not stated | AF28: https://www.di.se/nyheter/northvolt-grundare-utmanar-ssab-med-25-miljarder-i-ryggen/ | AG28: N/A | AH28: https://www.di.se/nyheter/northvolt-grundare-utmanar-ssab-med-25-miljarder-i-ryggen/ | AI28: IMAS Foundation, Vargas, Scania, InnoEnergy, Altor, Bilstein Group, SMS Group, Exor, Kingspan, FAM, Mercedez-Benz, Marcegaglia | AJ28: https://www.h2greensteel.com/green-steel | AK28: 2023-02-14 Just Climate, an investment business created by Generation Investment Management to address the net zero challenge at scale, has today announced (...) investments in (...) H2 Green Steel (...) Just Climate’s investment forms part of H2 Green Steel’s Series B fundraising announced in October 2022 2022-10-21 The main area of use for our green hydrogen will be to reduce iron ore to direct-reduced-iron, DRI (also referred to as iron sponge) ; After receiving the permissibility for its 5 million tonne steel plant in northern Sweden on July 1/2022, the company moves into the construction phase. Groundwork initiated. New entrant, greenfield steel mill with hydrogen direct reduction, EAFs, producing flat steel for automotive, white goods, furniture. Plan to use 40% scrap and 60% virgin input | AL28: https://www.h2greensteel.com/green-steel https://www.h2greensteel.com/articles/green-hydrogen-enables-the-decarbonization-of-steel-production https://greensteelworld.com/just-climate-announces-investment-in-h2-green-steel-abb-e-mobility-and-meva-energy | AM28: 44971 | AN28: 44255
A29: Liberty Steel | B29: TBD | C29: TBD | D29: N/A | E29: carbon neutrality | F29: N/A (see 2030 target) | G29: https://libertysteelgroup.com/about/message-from-the-chairman/ https://libertysteelgroup.com/news/liberty-steel-plants-to-merge-into-one-global-group-setting-sights-on-carbon-neutral-operations-by-2030/ | H29: <8 | I29: France | J29: Dunkirk | K29: 51.000206 | L29: 2.1673107 | M29: approximate (site) | N29: Europe | O29: https://www.thehindubusinessline.com/companies/liberty-steel-forms-joint-venture-for-hydrogen-based-steel-plant-in-france/article33902926.ece | P29: full scale | Q29: https://libertysteelgroup.com/news/liberty-develop-hydrogen-steel-making-plant/ | R29: NG-DR --> H-DR | S29: DRI | T29: Green electrolytic | U29: NG-DR --> H-DR | V29: https://libertysteelgroup.com/news/liberty-develop-hydrogen-steel-making-plant/ | W29: Not stated | X29: https://libertysteelgroup.com/news/liberty-develop-hydrogen-steel-making-plant/ | Y29: Not stated | Z29: https://libertysteelgroup.com/news/liberty-develop-hydrogen-steel-making-plant/ | AA29: Not stated | AB29: https://libertysteelgroup.com/news/liberty-develop-hydrogen-steel-making-plant/ | AC29: 2 | AD29: https://libertysteelgroup.com/news/liberty-develop-hydrogen-steel-making-plant/ | AE29: 1000 | AF29: https://libertysteelgroup.com/news/liberty-develop-hydrogen-steel-making-plant/ | AG29: N/A | AH29: https://libertysteelgroup.com/news/liberty-develop-hydrogen-steel-making-plant/ | AI29: Paul Wurth, Saar-Holding-Stahl | AJ29: https://libertysteelgroup.com/news/liberty-develop-hydrogen-steel-making-plant/ | AK29: 2022-10-24 No further comments MoU Signed - Initially mix of H2 and NG, transitioning to 100% hydrogen once (integrated) electrolysis production complete. Further asset acquisition might have happened after last company production capacity data point. | AL29: https://libertysteelgroup.com/news/liberty-develop-hydrogen-steel-making-plant/ | AM29: 44858 | AN29: 44249
A30: Liberty Steel | B30: TBD | C30: TBD | D30: SRO00001 | E30: carbon neutrality | F30: N/A (see 2030 target) | G30: https://libertysteelgroup.com/about/message-from-the-chairman/ https://libertysteelgroup.com/news/liberty-steel-plants-to-merge-into-one-global-group-setting-sights-on-carbon-neutral-operations-by-2030/ | H30: <8 | I30: Romania | J30: Galati | K30: 45.434119 | L30: 27.976244 | M30: exact | N30: Europe | O30: https://libertysteelgroup.com/ro/?lang=en | P30: full scale | Q30: https://libertysteelgroup.com/news/gfg-alliance-signs-mou-with-romanian-government-to-create-a-european-greensteel-flagship-at-liberty-galati/ | R30: NG-DR --> H-DR | S30: DRI | T30: Not stated | U30: NG-DR --> H-DR | V30: https://libertysteelgroup.com/news/gfg-alliance-signs-mou-with-romanian-government-to-create-a-european-greensteel-flagship-at-liberty-galati/ | W30: 2024 | X30: https://www.spglobal.com/platts/en/market-insights/latest-news/natural-gas/061120-gfg-alliance-plans-to-revamp-romanian-galati-plant-into-green-steelmaker | Y30: 1137 | Z30: https://www.romania-insider.com/liberty-galati-decarbonization-too-far | AA30: 4 | AB30: https://libertysteelgroup.com/news/gfg-alliance-signs-mou-with-romanian-government-to-create-a-european-greensteel-flagship-at-liberty-galati/ | AC30: 2.5 | AD30: https://libertysteelgroup.com/news/gfg-alliance-signs-mou-with-romanian-government-to-create-a-european-greensteel-flagship-at-liberty-galati/ | AE30: Not stated | AF30: https://libertysteelgroup.com/news/gfg-alliance-signs-mou-with-romanian-government-to-create-a-european-greensteel-flagship-at-liberty-galati/ | AG30: N/A | AH30: https://libertysteelgroup.com/news/gfg-alliance-signs-mou-with-romanian-government-to-create-a-european-greensteel-flagship-at-liberty-galati/ | AI30: Romgaz, Eximbank | AJ30: https://libertysteelgroup.com/news/gfg-alliance-signs-mou-with-romanian-government-to-create-a-european-greensteel-flagship-at-liberty-galati/ | AK30: 2022-10-24 We have an investment plan of EUR 1 bln for Romania [for Liberty Galati], we will initially build green energy units, about 200 MW solar and about 30 MW wind https://www.romania-insider.com/liberty-galati-decarbonization-too-far Transitioning to H2 as H2 production technology "becomes more cost effective"; not clear yet whether BF/BOFs will retire. Further asset acquisition might have happened after last company production capacity data point. | AL30: https://libertysteelgroup.com/news/gfg-alliance-signs-mou-with-romanian-government-to-create-a-european-greensteel-flagship-at-liberty-galati/ | AM30: 44858 | AN30: 43992
A31: LKAB | B31: TBD | C31: TBD | D31: TBD | E31: Not stated | F31: N/A (carbon neutrality by 2045) | G31: https://www.lkab.com/en/about-lkab/lkab-in-brief/strategy-and-goals/ | H31: N/A | I31: Sweden | J31: Kiruna, Malmberget, Svappavaara | K31: 62.945386 | L31: 17.186327 | M31: approximate (country) | N31: Europe | O31: https://mb.cision.com/Main/11419/3241684/1338565.pdf | P31: full scale | Q31: https://www.lkab.com/en/news-room/news/up-to-3000-new-jobs-and-major-investment-in-malmfalten/?aid=5232 | R31: H-DR | S31: DRI | T31: Green electrolytic | U31: H-DR (only ironmaking) | V31: https://mb.cision.com/Main/11419/3241684/1338565.pdf | W31: 2029 | X31: https://www.lkab.com/en/news-room/news/up-to-3000-new-jobs-and-major-investment-in-malmfalten/?aid=5232 | Y31: 32500 | Z31: https://mb.cision.com/Main/11419/3241684/1338565.pdf | AA31: N/A | AB31: https://mb.cision.com/Main/11419/3241684/1338565.pdf | AC31: 24.4 | AD31: https://mb.cision.com/Main/11419/3553029/1568944.pdf | AE31: Not stated | AF31: https://mb.cision.com/Main/11419/3241684/1338565.pdf | AG31: N/A | AH31: https://mb.cision.com/Main/11419/3241684/1338565.pdf | AI31: Not stated | AJ31: https://mb.cision.com/Main/11419/3241684/1338565.pdf | AK31: 2022-10-25 In March 2022 LKAB reported dramatically increased mineral reserves and mineral resources. This refers to deposits containing about 4 billion tonnes, which will enable production far beyond 2060 (..) by 2050, the target is for LKAB to produce 24.4 million tonnes of sponge iron per year with zero carbon dioxide emissions (...) LKAB's demand, needed mainly for hydrogen gas production, is 20 TWh/yr (2030) ; 50 TWh/yr (2040) ; 70 TWh/yr (2050) https://mb.cision.com/Main/11419/3553029/1568944.pdf // 2022-06-21 First hydrogen-reduced sponge iron produced at pilot scale Investment over 15 to 20 years; shift from iron ore pellets to hydrogen-based sponge iron. | AL31: https://mb.cision.com/Main/11419/3241684/1338565.pdf https://www.lkab.com/en/news-room/press-releases/hybrit-ssab-lkab-and-vattenfall-first-in-the-world-with-hydrogen-reduced-sponge-iron/ | AM31: 44859 | AN31: 44157
A32: Salzgitter | B32: μDRAL | C32: https://salcos.salzgitter-ag.com/en/mydral.html | D32: SDE00004 | E32: 50% reduction (baseline undefined) | F32: 95% reduction by 2050 (baseline undefined) | G32: https://salcos.salzgitter-ag.com/en/salcos.html#c132333 | H32: <8 | I32: Germany | J32: Salzgitter | K32: 52.161794 | L32: 10.409371 | M32: exact | N32: Europe | O32: https://www.salzgitter-flachstahl.de/en/index.html | P32: demo | Q32: https://www.salzgitter-ag.com/en/newsroom/press-releases/details/another-key-components-on-the-road-to-low-co2-steel-production-15046.html | R32: NG-DR --> H-DR | S32: DRI | T32: Not stated | U32: NG-DR --> H-DR | V32: https://www.salzgitter-ag.com/en/newsroom/press-releases/details/another-key-components-on-the-road-to-low-co2-steel-production-15046.html | W32: 2022 | X32: https://www.salzgitter-ag.com/en/newsroom/press-releases/details/another-key-components-on-the-road-to-low-co2-steel-production-15046.html | Y32: 16 | Z32: https://www.salzgitter-ag.com/en/newsroom/press-releases/details/another-key-components-on-the-road-to-low-co2-steel-production-15046.html | AA32: N/A | AB32: https://www.salzgitter-ag.com/en/newsroom/press-releases/details/another-key-components-on-the-road-to-low-co2-steel-production-15046.html | AC32: 1 | AD32: https://www.salzgitter-ag.com/en/newsroom/press-releases/details/another-key-components-on-the-road-to-low-co2-steel-production-15046.html | AE32: N/A | AF32: https://www.salzgitter-ag.com/en/newsroom/press-releases/details/another-key-components-on-the-road-to-low-co2-steel-production-15046.html | AG32: N/A | AH32: https://www.salzgitter-ag.com/en/newsroom/press-releases/details/another-key-components-on-the-road-to-low-co2-steel-production-15046.html | AI32: Fraunhofer Gesellschaft, Tenova | AJ32: https://www.salzgitter-ag.com/en/newsroom/press-releases/details/another-key-components-on-the-road-to-low-co2-steel-production-15046.html | AK32: 2022-11-02 Production to commence in first half of 2022 but no further information found / Salzgitter aims to complete the first Salcos expansion stage, reducing CO2 emissions in its steel production by 30% by the end of 2025, with a second phase concluded by the end of 2030, along with a 50% carbon reduction. / The full project is due to completed by 31 December 2033, reducing CO2 emissions by more than 95%. // 2022-02-21: Cooperation agreement signed with Uniper to supply green hydrogen https://www.salzgitter-ag.com/en/newsroom/press-releases/details/uniper-and-salzgitter-agree-close-cooperation-in-supplying-the-salcosr-transformation-project-with-green-hydrogen-from-unipers-major-green-wilhelmshavenr-hydrogen-project-19249.html // 2021-05-19 Project breaks ground https://hydrogen-central.com/salzgitter-steel-production-hydrogen-natural-gas/ Operated flexibly by NG and H2. MoU signed with Tenova, 5mEUR support from German environment ministry. | AL32: https://www.salzgitter-ag.com/en/newsroom/press-releases/details/another-key-components-on-the-road-to-low-co2-steel-production-15046.html https://www.rechargenews.com/energy-transition/largest-ever-green-steel-investment-salzgitter-approves-723m-spend-on-first-stage-of-hydrogen-focused-project/2-1-1261505 | AM32: 44867 | AN32: 44333
A33: Salzgitter | B33: GrInHy2.0 (Green Industrial Hydrogen) | C33: https://www.green-industrial-hydrogen.com/ | D33: SDE00004 | E33: 50% reduction (baseline undefined) | F33: 95% reduction by 2050 (baseline undefined) | G33: https://salcos.salzgitter-ag.com/en/salcos.html#c132332 | H33: <8 | I33: Germany | J33: Salzgitter | K33: 52.161794 | L33: 10.409371 | M33: exact | N33: Europe | O33: https://www.salzgitter-flachstahl.de/en/index.html | P33: demo | Q33: https://www.green-industrial-hydrogen.com/ | R33: Hydrogen production | S33: H2 production | T33: Green electrolytic | U33: hydrogen production (green hydrogen through SOEC electrolysis) | V33: https://www.green-industrial-hydrogen.com/ | W33: 2021 | X33: https://www.sunfire.de/de/news/detail/grinhy2-0-wasserstoff-fuer-eine-co2-arme-stahlproduktion | Y33: 6.5 | Z33: https://www.sunfire.de/de/news/detail/grinhy2-0-wasserstoff-fuer-eine-co2-arme-stahlproduktion | AA33: N/A | AB33: https://www.sunfire.de/de/news/detail/grinhy2-0-wasserstoff-fuer-eine-co2-arme-stahlproduktion | AC33: N/A | AD33: https://www.sunfire.de/de/news/detail/grinhy2-0-wasserstoff-fuer-eine-co2-arme-stahlproduktion | AE33: 0.72 | AF33: https://www.sunfire.de/de/news/detail/grinhy2-0-wasserstoff-fuer-eine-co2-arme-stahlproduktion | AG33: N/A | AH33: https://www.sunfire.de/de/news/detail/grinhy2-0-wasserstoff-fuer-eine-co2-arme-stahlproduktion | AI33: Sunfire GmbH, Paul Wurth S.A., Tenova S.p.A., CEA - Commissariat a l'Energie atomique | AJ33: https://www.green-industrial-hydrogen.com/ | AK33: 2022-10-17 Project completed with a record production of almost 100 tons of green hydrogen for the climate-neutral production of green steel. https://www.salzgitter-ag.com/en/newsroom/press-releases/details/grinhy20-green-hydrogen-for-green-steel-20194.html In (trial) operation as of March 2021. During the upcoming two years the system is to be operated for at least 13,000 hours and provide proof of plant availability in excess of 95%. Over this period, the electrolyzer is required to produce a minimum of 100 tons of green hydrogen and produce evidence of an electrical efficiency (without the Hydrogen Processing Unit) exceeding 84% LHV. Project partially funded by EU's Horizon 2020 research and innovation program under grant agreement No 826350 (Fuel Cells and Hydrogen 2 Joint Undertaking). | AL33: https://www.green-industrial-hydrogen.com/project/news/worlds-largest-high-temperature-electrolyser-first-hydrogen-injection https://www.salzgitter-ag.com/en/newsroom/press-releases/details/worlds-largest-high-temperature-electrolyzer-achieves-record-efficiency-19500.html https://www.salzgitter-ag.com/en/newsroom/press-releases/details/grinhy20-green-hydrogen-for-green-steel-20194.html | AM33: 44851 | AN33: 44116
A34: Salzgitter | B34: WindH2 | C34: https://www.windh2.de/en.html | D34: SDE00004 | E34: 50% reduction (baseline undefined) | F34: 95% reduction by 2050 (baseline undefined) | G34: https://salcos.salzgitter-ag.com/en/salcos.html#c132331 | H34: <8 | I34: Germany | J34: Salzgitter | K34: 52.172074 | L34: 10.430113 | M34: exact | N34: Europe | O34: https://www.salzgitter-flachstahl.de/en/index.html | P34: demo | Q34: https://www.salzgitter-ag.com/en/newsroom/press-releases/details/wind-hydrogen-salzgitter-windh2-an-important-step-on-the-path-to-decarbonizing-the-steel-industry-14823.html | R34: Hydrogen production | S34: H2 production | T34: Green electrolytic | U34: hydrogen production (green hydrogen through PEM electrolysis, wind energy powered) | V34: https://www.salzgitter-ag.com/en/newsroom/press-releases/details/wind-hydrogen-salzgitter-windh2-an-important-step-on-the-path-to-decarbonizing-the-steel-industry-14823.html | W34: 2021 | X34: https://salcos.salzgitter-ag.com/en/index.html?no_cache=1 | Y34: 60 | Z34: https://www.steelguru.com/steel/windwasserstoff-salzgitter-windh2-commissioned | AA34: N/A | AB34: https://www.steelguru.com/steel/windwasserstoff-salzgitter-windh2-commissioned | AC34: N/A | AD34: https://www.steelguru.com/steel/windwasserstoff-salzgitter-windh2-commissioned | AE34: 2.5 | AF34: https://www.salzgitter-ag.com/en/newsroom/press-releases/details/wind-hydrogen-salzgitter-windh2-an-important-step-on-the-path-to-decarbonizing-the-steel-industry-14823.html | AG34: N/A | AH34: https://www.steelguru.com/steel/windwasserstoff-salzgitter-windh2-commissioned | AI34: Avacon Natur GmbH, Siemens, Linde | AJ34: https://www.salzgitter-ag.com/en/newsroom/press-releases/details/wind-hydrogen-salzgitter-windh2-an-important-step-on-the-path-to-decarbonizing-the-steel-industry-14823.html | AK34: 2022-11-02 No further comments // In (trial) operation as of March 2021 | AL34: https://www.salzgitter-ag.com/en/newsroom/press-releases/details/wind-hydrogen-salzgitter-windh2-an-important-step-on-the-path-to-decarbonizing-the-steel-industry-14823.html | AM34: 44867 | AN34: 44266
A35: Salzgitter | B35: N/A | C35: N/A | D35: TBD | E35: 50% reduction (baseline undefined) | F35: 95% reduction by 2050 (baseline undefined) | G35: https://salcos.salzgitter-ag.com/en/salcos.html#c132330 | H35: <8 | I35: Germany | J35: Wilhelmshaven | K35: 53.581143 | L35: 8.1357795 | M35: approximate (city) | N35: Europe | O35: https://www.salzgitter-ag.com/en/newsroom/press-releases/details/project-organization-for-feasibility-study-direct-reduction-of-iron-ore-in-wilhelmshaven-now-established-14410.html | P35: R&D partnership | Q35: https://www.salzgitter-ag.com/en/newsroom/press-releases/details/project-organization-for-feasibility-study-direct-reduction-of-iron-ore-in-wilhelmshaven-now-established-14410.html | R35: H-DR | S35: DRI | T35: Green electrolytic | U35: H-DR | V35: https://www.salzgitter-ag.com/en/newsroom/press-releases/details/project-organization-for-feasibility-study-direct-reduction-of-iron-ore-in-wilhelmshaven-now-established-14410.html | W35: N/A | X35: https://www.salzgitter-ag.com/en/newsroom/press-releases/details/project-organization-for-feasibility-study-direct-reduction-of-iron-ore-in-wilhelmshaven-now-established-14410.html | Y35: N/A | Z35: https://www.salzgitter-ag.com/en/newsroom/press-releases/details/project-organization-for-feasibility-study-direct-reduction-of-iron-ore-in-wilhelmshaven-now-established-14410.html | AA35: N/A | AB35: https://www.salzgitter-ag.com/en/newsroom/press-releases/details/project-organization-for-feasibility-study-direct-reduction-of-iron-ore-in-wilhelmshaven-now-established-14410.html | AC35: 2 | AD35: https://www.recyclingtoday.com/article/salzgitter-direct-reduced-iron-steel-germany/ | AE35: N/A | AF35: https://www.salzgitter-ag.com/en/newsroom/press-releases/details/project-organization-for-feasibility-study-direct-reduction-of-iron-ore-in-wilhelmshaven-now-established-14410.html | AG35: N/A | AH35: https://www.salzgitter-ag.com/en/newsroom/press-releases/details/project-organization-for-feasibility-study-direct-reduction-of-iron-ore-in-wilhelmshaven-now-established-14410.html | AI35: Rhenus, Uniper | AJ35: https://www.salzgitter-ag.com/en/newsroom/press-releases/details/project-organization-for-feasibility-study-direct-reduction-of-iron-ore-in-wilhelmshaven-now-established-14410.html | AK35: 2022-11-03 No further comments // 2022-08-11 The consortium has applied for innovation funding backing from state sources for this project that could potentially provide 900€ million ($1.06 billion) or above 50% of its total cost, there is no clear timeline yet for this project to go ahead. | AL35: https://www.spglobal.com/platts/en/market-insights/latest-news/metals/081121-gray-steel-to-become-obsolete-in-eu-once-green-steel-advances-salzgitter-ceo https://www.salzgitter-ag.com/en/newsroom/press-releases/details/project-organization-for-feasibility-study-direct-reduction-of-iron-ore-in-wilhelmshaven-now-established-14410.html | AM35: 44868 | AN35: 44006
A36: SSAB | B36: FFS - Towards Fossil-Free Steel | C36: N/A | D36: TBD | E36: 26% reduction (baseline 2018) | F36: N/A (fossil-free by 2045) | G36: https://www.ssab.com/company/sustainability/ssab-and-sustainability/sustainability-targets-beyond-2020 | H36: 8.18 | I36: Finland | J36: Raahe | K36: 64.651111 | L36: 24.418544 | M36: exact | N36: Europe | O36: https://www.ssab.com/news/2021/07/ssab-has-launched-an-extensive-research-project-in-finland-to-replace-fossil-fuels-with-renewable-en | P36: R&D partnership | Q36: https://www.ssab.com/news/2021/07/ssab-has-launched-an-extensive-research-project-in-finland-to-replace-fossil-fuels-with-renewable-en | R36: Other | S36: other | T36: Not stated | U36: Several incuding smelting of H2-reduced sponge iron | V36: https://www.ssab.com/news/2021/07/ssab-has-launched-an-extensive-research-project-in-finland-to-replace-fossil-fuels-with-renewable-en | W36: 2023 | X36: https://www.ssab.com/news/2021/07/ssab-has-launched-an-extensive-research-project-in-finland-to-replace-fossil-fuels-with-renewable-en | Y36: 12.4 | Z36: https://www.ssab.com/news/2021/07/ssab-has-launched-an-extensive-research-project-in-finland-to-replace-fossil-fuels-with-renewable-en | AA36: Not stated | AB36: https://www.ssab.com/news/2021/07/ssab-has-launched-an-extensive-research-project-in-finland-to-replace-fossil-fuels-with-renewable-en | AC36: Not stated | AD36: https://www.ssab.com/news/2021/07/ssab-has-launched-an-extensive-research-project-in-finland-to-replace-fossil-fuels-with-renewable-en | AE36: Not stated | AF36: https://www.ssab.com/news/2021/07/ssab-has-launched-an-extensive-research-project-in-finland-to-replace-fossil-fuels-with-renewable-en | AG36: N/A | AH36: https://www.ssab.com/news/2021/07/ssab-has-launched-an-extensive-research-project-in-finland-to-replace-fossil-fuels-with-renewable-en | AI36: LKAB, Vattenfall | AJ36: https://www.ssab.com/news/2021/07/ssab-has-launched-an-extensive-research-project-in-finland-to-replace-fossil-fuels-with-renewable-en | AK36: 2022-11-03 Project ongoing (2021-08-01 – 2023-07-31). Project coordinated by University of Oulo, Finland. The FFS research project is a continuation of the 2020 Energy4HYBRIT prefeasibility project, which investigated the need and availability of biomaterial and bioenergy and the techno-economic possibilities to use these in the steel mill processes at SSAB Raahe. The FFS project will build on this work and the goal is to determine solutions to produce green forms of energy | AL36: https://www.ssab.com/news/2021/07/ssab-has-launched-an-extensive-research-project-in-finland-to-replace-fossil-fuels-with-renewable-en | AM36: 44868 | AN36: 44392
A37: SSAB | B37: HYBRIT | C37: https://www.hybritdevelopment.se/ | D37: TBD | E37: 26% reduction (baseline 2018) | F37: N/A (fossil-free by 2045) | G37: https://www.ssab.com/company/sustainability/ssab-and-sustainability/sustainability-targets-beyond-2020 | H37: 8.18 | I37: Finland | J37: Raahe | K37: 64.651111 | L37: 24.418544 | M37: exact | N37: Europe | O37: https://www.ssab.com/company/sustainability/sustainable-operations/hybrit-phases | P37: full scale | Q37: https://www.ssab.com/company/sustainability/sustainable-operations/hybrit-phases | R37: EAF | S37: EAF | T37: N/A | U37: BF/BOF to scrap-EAF conversion | V37: https://www.ssab.fi/ssab-konserni/tietoja-ssabsta/tuotantopaikkakunnat-suomessa/raahe/kohti-fossiilivapaata-terastuotantoa | W37: 2030 | X37: https://www.ssab.fi/ssab-konserni/tietoja-ssabsta/tuotantopaikkakunnat-suomessa/raahe/kohti-fossiilivapaata-terastuotantoa | Y37: Not stated | Z37: https://www.ssab.fi/ssab-konserni/tietoja-ssabsta/tuotantopaikkakunnat-suomessa/raahe/kohti-fossiilivapaata-terastuotantoa | AA37: Not stated | AB37: https://www.ssab.fi/ssab-konserni/tietoja-ssabsta/tuotantopaikkakunnat-suomessa/raahe/kohti-fossiilivapaata-terastuotantoa | AC37: Not stated | AD37: https://www.ssab.fi/ssab-konserni/tietoja-ssabsta/tuotantopaikkakunnat-suomessa/raahe/kohti-fossiilivapaata-terastuotantoa | AE37: Not stated | AF37: https://www.ssab.fi/ssab-konserni/tietoja-ssabsta/tuotantopaikkakunnat-suomessa/raahe/kohti-fossiilivapaata-terastuotantoa | AG37: N/A | AH37: https://www.ssab.fi/ssab-konserni/tietoja-ssabsta/tuotantopaikkakunnat-suomessa/raahe/kohti-fossiilivapaata-terastuotantoa | AI37: LKAB, Vattenfall | AJ37: https://www.ssab.fi/ssab-konserni/tietoja-ssabsta/tuotantopaikkakunnat-suomessa/raahe/kohti-fossiilivapaata-terastuotantoa | AK37: 2022-11-03 No further comments 2039 The second blast furnace will also be closed and replaced with an arc furnace-based production technology. | AL37: https://www.ssab.fi/ssab-konserni/tietoja-ssabsta/tuotantopaikkakunnat-suomessa/raahe/kohti-fossiilivapaata-terastuotantoa | AM37: 44868 | AN37: 43803
A38: SSAB | B38: HYBRIT | C38: https://www.hybritdevelopment.se/ | D38: SSE00004 | E38: 26% reduction (baseline 2018) | F38: N/A (fossil-free by 2045) | G38: https://www.ssab.com/company/sustainability/ssab-and-sustainability/sustainability-targets-beyond-2020 | H38: 8.18 | I38: Sweden | J38: Gällivare | K38: 67.139064 | L38: 20.659878 | M38: approximate (city) | N38: Europe | O38: https://www.ssab.com/news/2021/03/hybrit-ssab-lkab-and-vattenfall-to-begin-industrialization-of-future-fossilfree-steelmaking-by-estab | P38: demo | Q38: https://www.hybritdevelopment.se/en/a-fossil-free-development/direct-reduction-hydrogen-demonstrationscale/ | R38: H-DR | S38: DRI | T38: Green electrolytic | U38: H-DR | V38: https://www.hybritdevelopment.se/en/a-fossil-free-development/direct-reduction-hydrogen-demonstrationscale/ | W38: 2026 | X38: https://www.hybritdevelopment.se/en/a-fossil-free-development/direct-reduction-hydrogen-demonstrationscale/ | Y38: 1000 | Z38: https://www.sei.org/wp-content/uploads/2020/07/bigger-is-sometimes-better.pdf | AA38: N/A | AB38: https://www.hybritdevelopment.se/en/march-24-2021-hybrit-ssab-lkab-and-vattenfall-to-begin-industrialization-of-future-fossil-free-steelmaking-by-establishing-the-worlds-first-production-plant-for-fossil-free-sponge-iron-in/ | AC38: 1.3 | AD38: https://www.hybritdevelopment.se/en/march-24-2021-hybrit-ssab-lkab-and-vattenfall-to-begin-industrialization-of-future-fossil-free-steelmaking-by-establishing-the-worlds-first-production-plant-for-fossil-free-sponge-iron-in/ | AE38: Not stated | AF38: https://www.hybritdevelopment.se/en/march-24-2021-hybrit-ssab-lkab-and-vattenfall-to-begin-industrialization-of-future-fossil-free-steelmaking-by-establishing-the-worlds-first-production-plant-for-fossil-free-sponge-iron-in/ | AG38: N/A | AH38: https://www.hybritdevelopment.se/en/march-24-2021-hybrit-ssab-lkab-and-vattenfall-to-begin-industrialization-of-future-fossil-free-steelmaking-by-establishing-the-worlds-first-production-plant-for-fossil-free-sponge-iron-in/ | AI38: LKAB, Vattenfall | AJ38: https://www.hybritdevelopment.se/ | AK38: 2022-11-03 No further comments // 2022-04-01 The project receives in total €143 million from EU Innovation Fund Goal to expand to 2.7 Mt by 2030 with another plant in Gällivare planned to operate in 2030 | AL38: https://www.hybritdevelopment.se/en/march-24-2021-hybrit-ssab-lkab-and-vattenfall-to-begin-industrialization-of-future-fossil-free-steelmaking-by-establishing-the-worlds-first-production-plant-for-fossil-free-sponge-iron-in/ https://www.ssab.com/en/news/2022/04/hybrit-receives-support-from-the-eu-innovation-fund | AM38: 44868 | AN38: 44279
A39: SSAB | B39: HYBRIT | C39: https://www.hybritdevelopment.se/ | D39: SSE00002 | E39: 26% reduction (baseline 2018) | F39: N/A (fossil-free by 2045) | G39: https://www.ssab.com/company/sustainability/ssab-and-sustainability/sustainability-targets-beyond-2020 | H39: 8.18 | I39: Sweden | J39: Luleå | K39: 65.559719 | L39: 22.219699 | M39: exact | N39: Europe | O39: https://www.ssab.com/contact | P39: pilot | Q39: https://www.hybritdevelopment.se/en/a-fossil-free-development/direct-reduction-hydrogen-pilotscale/ | R39: H-DR | S39: DRI | T39: Green electrolytic | U39: H-DR | V39: https://www.hybritdevelopment.se/en/a-fossil-free-development/direct-reduction-hydrogen-pilotscale/ | W39: 2021 | X39: https://www.hybritdevelopment.se/en/a-fossil-free-development/direct-reduction-hydrogen-pilotscale/ | Y39: 150 | Z39: https://www.sei.org/wp-content/uploads/2020/07/bigger-is-sometimes-better.pdf | AA39: N/A | AB39: https://www.hybritdevelopment.se/en/a-fossil-free-development/direct-reduction-hydrogen-pilotscale/ | AC39: Not stated | AD39: https://www.hybritdevelopment.se/en/a-fossil-free-development/direct-reduction-hydrogen-pilotscale/ | AE39: Not stated | AF39: https://www.ssab.com/news/2021/04/hybrit-ssab-lkab-and-vattenfall-building-unique-pilot-project-in-lule-for-largescale-hydrogen-storag | AG39: N/A | AH39: https://www.hybritdevelopment.se/en/a-fossil-free-development/direct-reduction-hydrogen-pilotscale/ | AI39: LKAB, Vattenfall | AJ39: https://www.hybritdevelopment.se/ | AK39: 2202-11-03 No further comments // 2202-09-22 Pilot facility for hydrogen storage up and running https://www.ssab.com/en/news/2022/09/hybrit-milestone-reached--pilot-facility-for-hydrogen-storage-up-and-running Starting with reduction using natural gas, will switch to electrolyzer H2 in 1st half of 2021. HYBRIT building unique pilot project in Luleå for large-scale hydrogen storage investing a quarter of a billion Swedish kronor (approx. $30m USD). 2030-2040: conversion of BFs to EAF | AL39: https://www.hybritdevelopment.se/en/hybrit-a-unique-hydrogen-storage-facility-in-lulea-is-taking-shape/ https://www.ssab.com/en/news/2022/09/hybrit-milestone-reached--pilot-facility-for-hydrogen-storage-up-and-running | AM39: 44868 | AN39: 44293
A40: SSAB | B40: HYBRIT | C40: https://www.hybritdevelopment.se/ | D40: SSE00001 | E40: 26% reduction (baseline 2018) | F40: N/A (fossil-free by 2045) | G40: https://www.ssab.com/company/sustainability/ssab-and-sustainability/sustainability-targets-beyond-2020 | H40: 8.18 | I40: Sweden | J40: Oxelösund | K40: 58.670789 | L40: 17.127786 | M40: exact | N40: Europe | O40: https://www.ssab.com/contact | P40: full scale | Q40: https://www.ssab.com/news/2020/12/green-light-for-fossilfree-steel-in-oxelsund | R40: EAF | S40: EAF | T40: N/A | U40: BF/BOF to scrap-EAF conversion | V40: https://www.ssab.com/news/2020/12/green-light-for-fossilfree-steel-in-oxelsund | W40: 2025 | X40: https://www.ssab.com/news/2020/12/green-light-for-fossilfree-steel-in-oxelsund | Y40: Not stated | Z40: https://www.ssab.com/news/2020/12/green-light-for-fossilfree-steel-in-oxelsund | AA40: Not stated | AB40: https://www.ssab.com/news/2020/12/green-light-for-fossilfree-steel-in-oxelsund | AC40: Not stated | AD40: https://www.ssab.com/news/2020/12/green-light-for-fossilfree-steel-in-oxelsund | AE40: Not stated | AF40: https://www.ssab.com/news/2020/12/green-light-for-fossilfree-steel-in-oxelsund | AG40: N/A | AH40: https://www.ssab.com/news/2020/12/green-light-for-fossilfree-steel-in-oxelsund | AI40: LKAB, Vattenfall | AJ40: https://www.hybritdevelopment.se/ | AK40: 2022-11-03 No further comments // 2022-06-23 Environmental permit to convert plant to EAF upheld | AL40: N/A | AM40: 44868 | AN40: 44188
A41: Tata Steel | B41: N/A | C41: N/A | D41: SNL00001 | E41: 30% reduction (baseline 2020) | F41: carbon neutrality | G41: https://www.tatasteeleurope.com/ts/sites/default/files/TSE%20Sustainability%20report%202019-20%20%28EN%29.pdf | H41: 30.59 | I41: Netherlands | J41: Ijmuiden | K41: 52.484118 | L41: 4.615584 | M41: exact | N41: Europe | O41: https://www.tatasteeleurope.com/corporate/news/tata-steel-opts-for-hydrogen-route-at-its-ijmuiden-steelworks | P41: full scale | Q41: https://www.tatasteeleurope.com/corporate/news/tata-steel-opts-for-hydrogen-route-at-its-ijmuiden-steelworks | R41: H-DR | S41: DRI | T41: Not stated | U41: H-DR | V41: https://www.tatasteeleurope.com/corporate/news/tata-steel-opts-for-hydrogen-route-at-its-ijmuiden-steelworks | W41: 2030 | X41: https://www.tatasteeleurope.com/corporate/news/tata-steel-opts-for-hydrogen-route-at-its-ijmuiden-steelworks | Y41: 64.8 | Z41: https://www.tatasteeleurope.com/corporate/news/Tata-Steel-invests-65-million-euroin-next-phase-hydrogen-route | AA41: Not stated | AB41: https://www.tatasteeleurope.com/corporate/news/tata-steel-opts-for-hydrogen-route-at-its-ijmuiden-steelworks | AC41: Not stated | AD41: https://www.tatasteeleurope.com/corporate/news/tata-steel-opts-for-hydrogen-route-at-its-ijmuiden-steelworks | AE41: Not stated | AF41: https://www.tatasteeleurope.com/corporate/news/tata-steel-opts-for-hydrogen-route-at-its-ijmuiden-steelworks | AG41: N/A | AH41: https://www.tatasteeleurope.com/corporate/news/tata-steel-opts-for-hydrogen-route-at-its-ijmuiden-steelworks | AI41: McDermott, Danieli, Hatch | AJ41: https://www.tatasteeleurope.com/corporate/news/Tata-Steel-invests-65-million-euroin-next-phase-hydrogen-route | AK41: 2022-11-03 Announced on 30th August 2022: Tata Steel Nederland has signed contracts with three companies – McDermott, Danieli and Hatch – for the further technical preparations of the hydrogen route. (…) The cost for this first development step are in excess of 65 million euros and will result in an engineering package that forms the basis for a final permitting and project planning. (...) Project is led by the Tata Steel internal project and sustainability team. (...) McDermott is responsible for the construction input and support of the technical project management. Danieli is responsible for the engineering design for the plant and technology that delivers DRI. Hatch is the technology licensor of the electric furnaces (REF) that melt the DRI. // Tata Steel Nederland has already signed a memorandum of understanding with Ford in Europe (...) makes Ford the first customer committed to offtake the green steel that Tata Steel plans to produce. | AL41: https://www.tatasteeleurope.com/corporate/news/Tata-Steel-invests-65-million-euroin-next-phase-hydrogen-route https://gmk.center/en/news/tata-steel-to-invest-e65-million-in-the-decarbonization-of-a-plant-in-the-netherlands/ | AM41: 44868 | AN41: 44455
A42: Tata Steel | B42: Project H2ermes | C42: https://h2ermes.nl/project-en/ | D42: SNL00001 | E42: 30% reduction (baseline 2020) | F42: carbon neutrality | G42: https://www.tatasteeleurope.com/ts/sites/default/files/TSE%20Sustainability%20report%202019-20%20%28EN%29.pdf | H42: 30.59 | I42: Netherlands | J42: Ijmuiden | K42: 52.484118 | L42: 4.615584 | M42: exact | N42: Europe | O42: https://prtr.eea.europa.eu/#/facilitylevels | P42: full scale | Q42: https://h2ermes.nl/project-en/ | R42: Hydrogen production | S42: H2 production | T42: Green electrolytic | U42: Hydrogen production (green hydrogen) | V42: https://h2ermes.nl/project-en/ | W42: 2025 | X42: https://h2ermes.nl/project-en/ | Y42: Not stated | Z42: https://h2ermes.nl/project-en/ | AA42: N/A | AB42: https://h2ermes.nl/project-en/ | AC42: N/A | AD42: https://h2ermes.nl/project-en/ | AE42: 100 | AF42: https://h2ermes.nl/project-en/ | AG42: N/A | AH42: https://h2ermes.nl/project-en/ | AI42: HyCC, Port of Amsterdam | AJ42: https://h2ermes.nl/project-en/ | AK42: 2022-11-03 In 2022, the permitting phase of the project will be started so that the first hydrogen can be supplied to Tata Steel and the Amsterdam Metropolitan Area in 2025/2026. Electrolysis facility to be located in Amsterdam, producing 15,000 tons of hydrogen per year and oxygen for industrial use at Tata Steel IJmuiden Works | AL42: https://h2ermes.nl/project-en/ | AM42: 44868 | AN42: 43392
A43: Tata Steel | B43: Hlsarna | C43: https://www.tatasteeleurope.com/ts/sustainability/carbon-neutral-steel | D43: SNL00001 | E43: 30% reduction (baseline 2020) | F43: carbon neutrality | G43: https://www.tatasteeleurope.com/ts/sites/default/files/TSE%20Sustainability%20report%202019-20%20%28EN%29.pdf | H43: 30.59 | I43: Netherlands | J43: Ijmuiden | K43: 52.484118 | L43: 4.615584 | M43: exact | N43: Europe | O43: https://prtr.eea.europa.eu/#/facilitylevels | P43: pilot | Q43: https://www.tatasteeleurope.com/ts/sites/default/files/TS%20Factsheet%20Hisarna%20ENG%20jan2020%20Vfinal03%204%20pag%20digital.pdf | R43: Other | S43: other | T43: N/A | U43: Smelting reduction | V43: https://www.tatasteeleurope.com/ts/sites/default/files/TS%20Factsheet%20Hisarna%20ENG%20jan2020%20Vfinal03%204%20pag%20digital.pdf | W43: 2017 | X43: https://www.tatasteeleurope.com/ts/sites/default/files/TS%20Factsheet%20Hisarna%20ENG%20jan2020%20Vfinal03%204%20pag%20digital.pdf | Y43: 100 | Z43: https://www.pmi.org/-/media/pmi/documents/public/pdf/academics/call-for-proposal/tata-hisarna-project.pdf?v=af070ea8-50e1-485e-b025-9042674a0803 | AA43: N/A | AB43: https://www.tatasteeleurope.com/ts/sites/default/files/TS%20Factsheet%20Hisarna%20ENG%20jan2020%20Vfinal03%204%20pag%20digital.pdf | AC43: 0.06 | AD43: https://www.tatasteeleurope.com/ts/sites/default/files/TS%20Factsheet%20Hisarna%20ENG%20jan2020%20Vfinal03%204%20pag%20digital.pdf | AE43: N/A | AF43: https://www.tatasteeleurope.com/ts/sites/default/files/TS%20Factsheet%20Hisarna%20ENG%20jan2020%20Vfinal03%204%20pag%20digital.pdf | AG43: N/A | AH43: https://www.tatasteeleurope.com/ts/sites/default/files/TS%20Factsheet%20Hisarna%20ENG%20jan2020%20Vfinal03%204%20pag%20digital.pdf | AI43: Rio Tinto, Tata steel, ULCOS, EU | AJ43: https://www.pmi.org/-/media/pmi/documents/public/pdf/academics/call-for-proposal/tata-hisarna-project.pdf?v=af070ea8-50e1-485e-b025-9042674a0803 | AK43: 2022-11-02 By 2033, our ambition is to have it scaled up it at full scale and it is ready to replace one of our blast furnaces. HIsarna can cut up to 100% of CO2 emissions, when combined with carbon capture. https://www.tatasteeleurope.com/construction/sustainability/performance-at-our-sites/ijmuiden A new reactor has been developed, which can be used to produce steel from iron ore, coal fines and oxygen. It has the potential to reduce direct CO2 emissions by 20% . With CCS 80 % of the emissions could be reduced as the reactor releases a pure stream of CO2. The technology was developed by Tata steel and Rio Tinto, but Tata steel owns the IP now. The plans to build an industrial demonstration plant in the Netherlands were shelved because of the low-demand of steel in the EU. The industrial demo plant could be commissioned in Jamshedpur, India which is the headquarters of Tata Steel. | AL43: https://www.nhnieuws.nl/nieuws/235611/Tata-Steel-kiest-onverwacht-niet-voor-IJmuiden-om-nieuwe-fabriek-te-vestigen | AM43: 44867 | AN43: 40688
A44: Tenaris | B44: Dalmine Zero Emissions | C44: N/A | D44: TBD | E44: N/A | F44: N/A | G44: https://www.tenaris.com/en/newsroom/news-listing/tenaris-joins-edison-and-snam-to-trial-steelmaking--23383824921 | H44: <8 | I44: Italy | J44: Dalmine | K44: 45.641516 | L44: 9.600242 | M44: exact | N44: Europe | O44: https://www.tenaris.com/en/newsroom/news-listing/tenaris-joins-edison-and-snam-to-trial-steelmaking--23383824921 | P44: full scale | Q44: https://www.tenaris.com/en/newsroom/news-listing/tenaris-joins-edison-and-snam-to-trial-steelmaking--23383824921 | R44: Hydrogen production | S44: H2 production | T44: Green electrolytic | U44: Hydrogen production (green hydrogen) | V44: https://www.tenaris.com/en/newsroom/news-listing/tenaris-joins-edison-and-snam-to-trial-steelmaking--23383824921 | W44: Not stated | X44: https://www.tenaris.com/en/newsroom/news-listing/tenaris-joins-edison-and-snam-to-trial-steelmaking--23383824921 | Y44: Not stated | Z44: https://www.tenaris.com/en/newsroom/news-listing/tenaris-joins-edison-and-snam-to-trial-steelmaking--23383824921 | AA44: Not stated | AB44: https://www.tenaris.com/en/newsroom/news-listing/tenaris-joins-edison-and-snam-to-trial-steelmaking--23383824921 | AC44: N/A | AD44: https://www.tenaris.com/en/newsroom/news-listing/tenaris-joins-edison-and-snam-to-trial-steelmaking--23383824921 | AE44: 20 | AF44: https://www.tenaris.com/en/newsroom/news-listing/tenaris-joins-edison-and-snam-to-trial-steelmaking--23383824921 | AG44: N/A | AH44: https://www.tenaris.com/en/newsroom/news-listing/tenaris-joins-edison-and-snam-to-trial-steelmaking--23383824921 | AI44: Edison, Snam | AJ44: https://www.tenaris.com/en/newsroom/news-listing/tenaris-joins-edison-and-snam-to-trial-steelmaking--23383824921 | AK44: 2022-11-03 No further comments // 2021-11-01 Letter of intent signed by partners | AL44: https://www.tenaris.com/en/newsroom/news-listing/tenaris-joins-edison-and-snam-to-trial-steelmaking--23383824921 | AM44: 44868 | AN44: 44501
A45: Thyssenkrupp | B45: Blast Furnace 2.0 | C45: N/A | D45: SDE00001 | E45: 30% reduction (baseline 2018) | F45: climate neutral | G45: https://www.thyssenkrupp.com/en/company/sustainability/climate-strategy-and-targets | H45: 12 | I45: Germany | J45: Duisburg | K45: 51.491649 | L45: 6.733051 | M45: exact | N45: Europe | O45: https://www.thyssenkrupp-steel.com/en/contact.html | P45: full scale | Q45: https://www.thyssenkrupp-steel.com/en/newsroom/press-releases/thyssenkrupp-presents-altmaier-and-laschet-concept-for-green-transformation-of-duisburg-steel-mill.html | R45: NG-DR --> H-DR | S45: DRI | T45: Green electrolytic | U45: NG-DR --> H-DR | V45: https://www.thyssenkrupp-steel.com/en/newsroom/press-releases/thyssenkrupp-presents-altmaier-and-laschet-concept-for-green-transformation-of-duisburg-steel-mill.html | W45: 2025 | X45: https://www.thyssenkrupp-steel.com/en/newsroom/press-releases/thyssenkrupp-presents-altmaier-and-laschet-concept-for-green-transformation-of-duisburg-steel-mill.html | Y45: Not stated | Z45: https://www.thyssenkrupp-steel.com/en/newsroom/press-releases/thyssenkrupp-presents-altmaier-and-laschet-concept-for-green-transformation-of-duisburg-steel-mill.html | AA45: N/A | AB45: https://www.thyssenkrupp-steel.com/en/newsroom/press-releases/thyssenkrupp-presents-altmaier-and-laschet-concept-for-green-transformation-of-duisburg-steel-mill.html | AC45: 1.2 | AD45: https://www.thyssenkrupp-steel.com/en/newsroom/press-releases/thyssenkrupp-presents-altmaier-and-laschet-concept-for-green-transformation-of-duisburg-steel-mill.html | AE45: N/A | AF45: https://www.thyssenkrupp-steel.com/en/newsroom/press-releases/thyssenkrupp-presents-altmaier-and-laschet-concept-for-green-transformation-of-duisburg-steel-mill.html | AG45: N/A | AH45: https://www.thyssenkrupp-steel.com/en/newsroom/press-releases/thyssenkrupp-presents-altmaier-and-laschet-concept-for-green-transformation-of-duisburg-steel-mill.html | AI45: N/A | AJ45: https://www.thyssenkrupp-steel.com/en/newsroom/press-releases/thyssenkrupp-presents-altmaier-and-laschet-concept-for-green-transformation-of-duisburg-steel-mill.html | AK45: 2023-03-13 In pursuit of the best technological solution, thyssenkrupp will be the first steelmaker in the world to combine a 100-percent hydrogen-capable direct reduction plant with innovative melters. The direct reduction plant is based on MIDREX Flex technology. 2023-03-02 German plantmaker SMS Group has announced that it will supply a direct reduction plant worth €1.8 billion to Germany-based steelmaker Thyssenkrupp Steel’s Duisburg plant (...) scheduled to start-up by the end of 2026. 2022-11-08 The plant with a capacity of 2.5 million metric tons, will avoid the emission of 3.5 million metric tons of CO2. Construction will involve investment of more than €2 billion DRI processed in an integrated melting unit to "electrical hot metal", then fed into BOFs (transition) // Online year subject to positive investment decision in 2023 | AL45: https://greensteelworld.com/thyssenkrupp-steel-awards-contract-worth-billions-of-euros-to-sms-group-for-dri-plant https://www.steelorbis.com/steel-news/latest-news/thyssenkrupp-steel-orders-dri-plant-for-decarbonization-efforts-1281017.htm https://www.greencarcongress.com/2022/09/20220909-thyssenkrupp.html | AM45: 44998 | AN45: 44071
A46: Thyssenkrupp | B46: HydrOxy Hub Walsum | C46: https://www.steag.com/en/news/current-projects/hydroxy-walsum | D46: SDE00001 | E46: 30% reduction (baseline 2018) | F46: climate neutral | G46: https://www.thyssenkrupp.com/en/company/sustainability/climate-strategy-and-targets | H46: 12 | I46: Germany | J46: Duisburg | K46: 51.491649 | L46: 6.733051 | M46: exact | N46: Europe | O46: https://www.thyssenkrupp-steel.com/en/contact.html | P46: full scale | Q46: https://www.steag.com/en/news/current-projects/hydroxy-walsum | R46: Hydrogen production | S46: H2 production | T46: Green electrolytic | U46: Hydrogen production (green hydrogen) | V46: https://www.steag.com/en/news/current-projects/hydroxy-walsum | W46: 2025 | X46: https://www.steag.com/en/news/current-projects/hydroxy-walsum | Y46: 600 | Z46: https://www.steag.com/en/news/current-projects/hydroxy-walsum | AA46: N/A | AB46: https://www.steag.com/en/news/current-projects/hydroxy-walsum | AC46: N/A | AD46: https://www.steag.com/en/news/current-projects/hydroxy-walsum | AE46: 520 | AF46: https://www.steag.com/en/press-release/21-03-2022-thyssenkrupp-steel-and-steag-agree-delivery-of-hydrogen | AG46: N/A | AH46: https://www.steag.com/en/news/current-projects/hydroxy-walsum | AI46: Thyssenkrupp Uhde Chlorine Engineers, Steag | AJ46: https://www.steag.com/en/news/current-projects/hydroxy-walsum | AK46: 2022-12-30 Air Liquide will supply hydrogen to the plant from 2024 2022-11-08 an agreement in the form of a memorandum of understanding [repared by the project partners STEAG and thyssenkrupp] has now been reached on the planned delivery of hydrogen and oxygen to thyssenkrupp Steel in Duisburg from the neighboring STEAG site in Duisburg-Walsum. If an investment decision is made in spring 2023, commercial operation of the plant is conceivable in early 2025. // Hydrogen to be supplied to Duisburg steel mills; application for IPCEI intended. | AL46: https://www.steelorbis.com/steel-news/latest-news/air-liquides-new-pipeline-to-supply-hydrogen-to-thyssenkrupps-duisburg-plant-from-2024-1273488.htm https://www.steag.com/en/press-release/21-03-2022-thyssenkrupp-steel-and-steag-agree-delivery-of-hydrogen | AM46: 44993 | AN46: 44251
A47: Thyssenkrupp | B47: H2morrow | C47: https://oge.net/en/us/projects/h2morrow | D47: N/A | E47: 30% reduction (baseline 2018) | F47: climate neutral | G47: https://www.thyssenkrupp.com/en/company/sustainability/climate-strategy-and-targets | H47: 12 | I47: Germany | J47: Duisburg (location of hydrogen use) | K47: 51.491649 | L47: 6.733051 | M47: exact | N47: Europe | O47: https://www.thyssenkrupp-steel.com/en/contact.html | P47: full scale | Q47: https://oge.net/en/us/projects/h2morrow | R47: Hydrogen production | S47: H2 production | T47: Blue | U47: Hydrogen production (blue hydrogen with carbon capture and offshore storage) | V47: https://www.energate-messenger.de/news/208774/blauer-wasserstoff-fuer-duisburger-stahlwerk | W47: 2027 | X47: https://www.energate-messenger.de/news/208774/blauer-wasserstoff-fuer-duisburger-stahlwerk | Y47: Not stated | Z47: https://oge.net/en/us/projects/h2morrow | AA47: N/A | AB47: https://oge.net/en/us/projects/h2morrow | AC47: Not stated | AD47: https://oge.net/en/us/projects/h2morrow | AE47: 1400 | AF47: https://www.thyssenkrupp-steel.com/en/newsroom/press-releases/h2morrow-steel-concludes-feasibility-study.html | AG47: Not stated | AH47: https://www.thyssenkrupp-steel.com/en/newsroom/press-releases/h2morrow-steel-concludes-feasibility-study.html | AI47: Equinor, OGE | AJ47: https://www.thyssenkrupp-steel.com/en/newsroom/press-releases/h2morrow-steel-concludes-feasibility-study.html | AK47: 2022-11-08 No further comments // 2021-05-02 Feasibility study concluded in Jan 2021, considering project technically feasible, further details to be investigated for investment decision Reforming of natural gas imported from Norway to produce hydrogen, carbon capture for offshore storage; use existing gas pipelines (convert for pure H2 use); hydrogen to be supplied to Thyssenkrupp Steel Europe to replace coking coal; capacity scenarios researched: 1.4 and 2.7 GW | AL47: https://www.thyssenkrupp-steel.com/en/newsroom/press-releases/h2morrow-steel-concludes-feasibility-study.html | AM47: 44873 | AN47: 44208
A48: Voestalpine | B48: HYFOR | C48: https://magazine.primetals.com/2021/06/24/zero-carbon-hyfor-direct-reduction-pilot-plant-commences-operation-in-donawitz-austria/ | D48: SAT00002 | E48: 30% reduction (baseline undefined) | F48: carbon neutrality | G48: https://www.voestalpine.com/greentecsteel/en/ | H48: <8 | I48: Austria | J48: Donawitz | K48: 47.380455 | L48: 15.065182 | M48: exact | N48: Europe | O48: https://www.voestalpine.com/stahldonawitz/en/ | P48: pilot | Q48: https://www.primetals.com/de/presse-medien/news/primetals-technologies-develops-breakthrough-technology-for-carbon-free-hydrogen-based-direct-reduction-for-iron-ore-fines | R48: H-DR | S48: DRI | T48: Not stated | U48: H-DR | V48: https://asia.nikkei.com/Spotlight/Environment/Climate-Change/Mitsubishi-Heavy-to-build-biggest-zero-carbon-steel-plant | W48: 2021 | X48: https://www.primetals.com/de/presse-medien/news/primetals-technologies-develops-breakthrough-technology-for-carbon-free-hydrogen-based-direct-reduction-for-iron-ore-fines | Y48: Not stated | Z48: https://www.primetals.com/de/presse-medien/news/primetals-technologies-develops-breakthrough-technology-for-carbon-free-hydrogen-based-direct-reduction-for-iron-ore-fines | AA48: N/A | AB48: https://www.primetals.com/de/presse-medien/news/primetals-technologies-develops-breakthrough-technology-for-carbon-free-hydrogen-based-direct-reduction-for-iron-ore-fines | AC48: 0.25 | AD48: https://asia.nikkei.com/Spotlight/Environment/Climate-Change/Mitsubishi-Heavy-to-build-biggest-zero-carbon-steel-plant | AE48: Not stated | AF48: https://asia.nikkei.com/Spotlight/Environment/Climate-Change/Mitsubishi-Heavy-to-build-biggest-zero-carbon-steel-plant | AG48: N/A | AH48: https://asia.nikkei.com/Spotlight/Environment/Climate-Change/Mitsubishi-Heavy-to-build-biggest-zero-carbon-steel-plant | AI48: Mitsubishi Heavy, Primetals Technologies | AJ48: https://asia.nikkei.com/Spotlight/Environment/Climate-Change/Mitsubishi-Heavy-to-build-biggest-zero-carbon-steel-plant // https://www.primetals.com/de/presse-medien/news/primetals-technologies-develops-breakthrough-technology-for-carbon-free-hydrogen-based-direct-reduction-for-iron-ore-fines | AK48: 2022-11-02 No further comment // 2021-08-25 Building an industrial-scale HYFOR prototype will be decided by the end of 2022 https://magazine.primetals.com/2021/08/24/zero-carbon-iron-primetals-technologies-and-mhi-australia-join-hilt-crc/ // 2021-06-24 First tests successfully executed in April and May 2021 | AL48: https://magazine.primetals.com/2021/06/24/zero-carbon-hyfor-direct-reduction-pilot-plant-commences-operation-in-donawitz-austria/ https://magazine.primetals.com/2021/08/24/zero-carbon-iron-primetals-technologies-and-mhi-australia-join-hilt-crc/ | AM48: 44868 | AN48: 44193
A49: Voestalpine | B49: SuSteel | C49: https://www.k1-met.com/en/research_programme/susteel/ | D49: SAT00002 | E49: 30% reduction (baseline undefined) | F49: carbon neutrality | G49: https://www.voestalpine.com/greentecsteel/en/ | H49: <8 | I49: Austria | J49: Donawitz | K49: 47.380455 | L49: 15.065182 | M49: exact | N49: Europe | O49: https://www.voestalpine.com/stahldonawitz/en/ | P49: pilot | Q49: https://www.k1-met.com/en/research_programme/susteel/ | R49: Other | S49: other | T49: N/A | U49: Plasma smelting reduction | V49: https://www.k1-met.com/en/research_programme/susteel/ | W49: 2020 | X49: https://www.k1-met.com/en/research_programme/susteel/ | Y49: Not stated | Z49: https://www.k1-met.com/en/research_programme/susteel/ | AA49: N/A | AB49: https://www.k1-met.com/en/research_programme/susteel/ | AC49: 0 | AD49: https://www.k1-met.com/en/research_programme/susteel/ | AE49: N/A | AF49: https://www.k1-met.com/en/research_programme/susteel/ | AG49: N/A | AH49: https://www.k1-met.com/en/research_programme/susteel/ | AI49: K1-MET GmbH, University of Leoben | AJ49: https://www.k1-met.com/en/research_programme/susteel/ | AK49: Project ended in February 2020, pilot said to be successful; however no mention of any follow up in voestalpine Environmental report 2020 | AL49: https://www.k1-met.com/en/research_programme/susteel/ | AM49: 44851 | AN49: 42614
