Workbook

Sheet Read me
A1: Trade flows — the input–output model of EU-27 manufacturing · IO-model masterfile v1
A2: Workbook | B2: Trade flows — IO-model masterfile v1 (EU-27 manufacturing input–output model, dashboard, underlying data and sources)
A3: Compiled | B3: 2026-08-11
A4: Status | B4: AI-compiled — pending Secretariat verification. Every statistical value is fetched from the public Eurostat API by the scripts named below; every curated figure carries its source on its own sheet and in the Sources sheet.
A5: What this is | B5: The COMPLETE input–output modelling behind /beta/overview-industry/trade-flows, rebuilt inside one workbook: the FIGARO use matrices (total / domestic / imported), the technical and import coefficient matrices, the Leontief inverse, the import-requirements matrix, multipliers, the import and value-added content of final demand and of extra-EU exports — plus the dashboard, the Eurostat trade backbone, the published FIGARO layers and every curated dependency register. It is a superset of the in-page "handover workbook" download, which only carries the result tables.
A6: Live formulas | B6: Everything derived is an Excel formula: the coefficient sheets divide the Z sheets by output, the Leontief inverse is one MINVERSE array formula over (I − A), the import-requirements sheet is one MMULT array formula, and the Multipliers and Dashboard sheets are built from SUM / SUMPRODUCT / INDEX / MATCH / COUNTIF over the data sheets. Change any underlying cell (a Z-matrix value, a backbone flow, a curated register row) and every dependent figure — up to and including the Dashboard — recalculates. Full recalculation on open is switched on.
A7: How to make changes | B7: 1) Edit the underlying cell (Z sheets, Trade backbone, or a curated register). 2) Let Excel recalculate (F9 / on open). 3) Record the edit in the Change log sheet (date, cell, old → new, reason, source). 4) For changes that should persist, carry them back to the repository — the canonical data lives in trade-data.ts / the generated extracts, and this file is regenerated from them; a hand-edited copy of this workbook is a working copy, not the source of truth.
A8: Model scope | B8: Reference year 2023; EU-27 treated as one economy ("imported" = from outside the EU). 64 A*64 industries (the whole economy, not only manufacturing — a manufacturing-only model would misstate the chains through energy, mining and services). € million, current basic prices. Matrices condensed from Eurostat FIGARO naio_10_fcp_ii4 (~11 M cells) by scripts/fetch-figaro-io-dataset.mjs; aggregation choices are documented in that script's header.
A9: Three data layers | B9: Layer 1 — trade backbone: ext_tec01, all 24 Section C divisions, 2023 + 2024, enterprise attribution. Layer 2 — input–output: the FIGARO matrices modelled here, plus the published application datasets (use-table input mixes, import origins, export destinations, foreign value added). Layer 3 — curated dependency registers: EC/JRC critical raw materials, SWD(2021) 352 strategic families, manufactured-product dependencies, energy dependency — "as reported by <source>", NOT derivable from official statistics and never arithmetically combined with the statistical layers.
A10: Raw data included | B10: The ENTIRE condensed FIGARO account is embedded: "FIGARO raw 2023" and "FIGARO raw 2022" hold every origin block (24 origins × 70 product/VA rows × 69 use columns per year, € million, zero cells blank), and "FIGARO exports raw" holds extra-EU exports by industry × destination (intermediate + final, both years). NOTHING between the raw sheets and the Dashboard is pre-computed outside Excel: the Z sheets are SUMs/references over the raw 2023 sheet (fixed 24-row stride per product row, EU27 origin first), the IO model reads the Z and exports-raw sheets, and everything above reads the IO model — edit one raw cell and the whole chain recalculates. 2022 is included for reference; to model it, repoint the Z-sheet formulas (same layout).
A11: Sheet map | B11: Dashboard → Figures (NATIVE Excel charts generated from the sheet data: trade balance, dependency map, import content — they recalculate with the sheets) → Methodology → Method figure (the model as one diagram) → Concepts (plain-language glossary: what an IO table is, what the Leontief inverse does, …) → FIGARO raw 2023 / FIGARO raw 2022 / FIGARO exports raw (the full embedded dataset) → IO model → Z total / Z domestic / Z imported (derived from the raw sheets by formula) → A domestic / A import → I minus A → Leontief inverse → Import requirements → Multipliers → Trade backbone → FIGARO partners → Foreign value added → Imported inputs → Critical materials → Product dependencies → Strategic dependencies → Energy dependency → Risk map → Critical inputs → Sources → Change log. The Methodology sheet states, for every derived sheet, the formula it implements and the exact cell references. Only the method diagram is an image; the data figures are real charts over live ranges.
A12: Reproducible | B12: node scripts/build-trade-flows-io-model-workbook.mjs rebuilds this file. Upstream: node scripts/fetch-figaro-io-dataset.mjs (FIGARO matrices), node scripts/fetch-trade-flows-io-data.mjs (backbone + published IO layers). Curated registers: beta/modules/overview-industry/trade-flows/trade-data.ts.
A13: Live module | B13: /beta/overview-industry/trade-flows on the MethodHub — same data, with the FIGARO table viewer and analysis dashboard at /trade-flows/figaro.

Sheet Dashboard
A1: Dashboard — every figure below is an Excel formula over the data sheets and recalculates when they are edited
A3: Headline — Section C manufacturing, reference year 2023 (Trade backbone, published IO layers, model)
A4: Extra-EU exports € bn (aggregate row) | B4: =INDEX('Trade backbone'!E:E,MATCH("C",'Trade backbone'!A:A,0)) -> 1649.9 | F4: ext_tec01 Section C aggregate; enterprise attribution.
A5: Extra-EU imports € bn (aggregate row) | B5: =INDEX('Trade backbone'!D:D,MATCH("C",'Trade backbone'!A:A,0)) -> 975.7 | F5: Includes trade not allocable to a division.
A6: Extra-EU trade balance € bn | B6: =INDEX('Trade backbone'!E:E,MATCH("C",'Trade backbone'!A:A,0))-INDEX('Trade backbone'!D:D,MATCH("C",'Trade backbone'!A:A,0)) -> 674.2 | F6: A large surplus that masks acute input dependencies.
A7: Foreign value added in exports % (published) | B7: =INDEX('Foreign value added'!E:E,MATCH("C",'Foreign value added'!A:A,0)) -> 22.4 | F7: FIGARO naio_10_fgfoee, EU-27 as one economy.
A8: Imported share of intermediate inputs % (use table) | B8: =INDEX('Imported inputs'!E:E,MATCH("C",'Imported inputs'!A:A,0)) -> 19.2 | F8: EU-27 use table at basic prices.
A9: Model: import content of manufacturing exports % (export-weighted) | B9: =SUMPRODUCT(('Multipliers'!$C$3:$C$66="C")*'Multipliers'!$E$3:$E$66,'Multipliers'!$H$3:$H$66)/SUMPRODUCT(('Multipliers'!$C$3:$C$66="C")*1,'Multipliers'!$H$3:$H$66) -> 23.91503 | F9: This workbook's own Leontief derivation (Multipliers sheet), weighted by extra-EU exports across the C industries.
A10: Model health: worst accounting-identity error (pp) | B10: =MAX(ABS('Multipliers'!G3:G66)) -> 8.8817842e-14 | F10: Import content + VA content − 100, worst industry. Near zero when the model is consistent; grows if an edit breaks the balance. Array-entered (Ctrl+Shift+Enter) in older Excel.
A12: Curated dependency registers — counts (COUNTIF over the register sheets)
A13: Critical raw materials tracked | B13: =COUNTA('Critical materials'!A2:A15) -> 14 | F13: CRMA Annex I/II designations with EC/JRC reliance figures.
A14: — of which Strategic (CRMA Annex I) | B14: =COUNTIF('Critical materials'!B2:B15,"Strategic*") -> 12
A15: Manufactured-product dependencies tracked | B15: =COUNTA('Product dependencies'!A2:A12) -> 11 | F15: The "not just raw materials" register.
A16: Strategic product families (SWD(2021) 352) | B16: =COUNTA('Strategic dependencies'!A2:A7) -> 6
A17: Dependencies with China as largest supplier (materials + products) | B17: =COUNTIF('Critical materials'!D2:D15,"*China*")+COUNTIF('Product dependencies'!E2:E12,"*China*") -> 18 | F17: Largest single supplier, as reported by each source.
A18: Materials with 100 % import reliance | B18: =COUNTIF('Critical materials'!C2:C15,100) -> 11
A19: Overall EU energy import dependency % | B19: ='Energy dependency'!C2 -> 57.3 | F19: Live nrg_ind_id headline row.
A21: Dependencies by supplier country (COUNTIF across the three curated registers)
A22: Supplier (as recorded) | B22: Materials | C22: Products | D22: Strategic families | E22: Total
A23: Brazil | B23: =COUNTIF('Critical materials'!D2:D15,"Brazil") -> 1 | C23: =COUNTIF('Product dependencies'!E2:E12,"Brazil") -> 0 | D23: =COUNTIF('Strategic dependencies'!E2:E7,"Brazil") -> 0 | E23: =SUM(B23:D23) -> 1
A24: Chile | B24: =COUNTIF('Critical materials'!D2:D15,"Chile") -> 1 | C24: =COUNTIF('Product dependencies'!E2:E12,"Chile") -> 0 | D24: =COUNTIF('Strategic dependencies'!E2:E7,"Chile") -> 0 | E24: =SUM(B24:D24) -> 1
A25: China | B25: =COUNTIF('Critical materials'!D2:D15,"China") -> 9 | C25: =COUNTIF('Product dependencies'!E2:E12,"China") -> 8 | D25: =COUNTIF('Strategic dependencies'!E2:E7,"China") -> 2 | E25: =SUM(B25:D25) -> 19
A26: China / India | B26: =COUNTIF('Critical materials'!D2:D15,"China / India") -> 0 | C26: =COUNTIF('Product dependencies'!E2:E12,"China / India") -> 1 | D26: =COUNTIF('Strategic dependencies'!E2:E7,"China / India") -> 1 | E26: =SUM(B26:D26) -> 2
A27: DR Congo (mining) | B27: =COUNTIF('Critical materials'!D2:D15,"DR Congo (mining)") -> 1 | C27: =COUNTIF('Product dependencies'!E2:E12,"DR Congo (mining)") -> 0 | D27: =COUNTIF('Strategic dependencies'!E2:E7,"DR Congo (mining)") -> 0 | E27: =SUM(B27:D27) -> 1
A28: South Africa | B28: =COUNTIF('Critical materials'!D2:D15,"South Africa") -> 1 | C28: =COUNTIF('Product dependencies'!E2:E12,"South Africa") -> 0 | D28: =COUNTIF('Strategic dependencies'!E2:E7,"South Africa") -> 1 | E28: =SUM(B28:D28) -> 2
A29: South-East Asia | B29: =COUNTIF('Critical materials'!D2:D15,"South-East Asia") -> 0 | C29: =COUNTIF('Product dependencies'!E2:E12,"South-East Asia") -> 1 | D29: =COUNTIF('Strategic dependencies'!E2:E7,"South-East Asia") -> 0 | E29: =SUM(B29:D29) -> 1
A30: Taiwan / East Asia | B30: =COUNTIF('Critical materials'!D2:D15,"Taiwan / East Asia") -> 0 | C30: =COUNTIF('Product dependencies'!E2:E12,"Taiwan / East Asia") -> 1 | D30: =COUNTIF('Strategic dependencies'!E2:E7,"Taiwan / East Asia") -> 1 | E30: =SUM(B30:D30) -> 2
A31: Türkiye | B31: =COUNTIF('Critical materials'!D2:D15,"Türkiye") -> 1 | C31: =COUNTIF('Product dependencies'!E2:E12,"Türkiye") -> 0 | D31: =COUNTIF('Strategic dependencies'!E2:E7,"Türkiye") -> 1 | E31: =SUM(B31:D31) -> 2
A33: By NACE division — balance, input mix, dependency count (INDEX/MATCH + COUNTIF)
A34: Division | B34: Extra-EU balance 2023 €bn | C34: Imported-input share % | D34: Curated dependency mentions | F34: Label / note
A35: C10 | B35: =INDEX('Trade backbone'!F:F,MATCH("C10",'Trade backbone'!A:A,0)) -> 53 | C35: =INDEX('Imported inputs'!E:E,MATCH("C10-12",'Imported inputs'!A:A,0)) -> 10.4 | D35: =COUNTIF('Critical materials'!F2:F15,"*C10*")+COUNTIF('Product dependencies'!C2:C12,"*C10*")+COUNTIF('Strategic dependencies'!B2:B7,"*C10*")+COUNTIF('Critical inputs'!A:A,"C10") -> 2 | F35: Food products — input mix is the C10-12 group figure
A36: C11 | B36: =INDEX('Trade backbone'!F:F,MATCH("C11",'Trade backbone'!A:A,0)) -> 18.6 | C36: =INDEX('Imported inputs'!E:E,MATCH("C10-12",'Imported inputs'!A:A,0)) -> 10.4 | D36: =COUNTIF('Critical materials'!F2:F15,"*C11*")+COUNTIF('Product dependencies'!C2:C12,"*C11*")+COUNTIF('Strategic dependencies'!B2:B7,"*C11*")+COUNTIF('Critical inputs'!A:A,"C11") -> 0 | F36: Beverages — input mix is the C10-12 group figure
A37: C12 | B37: =INDEX('Trade backbone'!F:F,MATCH("C12",'Trade backbone'!A:A,0)) -> 0.6 | C37: =INDEX('Imported inputs'!E:E,MATCH("C10-12",'Imported inputs'!A:A,0)) -> 10.4 | D37: =COUNTIF('Critical materials'!F2:F15,"*C12*")+COUNTIF('Product dependencies'!C2:C12,"*C12*")+COUNTIF('Strategic dependencies'!B2:B7,"*C12*")+COUNTIF('Critical inputs'!A:A,"C12") -> 0 | F37: Tobacco products — input mix is the C10-12 group figure
A38: C13 | B38: =INDEX('Trade backbone'!F:F,MATCH("C13",'Trade backbone'!A:A,0)) -> 4.1 | C38: =INDEX('Imported inputs'!E:E,MATCH("C13-15",'Imported inputs'!A:A,0)) -> 17.8 | D38: =COUNTIF('Critical materials'!F2:F15,"*C13*")+COUNTIF('Product dependencies'!C2:C12,"*C13*")+COUNTIF('Strategic dependencies'!B2:B7,"*C13*")+COUNTIF('Critical inputs'!A:A,"C13") -> 0 | F38: Textiles — input mix is the C13-15 group figure
A39: C14 | B39: =INDEX('Trade backbone'!F:F,MATCH("C14",'Trade backbone'!A:A,0)) -> -0.6 | C39: =INDEX('Imported inputs'!E:E,MATCH("C13-15",'Imported inputs'!A:A,0)) -> 17.8 | D39: =COUNTIF('Critical materials'!F2:F15,"*C14*")+COUNTIF('Product dependencies'!C2:C12,"*C14*")+COUNTIF('Strategic dependencies'!B2:B7,"*C14*")+COUNTIF('Critical inputs'!A:A,"C14") -> 1 | F39: Wearing apparel — input mix is the C13-15 group figure
A40: C15 | B40: =INDEX('Trade backbone'!F:F,MATCH("C15",'Trade backbone'!A:A,0)) -> 4.3 | C40: =INDEX('Imported inputs'!E:E,MATCH("C13-15",'Imported inputs'!A:A,0)) -> 17.8 | D40: =COUNTIF('Critical materials'!F2:F15,"*C15*")+COUNTIF('Product dependencies'!C2:C12,"*C15*")+COUNTIF('Strategic dependencies'!B2:B7,"*C15*")+COUNTIF('Critical inputs'!A:A,"C15") -> 0 | F40: Leather & footwear — input mix is the C13-15 group figure
A41: C16 | B41: =INDEX('Trade backbone'!F:F,MATCH("C16",'Trade backbone'!A:A,0)) -> 9.7 | C41: =INDEX('Imported inputs'!E:E,MATCH("C16",'Imported inputs'!A:A,0)) -> 9.6 | D41: =COUNTIF('Critical materials'!F2:F15,"*C16*")+COUNTIF('Product dependencies'!C2:C12,"*C16*")+COUNTIF('Strategic dependencies'!B2:B7,"*C16*")+COUNTIF('Critical inputs'!A:A,"C16") -> 0 | F41: Wood & cork products
A42: C17 | B42: =INDEX('Trade backbone'!F:F,MATCH("C17",'Trade backbone'!A:A,0)) -> 9.1 | C42: =INDEX('Imported inputs'!E:E,MATCH("C17",'Imported inputs'!A:A,0)) -> 11.7 | D42: =COUNTIF('Critical materials'!F2:F15,"*C17*")+COUNTIF('Product dependencies'!C2:C12,"*C17*")+COUNTIF('Strategic dependencies'!B2:B7,"*C17*")+COUNTIF('Critical inputs'!A:A,"C17") -> 2 | F42: Paper & paper products
A43: C18 | B43: =INDEX('Trade backbone'!F:F,MATCH("C18",'Trade backbone'!A:A,0)) -> 1.4 | C43: =INDEX('Imported inputs'!E:E,MATCH("C18",'Imported inputs'!A:A,0)) -> 12.4 | D43: =COUNTIF('Critical materials'!F2:F15,"*C18*")+COUNTIF('Product dependencies'!C2:C12,"*C18*")+COUNTIF('Strategic dependencies'!B2:B7,"*C18*")+COUNTIF('Critical inputs'!A:A,"C18") -> 0 | F43: Printing & recorded media
A44: C19 | B44: =INDEX('Trade backbone'!F:F,MATCH("C19",'Trade backbone'!A:A,0)) -> -161.8 | C44: =INDEX('Imported inputs'!E:E,MATCH("C19",'Imported inputs'!A:A,0)) -> 63.4 | D44: =COUNTIF('Critical materials'!F2:F15,"*C19*")+COUNTIF('Product dependencies'!C2:C12,"*C19*")+COUNTIF('Strategic dependencies'!B2:B7,"*C19*")+COUNTIF('Critical inputs'!A:A,"C19") -> 1 | F44: Coke & refined petroleum
A45: C20 | B45: =INDEX('Trade backbone'!F:F,MATCH("C20",'Trade backbone'!A:A,0)) -> 73.9 | C45: =INDEX('Imported inputs'!E:E,MATCH("C20",'Imported inputs'!A:A,0)) -> 19.8 | D45: =COUNTIF('Critical materials'!F2:F15,"*C20*")+COUNTIF('Product dependencies'!C2:C12,"*C20*")+COUNTIF('Strategic dependencies'!B2:B7,"*C20*")+COUNTIF('Critical inputs'!A:A,"C20") -> 10 | F45: Chemicals & chemical products
A46: C21 | B46: =INDEX('Trade backbone'!F:F,MATCH("C21",'Trade backbone'!A:A,0)) -> 110.8 | C46: =INDEX('Imported inputs'!E:E,MATCH("C21",'Imported inputs'!A:A,0)) -> 29.3 | D46: =COUNTIF('Critical materials'!F2:F15,"*C21*")+COUNTIF('Product dependencies'!C2:C12,"*C21*")+COUNTIF('Strategic dependencies'!B2:B7,"*C21*")+COUNTIF('Critical inputs'!A:A,"C21") -> 2 | F46: Pharmaceuticals
A47: C22 | B47: =INDEX('Trade backbone'!F:F,MATCH("C22",'Trade backbone'!A:A,0)) -> 19.6 | C47: =INDEX('Imported inputs'!E:E,MATCH("C22",'Imported inputs'!A:A,0)) -> 16.7 | D47: =COUNTIF('Critical materials'!F2:F15,"*C22*")+COUNTIF('Product dependencies'!C2:C12,"*C22*")+COUNTIF('Strategic dependencies'!B2:B7,"*C22*")+COUNTIF('Critical inputs'!A:A,"C22") -> 1 | F47: Rubber & plastics
A48: C23 | B48: =INDEX('Trade backbone'!F:F,MATCH("C23",'Trade backbone'!A:A,0)) -> 15.1 | C48: =INDEX('Imported inputs'!E:E,MATCH("C23",'Imported inputs'!A:A,0)) -> 12.8 | D48: =COUNTIF('Critical materials'!F2:F15,"*C23*")+COUNTIF('Product dependencies'!C2:C12,"*C23*")+COUNTIF('Strategic dependencies'!B2:B7,"*C23*")+COUNTIF('Critical inputs'!A:A,"C23") -> 6 | F48: Non-metallic minerals (cement, glass, ceramics)
A49: C24 | B49: =INDEX('Trade backbone'!F:F,MATCH("C24",'Trade backbone'!A:A,0)) -> 4.1 | C49: =INDEX('Imported inputs'!E:E,MATCH("C24",'Imported inputs'!A:A,0)) -> 21.2 | D49: =COUNTIF('Critical materials'!F2:F15,"*C24*")+COUNTIF('Product dependencies'!C2:C12,"*C24*")+COUNTIF('Strategic dependencies'!B2:B7,"*C24*")+COUNTIF('Critical inputs'!A:A,"C24") -> 11 | F49: Basic metals
A50: C25 | B50: =INDEX('Trade backbone'!F:F,MATCH("C25",'Trade backbone'!A:A,0)) -> 28.7 | C50: =INDEX('Imported inputs'!E:E,MATCH("C25",'Imported inputs'!A:A,0)) -> 11.1 | D50: =COUNTIF('Critical materials'!F2:F15,"*C25*")+COUNTIF('Product dependencies'!C2:C12,"*C25*")+COUNTIF('Strategic dependencies'!B2:B7,"*C25*")+COUNTIF('Critical inputs'!A:A,"C25") -> 1 | F50: Fabricated metal products
A51: C26 | B51: =INDEX('Trade backbone'!F:F,MATCH("C26",'Trade backbone'!A:A,0)) -> 22.2 | C51: =INDEX('Imported inputs'!E:E,MATCH("C26",'Imported inputs'!A:A,0)) -> 28.2 | D51: =COUNTIF('Critical materials'!F2:F15,"*C26*")+COUNTIF('Product dependencies'!C2:C12,"*C26*")+COUNTIF('Strategic dependencies'!B2:B7,"*C26*")+COUNTIF('Critical inputs'!A:A,"C26") -> 11 | F51: Computer, electronic & optical
A52: C27 | B52: =INDEX('Trade backbone'!F:F,MATCH("C27",'Trade backbone'!A:A,0)) -> 23.6 | C52: =INDEX('Imported inputs'!E:E,MATCH("C27",'Imported inputs'!A:A,0)) -> 18.7 | D52: =COUNTIF('Critical materials'!F2:F15,"*C27*")+COUNTIF('Product dependencies'!C2:C12,"*C27*")+COUNTIF('Strategic dependencies'!B2:B7,"*C27*")+COUNTIF('Critical inputs'!A:A,"C27") -> 12 | F52: Electrical equipment
A53: C28 | B53: =INDEX('Trade backbone'!F:F,MATCH("C28",'Trade backbone'!A:A,0)) -> 165 | C53: =INDEX('Imported inputs'!E:E,MATCH("C28",'Imported inputs'!A:A,0)) -> 13.1 | D53: =COUNTIF('Critical materials'!F2:F15,"*C28*")+COUNTIF('Product dependencies'!C2:C12,"*C28*")+COUNTIF('Strategic dependencies'!B2:B7,"*C28*")+COUNTIF('Critical inputs'!A:A,"C28") -> 6 | F53: Machinery & equipment n.e.c.
A54: C29 | B54: =INDEX('Trade backbone'!F:F,MATCH("C29",'Trade backbone'!A:A,0)) -> 160.1 | C54: =INDEX('Imported inputs'!E:E,MATCH("C29",'Imported inputs'!A:A,0)) -> 13.1 | D54: =COUNTIF('Critical materials'!F2:F15,"*C29*")+COUNTIF('Product dependencies'!C2:C12,"*C29*")+COUNTIF('Strategic dependencies'!B2:B7,"*C29*")+COUNTIF('Critical inputs'!A:A,"C29") -> 13 | F54: Motor vehicles & parts
A55: C30 | B55: =INDEX('Trade backbone'!F:F,MATCH("C30",'Trade backbone'!A:A,0)) -> 63.1 | C55: =INDEX('Imported inputs'!E:E,MATCH("C30",'Imported inputs'!A:A,0)) -> 21.6 | D55: =COUNTIF('Critical materials'!F2:F15,"*C30*")+COUNTIF('Product dependencies'!C2:C12,"*C30*")+COUNTIF('Strategic dependencies'!B2:B7,"*C30*")+COUNTIF('Critical inputs'!A:A,"C30") -> 2 | F55: Other transport equipment (aero, rail, ships)
A56: C31 | B56: =INDEX('Trade backbone'!F:F,MATCH("C31",'Trade backbone'!A:A,0)) -> 9.5 | C56: =INDEX('Imported inputs'!E:E,MATCH("C31_32",'Imported inputs'!A:A,0)) -> 16.4 | D56: =COUNTIF('Critical materials'!F2:F15,"*C31*")+COUNTIF('Product dependencies'!C2:C12,"*C31*")+COUNTIF('Strategic dependencies'!B2:B7,"*C31*")+COUNTIF('Critical inputs'!A:A,"C31") -> 1 | F56: Furniture — input mix is the C31_32 group figure
A57: C32 | B57: =INDEX('Trade backbone'!F:F,MATCH("C32",'Trade backbone'!A:A,0)) -> 25.2 | C57: =INDEX('Imported inputs'!E:E,MATCH("C31_32",'Imported inputs'!A:A,0)) -> 16.4 | D57: =COUNTIF('Critical materials'!F2:F15,"*C32*")+COUNTIF('Product dependencies'!C2:C12,"*C32*")+COUNTIF('Strategic dependencies'!B2:B7,"*C32*")+COUNTIF('Critical inputs'!A:A,"C32") -> 1 | F57: Other manufacturing (medical, instruments, jewellery) — input mix is the C31_32 group figure
A58: C33 | B58: =INDEX('Trade backbone'!F:F,MATCH("C33",'Trade backbone'!A:A,0)) -> -6.1 | C58: =INDEX('Imported inputs'!E:E,MATCH("C33",'Imported inputs'!A:A,0)) -> 13.5 | D58: =COUNTIF('Critical materials'!F2:F15,"*C33*")+COUNTIF('Product dependencies'!C2:C12,"*C33*")+COUNTIF('Strategic dependencies'!B2:B7,"*C33*")+COUNTIF('Critical inputs'!A:A,"C33") -> 0 | F58: Repair & installation of machinery
A60: Model top 10 — import content of final demand % (LARGE + INDEX/MATCH over the Multipliers sheet)
A61: =INDEX('Multipliers'!$B$3:$B$66,MATCH(LARGE('Multipliers'!$E$3:$E$66,1),'Multipliers'!$E$3:$E$66,0)) -> Manufacture of coke and refined petroleum products | B61: =LARGE('Multipliers'!$E$3:$E$66,1) -> 63.66912
A62: =INDEX('Multipliers'!$B$3:$B$66,MATCH(LARGE('Multipliers'!$E$3:$E$66,2),'Multipliers'!$E$3:$E$66,0)) -> Manufacture of basic metals | B62: =LARGE('Multipliers'!$E$3:$E$66,2) -> 31.718899
A63: =INDEX('Multipliers'!$B$3:$B$66,MATCH(LARGE('Multipliers'!$E$3:$E$66,3),'Multipliers'!$E$3:$E$66,0)) -> Water transport | B63: =LARGE('Multipliers'!$E$3:$E$66,3) -> 30.44361
A64: =INDEX('Multipliers'!$B$3:$B$66,MATCH(LARGE('Multipliers'!$E$3:$E$66,4),'Multipliers'!$E$3:$E$66,0)) -> Manufacture of chemicals and chemical products | B64: =LARGE('Multipliers'!$E$3:$E$66,4) -> 28.887716
A65: =INDEX('Multipliers'!$B$3:$B$66,MATCH(LARGE('Multipliers'!$E$3:$E$66,5),'Multipliers'!$E$3:$E$66,0)) -> Air transport | B65: =LARGE('Multipliers'!$E$3:$E$66,5) -> 28.422098
A66: =INDEX('Multipliers'!$B$3:$B$66,MATCH(LARGE('Multipliers'!$E$3:$E$66,6),'Multipliers'!$E$3:$E$66,0)) -> Manufacture of other transport equipment | B66: =LARGE('Multipliers'!$E$3:$E$66,6) -> 27.228614
A67: =INDEX('Multipliers'!$B$3:$B$66,MATCH(LARGE('Multipliers'!$E$3:$E$66,7),'Multipliers'!$E$3:$E$66,0)) -> Manufacture of electrical equipment | B67: =LARGE('Multipliers'!$E$3:$E$66,7) -> 22.921232
A68: =INDEX('Multipliers'!$B$3:$B$66,MATCH(LARGE('Multipliers'!$E$3:$E$66,8),'Multipliers'!$E$3:$E$66,0)) -> Manufacture of rubber and plastic products | B68: =LARGE('Multipliers'!$E$3:$E$66,8) -> 22.440508
A69: =INDEX('Multipliers'!$B$3:$B$66,MATCH(LARGE('Multipliers'!$E$3:$E$66,9),'Multipliers'!$E$3:$E$66,0)) -> Manufacture of motor vehicles, trailers and semi-trailers | B69: =LARGE('Multipliers'!$E$3:$E$66,9) -> 21.560623
A70: =INDEX('Multipliers'!$B$3:$B$66,MATCH(LARGE('Multipliers'!$E$3:$E$66,10),'Multipliers'!$E$3:$E$66,0)) -> Manufacture of computer, electronic and optical products | B70: =LARGE('Multipliers'!$E$3:$E$66,10) -> 21.061637
A72: Model top 10 — output multipliers (total output per € of final demand)
A73: =INDEX('Multipliers'!$B$3:$B$66,MATCH(LARGE('Multipliers'!$D$3:$D$66,1),'Multipliers'!$D$3:$D$66,0)) -> Manufacture of food products | B73: =LARGE('Multipliers'!$D$3:$D$66,1) -> 2.4421365
A74: =INDEX('Multipliers'!$B$3:$B$66,MATCH(LARGE('Multipliers'!$D$3:$D$66,2),'Multipliers'!$D$3:$D$66,0)) -> Manufacture of basic metals | B74: =LARGE('Multipliers'!$D$3:$D$66,2) -> 2.3835029
A75: =INDEX('Multipliers'!$B$3:$B$66,MATCH(LARGE('Multipliers'!$D$3:$D$66,3),'Multipliers'!$D$3:$D$66,0)) -> Manufacture of paper and paper products | B75: =LARGE('Multipliers'!$D$3:$D$66,3) -> 2.3820274
A76: =INDEX('Multipliers'!$B$3:$B$66,MATCH(LARGE('Multipliers'!$D$3:$D$66,4),'Multipliers'!$D$3:$D$66,0)) -> Manufacture of motor vehicles, trailers and semi-trailers | B76: =LARGE('Multipliers'!$D$3:$D$66,4) -> 2.3743895
A77: =INDEX('Multipliers'!$B$3:$B$66,MATCH(LARGE('Multipliers'!$D$3:$D$66,5),'Multipliers'!$D$3:$D$66,0)) -> Travel agency, tour operator reservation service and related activiti… | B77: =LARGE('Multipliers'!$D$3:$D$66,5) -> 2.3623548
A78: =INDEX('Multipliers'!$B$3:$B$66,MATCH(LARGE('Multipliers'!$D$3:$D$66,6),'Multipliers'!$D$3:$D$66,0)) -> Manufacture of wood and of products of wood and cork, except furniture | B78: =LARGE('Multipliers'!$D$3:$D$66,6) -> 2.2755152
A79: =INDEX('Multipliers'!$B$3:$B$66,MATCH(LARGE('Multipliers'!$D$3:$D$66,7),'Multipliers'!$D$3:$D$66,0)) -> Manufacture of chemicals and chemical products | B79: =LARGE('Multipliers'!$D$3:$D$66,7) -> 2.2180476
A80: =INDEX('Multipliers'!$B$3:$B$66,MATCH(LARGE('Multipliers'!$D$3:$D$66,8),'Multipliers'!$D$3:$D$66,0)) -> Manufacture of fabricated metal products, except machinery and equipm… | B80: =LARGE('Multipliers'!$D$3:$D$66,8) -> 2.2030813
A81: =INDEX('Multipliers'!$B$3:$B$66,MATCH(LARGE('Multipliers'!$D$3:$D$66,9),'Multipliers'!$D$3:$D$66,0)) -> Construction | B81: =LARGE('Multipliers'!$D$3:$D$66,9) -> 2.1976922
A82: =INDEX('Multipliers'!$B$3:$B$66,MATCH(LARGE('Multipliers'!$D$3:$D$66,10),'Multipliers'!$D$3:$D$66,0)) -> Manufacture of other transport equipment | B82: =LARGE('Multipliers'!$D$3:$D$66,10) -> 2.1900075

Sheet Figures
A1: Figures — NATIVE Excel charts, generated from the sheet data: each chart reads a live range (named in its caption), so editing the underlying sheets moves the charts. The chart-data blocks in columns N–V are formulas over the data sheets — do not delete them. Only the row ORDER of figures 1 and 3 is fixed at build time (Excel cannot re-sort a chart range); values, bar lengths, positions and the surplus/deficit colour routing are all live. Chart colours are colour-vision-deficiency checked (teal = surplus, red = deficit; blue = raw material, orange = product).
N2: Chart data — live formulas over the data sheets. The charts read these ranges; do not delete.
A3: Figure 1 · Extra-EU trade balance by division, 2023 — native chart over Figures!P5:Q28 (live formulas over the Trade backbone sheet)
N4: Division | O4: Extra-EU balance 2023 €bn | P4: Surplus | Q4: Deficit | T4: Code | U4: Industry | V4: Import content %
N5: C28 · Machinery & equipment n.e.c. | O5: =INDEX('Trade backbone'!$F:$F,MATCH("C28",'Trade backbone'!$A:$A,0)) -> 165 | P5: =IF(O5>=0,O5,NA()) -> 165 | Q5: =IF(O5<0,O5,NA()) -> #N/A | T5: C19 | U5: =$T5&" · "&INDEX('Multipliers'!$B:$B,MATCH($T5,'Multipliers'!$A:$A,0)) -> C19 · Manufacture of coke and refined petroleum products | V5: =INDEX('Multipliers'!$E:$E,MATCH($T5,'Multipliers'!$A:$A,0)) -> 63.7
N6: C29 · Motor vehicles & parts | O6: =INDEX('Trade backbone'!$F:$F,MATCH("C29",'Trade backbone'!$A:$A,0)) -> 160.1 | P6: =IF(O6>=0,O6,NA()) -> 160.1 | Q6: =IF(O6<0,O6,NA()) -> #N/A | T6: C24 | U6: =$T6&" · "&INDEX('Multipliers'!$B:$B,MATCH($T6,'Multipliers'!$A:$A,0)) -> C24 · Manufacture of basic metals | V6: =INDEX('Multipliers'!$E:$E,MATCH($T6,'Multipliers'!$A:$A,0)) -> 31.7
N7: C21 · Pharmaceuticals | O7: =INDEX('Trade backbone'!$F:$F,MATCH("C21",'Trade backbone'!$A:$A,0)) -> 110.8 | P7: =IF(O7>=0,O7,NA()) -> 110.8 | Q7: =IF(O7<0,O7,NA()) -> #N/A | T7: H50 | U7: =$T7&" · "&INDEX('Multipliers'!$B:$B,MATCH($T7,'Multipliers'!$A:$A,0)) -> H50 · Water transport | V7: =INDEX('Multipliers'!$E:$E,MATCH($T7,'Multipliers'!$A:$A,0)) -> 30.4
N8: C20 · Chemicals & chemical products | O8: =INDEX('Trade backbone'!$F:$F,MATCH("C20",'Trade backbone'!$A:$A,0)) -> 73.9 | P8: =IF(O8>=0,O8,NA()) -> 73.9 | Q8: =IF(O8<0,O8,NA()) -> #N/A | T8: C20 | U8: =$T8&" · "&INDEX('Multipliers'!$B:$B,MATCH($T8,'Multipliers'!$A:$A,0)) -> C20 · Manufacture of chemicals and chemical products | V8: =INDEX('Multipliers'!$E:$E,MATCH($T8,'Multipliers'!$A:$A,0)) -> 28.9
N9: C30 · Other transport equipment (aero, … | O9: =INDEX('Trade backbone'!$F:$F,MATCH("C30",'Trade backbone'!$A:$A,0)) -> 63.1 | P9: =IF(O9>=0,O9,NA()) -> 63.1 | Q9: =IF(O9<0,O9,NA()) -> #N/A | T9: H51 | U9: =$T9&" · "&INDEX('Multipliers'!$B:$B,MATCH($T9,'Multipliers'!$A:$A,0)) -> H51 · Air transport | V9: =INDEX('Multipliers'!$E:$E,MATCH($T9,'Multipliers'!$A:$A,0)) -> 28.4
N10: C10 · Food products | O10: =INDEX('Trade backbone'!$F:$F,MATCH("C10",'Trade backbone'!$A:$A,0)) -> 53 | P10: =IF(O10>=0,O10,NA()) -> 53 | Q10: =IF(O10<0,O10,NA()) -> #N/A | T10: C30 | U10: =$T10&" · "&INDEX('Multipliers'!$B:$B,MATCH($T10,'Multipliers'!$A:$A,0)) -> C30 · Manufacture of other transport equipment | V10: =INDEX('Multipliers'!$E:$E,MATCH($T10,'Multipliers'!$A:$A,0)) -> 27.2
N11: C25 · Fabricated metal products | O11: =INDEX('Trade backbone'!$F:$F,MATCH("C25",'Trade backbone'!$A:$A,0)) -> 28.7 | P11: =IF(O11>=0,O11,NA()) -> 28.7 | Q11: =IF(O11<0,O11,NA()) -> #N/A | T11: C27 | U11: =$T11&" · "&INDEX('Multipliers'!$B:$B,MATCH($T11,'Multipliers'!$A:$A,0)) -> C27 · Manufacture of electrical equipment | V11: =INDEX('Multipliers'!$E:$E,MATCH($T11,'Multipliers'!$A:$A,0)) -> 22.9
N12: C32 · Other manufacturing (medical, ins… | O12: =INDEX('Trade backbone'!$F:$F,MATCH("C32",'Trade backbone'!$A:$A,0)) -> 25.2 | P12: =IF(O12>=0,O12,NA()) -> 25.2 | Q12: =IF(O12<0,O12,NA()) -> #N/A | T12: C22 | U12: =$T12&" · "&INDEX('Multipliers'!$B:$B,MATCH($T12,'Multipliers'!$A:$A,0)) -> C22 · Manufacture of rubber and plastic products | V12: =INDEX('Multipliers'!$E:$E,MATCH($T12,'Multipliers'!$A:$A,0)) -> 22.4
N13: C27 · Electrical equipment | O13: =INDEX('Trade backbone'!$F:$F,MATCH("C27",'Trade backbone'!$A:$A,0)) -> 23.6 | P13: =IF(O13>=0,O13,NA()) -> 23.6 | Q13: =IF(O13<0,O13,NA()) -> #N/A | T13: C29 | U13: =$T13&" · "&INDEX('Multipliers'!$B:$B,MATCH($T13,'Multipliers'!$A:$A,0)) -> C29 · Manufacture of motor vehicles, trailers and semi-trailers | V13: =INDEX('Multipliers'!$E:$E,MATCH($T13,'Multipliers'!$A:$A,0)) -> 21.6
N14: C26 · Computer, electronic & optical | O14: =INDEX('Trade backbone'!$F:$F,MATCH("C26",'Trade backbone'!$A:$A,0)) -> 22.2 | P14: =IF(O14>=0,O14,NA()) -> 22.2 | Q14: =IF(O14<0,O14,NA()) -> #N/A | T14: C26 | U14: =$T14&" · "&INDEX('Multipliers'!$B:$B,MATCH($T14,'Multipliers'!$A:$A,0)) -> C26 · Manufacture of computer, electronic and optical products | V14: =INDEX('Multipliers'!$E:$E,MATCH($T14,'Multipliers'!$A:$A,0)) -> 21.1
N15: C22 · Rubber & plastics | O15: =INDEX('Trade backbone'!$F:$F,MATCH("C22",'Trade backbone'!$A:$A,0)) -> 19.6 | P15: =IF(O15>=0,O15,NA()) -> 19.6 | Q15: =IF(O15<0,O15,NA()) -> #N/A | T15: C21 | U15: =$T15&" · "&INDEX('Multipliers'!$B:$B,MATCH($T15,'Multipliers'!$A:$A,0)) -> C21 · Manufacture of basic pharmaceutical products and pharmaceutical prepa… | V15: =INDEX('Multipliers'!$E:$E,MATCH($T15,'Multipliers'!$A:$A,0)) -> 21
N16: C11 · Beverages | O16: =INDEX('Trade backbone'!$F:$F,MATCH("C11",'Trade backbone'!$A:$A,0)) -> 18.6 | P16: =IF(O16>=0,O16,NA()) -> 18.6 | Q16: =IF(O16<0,O16,NA()) -> #N/A | T16: C13-15 | U16: =$T16&" · "&INDEX('Multipliers'!$B:$B,MATCH($T16,'Multipliers'!$A:$A,0)) -> C13-15 · Manufacture of textiles, wearing apparel, leather and related products | V16: =INDEX('Multipliers'!$E:$E,MATCH($T16,'Multipliers'!$A:$A,0)) -> 20.6
N17: C23 · Non-metallic minerals (cement, gl… | O17: =INDEX('Trade backbone'!$F:$F,MATCH("C23",'Trade backbone'!$A:$A,0)) -> 15.1 | P17: =IF(O17>=0,O17,NA()) -> 15.1 | Q17: =IF(O17<0,O17,NA()) -> #N/A
N18: C16 · Wood & cork products | O18: =INDEX('Trade backbone'!$F:$F,MATCH("C16",'Trade backbone'!$A:$A,0)) -> 9.7 | P18: =IF(O18>=0,O18,NA()) -> 9.7 | Q18: =IF(O18<0,O18,NA()) -> #N/A
N19: C31 · Furniture | O19: =INDEX('Trade backbone'!$F:$F,MATCH("C31",'Trade backbone'!$A:$A,0)) -> 9.5 | P19: =IF(O19>=0,O19,NA()) -> 9.5 | Q19: =IF(O19<0,O19,NA()) -> #N/A
N20: C17 · Paper & paper products | O20: =INDEX('Trade backbone'!$F:$F,MATCH("C17",'Trade backbone'!$A:$A,0)) -> 9.1 | P20: =IF(O20>=0,O20,NA()) -> 9.1 | Q20: =IF(O20<0,O20,NA()) -> #N/A
N21: C15 · Leather & footwear | O21: =INDEX('Trade backbone'!$F:$F,MATCH("C15",'Trade backbone'!$A:$A,0)) -> 4.3 | P21: =IF(O21>=0,O21,NA()) -> 4.3 | Q21: =IF(O21<0,O21,NA()) -> #N/A
N22: C13 · Textiles | O22: =INDEX('Trade backbone'!$F:$F,MATCH("C13",'Trade backbone'!$A:$A,0)) -> 4.1 | P22: =IF(O22>=0,O22,NA()) -> 4.1 | Q22: =IF(O22<0,O22,NA()) -> #N/A
N23: C24 · Basic metals | O23: =INDEX('Trade backbone'!$F:$F,MATCH("C24",'Trade backbone'!$A:$A,0)) -> 4.1 | P23: =IF(O23>=0,O23,NA()) -> 4.1 | Q23: =IF(O23<0,O23,NA()) -> #N/A
N24: C18 · Printing & recorded media | O24: =INDEX('Trade backbone'!$F:$F,MATCH("C18",'Trade backbone'!$A:$A,0)) -> 1.4 | P24: =IF(O24>=0,O24,NA()) -> 1.4 | Q24: =IF(O24<0,O24,NA()) -> #N/A
N25: C12 · Tobacco products | O25: =INDEX('Trade backbone'!$F:$F,MATCH("C12",'Trade backbone'!$A:$A,0)) -> 0.6 | P25: =IF(O25>=0,O25,NA()) -> 0.6 | Q25: =IF(O25<0,O25,NA()) -> #N/A
N26: C14 · Wearing apparel | O26: =INDEX('Trade backbone'!$F:$F,MATCH("C14",'Trade backbone'!$A:$A,0)) -> -0.6 | P26: =IF(O26>=0,O26,NA()) -> #N/A | Q26: =IF(O26<0,O26,NA()) -> -0.6
N27: C33 · Repair & installation of machinery | O27: =INDEX('Trade backbone'!$F:$F,MATCH("C33",'Trade backbone'!$A:$A,0)) -> -6.1 | P27: =IF(O27>=0,O27,NA()) -> #N/A | Q27: =IF(O27<0,O27,NA()) -> -6.1
N28: C19 · Coke & refined petroleum | O28: =INDEX('Trade backbone'!$F:$F,MATCH("C19",'Trade backbone'!$A:$A,0)) -> -161.8 | P28: =IF(O28>=0,O28,NA()) -> #N/A | Q28: =IF(O28<0,O28,NA()) -> -161.8
A49: Figure 2 · The import-dependency map — native scatter over the Risk map sheet columns D:E; per-point details are in that sheet's table
A84: Figure 3 · Import content of final demand, top 12 industries — native chart over Figures!U5:V16 (live formulas over the Multipliers sheet)

Sheet Methodology
A1: Methodology & derivations — how every number in this workbook is computed
A2: 1 · The accounting identity | B2: An input–output table reads each industry twice: each ROW is an industry as a seller, each COLUMN the same industry as a buyer. Reading a column down gives the industry's input recipe. Every euro of output is bought either as another industry's intermediate input or as final demand: x = A·x + f (output = intermediate demand + final demand). In this workbook the identity is checked per industry on the IO model sheet: column-based output (everything industry j buys, incl. value added — Z total column sums) against row-based output (everything EU industry i sells: its DOMESTIC deliveries to EU intermediate use and final demand — Z domestic rows, because the Z total rows additionally contain imported supply of the same products — plus extra-EU exports). The residual column should stay near zero (rounding and the FIGARO balancing item only) — if an edit breaks it, the edit broke the balance.
A3: 2 · Technical coefficients (A domestic) | B3: a_ij = Z_domestic(i,j) / x_j — the euros of DOMESTIC (intra-EU) product i needed per euro of output of industry j. Sheet "A domestic", each cell an explicit division of the Z domestic sheet by output on the IO model sheet (e.g. cell C3 = 'Z domestic'!C3 / 'IO model'!$D$4). The import coefficients m_ij = Z_imported(i,j) / x_j are the same construction on sheet "A import" — the extra-EU input recipe.
A4: 3 · Leontief inverse | B4: Solving x = A·x + f for output gives x = (I − A)⁻¹ · f. The matrix L = (I − A_domestic)⁻¹ (sheet "Leontief inverse", one MINVERSE array formula over the "I minus A" sheet) converts a bill of final demand into the TOTAL output every industry must produce — direct plus indirect: one euro of car demand pulls in steel, the steel pulls in iron ore and electricity, and so on; L sums the whole regress (I + A + A² + …). Column sums of L are the output multipliers on the Multipliers sheet.
A5: 4 · Import requirements | B5: M = A_import · L (sheet "Import requirements", one MMULT array formula): cell (i,j) is the euros of extra-EU imports of product i required — directly and through all domestic supply chains — per euro of final demand for industry j's output. Column sums are the IMPORT CONTENT of final demand (Multipliers sheet): what one euro spent on industry j's output pulls in from outside the EU.
A6: 5 · Value-added content and the model check | B6: v_j = (all six value-added and adjustment rows) / x_j on the IO model sheet. The value-added content of final demand is v′·L (SUMPRODUCT of the v vector with each L column). Accounting identity: import content + value-added content = 1 exactly (every euro of final demand is ultimately either extra-EU imports or EU value added, taxes included). The Multipliers sheet carries the check column; the Dashboard surfaces its worst deviation.
A7: 6 · Imports embodied in exports | B7: Applying the same requirements to extra-EU exports e (IO model sheet, from the FIGARO inter-country accounts): imports embodied in industry j's exports = import content_j × e_j; the output needed economy-wide to produce the EU's exports is L·e (an MMULT column on the Multipliers sheet). This is the workbook's own derivation of what Eurostat publishes as "foreign value added in exports".
A8: 7 · Cross-check vs the published FVA | B8: The Multipliers sheet compares the model's import content of exports with the PUBLISHED FIGARO foreign-value-added shares (naio_10_fgfoee, on the Foreign value added sheet). The two are close but conceptually distinct and are NOT expected to be identical: import content counts gross imported inputs (which contain the partner's own imported inputs, and re-imported EU value), while FVA counts only foreign value added, computed by Eurostat from the full 46-country inter-country model rather than this condensed EU-vs-rest account. Differences of a few percentage points are the method, not an error. OECD TiVA offers an independent series for level checks.
A9: 8 · Enterprise vs product attribution | B9: "Imports of division X" is not one number. The Trade backbone (ext_tec01) books trade to the NACE code of the trading ENTERPRISE; the IO layer follows the PRODUCT. C19 is the worked example: refiners import ~€218 bn of crude (enterprise view, backbone sheet), but crude is a MINING product, so the product view (FIGARO partners sheet) shows only ~€62 bn of refined-product imports — and the crude reappears on the model sheets as imported intermediate input INTO refining (row B of the Z imported column for C19). All three lenses are kept, each labelled; each answers a different question: who imports (enterprise), what crosses the border (product), what does an industry depend on (input–output).
A10: 9 · Grouped industries | B10: FIGARO and the use table publish some divisions only as groups: C10-12 (food, beverages & tobacco), C13-15 (textiles, apparel & leather), C31_32 (furniture & other manufacturing). Those divisions inherit group-level figures. Known within-group skews: C14: Within C13–C15, finished-apparel imports are far more concentrated in China, Bangladesh, Türkiye and India than the group average. | C31: Within C31–C32, furniture imports are strongly China-weighted; C32 (medical devices, instruments) leans US/CH.
A11: 10 · Curated-layer definitions | B11: Import reliance (critical materials, risk map x-axis): IR = (imports − exports) / (domestic production + imports − exports) — the EC criticality methodology; it nets out re-exports, so it differs from customs shares. Supplier concentration (y-axis): the largest single supplier's share of EU supply — a first-moment proxy for the HHI; it understates concentration when suppliers two and three are also non-diversified and says nothing about substitutability, stocks or recyclability. Product-dependency shares are customs-based ("largest supplier's share of extra-EU imports") unless the Share basis column says otherwise. All curated figures are quoted "as reported by <source>" and must not be arithmetically combined with the statistical layers.
A12: 11 · Known limits | B12: Modelled statistics: FIGARO balances supply and use across countries and can differ from raw customs data (CIF/FOB, re-exports, balancing). Proportionality: every euro of an industry's output is assumed to use the same input recipe (no scale effects, no substitution). Current prices: year-on-year changes mix price and volume. Named partners: FIGARO names 23 partner areas — Taiwan is inside "Rest of the world", so the semiconductor dependency is invisible in the named-partner shares and appears only in the curated layer. The Section C aggregate of ext_tec01 does not equal the sum of its 24 divisions (non-allocable trade; both are shown on the Trade backbone sheet).
A13: 12 · Where every derivation lives | B13: Z total C3 = SUM of the 24 origin rows of 'FIGARO raw 2023' for that product row × use column; Z domestic C3 = the EU27 origin row; Z imported C3 = SUM of the 23 partner rows (fixed 24-row stride per product row). IO model: x_j = SUM of Z total column j (rows 3–72); exports = SUM of the industry's row in both 2023 blocks of 'FIGARO exports raw'; residual check per industry. A domestic C3 = 'Z domestic'!C3/'IO model'!$D$4 (and so on cell by cell). A import C3 = 'Z imported'!C3/'IO model'!$D$4. I minus A C3 = 1−'A domestic'!C3 on the diagonal, else −'A domestic'!C3. Leontief inverse: {=MINVERSE('I minus A'!C3:BN66)}. Import requirements: {=MMULT('A import'!C3:BN66,'Leontief inverse'!C3:BN66)}. Multipliers: output multiplier = SUM(L column); import content = SUM(Import requirements column); VA content = SUMPRODUCT(v vector, L column); check = import + VA content − 1; embodied imports = import content × exports; output for exports = {=MMULT(L, exports)}. Dashboard: INDEX/MATCH on the backbone and published sheets; COUNTIF/SUMPRODUCT over the curated registers; LARGE/INDEX/MATCH for the top-10 tables.

Sheet Method figure
A1: The method, as one picture — read with the Methodology and Concepts sheets. Every box names the workbook sheet that holds that step as live formulas.
A3: Method figure · From the FIGARO table to every derived number

Sheet Concepts
A1: Term | B1: Plain-language explanation | C1: Where it lives in this workbook
A2: Input–output (IO) table | B2: A grid of the whole economy. Each ROW is an industry as a seller (who buys its product); each COLUMN is the same industry as a buyer (what it must purchase to produce). Reading a column down gives that industry's complete shopping list — its "recipe". Invented by Wassily Leontief in the 1930s (Nobel Prize 1973); today every EU national accounts system publishes one. | C2: Z total / Z domestic / Z imported
A3: Use table (at basic prices) | B3: The half of the IO framework used here: what each industry USES as inputs, valued at the prices producers actually receive (basic prices — before trade margins, transport margins and product taxes are stacked on top). Its counterpart, the supply table, records who makes what; Eurostat balances the two before publication. | C3: Z sheets; the published mixes on "Imported inputs"
A4: Intermediate consumption / intermediate demand | B4: Goods and services bought by one industry and USED UP making something else — crude oil into a refinery, steel into a car, electricity into a smelter. This is what the Z matrix contains. It is the opposite of final demand: intermediate purchases stay inside the production system. | C4: Z sheets; "IO model" columns E and K
A5: Final demand (f) | B5: Where output leaves the production system for good: household consumption, government consumption, non-profit consumption, investment (gross fixed capital formation) and inventory changes. In this EU-27 account, extra-EU exports are a sixth destination, held in their own column on the IO model sheet. | C5: Z sheets, last 5 columns; exports on "IO model" col M
A6: Gross output (x) | B6: Everything an industry produces in a year, in euros. Two ways to count it must agree: everything the industry PAYS FOR (all inputs + all value added — the column sum) and everything it SELLS (intermediate deliveries + final demand + exports — the row sum). The IO model sheet computes both and shows the residual; if an edit makes them disagree, the edit broke the accounting. | C6: "IO model" cols D and N, residual col O
A7: Value added (v) | B7: What is left of an industry's revenue after paying for inputs: wages (compensation of employees, D1), profits (gross operating surplus, B2A3G) and production taxes net of subsidies. Value added is what GDP sums. In the FIGARO account it occupies six extra rows under the 64 industry rows. | C7: "Z domestic" rows 67–72; "IO model" cols F–I
A8: Technical coefficient (a_ij) | B8: The recipe per euro: how many cents of product i industry j needs to produce one euro of its own output. Computed by dividing every cell of the domestic Z matrix by the buying industry's output. The full 64×64 grid of these is the A matrix — the economy's complete recipe book. | C8: "A domestic" (every cell a live division)
A9: Import coefficient (m_ij) | B9: The same recipe, but counting only inputs bought from OUTSIDE the EU: cents of imported product i per euro of industry j's output. Together, domestic coefficients + import coefficients + value added per euro sum to exactly 1 for every industry — every euro of output is fully accounted for. | C9: "A import"
A10: Leontief inverse (L = (I − A)⁻¹) | B10: THE central object of IO modelling. A alone only gives the DIRECT inputs. But the steel in a car needed iron ore; the ore needed mining machinery; the machinery needed steel again — an infinite ripple (I + A + A² + A³ + …). The Leontief inverse sums that entire infinite chain in one matrix operation: cell (i,j) says how much TOTAL output of industry i is needed, directly and indirectly, per euro of final demand for industry j. In this workbook it is one live MINVERSE formula, so it re-solves itself whenever A changes. ("Leontief reserve" is a common mishearing — the term is Leontief INVERSE, after Wassily Leontief.) | C10: "Leontief inverse" (one MINVERSE array formula)
A11: Output multiplier | B11: The column sum of the Leontief inverse: total euros of economy-wide output triggered by one euro of final demand for an industry's product. A multiplier of 1.6 means one euro of car demand generates €1.60 of production across the whole EU economy — the car itself plus €0.60 of upstream deliveries. | C11: "Multipliers" col D; top-10 on the Dashboard
A12: Import content of final demand | B12: The column sum of the import-requirements matrix M = A_import · L: cents of every euro of final demand that end up as extra-EU imports, counting both direct imports and imports hidden deep in the domestic supply chain. Refined petroleum is the extreme case — most of a euro spent on it leaks abroad as crude. | C12: "Import requirements", "Multipliers" col E
... A24: CBAM / CRMA | B24: The policy front lines this module feeds: the Carbon Border Adjustment Mechanism (imports of cement, steel, aluminium, fertilisers, electricity, hydrogen pay a carbon price at the border) and the Critical Raw Materials Act, Reg. (EU) 2024/1252 (34 critical materials, 17 of them strategic, with 2030 extraction/processing/recycling benchmarks). The dependency registers use the CRMA's legal Annex I/II designations, not editorial ratings. | C24: "Critical materials", "Strategic dependencies"

Sheet FIGARO raw 2023
A1: FIGARO raw dataset — 2023, € million (naio_10_fcp_ii4, condensed to EU-27 as one economy; extract of 2026-07-07). One row per product row × origin, the 24 origins contiguous per product row: origin EU27 is intra-EU supply (and carries the six value-added rows); every other origin is that partner's exports into EU-27 use. Zero cells are left blank. The Z sheets derive from THIS sheet by formula (fixed 24-row stride) — edit a cell here and the whole model recalculates.
A2: Row code | B2: Row label | C2: Origin | D2: A01 | E2: A02 | F2: A03 | G2: B | H2: C10-12 | I2: C13-15 | J2: C16 | K2: C17 | L2: C18 | M2: C19 | N2: C20 | O2: C21 | P2: C22 | Q2: C23 | R2: C24 | S2: C25 | T2: C26 | U2: C27 | V2: C28 | W2: C29 | X2: C30 | Y2: C31_32 | Z2: C33 | AA2: D35 | AB2: E36 | AC2: E37-39 | AD2: F | AE2: G45 | AF2: G46 | AG2: G47 | AH2: H49 | AI2: H50 | AJ2: H51 | AK2: H52 | AL2: H53 | AM2: I | AN2: J58 | AO2: J59_60 | AP2: J61 | AQ2: J62_63 | AR2: K64 | AS2: K65 | AT2: K66 | AU2: L | AV2: M69_70 | AW2: M71 | AX2: M72 | AY2: M73 | AZ2: M74_75 | BA2: N77 | BB2: N78 | BC2: N79 | BD2: N80-82 | BE2: O84 | BF2: P85 | BG2: Q86 | BH2: Q87_88 | BI2: R90-92 | BJ2: R93 | BK2: S94 | BL2: S95 | BM2: S96 | BN2: T | BO2: U | BP2: P3_S13 | BQ2: P3_S14 | BR2: P3_S15 | BS2: P51G | BT2: P5M
D3: Crop and animal production, hunting and related service activities | E3: Forestry and logging | F3: Fishing and aquaculture | G3: Mining and quarrying | H3: Manufacture of food products | I3: Manufacture of textiles, wearing apparel, leather and related products | J3: Manufacture of wood and of products of wood and cork, except furniture | K3: Manufacture of paper and paper products | L3: Printing and reproduction of recorded media | M3: Manufacture of coke and refined petroleum products | N3: Manufacture of chemicals and chemical products | O3: Manufacture of basic pharmaceutical products and pharmaceutical prepa… | P3: Manufacture of rubber and plastic products | Q3: Manufacture of other non-metallic mineral products | R3: Manufacture of basic metals | S3: Manufacture of fabricated metal products, except machinery and equipm… | T3: Manufacture of computer, electronic and optical products | U3: Manufacture of electrical equipment | V3: Manufacture of machinery and equipment n.e.c. | W3: Manufacture of motor vehicles, trailers and semi-trailers | X3: Manufacture of other transport equipment | Y3: Manufacture of furniture | Z3: Repair and installation of machinery and equipment | AA3: Electricity, gas, steam and air conditioning supply | AB3: Water collection, treatment and supply | AC3: Sewerage, waste management, remediation activities | AD3: Construction | AE3: Wholesale and retail trade and repair of motor vehicles and motorcycl… | AF3: Wholesale trade, except of motor vehicles and motorcycles | AG3: Retail trade, except of motor vehicles and motorcycles | AH3: Land transport and transport via pipelines | AI3: Water transport | AJ3: Air transport | AK3: Warehousing and support activities for transportation | AL3: Postal and courier activities | AM3: Accommodation and food service activities | AN3: Publishing activities | AO3: Motion picture, video, television programme production | AP3: Telecommunications | AQ3: Computer programming, consultancy, and information service activities | AR3: Financial service activities, except insurance and pension funding | AS3: Insurance, reinsurance and pension funding, except compulsory social … | AT3: Activities auxiliary to financial services and insurance activities | AU3: Real estate activities | AV3: Legal and accounting activities | AW3: Architectural and engineering activities | AX3: Scientific research and development | AY3: Advertising and market research | AZ3: Other professional, scientific and technical activities | BA3: Rental and leasing activities | BB3: Employment activities | BC3: Travel agency, tour operator reservation service and related activiti… | BD3: Security and investigation, service and landscape, office administrat… | BE3: Public administration and defence | BF3: Education | BG3: Human health activities | BH3: Residential care activities and social work activities without accomm… | BI3: Creative, arts and entertainment activities | BJ3: Sports activities and amusement and recreation activities | BK3: Activities of membership organisations | BL3: Repair of computers and personal and household goods | BM3: Other personal service activities | BN3: Activities of households as employers | BO3: Activities of extraterritorial organisations and bodies | BP3: Government consumption | BQ3: Household consumption | BR3: NPISH consumption | BS3: Gross fixed capital formation | BT3: Changes in inventories & valuables
A4: A01 | B4: Crop and animal production, hunting and related service activities | C4: EU27 | D4: 67150.7 | E4: 614.2 | F4: 95.6 | G4: 86 | H4: 253682.6 | I4: 2698.5 | J4: 390.8 | K4: 262.2 | L4: 24.9 | M4: 120.2 | N4: 2182.4 | O4: 503.7 | P4: 1483 | Q4: 149.3 | R4: 212.6 | S4: 199.2 | T4: 184.8 | U4: 118.3 | V4: 250.5 | W4: 306.8 | X4: 97.9 | Y4: 250 | Z4: 77.4 | AA4: 1620.4 | AB4: 48.2 | AC4: 152 | AD4: 1405.8 | AE4: 130.6 | AF4: 7522.9 | AG4: 3588.9 | AH4: 354.6 | AI4: 115.1 | AJ4: 112.1 | AK4: 374.9 | AL4: 28.2 | AM4: 15037.7 | AN4: 46.8 | AO4: 89.2 | AP4: 96.6 | AQ4: 237.5 | AR4: 62.2 | AS4: 58.3 | AT4: 42.8 | AU4: 428.7 | AV4: 325.7 | AW4: 220.3 | AX4: 260.1 | AY4: 55 | AZ4: 151.3 | BA4: 115.6 | BB4: 54.1 | BC4: 102.1 | BD4: 3732.3 | BE4: 1535.3 | BF4: 749.5 | BG4: 1154 | BH4: 863.1 | BI4: 272.1 | BJ4: 343.6 | BK4: 149.3 | BL4: 11.9 | BM4: 188.8 | BP4: 1987.4 | BQ4: 143744.9 | BR4: 54.7 | BS4: 9052.5 | BT4: 5093.2
A5: A01 | B5: Crop and animal production, hunting and related service activities | C5: NO | D5: 1.7 | E5: 6.6 | H5: 9.3 | J5: 19.3 | K5: 5.7 | N5: 0.3 | O5: 0.4 | P5: 0.2 | S5: 0.1 | Y5: 0.8 | AA5: 0.2 | AD5: 0.5 | AF5: 0.1 | AM5: 0.7 | BD5: 0.2 | BE5: 0.1 | BG5: 0.2 | BH5: 0.1 | BM5: 0.1 | BP5: 0.2 | BQ5: 14.1 | BS5: 0.1 | BT5: 0.5
A6: A01 | B6: Crop and animal production, hunting and related service activities | C6: CH | D6: 16.2 | E6: 0.3 | F6: 0.1 | G6: 0.1 | H6: 97.4 | I6: 1.6 | J6: 0.2 | K6: 0.2 | L6: 0.1 | M6: 0.3 | N6: 1.8 | O6: 0.8 | P6: 3.4 | Q6: 0.3 | R6: 0.3 | S6: 0.3 | T6: 0.3 | U6: 0.3 | V6: 0.4 | W6: 0.4 | X6: 0.2 | Y6: 0.4 | Z6: 0.2 | AA6: 0.7 | AB6: 0.1 | AC6: 0.2 | AD6: 0.5 | AE6: 0.2 | AF6: 1.8 | AG6: 0.7 | AH6: 0.2 | AI6: 0.3 | AJ6: 0.2 | AK6: 0.2 | AL6: 0.1 | AM6: 5.8 | AN6: 0.2 | AO6: 0.3 | AP6: 0.2 | AQ6: 0.4 | AR6: 0.1 | AS6: 0.1 | AT6: 0.1 | AU6: 0.1 | AV6: 0.2 | AW6: 0.2 | AX6: 0.2 | AY6: 0.2 | AZ6: 0.2 | BA6: 0.2 | BB6: 0.1 | BC6: 0.2 | BD6: 1.1 | BE6: 0.6 | BF6: 0.4 | BG6: 0.7 | BH6: 0.6 | BI6: 0.3 | BJ6: 0.2 | BK6: 0.1 | BL6: 0.1 | BM6: 0.2 | BP6: 0.7 | BQ6: 79.2 | BS6: 2.3 | BT6: 5.4
A7: A01 | B7: Crop and animal production, hunting and related service activities | C7: UK | D7: 166.7 | E7: 0.7 | G7: 0.1 | H7: 982.3 | I7: 4.9 | J7: 0.2 | K7: 0.6 | L7: 0.1 | M7: 0.8 | N7: 14.2 | O7: 14.9 | P7: 7 | Q7: 0.4 | R7: 0.7 | S7: 0.7 | T7: 1.2 | U7: 0.6 | V7: 1.2 | W7: 1.5 | X7: 0.4 | Y7: 1 | Z7: 0.3 | AA7: 2 | AB7: 0.1 | AC7: 0.6 | AD7: 4.1 | AE7: 0.5 | AF7: 28.7 | AG7: 2.2 | AH7: 1 | AI7: 0.5 | AJ7: 0.6 | AK7: 1.1 | AL7: 0.2 | AM7: 24.3 | AN7: 1.1 | AO7: 0.7 | AP7: 0.7 | AQ7: 7 | AR7: 0.7 | AS7: 0.5 | AT7: 0.8 | AU7: 0.7 | AV7: 4.7 | AW7: 1.5 | AX7: 0.6 | AY7: 0.5 | AZ7: 0.5 | BA7: 1.1 | BB7: 0.2 | BC7: 0.7 | BD7: 6.2 | BE7: 2.7 | BF7: 1.4 | BG7: 7.8 | BH7: 4.1 | BI7: 0.7 | BJ7: 0.5 | BK7: 0.3 | BM7: 0.4 | BP7: 54 | BQ7: 562.4 | BS7: 28.6 | BT7: 34
A8: A01 | B8: Crop and animal production, hunting and related service activities | C8: ME | D8: 1 | H8: 6.2 | I8: 0.1 | J8: 0.3 | N8: 0.2 | P8: 0.1 | AF8: 0.3 | AM8: 0.6 | BD8: 0.1 | BE8: 0.1 | BG8: 0.1 | BH8: 0.1 | BP8: 0.1 | BQ8: 10.3 | BS8: 0.1 | BT8: 0.4
A9: A01 | B9: Crop and animal production, hunting and related service activities | C9: MK | D9: 28.7 | E9: 0.1 | H9: 65.6 | I9: 0.7 | N9: 1.5 | O9: 0.2 | P9: 1.5 | Q9: 0.1 | AA9: 0.8 | AD9: 0.5 | AF9: 2.3 | AG9: 0.3 | AH9: 0.1 | AI9: 0.1 | AM9: 4.2 | BA9: 0.1 | BD9: 0.6 | BE9: 0.4 | BF9: 0.2 | BG9: 0.6 | BH9: 0.3 | BI9: 0.1 | BP9: 0.5 | BQ9: 94.8 | BS9: 1.3 | BT9: 2.2
A10: A01 | B10: Crop and animal production, hunting and related service activities | C10: AL | D10: 8.2 | E10: 0.1 | F10: 0.1 | H10: 44.1 | I10: 1.1 | K10: 0.1 | M10: 0.1 | N10: 1.6 | O10: 0.5 | P10: 0.5 | Y10: 0.1 | AA10: 0.3 | AD10: 0.1 | AF10: 1.3 | AG10: 0.2 | AH10: 0.1 | AI10: 0.1 | AM10: 3.5 | BC10: 0.1 | BD10: 0.2 | BE10: 0.2 | BF10: 0.1 | BG10: 0.3 | BH10: 0.2 | BJ10: 0.1 | BP10: 0.4 | BQ10: 57.4 | BS10: 0.9 | BT10: 0.9
A11: A01 | B11: Crop and animal production, hunting and related service activities | C11: RS | D11: 60.9 | E11: 0.3 | H11: 379.1 | I11: 10.5 | J11: 0.2 | K11: 0.3 | M11: 0.1 | N11: 5.2 | O11: 1.2 | P11: 8.2 | Q11: 0.1 | R11: 0.1 | S11: 0.2 | T11: 0.2 | U11: 0.2 | V11: 0.3 | W11: 0.2 | Y11: 0.7 | AA11: 0.7 | AC11: 0.2 | AD11: 0.3 | AE11: 0.1 | AF11: 6.5 | AG11: 0.8 | AH11: 0.1 | AI11: 0.1 | AK11: 0.1 | AM11: 6.4 | AN11: 0.1 | AP11: 0.1 | AQ11: 0.8 | AU11: 0.1 | AV11: 0.3 | AX11: 0.1 | AY11: 0.1 | AZ11: 0.1 | BD11: 1.8 | BE11: 1 | BF11: 0.4 | BG11: 0.8 | BH11: 0.7 | BI11: 0.2 | BK11: 0.1 | BM11: 0.1 | BP11: 2.2 | BQ11: 254.4 | BS11: 6.7 | BT11: 12.9
A12: A01 | B12: Crop and animal production, hunting and related service activities | C12: TR | D12: 106 | E12: 0.6 | F12: 0.2 | H12: 409.8 | I12: 8.4 | J12: 0.1 | K12: 0.3 | M12: 0.2 | N12: 8.2 | O12: 1.6 | P12: 6.8 | Q12: 0.1 | U12: 0.1 | V12: 0.1 | Y12: 0.5 | AA12: 3.3 | AC12: 0.2 | AD12: 0.5 | AF12: 8.4 | AG12: 1.6 | AH12: 0.4 | AI12: 0.4 | AK12: 0.1 | AM12: 21.6 | AO12: 0.1 | AQ12: 0.1 | AU12: 0.2 | AV12: 0.2 | AX12: 0.2 | AY12: 0.1 | AZ12: 0.1 | BA12: 0.1 | BD12: 2.4 | BE12: 2.3 | BF12: 1.1 | BG12: 3.5 | BH12: 2 | BI12: 0.2 | BJ12: 0.3 | BK12: 0.2 | BM12: 0.2 | BP12: 0.8 | BQ12: 518.4 | BS12: 8.8 | BT12: 15.3
A13: A01 | B13: Crop and animal production, hunting and related service activities | C13: RU | D13: 35.4 | E13: 0.2 | H13: 207 | I13: 3.9 | J13: 0.1 | K13: 0.2 | M13: 1.3 | N13: 5.9 | O13: 0.7 | P13: 3.3 | Q13: 0.1 | R13: 0.5 | S13: 0.2 | T13: 0.1 | U13: 0.1 | V13: 0.2 | W13: 0.2 | Y13: 0.4 | AA13: 2.2 | AC13: 0.2 | AD13: 0.4 | AE13: 0.1 | AF13: 2.4 | AG13: 0.6 | AH13: 0.4 | AI13: 0.3 | AJ13: 0.1 | AK13: 0.5 | AM13: 5.8 | AN13: 0.1 | AP13: 0.1 | AQ13: 0.3 | AR13: 0.1 | AU13: 0.1 | AV13: 0.2 | AX13: 0.1 | AY13: 0.1 | BA13: 0.1 | BD13: 0.7 | BE13: 0.6 | BF13: 0.4 | BG13: 0.8 | BH13: 0.4 | BI13: 0.1 | BJ13: 0.1 | BK13: 0.1 | BM13: 0.1 | BP13: 0.1 | BQ13: 184.9 | BS13: 4.8 | BT13: 2.8
A14: A01 | B14: Crop and animal production, hunting and related service activities | C14: ZA | D14: 53.1 | E14: 0.9 | H14: 435.2 | I14: 5.9 | J14: 0.2 | K14: 0.3 | M14: 0.1 | N14: 11.8 | O14: 1.5 | P14: 6.6 | Q14: 0.2 | S14: 0.1 | T14: 0.1 | U14: 0.1 | V14: 0.2 | W14: 0.4 | Y14: 0.5 | AA14: 1.3 | AC14: 0.2 | AD14: 0.4 | AE14: 0.1 | AF14: 2.7 | AG14: 0.7 | AH14: 0.2 | AI14: 0.4 | AJ14: 0.1 | AK14: 0.1 | AM14: 20.5 | AO14: 0.2 | AP14: 0.1 | AQ14: 0.4 | AU14: 0.1 | AV14: 0.2 | AW14: 0.1 | AX14: 0.1 | AY14: 0.1 | AZ14: 0.1 | BA14: 0.2 | BC14: 0.6 | BD14: 3.7 | BE14: 3.2 | BF14: 0.8 | BG14: 2.6 | BH14: 2.3 | BI14: 0.4 | BJ14: 0.4 | BK14: 0.2 | BM14: 0.3 | BP14: 1.4 | BQ14: 325.9 | BS14: 7.6 | BT14: 8.8
A15: A01 | B15: Crop and animal production, hunting and related service activities | C15: CA | D15: 75.6 | E15: 0.4 | F15: 0.1 | H15: 575 | I15: 14.9 | J15: 0.3 | K15: 0.7 | L15: 0.1 | M15: 2.2 | N15: 14.1 | O15: 4 | P15: 10.5 | Q15: 0.3 | R15: 1 | S15: 0.3 | T15: 0.2 | U15: 0.2 | V15: 0.3 | W15: 0.5 | X15: 0.3 | Y15: 1 | Z15: 0.1 | AA15: 1.1 | AC15: 0.3 | AD15: 0.9 | AE15: 0.1 | AF15: 7.4 | AG15: 0.6 | AH15: 0.7 | AI15: 0.1 | AK15: 0.5 | AM15: 12.2 | AN15: 0.1 | AO15: 0.1 | AQ15: 0.2 | AU15: 0.1 | AV15: 0.3 | AW15: 0.1 | AX15: 0.2 | AY15: 0.1 | AZ15: 0.1 | BA15: 0.1 | BD15: 1.5 | BE15: 1.1 | BF15: 0.7 | BG15: 2.3 | BH15: 1.3 | BI15: 0.1 | BJ15: 0.1 | BK15: 0.1 | BM15: 0.2 | BP15: 8.7 | BQ15: 316.7 | BS15: 12.3 | BT15: 19.6
A16: A01 | B16: Crop and animal production, hunting and related service activities | C16: US | D16: 231 | E16: 3.7 | F16: 3.1 | H16: 2541.1 | I16: 28.3 | J16: 3.8 | K16: 1.7 | N16: 32.9 | O16: 5.4 | P16: 28.5 | Q16: 0.1 | S16: 0.1 | W16: 0.2 | Y16: 1.8 | AA16: 2.1 | AC16: 0.6 | AD16: 1 | AF16: 11.2 | AG16: 1.5 | AH16: 0.2 | AI16: 2 | AJ16: 0.1 | AK16: 0.2 | AM16: 73.8 | AO16: 0.4 | AR16: 0.1 | AU16: 0.2 | AV16: 0.5 | AX16: 0.4 | AY16: 0.1 | AZ16: 0.3 | BC16: 0.3 | BD16: 17.2 | BE16: 15.5 | BF16: 3.3 | BG16: 11.2 | BH16: 9.6 | BI16: 1.8 | BJ16: 0.3 | BK16: 0.7 | BM16: 1.1 | BP16: 8.9 | BQ16: 1735 | BS16: 53.2 | BT16: 88.9
A17: A01 | B17: Crop and animal production, hunting and related service activities | C17: MX | D17: 17.5 | E17: 0.2 | H17: 148.9 | I17: 1 | K17: 0.1 | M17: 0.1 | N17: 1.2 | O17: 0.2 | P17: 1.1 | Y17: 0.1 | AA17: 0.3 | AD17: 0.2 | AF17: 0.5 | AG17: 0.2 | AI17: 0.1 | AM17: 3.9 | BD17: 1 | BE17: 0.7 | BF17: 0.3 | BG17: 0.7 | BH17: 0.5 | BI17: 0.1 | BJ17: 0.1 | BM17: 0.1 | BP17: 0.2 | BQ17: 124.1 | BS17: 4.6 | BT17: 6.8
A18: A01 | B18: Crop and animal production, hunting and related service activities | C18: AR | D18: 19.4 | E18: 0.1 | H18: 136.3 | I18: 2.3 | K18: 0.1 | N18: 2.3 | O18: 0.4 | P18: 2.2 | Y18: 0.1 | AA18: 0.6 | AD18: 0.1 | AF18: 0.8 | AG18: 0.2 | AM18: 3.2 | BD18: 0.6 | BE18: 0.5 | BF18: 0.2 | BG18: 0.4 | BH18: 0.3 | BP18: 0.4 | BQ18: 104.6 | BS18: 4 | BT18: 5.7
A19: A01 | B19: Crop and animal production, hunting and related service activities | C19: BR | D19: 194.2 | E19: 1.9 | H19: 1687.8 | I19: 29.3 | J19: 13.6 | K19: 17.6 | M19: 4.2 | N19: 30.6 | O19: 3.5 | P19: 21.5 | Q19: 0.2 | R19: 0.5 | S19: 0.1 | V19: 0.1 | W19: 0.3 | Y19: 2 | Z19: 0.1 | AA19: 2.8 | AC19: 0.6 | AD19: 2.4 | AF19: 7.5 | AG19: 1.5 | AH19: 0.3 | AI19: 0.7 | AJ19: 0.1 | AK19: 0.2 | AM19: 43.4 | AO19: 0.1 | AQ19: 0.1 | AU19: 0.3 | AV19: 0.5 | AW19: 0.1 | AX19: 0.3 | AY19: 0.2 | AZ19: 0.2 | BC19: 0.1 | BD19: 8.1 | BE19: 6.2 | BF19: 2.6 | BG19: 6.2 | BH19: 5 | BI19: 0.6 | BJ19: 0.5 | BK19: 0.3 | BM19: 0.6 | BP19: 2.3 | BQ19: 1118 | BS19: 41.1 | BT19: 61.4
A20: A01 | B20: Crop and animal production, hunting and related service activities | C20: CN | D20: 70.5 | E20: 0.6 | H20: 575.6 | I20: 10.7 | J20: 0.1 | K20: 0.3 | N20: 5 | O20: 1.7 | P20: 8.3 | Q20: 0.1 | Y20: 0.7 | AA20: 1.7 | AC20: 0.2 | AD20: 0.2 | AF20: 3.6 | AG20: 0.6 | AH20: 0.1 | AI20: 0.2 | AK20: 0.1 | AM20: 12 | AU20: 0.1 | AV20: 0.2 | AX20: 0.1 | AZ20: 0.1 | BD20: 3.2 | BE20: 2.1 | BF20: 0.7 | BG20: 1.9 | BH20: 1.5 | BI20: 0.2 | BJ20: 0.1 | BK20: 0.1 | BM20: 0.2 | BP20: 1.7 | BQ20: 380.9 | BS20: 12.7 | BT20: 22
A21: A01 | B21: Crop and animal production, hunting and related service activities | C21: JP | D21: 1.2 | H21: 10.3 | I21: 0.1 | N21: 0.1 | P21: 0.1 | AF21: 0.1 | AM21: 0.5 | BD21: 0.1 | BG21: 0.1 | BH21: 0.1 | BP21: 0.1 | BQ21: 6.9 | BS21: 0.1 | BT21: 0.2
A22: A01 | B22: Crop and animal production, hunting and related service activities | C22: KR | D22: 0.8 | H22: 5.9 | N22: 0.1 | P22: 0.1 | AM22: 0.3 | BD22: 0.1 | BQ22: 4.7 | BS22: 0.1 | BT22: 0.2
A23: A01 | B23: Crop and animal production, hunting and related service activities | C23: IN | D23: 25.2 | E23: 0.3 | H23: 183.8 | I23: 3.2 | K23: 0.1 | N23: 1.9 | O23: 0.5 | P23: 3 | Y23: 0.2 | AA23: 0.6 | AD23: 0.1 | AF23: 1.2 | AG23: 0.3 | AI23: 0.1 | AM23: 5 | AX23: 0.1 | AY23: 0.1 | BD23: 1.3 | BE23: 1 | BF23: 0.3 | BG23: 0.7 | BH23: 0.6 | BI23: 0.1 | BJ23: 0.1 | BK23: 0.1 | BM23: 0.1 | BP23: 0.6 | BQ23: 138.1 | BS23: 3.2 | BT23: 7
A24: A01 | B24: Crop and animal production, hunting and related service activities | C24: ID | D24: 43.5 | E24: 0.3 | H24: 229.8 | I24: 3 | J24: 0.1 | K24: 0.1 | N24: 5.2 | O24: 0.5 | P24: 10.7 | Q24: 0.1 | Y24: 0.2 | AA24: 1.8 | AC24: 0.1 | AD24: 0.1 | AF24: 2.3 | AG24: 0.6 | AH24: 0.1 | AI24: 0.1 | AM24: 7.1 | AO24: 0.5 | AU24: 0.1 | AX24: 0.1 | BD24: 1.7 | BE24: 0.9 | BF24: 0.4 | BG24: 0.8 | BH24: 0.6 | BI24: 0.2 | BJ24: 0.1 | BK24: 0.1 | BM24: 0.1 | BP24: 0.1 | BQ24: 183.2 | BS24: 7.5 | BT24: 7.1
A25: A01 | B25: Crop and animal production, hunting and related service activities | C25: SA | D25: 0.2 | H25: 2.2 | AM25: 0.1 | BQ25: 1.8 | BT25: -0.3
A26: A01 | B26: Crop and animal production, hunting and related service activities | C26: AU | D26: 30.2 | E26: 0.4 | H26: 211.7 | I26: 2.1 | M26: 0.3 | N26: 1.8 | O26: 0.3 | P26: 1.6 | R26: 0.1 | Y26: 0.1 | AA26: 0.2 | AD26: 0.1 | AF26: 0.9 | AG26: 0.1 | AH26: 0.1 | AI26: 0.7 | AJ26: 0.1 | AK26: 0.2 | AM26: 6.2 | BD26: 1.8 | BE26: 1.8 | BF26: 0.2 | BG26: 0.9 | BH26: 0.8 | BI26: 0.2 | BK26: 0.1 | BM26: 0.1 | BP26: 0.1 | BQ26: 227.6 | BS26: 4.4 | BT26: 18.2
A27: A01 | B27: Crop and animal production, hunting and related service activities | C27: WRL_REST | D27: 2233.2 | E27: 18.1 | F27: 0.6 | G27: 0.6 | H27: 15073.7 | I27: 176.5 | J27: 3.5 | K27: 9.2 | L27: 0.3 | M27: 6.1 | N27: 195.8 | O27: 29.4 | P27: 203.1 | Q27: 2.5 | R27: 1.3 | S27: 1.6 | T27: 0.6 | U27: 1.5 | V27: 1.9 | W27: 3.1 | X27: 0.4 | Y27: 12.9 | Z27: 0.5 | AA27: 48.6 | AB27: 0.3 | AC27: 4.7 | AD27: 11.1 | AE27: 0.6 | AF27: 101.8 | AG27: 21.6 | AH27: 4 | AI27: 6.7 | AJ27: 0.8 | AK27: 2.7 | AL27: 0.1 | AM27: 415.9 | AN27: 0.3 | AO27: 1.6 | AP27: 0.2 | AQ27: 1 | AR27: 0.3 | AS27: 0.2 | AT27: 0.2 | AU27: 3.2 | AV27: 3.8 | AW27: 0.5 | AX27: 4.1 | AY27: 2.3 | AZ27: 2.2 | BA27: 0.8 | BB27: 0.4 | BC27: 1.8 | BD27: 101.3 | BE27: 61.1 | BF27: 22.4 | BG27: 58.4 | BH27: 47.1 | BI27: 7 | BJ27: 3.5 | BK27: 3.5 | BM27: 6.1 | BP27: 24.2 | BQ27: 12127.6 | BS27: 403.5 | BT27: 631.6
A28: A02 | B28: Forestry and logging | C28: EU27 | D28: 638.8 | E28: 15576.3 | F28: 38.5 | G28: 69.7 | H28: 526.2 | I28: 16.1 | J28: 16502.8 | K28: 6988.6 | L28: 9.9 | M28: 9.5 | N28: 269 | O28: 14.1 | P28: 75.2 | Q28: 34.2 | R28: 31.6 | S28: 32.8 | T28: 9.8 | U28: 17.5 | V28: 21.7 | W28: 47 | X28: 8.1 | Y28: 978.5 | Z28: 5.6 | AA28: 1218.5 | AB28: 5 | AC28: 20 | AD28: 731.7 | AE28: 13.2 | AF28: 273.8 | AG28: 49.2 | AH28: 57.1 | AI28: 2.1 | AJ28: 4.2 | AK28: 26.9 | AL28: 1.9 | AM28: 87.8 | AN28: 2.6 | AO28: 4.9 | AP28: 3.9 | AQ28: 14.4 | AR28: 5.2 | AS28: 1.2 | AT28: 2.1 | AU28: 41.2 | AV28: 14.1 | AW28: 46.6 | AX28: 11.1 | AY28: 4.7 | AZ28: 5.9 | BA28: 4 | BB28: 2.8 | BC28: 2.6 | BD28: 155.7 | BE28: 262.6 | BF28: 31.4 | BG28: 45 | BH28: 16 | BI28: 28.1 | BJ28: 21.4 | BK28: 16 | BL28: 7.4 | BM28: 21.6 | BP28: 1547.1 | BQ28: 11516.8 | BR28: 8.1 | BS28: 487.5 | BT28: 1141.6
A29: A02 | B29: Forestry and logging | C29: NO | D29: 0.4 | E29: 36.8 | H29: 1 | I29: 0.1 | J29: 107.5 | K29: 31.6 | N29: 1 | O29: 0.6 | P29: 0.2 | Q29: 0.1 | S29: 0.3 | Y29: 4.4 | AA29: 1 | AD29: 2.7 | AF29: 0.1 | AH29: 0.1 | AM29: 0.6 | AW29: 0.1 | BD29: 0.6 | BE29: 0.4 | BG29: 0.2 | BH29: 0.2 | BI29: 0.1 | BK29: 0.2 | BM29: 0.3 | BQ29: 27.2 | BT29: 0.7
A30: A02 | B30: Forestry and logging | C30: CH | D30: 0.4 | E30: 1.9 | H30: 2 | I30: 0.1 | J30: 32.1 | K30: 5.7 | N30: 1.8 | O30: 0.1 | P30: 0.2 | Q30: 0.1 | R30: 0.1 | S30: 0.1 | W30: 0.1 | Y30: 0.9 | AA30: 1.4 | AD30: 0.8 | AF30: 0.4 | AG30: 0.1 | AJ30: 0.1 | AM30: 0.3 | AQ30: 0.1 | AW30: 0.1 | BD30: 0.4 | BE30: 0.4 | BG30: 0.1 | BH30: 0.1 | BI30: 0.1 | BK30: 0.1 | BM30: 0.1 | BQ30: 19.2 | BT30: 1.7
A31: A02 | B31: Forestry and logging | C31: UK | D31: 0.9 | E31: 1.7 | H31: 0.5 | J31: 11.8 | K31: 2 | N31: 0.3 | O31: 0.2 | P31: 0.1 | S31: 0.1 | T31: 0.1 | V31: 0.1 | W31: 0.1 | Y31: 0.5 | AA31: 0.4 | AD31: 1.7 | AF31: 0.5 | AG31: 0.1 | AH31: 0.1 | AJ31: 0.3 | AM31: 0.1 | AN31: 0.1 | AQ31: 0.5 | AV31: 0.1 | BA31: 0.1 | BC31: 0.1 | BD31: 0.1 | BE31: 0.5 | BG31: 0.1 | BI31: 0.2 | BQ31: 6.7 | BS31: 0.2 | BT31: 0.7
A32: A02 | B32: Forestry and logging | C32: ME | H32: 0.1 | J32: 0.6 | Y32: 0.2 | AD32: 0.5 | BQ32: 0.2 | BS32: 0.1 | BT32: 0.1
A33: A02 | B33: Forestry and logging | C33: MK | E33: 0.1 | J33: 0.9 | K33: 0.1 | BE33: 0.1 | BI33: 0.1 | BQ33: 0.2 | BS33: 0.1
A34: A02 | B34: Forestry and logging | C34: AL | J34: 0.1
A35: A02 | B35: Forestry and logging | C35: RS | D35: 0.1 | E35: 0.5 | H35: 0.2 | J35: 3.5 | K35: 0.7 | N35: 0.1 | Y35: 0.2 | AA35: 0.2 | AD35: 0.1 | AF35: 0.1 | BE35: 0.1 | BQ35: 1.6 | BT35: 0.4
A36: A02 | B36: Forestry and logging | C36: TR | D36: 0.1 | E36: 0.2 | H36: 0.1 | J36: 1.7 | K36: 0.3 | Y36: 0.1 | AA36: 0.1 | AD36: 0.1 | BE36: 0.1 | BQ36: 1.2
A37: A02 | B37: Forestry and logging | C37: RU | D37: 0.2 | E37: 0.6 | H37: 0.8 | J37: 3.7 | K37: 0.8 | M37: 1 | N37: 0.2 | P37: 0.1 | R37: 0.2 | V37: 0.1 | W37: 0.1 | Y37: 0.2 | AA37: 0.7 | AD37: 0.4 | AF37: 0.2 | AG37: 0.1 | AJ37: 0.1 | AK37: 0.1 | AM37: 0.1 | AQ37: 0.1 | BE37: 0.2 | BI37: 0.1 | BQ37: 3.2 | BS37: 0.1 | BT37: 0.4
A38: A02 | B38: Forestry and logging | C38: ZA | E38: 0.2 | J38: 2 | K38: 0.2 | P38: 0.1 | AA38: 0.1 | BE38: 0.2 | BI38: 0.1 | BQ38: 0.5
A39: A02 | B39: Forestry and logging | C39: CA | D39: 8.4 | E39: 0.5 | H39: 63.4 | I39: 1.7 | J39: 5.4 | K39: 0.6 | N39: 1.1 | O39: 0.5 | P39: 1.2 | S39: 0.1 | T39: 0.1 | V39: 0.1 | W39: 0.1 | Y39: 0.3 | AA39: 0.1 | AD39: 0.7 | AF39: 1 | AG39: 0.1 | AJ39: 0.1 | AK39: 0.1 | AM39: 1.1 | AN39: 0.1 | AQ39: 0.4 | AV39: 0.2 | AX39: 0.1 | BA39: 0.1 | BD39: 0.4 | BE39: 0.8 | BF39: 0.1 | BG39: 0.2 | BH39: 0.2 | BI39: 0.4 | BP39: 1 | BQ39: 34.3 | BS39: 1.7 | BT39: 2.2
A40: A02 | B40: Forestry and logging | C40: US | D40: 3.4 | E40: 4.6 | H40: 1.9 | J40: 50.6 | K40: 10.9 | N40: 1.9 | O40: 0.4 | P40: 0.5 | Q40: 0.1 | S40: 0.2 | Y40: 2 | AA40: 1.4 | AD40: 6.2 | AF40: 0.3 | AG40: 0.1 | AH40: 0.1 | AJ40: 0.2 | AM40: 0.3 | AW40: 0.1 | BD40: 0.4 | BE40: 1.6 | BG40: 0.1 | BH40: 0.1 | BI40: 0.8 | BK40: 0.1 | BM40: 0.1 | BQ40: 22.7 | BT40: 4.8
A41: A02 | B41: Forestry and logging | C41: MX | E41: 0.6 | H41: 0.1 | J41: 9.1 | K41: 0.5 | P41: 0.3 | AD41: 0.1 | BE41: 1.3 | BI41: 0.8 | BQ41: 0.6
A42: A02 | B42: Forestry and logging | C42: AR | H42: 0.2 | J42: 0.2 | K42: 0.2 | BQ42: 0.2
A43: A02 | B43: Forestry and logging | C43: BR | D43: 0.4 | E43: 0.9 | H43: 1.8 | J43: 96.8 | K43: 120.8 | M43: 0.1 | N43: 25 | P43: 0.1 | Y43: 2.4 | AA43: 0.6 | AD43: 0.7 | AF43: 0.4 | AG43: 1.3 | AJ43: 0.1 | AM43: 0.2 | BD43: 0.1 | BE43: 0.3 | BI43: 0.1 | BQ43: 8.8 | BT43: 0.5
A44: A02 | B44: Forestry and logging | C44: CN | D44: 0.2 | E44: 1.5 | H44: 0.3 | J44: 7.6 | K44: 1.6 | N44: 0.2 | P44: 0.1 | Y44: 0.5 | AA44: 0.4 | AD44: 0.4 | AJ44: 0.1 | AM44: 0.1 | BD44: 0.1 | BE44: 0.3 | BI44: 0.1 | BQ44: 5.5 | BT44: 0.3
A45: A02 | B45: Forestry and logging | C45: JP | E45: 0.2 | H45: 0.1 | J45: 1.2 | K45: 0.2 | Y45: 0.1 | AD45: 0.1 | BE45: 0.1 | BQ45: 0.9 | BT45: -0.1
A46: A02 | B46: Forestry and logging | C46: KR | D46: 0.2 | E46: 1.4 | H46: 0.3 | J46: 6.5 | K46: 1.4 | N46: 0.2 | P46: 0.1 | Y46: 0.4 | AA46: 0.5 | AD46: 0.4 | AF46: 0.1 | AJ46: 0.3 | AM46: 0.1 | BD46: 0.1 | BE46: 0.2 | BI46: 0.1 | BQ46: 4.5 | BT46: 0.5
A47: A02 | B47: Forestry and logging | C47: IN | D47: 0.7 | E47: 3.1 | H47: 0.9 | J47: 21.9 | K47: 4 | N47: 0.7 | O47: 0.1 | P47: 0.2 | S47: 0.1 | Y47: 1.3 | AA47: 1 | AD47: 1.3 | AF47: 0.1 | AJ47: 0.3 | AM47: 0.2 | AW47: 0.1 | BD47: 0.3 | BE47: 0.9 | BG47: 0.1 | BH47: 0.1 | BI47: 0.4 | BK47: 0.1 | BM47: 0.1 | BQ47: 14.7 | BT47: 1.6
A48: A02 | B48: Forestry and logging | C48: ID | E48: 0.5 | H48: 0.1 | J48: 1.7 | K48: 0.4 | N48: 0.1 | Y48: 0.2 | AA48: 0.3 | AD48: 0.1 | BQ48: 1.4 | BT48: 0.1
A49: A02 | B49: Forestry and logging | C49: SA | BT49: -0.3
A50: A02 | B50: Forestry and logging | C50: AU | D50: 0.3 | E50: 0.5 | H50: 0.1 | J50: 4.2 | K50: 0.5 | N50: 0.1 | P50: 0.1 | Y50: 0.2 | AA50: 0.1 | AD50: 0.5 | BE50: 0.3 | BI50: 0.2 | BQ50: 1.6 | BT50: 0.4
A51: A02 | B51: Forestry and logging | C51: WRL_REST | D51: 3.2 | E51: 23.4 | G51: 0.1 | H51: 8 | I51: 0.1 | J51: 137.5 | K51: 29.7 | L51: 0.1 | M51: 0.1 | N51: 5.5 | O51: 0.6 | P51: 1.4 | Q51: 0.2 | R51: 0.2 | S51: 0.4 | V51: 0.1 | W51: 0.1 | Y51: 8.3 | AA51: 4.5 | AB51: 0.1 | AC51: 0.1 | AD51: 8 | AF51: 1.2 | AG51: 0.3 | AH51: 0.5 | AI51: 0.1 | AJ51: 1.5 | AK51: 0.1 | AM51: 1.2 | AQ51: 0.1 | AU51: 0.1 | AV51: 0.1 | AW51: 0.4 | AX51: 0.1 | BD51: 1.2 | BE51: 6.6 | BF51: 0.2 | BG51: 0.4 | BH51: 0.3 | BI51: 2.7 | BJ51: 0.2 | BK51: 0.4 | BM51: 0.4 | BQ51: 121.3 | BS51: 0.3 | BT51: 20.9
A52: A03 | B52: Fishing and aquaculture | C52: EU27 | D52: 34.8 | E52: 2.3 | F52: 467.6 | G52: 0.8 | H52: 3021.8 | I52: 6.1 | J52: 1.8 | K52: 1.4 | L52: 0.5 | M52: 1.9 | N52: 17.2 | O52: 8.3 | P52: 1.7 | Q52: 1.7 | R52: 1.2 | S52: 2.9 | T52: 1.1 | U52: 1.7 | V52: 2.2 | W52: 2.3 | X52: 0.8 | Y52: 4.9 | Z52: 1.5 | AA52: 24.1 | AB52: 0.4 | AC52: 2.4 | AD52: 40.4 | AE52: 1.2 | AF52: 33.6 | AG52: 8.6 | AH52: 3.6 | AI52: 6.9 | AJ52: 1 | AK52: 4.8 | AL52: 0.3 | AM52: 1753.8 | AN52: 0.5 | AO52: 3 | AP52: 1.9 | AQ52: 5.4 | AR52: 2.2 | AS52: 0.9 | AT52: 0.5 | AU52: 3.8 | AV52: 4.4 | AW52: 2.1 | AX52: 1.8 | AY52: 1 | AZ52: 2.3 | BA52: 4 | BB52: 0.3 | BC52: 0.6 | BD52: 5.7 | BE52: 18.3 | BF52: 9.4 | BG52: 40.5 | BH52: 35.8 | BI52: 6.7 | BJ52: 9.6 | BK52: 35.1 | BL52: 0.2 | BM52: 1.3 | BP52: 18.5 | BQ52: 8139.5 | BR52: 2.5 | BS52: 77.4 | BT52: -372.9
A53: A03 | B53: Fishing and aquaculture | C53: NO | D53: 7.4 | E53: 0.6 | F53: 16.6 | G53: 0.1 | H53: 2649.8 | I53: 0.1 | J53: 0.2 | N53: 15.9 | O53: 47.7 | T53: 0.1 | V53: 0.1 | W53: 0.1 | Y53: 0.5 | AA53: 0.2 | AB53: 0.1 | AC53: 0.2 | AD53: 3.6 | AE53: 0.3 | AF53: 7.2 | AG53: 16.3 | AH53: 1 | AI53: 1.3 | AK53: 6.2 | AM53: 628.9 | AO53: 0.1 | AP53: 0.8 | AQ53: 4.9 | AR53: 0.5 | AS53: 0.6 | AT53: 0.2 | AU53: 1.7 | AV53: 6.5 | AW53: 1.6 | AX53: 1.4 | AY53: 0.5 | AZ53: 0.7 | BA53: 6.6 | BB53: 0.1 | BC53: 0.2 | BD53: 11.4 | BE53: 3 | BF53: 6.5 | BG53: 16.6 | BH53: 24.5 | BI53: 12.2 | BJ53: 11.4 | BK53: 1.8 | BM53: 0.3 | BQ53: 1473.2 | BS53: 3.2 | BT53: -53
A54: A03 | B54: Fishing and aquaculture | C54: CH | F54: 0.3 | H54: 7.5 | AM54: 2.6 | BG54: 0.2 | BH54: 0.2 | BQ54: 7.3 | BS54: 0.1 | BT54: -5.4
A55: A03 | B55: Fishing and aquaculture | C55: UK | D55: 0.3 | E55: 0.1 | F55: 5.3 | H55: 206.2 | I55: 0.5 | M55: 0.3 | N55: 0.8 | O55: 0.2 | R55: 0.1 | T55: 0.1 | V55: 0.1 | W55: 0.1 | Y55: 0.1 | AA55: 1.5 | AC55: 0.1 | AD55: 3.9 | AF55: 0.5 | AG55: 0.1 | AH55: 0.1 | AI55: 1.4 | AK55: 0.2 | AM55: 90.9 | AN55: 0.1 | AO55: 0.3 | AP55: 0.1 | AQ55: 0.2 | AV55: 0.1 | AX55: 0.1 | BD55: 0.1 | BE55: 0.1 | BG55: 1 | BH55: 0.9 | BI55: 0.2 | BJ55: 0.7 | BK55: 2.6 | BQ55: 182.4 | BS55: 1.2 | BT55: -12.7
A56: A03 | B56: Fishing and aquaculture | C56: ME
A57: A03 | B57: Fishing and aquaculture | C57: MK | H57: 0.1 | AM57: 0.1 | BQ57: 0.2 | BT57: -0.1
A58: A03 | B58: Fishing and aquaculture | C58: AL | H58: 2.4 | AF58: 0.1 | AM58: 0.2 | BQ58: 6.6 | BS58: 0.3
A59: A03 | B59: Fishing and aquaculture | C59: RS | H59: 0.8 | AM59: 0.3 | BQ59: 1 | BT59: -0.6
A60: A03 | B60: Fishing and aquaculture | C60: TR | F60: 1.5 | H60: 21.3 | Y60: 0.1 | AF60: 0.3 | AM60: 7.2 | BG60: 0.3 | BH60: 0.3 | BK60: 0.1 | BQ60: 69.8 | BS60: 0.8 | BT60: -3.2
A61: A03 | B61: Fishing and aquaculture | C61: RU | D61: 0.3 | F61: 0.1 | H61: 8.2 | I61: 0.1 | M61: 2.4 | N61: 0.5 | O61: 0.1 | P61: 0.1 | Q61: 0.1 | R61: 0.5 | S61: 0.1 | T61: 0.1 | U61: 0.1 | V61: 0.1 | W61: 0.1 | Y61: 0.1 | AA61: 0.3 | AD61: 0.1 | AF61: 0.5 | AG61: 0.1 | AH61: 0.1 | AI61: 0.8 | AJ61: 0.1 | AK61: 0.3 | AM61: 2.7 | AQ61: 0.1 | AV61: 0.1 | BE61: 0.1 | BG61: 0.3 | BH61: 0.2 | BQ61: 11.9 | BS61: 0.1 | BT61: -5
A62: A03 | B62: Fishing and aquaculture | C62: ZA | D62: 0.2 | H62: 2.9 | N62: 0.2 | AF62: 0.1 | AM62: 0.8 | BG62: 0.1 | BH62: 0.1 | BQ62: 7 | BT62: -3.1
A63: A03 | B63: Fishing and aquaculture | C63: CA | F63: 0.2 | H63: 8.7 | AD63: 0.1 | AF63: 0.1 | AM63: 3.7 | BG63: 0.1 | BH63: 0.1 | BQ63: 26.4 | BS63: 0.3 | BT63: -1.2
A64: A03 | B64: Fishing and aquaculture | C64: US | D64: 0.4 | F64: 7.9 | H64: 161.9 | N64: 0.3 | O64: 0.3 | Y64: 0.2 | AA64: 0.1 | AD64: 0.4 | AF64: 0.6 | AG64: 0.1 | AI64: 0.4 | AM64: 32.6 | AR64: 0.1 | AV64: 0.1 | BA64: 0.1 | BD64: 0.1 | BE64: 0.1 | BF64: 0.1 | BG64: 2.5 | BH64: 2 | BI64: 0.4 | BJ64: 0.1 | BK64: 0.3 | BQ64: 146.3 | BS64: 2.9 | BT64: -0.6
A65: A03 | B65: Fishing and aquaculture | C65: MX | H65: 0.5 | M65: 0.1 | AM65: 0.1 | BQ65: 0.5 | BS65: 0.1 | BT65: -0.8
A66: A03 | B66: Fishing and aquaculture | C66: AR | D66: 0.1 | F66: 0.8 | H66: 24.2 | N66: 0.1 | AD66: 0.1 | AF66: 0.1 | AM66: 7.5 | BG66: 0.4 | BH66: 0.4 | BI66: 0.1 | BK66: 0.1 | BQ66: 331 | BS66: 0.1 | BT66: 3.6
A67: A03 | B67: Fishing and aquaculture | C67: BR | F67: 0.2 | H67: 5.5 | M67: 0.1 | AM67: 1.9 | BG67: 0.2 | BH67: 0.1 | BQ67: 5.9 | BT67: -0.1
A68: A03 | B68: Fishing and aquaculture | C68: CN | F68: 0.7 | H68: 20.5 | N68: 0.1 | AD68: 0.1 | AF68: 0.1 | AM68: 6.1 | BG68: 0.4 | BH68: 0.3 | BI68: 0.1 | BK68: 0.1 | BQ68: 19.7 | BS68: 0.2 | BT68: -3.8
A69: A03 | B69: Fishing and aquaculture | C69: JP | F69: 0.2 | H69: 4.1 | AM69: 1.3 | BG69: 0.1 | BH69: 0.1 | BQ69: 3.9 | BT69: -8.4
A70: A03 | B70: Fishing and aquaculture | C70: KR | F70: 0.1 | H70: 2.8 | AM70: 1 | BG70: 0.1 | BQ70: 3.2 | BT70: -2
A71: A03 | B71: Fishing and aquaculture | C71: IN | F71: 1 | H71: 21.9 | N71: 0.1 | O71: 0.1 | AD71: 0.1 | AF71: 0.1 | AI71: 0.1 | AM71: 6.5 | BG71: 0.5 | BH71: 0.4 | BI71: 0.1 | BK71: 0.1 | BQ71: 19.1 | BS71: 0.1 | BT71: -0.8
A72: A03 | B72: Fishing and aquaculture | C72: ID | F72: 0.2 | H72: 4.9 | AM72: 1.6 | BG72: 0.1 | BH72: 0.1 | BQ72: 6.8 | BT72: -1.1
A73: A03 | B73: Fishing and aquaculture | C73: SA | H73: 1.1 | AM73: 0.4 | BQ73: 0.7
A74: A03 | B74: Fishing and aquaculture | C74: AU | F74: 0.1 | H74: 2.2 | AM74: 0.6 | BQ74: 2.5 | BS74: 0.1 | BT74: -1
A75: A03 | B75: Fishing and aquaculture | C75: WRL_REST | D75: 1.6 | F75: 30.8 | H75: 221.7 | I75: 0.3 | M75: 0.4 | N75: 1.4 | O75: 0.4 | R75: 0.1 | T75: 0.1 | V75: 0.1 | W75: 0.1 | Y75: 0.2 | AA75: 0.6 | AC75: 0.1 | AD75: 1.1 | AF75: 0.9 | AG75: 0.2 | AH75: 0.1 | AI75: 0.4 | AJ75: 0.1 | AK75: 0.1 | AM75: 66.7 | AO75: 0.1 | AP75: 0.1 | AQ75: 0.3 | AR75: 0.1 | AV75: 0.3 | AW75: 0.1 | AX75: 0.1 | BA75: 0.2 | BD75: 0.2 | BE75: 0.3 | BF75: 0.2 | BG75: 2.5 | BH75: 2.4 | BI75: 0.4 | BJ75: 0.2 | BK75: 0.9 | BM75: 0.1 | BQ75: 456.7 | BS75: 1.3 | BT75: -6.3
A76: B | B76: Mining and quarrying | C76: EU27 | D76: 886.9 | E76: 70.7 | F76: 47.7 | G76: 5759.9 | H76: 1208.2 | I76: 133.7 | J76: 108 | K76: 559.8 | L76: 50.6 | M76: 22711.2 | N76: 4167.2 | O76: 183.6 | P76: 444.3 | Q76: 9430.4 | R76: 8992.9 | S76: 2073 | T76: 170.4 | U76: 823.4 | V76: 828.5 | W76: 887.4 | X76: 195.3 | Y76: 537.5 | Z76: 187.1 | AA76: 14663.7 | AB76: 124.9 | AC76: 509.4 | AD76: 13998.9 | AE76: 86.1 | AF76: 881.9 | AG76: 280.9 | AH76: 423.4 | AI76: 42.5 | AJ76: 33.2 | AK76: 453.8 | AL76: 20 | AM76: 265.5 | AN76: 20.3 | AO76: 21.8 | AP76: 56 | AQ76: 159.8 | AR76: 60.4 | AS76: 14.4 | AT76: 35.1 | AU76: 432.8 | AV76: 338.3 | AW76: 254.3 | AX76: 84 | AY76: 34.8 | AZ76: 63.8 | BA76: 43.2 | BB76: 49 | BC76: 13 | BD76: 556.9 | BE76: 833.5 | BF76: 161.9 | BG76: 371.5 | BH76: 140.5 | BI76: 48.8 | BJ76: 71 | BK76: 74.2 | BL76: 7.2 | BM76: 65.3 | BP76: 381 | BQ76: 5004.9 | BR76: 5.1 | BS76: 2139.6 | BT76: -3004.5
A77: B | B77: Mining and quarrying | C77: NO | D77: 170.8 | E77: 2 | F77: 1.8 | G77: 404.2 | H77: 314.1 | I77: 31.3 | J77: 7.1 | K77: 369.8 | L77: 6.3 | M77: 46984.3 | N77: 3814.6 | O77: 37.8 | P77: 118.8 | Q77: 848.3 | R77: 6947.5 | S77: 146.6 | T77: 12.8 | U77: 52.7 | V77: 132.6 | W77: 44.1 | X77: 31.4 | Y77: 152.4 | Z77: 17 | AA77: 13092.6 | AB77: 5.1 | AC77: 25.9 | AD77: 1322.6 | AE77: 6.1 | AF77: 144.7 | AG77: 40.5 | AH77: 61.6 | AI77: 52 | AJ77: 37.2 | AK77: 56.6 | AL77: 3.9 | AM77: 62.9 | AN77: 2.4 | AO77: 2.2 | AP77: 5.4 | AQ77: 12.4 | AR77: 2 | AS77: 0.7 | AT77: 1.5 | AU77: 20 | AV77: 155.7 | AW77: 33.6 | AX77: 5.5 | AY77: 1.2 | AZ77: 1.4 | BA77: 10.1 | BB77: 2.6 | BC77: 0.5 | BD77: 54.2 | BE77: 89.3 | BF77: 16.2 | BG77: 59.3 | BH77: 37.1 | BI77: 5.3 | BJ77: 6.1 | BK77: 8.5 | BL77: 0.4 | BM77: 10.9 | BP77: 21.3 | BQ77: 2115 | BS77: 56.3 | BT77: 840.1
A78: B | B78: Mining and quarrying | C78: CH | D78: 0.1 | H78: 0.3 | K78: 0.1 | M78: 36 | N78: 1 | Q78: 0.5 | R78: 6.9 | S78: 0.1 | V78: 0.3 | W78: 0.1 | AA78: 8 | AD78: 0.2 | AF78: 0.1 | AG78: 0.1 | BE78: 0.1 | BG78: 0.1 | BH78: 0.1 | BP78: 0.1 | BQ78: 3.4 | BS78: 0.2 | BT78: 0.8
A79: B | B79: Mining and quarrying | C79: UK | D79: 183 | E79: 0.4 | F79: 0.3 | G79: 141.6 | H79: 279.5 | I79: 15.2 | J79: 6.6 | K79: 87.7 | L79: 2.6 | M79: 19402.2 | N79: 1062.9 | O79: 75.8 | P79: 25.9 | Q79: 294.9 | R79: 2889.3 | S79: 49.9 | T79: 14.4 | U79: 18.7 | V79: 83.1 | W79: 31.6 | X79: 34.9 | Y79: 117.5 | Z79: 6.8 | AA79: 4632.2 | AB79: 2.7 | AC79: 14.2 | AD79: 440 | AE79: 9.7 | AF79: 80.3 | AG79: 43.4 | AH79: 20.8 | AI79: 1.6 | AJ79: 3.3 | AK79: 23.6 | AL79: 5.1 | AM79: 65.1 | AN79: 7 | AO79: 2.3 | AP79: 12.1 | AQ79: 27.5 | AR79: 5.3 | AS79: 4 | AT79: 5.7 | AU79: 14.9 | AV79: 253.4 | AW79: 40.8 | AX79: 6.8 | AY79: 2.5 | AZ79: 2.1 | BA79: 8 | BB79: 2.7 | BC79: 1.7 | BD79: 33 | BE79: 78.1 | BF79: 22.4 | BG79: 49.5 | BH79: 39.1 | BI79: 7 | BJ79: 7.6 | BK79: 12 | BL79: 0.8 | BM79: 11.8 | BP79: 25.3 | BQ79: 1438.8 | BS79: 120.8 | BT79: 528.5
A80: B | B80: Mining and quarrying | C80: ME | G80: 0.1 | K80: 0.1 | M80: 13.7 | N80: 0.4 | Q80: 0.3 | R80: 2.1 | AA80: 2.5 | AD80: 0.4 | BQ80: 0.1 | BS80: 0.1 | BT80: -0.7
A81: B | B81: Mining and quarrying | C81: MK | D81: 0.5 | G81: 0.2 | H81: 1.9 | I81: 0.2 | J81: 0.2 | K81: 0.9 | M81: 91 | N81: 5.7 | O81: 2.1 | P81: 0.2 | Q81: 4.8 | R81: 33.3 | S81: 0.8 | T81: 0.1 | U81: 0.5 | V81: 0.5 | W81: 0.4 | X81: 0.1 | Y81: 0.2 | AA81: 58.2 | AC81: 0.1 | AD81: 2.8 | AF81: 0.1 | AG81: 0.1 | AH81: 0.2 | AM81: 0.1 | AU81: 0.1 | BE81: 0.1 | BG81: 0.4 | BP81: 0.1 | BQ81: 1.9 | BS81: 0.4 | BT81: 5
A82: B | B82: Mining and quarrying | C82: AL | G82: 0.2 | H82: 0.3 | I82: 0.1 | K82: 0.1 | M82: 103.9 | N82: 0.9 | O82: 0.1 | P82: 0.1 | Q82: 3.8 | R82: 15.4 | S82: 0.1 | U82: 0.1 | V82: 0.1 | W82: 0.1 | X82: 0.1 | Y82: 0.1 | AA82: 25.4 | AD82: 0.9 | AF82: 0.2 | AH82: 0.1 | AM82: 0.1 | BE82: 0.1 | BQ82: 2 | BT82: 0.4
A83: B | B83: Mining and quarrying | C83: RS | D83: 0.2 | G83: 0.2 | H83: 0.8 | I83: 0.1 | J83: 0.1 | K83: 0.5 | M83: 54.5 | N83: 2.4 | O83: 0.9 | P83: 0.1 | Q83: 2.3 | R83: 13.4 | S83: 0.2 | T83: 0.1 | U83: 0.2 | V83: 0.2 | W83: 0.4 | Y83: 0.1 | AA83: 24.2 | AD83: 1.3 | AF83: 0.4 | AG83: 0.1 | AH83: 0.1 | AK83: 0.1 | AM83: 0.1 | AQ83: 0.3 | AV83: 0.2 | AW83: 0.1 | AX83: 0.7 | BE83: 0.1 | BF83: 0.1 | BG83: 0.1 | BP83: 0.2 | BQ83: 1 | BS83: 7 | BT83: -5.3
A84: B | B84: Mining and quarrying | C84: TR | D84: 2 | F84: 0.3 | G84: 2.7 | H84: 21.6 | I84: 0.9 | J84: 0.5 | K84: 2.8 | L84: 0.1 | M84: 701.9 | N84: 17.7 | O84: 3.6 | P84: 1.5 | Q84: 18.8 | R84: 85.8 | S84: 2 | T84: 0.6 | U84: 1.2 | V84: 3 | W84: 2 | X84: 0.5 | Y84: 0.8 | Z84: 0.4 | AA84: 327.6 | AB84: 0.2 | AC84: 0.8 | AD84: 16.4 | AE84: 0.3 | AF84: 3 | AG84: 1.1 | AH84: 1.5 | AI84: 2.3 | AJ84: 0.2 | AK84: 3.7 | AL84: 0.1 | AM84: 1.3 | AN84: 0.2 | AO84: 0.1 | AP84: 0.3 | AQ84: 0.6 | AR84: 0.1 | AS84: 0.1 | AT84: 0.1 | AU84: 1 | AV84: 1.6 | AW84: 5.4 | AX84: 0.1 | AY84: 0.1 | AZ84: 0.1 | BA84: 0.2 | BC84: 0.1 | BD84: 0.6 | BE84: 1.1 | BF84: 0.3 | BG84: 1.6 | BH84: 0.4 | BI84: 0.1 | BJ84: 0.1 | BK84: 0.1 | BM84: 0.2 | BP84: 0.4 | BQ84: 31.9 | BS84: 4.5 | BT84: 7
A85: B | B85: Mining and quarrying | C85: RU | D85: 76.2 | E85: 1.2 | F85: 0.5 | G85: 22.2 | H85: 112.9 | I85: 13.1 | J85: 5.8 | K85: 49.1 | L85: 2.9 | M85: 8317.1 | N85: 695 | O85: 32.2 | P85: 36.6 | Q85: 237.7 | R85: 1333.6 | S85: 43 | T85: 10.7 | U85: 33.9 | V85: 28.5 | W85: 27.7 | X85: 8.4 | Y85: 17.4 | Z85: 2.8 | AA85: 4502.4 | AB85: 3.6 | AC85: 8.6 | AD85: 146.7 | AE85: 5.4 | AF85: 45.6 | AG85: 27.3 | AH85: 61.8 | AI85: 31.1 | AJ85: 13.9 | AK85: 20.5 | AL85: 1.8 | AM85: 16.9 | AN85: 0.7 | AO85: 3.9 | AP85: 2 | AQ85: 5.1 | AR85: 1 | AS85: 0.9 | AT85: 0.4 | AU85: 6.6 | AV85: 21 | AW85: 7.5 | AX85: 1.5 | AY85: 1 | AZ85: 1.3 | BA85: 2.4 | BB85: 1.2 | BC85: 0.3 | BD85: 9.8 | BE85: 28.8 | BF85: 15.9 | BG85: 16.6 | BH85: 3.9 | BI85: 2.1 | BJ85: 2.1 | BK85: 1.9 | BL85: 0.3 | BM85: 2.4 | BP85: 0.9 | BQ85: 722.7 | BS85: 4.4 | BT85: 130.4
A86: B | B86: Mining and quarrying | C86: ZA | D86: 4.4 | G86: 7.7 | H86: 26.9 | I86: 2.2 | J86: 1.1 | K86: 11.9 | L86: 0.5 | M86: 2226.9 | N86: 116.7 | O86: 6.6 | P86: 15.5 | Q86: 40.6 | R86: 1244 | S86: 272.6 | T86: 15.2 | U86: 83.4 | V86: 151.7 | W86: 107.3 | X86: 16.2 | Y86: 48.4 | Z86: 12.7 | AA86: 498.7 | AB86: 0.5 | AC86: 5.6 | AD86: 77.1 | AE86: 0.7 | AF86: 8.1 | AG86: 6.4 | AH86: 3.3 | AJ86: 0.1 | AK86: 3.4 | AL86: 0.3 | AM86: 2 | AN86: 0.1 | AO86: 0.2 | AP86: 0.4 | AQ86: 0.3 | AR86: 0.1 | AT86: 0.1 | AU86: 0.8 | AV86: 1.7 | AW86: 2.9 | AX86: 0.3 | AY86: 0.3 | AZ86: 0.1 | BA86: 0.3 | BD86: 3.1 | BE86: 8.7 | BF86: 0.6 | BG86: 7.5 | BH86: 4.2 | BI86: 0.4 | BJ86: 0.2 | BK86: 0.1 | BL86: 0.1 | BM86: 0.5 | BP86: 3.9 | BQ86: 205.1 | BS86: 12.5 | BT86: 69.2
A87: B | B87: Mining and quarrying | C87: CA | D87: 16.6 | E87: 0.3 | F87: 0.2 | G87: 11.9 | H87: 23.9 | I87: 3 | J87: 1.1 | K87: 13.1 | L87: 0.6 | M87: 3375.3 | N87: 183.5 | O87: 8.3 | P87: 19.3 | Q87: 70.5 | R87: 629.2 | S87: 31.8 | T87: 3.7 | U87: 9 | V87: 25.3 | W87: 14.6 | X87: 4.6 | Y87: 18.5 | Z87: 2.7 | AA87: 762.3 | AB87: 0.2 | AC87: 2.6 | AD87: 50.8 | AE87: 1.4 | AF87: 13 | AG87: 5.8 | AH87: 6.3 | AI87: 11.6 | AJ87: 4.5 | AK87: 3.2 | AL87: 0.7 | AM87: 5 | AN87: 1.5 | AO87: 0.8 | AP87: 1 | AQ87: 6.3 | AR87: 1.1 | AS87: 0.9 | AT87: 0.9 | AU87: 2.2 | AV87: 20.8 | AW87: 4 | AX87: 1.9 | AY87: 0.5 | AZ87: 0.6 | BA87: 2.7 | BB87: 0.4 | BC87: 0.6 | BD87: 6.6 | BE87: 9.4 | BF87: 1.8 | BG87: 9 | BH87: 4.5 | BI87: 0.9 | BJ87: 0.6 | BK87: 1.1 | BL87: 0.1 | BM87: 1.8 | BP87: 2.9 | BQ87: 167.8 | BS87: 11 | BT87: 97.5
A88: B | B88: Mining and quarrying | C88: US | D88: 178.2 | E88: 1 | F88: 1.5 | G88: 141.9 | H88: 222.4 | I88: 22.4 | J88: 4.1 | K88: 103.3 | L88: 4.8 | M88: 22236.7 | N88: 1079.3 | O88: 29.9 | P88: 30 | Q88: 420.4 | R88: 2862.1 | S88: 56.6 | T88: 10.7 | U88: 15.7 | V88: 72.4 | W88: 24.1 | X88: 34.2 | Y88: 24.6 | Z88: 6.3 | AA88: 5621.8 | AB88: 3.2 | AC88: 12.9 | AD88: 390.8 | AE88: 8.7 | AF88: 93.5 | AG88: 29.5 | AH88: 73.8 | AI88: 72.9 | AJ88: 55.1 | AK88: 31.7 | AL88: 5.6 | AM88: 67.5 | AN88: 7.9 | AO88: 1.3 | AP88: 4.1 | AQ88: 22.5 | AR88: 1.8 | AS88: 1.4 | AT88: 2 | AU88: 8.4 | AV88: 254.3 | AW88: 47.1 | AX88: 5.1 | AY88: 1.2 | AZ88: 1.2 | BA88: 7.2 | BB88: 2.1 | BC88: 0.3 | BD88: 26 | BE88: 63.4 | BF88: 19.3 | BG88: 44 | BH88: 33.5 | BI88: 5.3 | BJ88: 6.6 | BK88: 12.2 | BL88: 0.4 | BM88: 6.3 | BP88: 18.4 | BQ88: 1681.2 | BS88: 58.5 | BT88: 311.2
A89: B | B89: Mining and quarrying | C89: MX | D89: 0.7 | G89: 2.8 | H89: 4.1 | I89: 0.9 | J89: 0.1 | K89: 3.2 | L89: 0.2 | M89: 1624.9 | N89: 16.9 | O89: 0.9 | P89: 0.6 | Q89: 52.2 | R89: 253 | S89: 1.3 | T89: 0.2 | U89: 0.4 | V89: 2.3 | W89: 0.7 | X89: 0.2 | Y89: 0.7 | Z89: 0.1 | AA89: 387.8 | AB89: 0.1 | AC89: 0.4 | AD89: 6 | AE89: 0.1 | AF89: 3 | AG89: 0.7 | AH89: 1.1 | AK89: 0.5 | AM89: 0.7 | AQ89: 0.1 | AU89: 0.1 | AV89: 0.2 | AW89: 0.1 | AX89: 0.1 | BD89: 0.2 | BE89: 1.6 | BF89: 0.2 | BG89: 1.3 | BH89: 0.5 | BJ89: 0.1 | BM89: 0.1 | BP89: 0.4 | BQ89: 45.9 | BS89: 0.3 | BT89: 17.9
A90: B | B90: Mining and quarrying | C90: AR | D90: 1.2 | G90: 0.9 | H90: 1 | K90: 0.3 | M90: 73.9 | N90: 5.6 | Q90: 0.9 | R90: 9.4 | S90: 0.2 | V90: 0.2 | W90: 0.1 | X90: 0.3 | Y90: 0.5 | AA90: 7.3 | AD90: 2 | AF90: 0.3 | AG90: 0.1 | AK90: 0.1 | AM90: 0.4 | AQ90: 0.1 | AU90: 0.1 | AV90: 2.2 | AW90: 0.3 | BD90: 0.1 | BE90: 0.3 | BF90: 0.1 | BG90: 0.1 | BH90: 0.2 | BK90: 0.1 | BP90: 0.1 | BQ90: 5.6 | BS90: 0.5 | BT90: 1.3
A91: B | B91: Mining and quarrying | C91: BR | D91: 22.2 | E91: 0.1 | F91: 0.1 | G91: 27 | H91: 29.9 | I91: 2.9 | J91: 0.6 | K91: 18.4 | L91: 0.6 | M91: 6604.5 | N91: 167.2 | O91: 4.8 | P91: 3.2 | Q91: 128.5 | R91: 731.8 | S91: 10.6 | T91: 0.9 | U91: 3.4 | V91: 12.2 | W91: 3.6 | X91: 4.7 | Y91: 4.5 | Z91: 0.8 | AA91: 1594.5 | AB91: 0.4 | AC91: 1.6 | AD91: 68.1 | AE91: 0.8 | AF91: 10.3 | AG91: 3.8 | AH91: 3.6 | AI91: 0.5 | AJ91: 0.4 | AK91: 2.9 | AL91: 0.6 | AM91: 8.5 | AO91: 0.1 | AP91: 0.4 | AQ91: 0.2 | AR91: 0.2 | AS91: 0.2 | AT91: 0.2 | AU91: 1.5 | AV91: 34.3 | AW91: 5.1 | AX91: 0.5 | AY91: 0.1 | AZ91: 0.1 | BA91: 0.5 | BB91: 0.3 | BD91: 2.7 | BE91: 9.5 | BF91: 2.5 | BG91: 6.2 | BH91: 4.7 | BI91: 0.7 | BJ91: 0.8 | BK91: 1.6 | BM91: 0.8 | BP91: 2.5 | BQ91: 224.1 | BS91: 67.2 | BT91: 64.6
A92: B | B92: Mining and quarrying | C92: CN | D92: 0.4 | G92: 1.2 | H92: 1.5 | I92: 0.2 | K92: 1.2 | M92: 197 | N92: 9.9 | O92: 0.2 | P92: 0.3 | Q92: 4.5 | R92: 33.3 | S92: 0.5 | T92: 0.1 | U92: 0.3 | V92: 0.6 | W92: 0.2 | X92: 0.1 | Y92: 0.9 | AA92: 62.7 | AC92: 0.1 | AD92: 3.1 | AF92: 0.7 | AG92: 0.3 | AH92: 0.3 | AK92: 0.2 | AM92: 0.2 | AU92: 0.1 | AV92: 0.3 | AW92: 0.1 | BD92: 0.1 | BE92: 0.4 | BF92: 0.1 | BG92: 0.3 | BH92: 0.2 | BM92: 0.1 | BP92: 0.1 | BQ92: 10.9 | BS92: 0.4 | BT92: -0.1
A93: B | B93: Mining and quarrying | C93: JP | D93: 0.1 | G93: 0.2 | H93: 0.1 | K93: 0.1 | M93: 15.9 | N93: 0.8 | Q93: 0.3 | R93: 1.7 | S93: 0.1 | U93: 0.1 | V93: 0.1 | AA93: 6.2 | AD93: 0.3 | BQ93: 1.2 | BS93: 0.1 | BT93: -1.6
A94: B | B94: Mining and quarrying | C94: KR | D94: 0.1 | H94: 0.1 | M94: 1.8 | N94: 0.3 | P94: 0.1 | Q94: 0.2 | R94: 0.2 | U94: 0.1 | W94: 0.1 | AA94: 0.6 | AD94: 0.3 | AF94: 0.1 | AI94: 0.1 | AJ94: 0.1 | BQ94: 0.3 | BS94: 0.1 | BT94: -1.3
A95: B | B95: Mining and quarrying | C95: IN | D95: 0.1 | G95: 0.2 | H95: 0.4 | I95: 0.1 | K95: 0.3 | M95: 31.5 | N95: 1.7 | O95: 0.1 | P95: 0.1 | Q95: 0.9 | R95: 5.2 | S95: 0.1 | V95: 0.1 | Y95: 0.3 | AA95: 10 | AD95: 0.6 | AF95: 0.3 | AH95: 0.1 | AM95: 0.1 | AV95: 0.1 | BE95: 0.1 | BG95: 0.1 | BQ95: 3.4 | BS95: 0.1 | BT95: -2.8
A96: B | B96: Mining and quarrying | C96: ID | D96: 2.4 | E96: 0.1 | F96: 0.1 | G96: 5.1 | H96: 13.3 | I96: 1.6 | J96: 0.5 | K96: 6.7 | L96: 0.3 | M96: 1107.7 | N96: 36.5 | O96: 4.7 | P96: 1.7 | Q96: 38.5 | R96: 206.8 | S96: 3.3 | T96: 0.4 | U96: 1.6 | V96: 4.3 | W96: 1.3 | X96: 0.4 | Y96: 0.6 | Z96: 0.2 | AA96: 360.9 | AB96: 0.3 | AC96: 0.8 | AD96: 14.5 | AE96: 0.2 | AF96: 4.1 | AG96: 1.8 | AH96: 2.1 | AI96: 0.1 | AK96: 1.6 | AL96: 0.1 | AM96: 1.7 | AP96: 0.1 | AQ96: 0.1 | AR96: 0.1 | AU96: 0.5 | AV96: 1.3 | AW96: 2 | AX96: 0.1 | BD96: 0.5 | BE96: 2 | BF96: 0.7 | BG96: 2.5 | BH96: 0.9 | BI96: 0.1 | BJ96: 0.2 | BK96: 0.1 | BM96: 0.3 | BP96: 0.7 | BQ96: 69.2 | BS96: 0.2 | BT96: 24.2
A97: B | B97: Mining and quarrying | C97: SA | D97: 48.9 | E97: 0.8 | F97: 0.2 | G97: 129.1 | H97: 61.7 | I97: 12.4 | J97: 1.7 | K97: 42 | L97: 2.8 | M97: 11615.4 | N97: 457.4 | O97: 7.1 | P97: 12 | Q97: 257.1 | R97: 1168.6 | S97: 34.7 | T97: 2.2 | U97: 20.6 | V97: 21.6 | W97: 8.1 | X97: 6.2 | Y97: 4.5 | Z97: 2.3 | AA97: 3499.3 | AB97: 2.3 | AC97: 7 | AD97: 171 | AE97: 1.7 | AF97: 41.5 | AG97: 7 | AH97: 23.9 | AI97: 0.1 | AJ97: 0.4 | AK97: 7.5 | AL97: 0.7 | AM97: 18.7 | AN97: 0.1 | AO97: 0.1 | AP97: 0.8 | AQ97: 0.7 | AR97: 0.8 | AS97: 0.2 | AT97: 0.3 | AU97: 2.4 | AV97: 37.8 | AW97: 6.1 | AX97: 1.6 | AY97: 0.1 | AZ97: 0.3 | BA97: 1.2 | BB97: 0.4 | BC97: 0.1 | BD97: 13.8 | BE97: 17.3 | BF97: 5.2 | BG97: 13 | BH97: 6.2 | BI97: 1.1 | BJ97: 1.6 | BK97: 2.2 | BL97: 0.1 | BM97: 1.8 | BP97: 2.8 | BQ97: 712.2 | BS97: 4.5 | BT97: 29.5
A98: B | B98: Mining and quarrying | C98: AU | D98: 3.8 | E98: 0.1 | G98: 10 | H98: 16.9 | I98: 1.7 | J98: 0.3 | K98: 14.3 | L98: 0.3 | M98: 2668.1 | N98: 83.5 | O98: 1.2 | P98: 3.4 | Q98: 51.4 | R98: 480.1 | S98: 6.2 | T98: 1 | U98: 3.1 | V98: 14.6 | W98: 2.9 | X98: 0.8 | Y98: 4.9 | Z98: 0.7 | AA98: 708.1 | AB98: 0.4 | AC98: 1.2 | AD98: 26.9 | AE98: 0.3 | AF98: 6.4 | AG98: 5.7 | AH98: 2.3 | AI98: 1.9 | AJ98: 0.2 | AK98: 2.5 | AL98: 0.3 | AM98: 2.2 | AN98: 0.2 | AO98: 0.2 | AP98: 0.2 | AQ98: 0.8 | AR98: 0.1 | AT98: 0.1 | AU98: 0.7 | AV98: 1.4 | AW98: 1.2 | AX98: 0.2 | BA98: 0.1 | BB98: 0.1 | BD98: 1.8 | BE98: 6.9 | BF98: 1 | BG98: 5.6 | BH98: 3.2 | BI98: 0.4 | BJ98: 0.3 | BK98: 0.2 | BM98: 0.6 | BP98: 2.9 | BQ98: 158 | BS98: 0.7 | BT98: 97.3
A99: B | B99: Mining and quarrying | C99: WRL_REST | D99: 614.5 | E99: 2.4 | F99: 5.2 | G99: 637.4 | H99: 1332.2 | I99: 247.2 | J99: 35.1 | K99: 911.8 | L99: 63 | M99: 136625.9 | N99: 5837.5 | O99: 197.1 | P99: 199 | Q99: 3342.9 | R99: 17257 | S99: 466.3 | T99: 48.9 | U99: 138.7 | V99: 388.8 | W99: 167.6 | X99: 118.2 | Y99: 173.5 | Z99: 25.1 | AA99: 38837.7 | AB99: 43.2 | AC99: 87.9 | AD99: 1695.7 | AE99: 28.8 | AF99: 914.2 | AG99: 137.9 | AH99: 347.3 | AI99: 6 | AJ99: 11.5 | AK99: 194.3 | AL99: 14.7 | AM99: 344.2 | AN99: 1.5 | AO99: 3.9 | AP99: 19.4 | AQ99: 15.9 | AR99: 12.6 | AS99: 2.9 | AT99: 5.3 | AU99: 54.2 | AV99: 743 | AW99: 164.3 | AX99: 23.7 | AY99: 2.8 | AZ99: 5.8 | BA99: 11.5 | BB99: 6.9 | BC99: 1.3 | BD99: 93.2 | BE99: 260.4 | BF99: 111.1 | BG99: 273.8 | BH99: 120.3 | BI99: 19.3 | BJ99: 33.3 | BK99: 36.7 | BL99: 1.6 | BM99: 36.6 | BP99: 51 | BQ99: 12725.8 | BS99: 115 | BT99: 2367.9
A100: C10-12 | B100: Manufacture of food products | C100: EU27 | D100: 55773.3 | E100: 136.2 | F100: 611.3 | G100: 267.4 | H100: 223534.5 | I100: 2017.6 | J100: 376.1 | K100: 950.9 | L100: 153.4 | M100: 1237 | N100: 11528.5 | O100: 3351.8 | P100: 1437.6 | Q100: 769.6 | R100: 1198.6 | S100: 842.9 | T100: 635.8 | U100: 659.7 | V100: 1100.7 | W100: 1354.6 | X100: 334.8 | Y100: 1048.7 | Z100: 384.1 | AA100: 1962.2 | AB100: 124.2 | AC100: 1020.2 | AD100: 3779.2 | AE100: 807.1 | AF100: 14500.5 | AG100: 7322.1 | AH100: 1821.9 | AI100: 777.2 | AJ100: 513.2 | AK100: 1373.7 | AL100: 166.7 | AM100: 119151.6 | AN100: 474.8 | AO100: 622.1 | AP100: 698.1 | AQ100: 2095.6 | AR100: 543.1 | AS100: 239.3 | AT100: 351.5 | AU100: 955.9 | AV100: 2635.1 | AW100: 785.5 | AX100: 965.2 | AY100: 577.1 | AZ100: 683.6 | BA100: 966.8 | BB100: 264.5 | BC100: 418.7 | BD100: 2229.9 | BE100: 6802 | BF100: 6211 | BG100: 13493.2 | BH100: 8703.1 | BI100: 995.8 | BJ100: 2672.6 | BK100: 1402.8 | BL100: 107.1 | BM100: 507.7 | BP100: 2051.5 | BQ100: 632161.9 | BR100: 259.5 | BS100: 4327.8 | BT100: 19014.3
...

Sheet FIGARO raw 2022
A1: FIGARO raw dataset — 2022, € million (naio_10_fcp_ii4, condensed to EU-27 as one economy; extract of 2026-07-07). One row per product row × origin, the 24 origins contiguous per product row: origin EU27 is intra-EU supply (and carries the six value-added rows); every other origin is that partner's exports into EU-27 use. Zero cells are left blank. Reference year only — the model reads 2023. To model 2022 instead, repoint the Z-sheet formulas (same layout, same stride).
A2: Row code | B2: Row label | C2: Origin | D2: A01 | E2: A02 | F2: A03 | G2: B | H2: C10-12 | I2: C13-15 | J2: C16 | K2: C17 | L2: C18 | M2: C19 | N2: C20 | O2: C21 | P2: C22 | Q2: C23 | R2: C24 | S2: C25 | T2: C26 | U2: C27 | V2: C28 | W2: C29 | X2: C30 | Y2: C31_32 | Z2: C33 | AA2: D35 | AB2: E36 | AC2: E37-39 | AD2: F | AE2: G45 | AF2: G46 | AG2: G47 | AH2: H49 | AI2: H50 | AJ2: H51 | AK2: H52 | AL2: H53 | AM2: I | AN2: J58 | AO2: J59_60 | AP2: J61 | AQ2: J62_63 | AR2: K64 | AS2: K65 | AT2: K66 | AU2: L | AV2: M69_70 | AW2: M71 | AX2: M72 | AY2: M73 | AZ2: M74_75 | BA2: N77 | BB2: N78 | BC2: N79 | BD2: N80-82 | BE2: O84 | BF2: P85 | BG2: Q86 | BH2: Q87_88 | BI2: R90-92 | BJ2: R93 | BK2: S94 | BL2: S95 | BM2: S96 | BN2: T | BO2: U | BP2: P3_S13 | BQ2: P3_S14 | BR2: P3_S15 | BS2: P51G | BT2: P5M
D3: Crop and animal production, hunting and related service activities | E3: Forestry and logging | F3: Fishing and aquaculture | G3: Mining and quarrying | H3: Manufacture of food products | I3: Manufacture of textiles, wearing apparel, leather and related products | J3: Manufacture of wood and of products of wood and cork, except furniture | K3: Manufacture of paper and paper products | L3: Printing and reproduction of recorded media | M3: Manufacture of coke and refined petroleum products | N3: Manufacture of chemicals and chemical products | O3: Manufacture of basic pharmaceutical products and pharmaceutical prepa… | P3: Manufacture of rubber and plastic products | Q3: Manufacture of other non-metallic mineral products | R3: Manufacture of basic metals | S3: Manufacture of fabricated metal products, except machinery and equipm… | T3: Manufacture of computer, electronic and optical products | U3: Manufacture of electrical equipment | V3: Manufacture of machinery and equipment n.e.c. | W3: Manufacture of motor vehicles, trailers and semi-trailers | X3: Manufacture of other transport equipment | Y3: Manufacture of furniture | Z3: Repair and installation of machinery and equipment | AA3: Electricity, gas, steam and air conditioning supply | AB3: Water collection, treatment and supply | AC3: Sewerage, waste management, remediation activities | AD3: Construction | AE3: Wholesale and retail trade and repair of motor vehicles and motorcycl… | AF3: Wholesale trade, except of motor vehicles and motorcycles | AG3: Retail trade, except of motor vehicles and motorcycles | AH3: Land transport and transport via pipelines | AI3: Water transport | AJ3: Air transport | AK3: Warehousing and support activities for transportation | AL3: Postal and courier activities | AM3: Accommodation and food service activities | AN3: Publishing activities | AO3: Motion picture, video, television programme production | AP3: Telecommunications | AQ3: Computer programming, consultancy, and information service activities | AR3: Financial service activities, except insurance and pension funding | AS3: Insurance, reinsurance and pension funding, except compulsory social … | AT3: Activities auxiliary to financial services and insurance activities | AU3: Real estate activities | AV3: Legal and accounting activities | AW3: Architectural and engineering activities | AX3: Scientific research and development | AY3: Advertising and market research | AZ3: Other professional, scientific and technical activities | BA3: Rental and leasing activities | BB3: Employment activities | BC3: Travel agency, tour operator reservation service and related activiti… | BD3: Security and investigation, service and landscape, office administrat… | BE3: Public administration and defence | BF3: Education | BG3: Human health activities | BH3: Residential care activities and social work activities without accomm… | BI3: Creative, arts and entertainment activities | BJ3: Sports activities and amusement and recreation activities | BK3: Activities of membership organisations | BL3: Repair of computers and personal and household goods | BM3: Other personal service activities | BN3: Activities of households as employers | BO3: Activities of extraterritorial organisations and bodies | BP3: Government consumption | BQ3: Household consumption | BR3: NPISH consumption | BS3: Gross fixed capital formation | BT3: Changes in inventories & valuables
A4: A01 | B4: Crop and animal production, hunting and related service activities | C4: EU27 | D4: 67372.3 | E4: 659.4 | F4: 89.6 | G4: 93.8 | H4: 249554.9 | I4: 2664.5 | J4: 423.5 | K4: 265.5 | L4: 25.6 | M4: 119.9 | N4: 2371.2 | O4: 584.1 | P4: 1465 | Q4: 152.1 | R4: 218.4 | S4: 202 | T4: 190.6 | U4: 114.9 | V4: 240.7 | W4: 284.6 | X4: 99.8 | Y4: 245 | Z4: 76 | AA4: 1683.5 | AB4: 47.8 | AC4: 148.3 | AD4: 1365.8 | AE4: 126.2 | AF4: 7488.9 | AG4: 3466 | AH4: 357.6 | AI4: 120.1 | AJ4: 105.6 | AK4: 390.6 | AL4: 27.2 | AM4: 13600.9 | AN4: 49.9 | AO4: 85.3 | AP4: 93.8 | AQ4: 255.1 | AR4: 59.9 | AS4: 59 | AT4: 41.1 | AU4: 478.3 | AV4: 302.7 | AW4: 212.3 | AX4: 256.3 | AY4: 54.1 | AZ4: 143 | BA4: 106.6 | BB4: 52.5 | BC4: 101.6 | BD4: 3711.2 | BE4: 1508.5 | BF4: 699.6 | BG4: 1127.4 | BH4: 825.3 | BI4: 261.4 | BJ4: 332.1 | BK4: 144.7 | BL4: 12 | BM4: 182.5 | BP4: 1799.4 | BQ4: 133858.9 | BR4: 54.9 | BS4: 8507.9 | BT4: 14246
A5: A01 | B5: Crop and animal production, hunting and related service activities | C5: NO | D5: 2.1 | E5: 7.6 | H5: 10.6 | I5: 0.1 | J5: 22.7 | K5: 5.3 | N5: 0.3 | O5: 0.4 | P5: 0.2 | Y5: 0.8 | AA5: 0.2 | AD5: 0.4 | AF5: 0.1 | AM5: 0.8 | BD5: 0.3 | BE5: 0.2 | BF5: 0.1 | BG5: 0.3 | BH5: 0.1 | BK5: 0.1 | BM5: 0.1 | BP5: 0.2 | BQ5: 16.7 | BS5: 0.1 | BT5: 1.5
A6: A01 | B6: Crop and animal production, hunting and related service activities | C6: CH | D6: 2 | E6: 0.1 | F6: 0.1 | G6: 0.1 | H6: 13.1 | I6: 0.6 | J6: 0.2 | K6: 0.2 | L6: 0.1 | M6: 0.2 | N6: 0.7 | O6: 0.4 | P6: 0.9 | Q6: 0.2 | R6: 0.3 | S6: 0.4 | T6: 0.4 | U6: 0.3 | V6: 0.4 | W6: 0.5 | X6: 0.2 | Y6: 0.3 | Z6: 0.2 | AA6: 0.3 | AB6: 0.1 | AC6: 0.2 | AD6: 0.5 | AE6: 0.2 | AF6: 1.1 | AG6: 0.6 | AH6: 0.2 | AI6: 0.2 | AJ6: 0.2 | AK6: 0.2 | AL6: 0.1 | AM6: 1.2 | AN6: 0.2 | AO6: 0.3 | AP6: 0.2 | AQ6: 0.4 | AR6: 0.1 | AS6: 0.2 | AT6: 0.2 | AU6: 0.1 | AV6: 0.2 | AW6: 0.2 | AX6: 0.2 | AY6: 0.2 | AZ6: 0.2 | BA6: 0.2 | BB6: 0.1 | BC6: 0.2 | BD6: 0.3 | BE6: 0.3 | BF6: 0.2 | BG6: 0.4 | BH6: 0.3 | BI6: 0.2 | BJ6: 0.2 | BK6: 0.1 | BL6: 0.1 | BM6: 0.1 | BP6: 0.3 | BQ6: 15.2 | BS6: 0.6 | BT6: 1.6
A7: A01 | B7: Crop and animal production, hunting and related service activities | C7: UK | D7: 132 | E7: 0.7 | G7: 0.1 | H7: 781.1 | I7: 4.4 | J7: 0.3 | K7: 0.6 | L7: 0.1 | M7: 0.6 | N7: 12.9 | O7: 15.6 | P7: 6.1 | Q7: 0.5 | R7: 0.7 | S7: 0.9 | T7: 1.5 | U7: 0.8 | V7: 1.4 | W7: 1.8 | X7: 0.5 | Y7: 1.1 | Z7: 0.4 | AA7: 2.1 | AB7: 0.1 | AC7: 0.7 | AD7: 4.8 | AE7: 0.7 | AF7: 23.8 | AG7: 2.3 | AH7: 1.2 | AI7: 0.6 | AJ7: 0.6 | AK7: 1.3 | AL7: 0.2 | AM7: 20.2 | AN7: 1.1 | AO7: 0.8 | AP7: 0.8 | AQ7: 7.4 | AR7: 0.8 | AS7: 0.6 | AT7: 0.9 | AU7: 0.9 | AV7: 5.7 | AW7: 1.9 | AX7: 0.7 | AY7: 0.6 | AZ7: 0.6 | BA7: 1.4 | BB7: 0.3 | BC7: 0.7 | BD7: 6.2 | BE7: 2.8 | BF7: 1.2 | BG7: 6.4 | BH7: 3.4 | BI7: 0.9 | BJ7: 0.4 | BK7: 0.3 | BL7: 0.1 | BM7: 0.4 | BP7: 34.9 | BQ7: 431.6 | BS7: 24.7 | BT7: 45.3
A8: A01 | B8: Crop and animal production, hunting and related service activities | C8: ME | D8: 0.9 | H8: 5.6 | I8: 0.2 | J8: 0.3 | K8: 0.1 | N8: 0.1 | P8: 0.1 | AF8: 0.2 | AM8: 0.6 | BG8: 0.1 | BP8: 0.1 | BQ8: 7.1 | BS8: 0.1 | BT8: 0.9
A9: A01 | B9: Crop and animal production, hunting and related service activities | C9: MK | D9: 37.1 | E9: 0.2 | H9: 87 | I9: 1.2 | K9: 0.1 | N9: 2 | O9: 0.2 | P9: 1.6 | Q9: 0.1 | Y9: 0.1 | AA9: 0.6 | AD9: 0.3 | AF9: 3.5 | AG9: 0.5 | AH9: 0.1 | AI9: 0.1 | AM9: 5.4 | BA9: 0.1 | BD9: 0.8 | BE9: 0.6 | BF9: 0.2 | BG9: 0.7 | BH9: 0.4 | BI9: 0.1 | BK9: 0.1 | BP9: 0.5 | BQ9: 121.2 | BS9: 1.7 | BT9: 9
A10: A01 | B10: Crop and animal production, hunting and related service activities | C10: AL | D10: 3.2 | F10: 0.1 | H10: 26 | I10: 0.7 | K10: 0.1 | N10: 0.9 | O10: 0.4 | P10: 0.2 | AA10: 0.1 | AF10: 0.8 | AG10: 0.1 | AH10: 0.1 | AI10: 0.1 | AM10: 2.8 | BC10: 0.1 | BD10: 0.1 | BE10: 0.1 | BF10: 0.1 | BG10: 0.2 | BH10: 0.1 | BP10: 0.2 | BQ10: 40.3 | BS10: 0.3
A11: A01 | B11: Crop and animal production, hunting and related service activities | C11: RS | D11: 71.8 | E11: 0.4 | F11: 0.1 | H11: 373.5 | I11: 8.5 | J11: 0.1 | K11: 0.3 | M11: 0.1 | N11: 11.3 | O11: 1.1 | P11: 9.6 | Q11: 0.1 | R11: 0.1 | S11: 0.2 | T11: 0.2 | U11: 0.2 | V11: 0.3 | W11: 0.2 | Y11: 0.6 | AA11: 0.6 | AC11: 0.2 | AD11: 0.3 | AE11: 0.1 | AF11: 6.6 | AG11: 1.2 | AH11: 0.1 | AI11: 0.1 | AK11: 0.2 | AM11: 7.9 | AN11: 0.1 | AP11: 0.1 | AQ11: 0.9 | AU11: 0.1 | AV11: 0.3 | AW11: 0.1 | AX11: 0.3 | AY11: 0.1 | AZ11: 0.1 | BD11: 2.1 | BE11: 1 | BF11: 0.5 | BG11: 0.7 | BH11: 0.8 | BI11: 0.2 | BJ11: 0.1 | BK11: 0.1 | BM11: 0.2 | BP11: 1.6 | BQ11: 293.5 | BS11: 6.2 | BT11: 31.8
A12: A01 | B12: Crop and animal production, hunting and related service activities | C12: TR | D12: 72.4 | E12: 0.6 | F12: 0.2 | H12: 309.6 | I12: 5.5 | K12: 0.3 | M12: 0.2 | N12: 7.5 | O12: 1.4 | P12: 4.3 | Q12: 0.1 | V12: 0.1 | Y12: 0.3 | AA12: 1.7 | AC12: 0.2 | AD12: 0.4 | AF12: 8.1 | AG12: 1.6 | AH12: 0.3 | AI12: 0.4 | AK12: 0.1 | AM12: 19.9 | AO12: 0.1 | AQ12: 0.1 | AU12: 0.1 | AV12: 0.1 | AX12: 0.2 | AY12: 0.1 | AZ12: 0.1 | BA12: 0.1 | BD12: 2.3 | BE12: 2.3 | BF12: 0.9 | BG12: 3.3 | BH12: 2 | BI12: 0.2 | BJ12: 0.3 | BK12: 0.2 | BM12: 0.2 | BP12: 0.7 | BQ12: 418.3 | BS12: 6.4 | BT12: 31.7
A13: A01 | B13: Crop and animal production, hunting and related service activities | C13: RU | D13: 66.1 | E13: 0.6 | F13: 0.1 | G13: 0.1 | H13: 314.1 | I13: 4.8 | J13: 0.4 | K13: 0.5 | M13: 2.6 | N13: 13.4 | O13: 1.2 | P13: 5.4 | Q13: 0.3 | R13: 1.1 | S13: 0.3 | T13: 0.2 | U13: 0.2 | V13: 0.4 | W13: 0.3 | X13: 0.1 | Y13: 0.6 | Z13: 0.1 | AA13: 3.6 | AC13: 0.3 | AD13: 0.9 | AE13: 0.1 | AF13: 4.2 | AG13: 1.1 | AH13: 1 | AI13: 0.7 | AJ13: 0.2 | AK13: 0.9 | AM13: 11.4 | AN13: 0.1 | AO13: 0.1 | AP13: 0.1 | AQ13: 0.5 | AR13: 0.1 | AT13: 0.1 | AU13: 0.3 | AV13: 0.4 | AW13: 0.1 | AX13: 0.1 | AY13: 0.2 | AZ13: 0.1 | BA13: 0.2 | BD13: 1.5 | BE13: 1.4 | BF13: 0.6 | BG13: 1.6 | BH13: 1 | BI13: 0.1 | BJ13: 0.1 | BK13: 0.2 | BM13: 0.1 | BP13: 0.2 | BQ13: 326.5 | BS13: 5.6 | BT13: 32.6
A14: A01 | B14: Crop and animal production, hunting and related service activities | C14: ZA | D14: 61.7 | E14: 1.1 | F14: 0.1 | H14: 482.4 | I14: 6.8 | J14: 0.2 | K14: 0.4 | M14: 0.2 | N14: 11.1 | O14: 2 | P14: 6.7 | Q14: 0.2 | S14: 0.1 | T14: 0.1 | U14: 0.1 | V14: 0.1 | W14: 0.3 | Y14: 0.6 | AA14: 1.2 | AC14: 0.2 | AD14: 0.4 | AE14: 0.1 | AF14: 3.4 | AG14: 0.8 | AH14: 0.2 | AI14: 0.4 | AJ14: 0.1 | AK14: 0.2 | AM14: 22.7 | AO14: 0.2 | AP14: 0.1 | AQ14: 0.5 | AU14: 0.1 | AV14: 0.3 | AW14: 0.1 | AX14: 0.2 | AY14: 0.1 | AZ14: 0.2 | BA14: 0.2 | BC14: 1.5 | BD14: 4.5 | BE14: 3.7 | BF14: 0.9 | BG14: 2.8 | BH14: 2.6 | BI14: 0.5 | BJ14: 0.6 | BK14: 0.2 | BM14: 0.4 | BP14: 1.4 | BQ14: 340.5 | BS14: 8.3 | BT14: 28.9
A15: A01 | B15: Crop and animal production, hunting and related service activities | C15: CA | D15: 97.5 | E15: 0.6 | F15: 0.1 | H15: 692.6 | I15: 17.1 | J15: 0.4 | K15: 0.8 | L15: 0.1 | M15: 2.1 | N15: 17.5 | O15: 5 | P15: 12.1 | Q15: 0.3 | R15: 1.2 | S15: 0.4 | T15: 0.2 | U15: 0.3 | V15: 0.4 | W15: 0.7 | X15: 0.5 | Y15: 1.1 | Z15: 0.2 | AA15: 1.4 | AC15: 0.3 | AD15: 1 | AE15: 0.2 | AF15: 8.6 | AG15: 0.8 | AH15: 1.1 | AI15: 0.1 | AJ15: 0.1 | AK15: 0.8 | AM15: 16.6 | AN15: 0.1 | AO15: 0.1 | AQ15: 0.2 | AU15: 0.1 | AV15: 0.4 | AW15: 0.1 | AX15: 0.2 | AY15: 0.1 | AZ15: 0.1 | BA15: 0.1 | BD15: 1.8 | BE15: 1.3 | BF15: 0.7 | BG15: 2.4 | BH15: 1.5 | BI15: 0.2 | BJ15: 0.1 | BK15: 0.1 | BM15: 0.2 | BP15: 7.4 | BQ15: 423.4 | BS15: 16.9 | BT15: 81.4
A16: A01 | B16: Crop and animal production, hunting and related service activities | C16: US | D16: 214.4 | E16: 3.2 | F16: 3.8 | H16: 2287.3 | I16: 24.1 | J16: 3.8 | K16: 1.5 | N16: 24.1 | O16: 6 | P16: 28.4 | Q16: 0.1 | W16: 0.2 | Y16: 1.7 | AA16: 1.9 | AC16: 0.5 | AD16: 1 | AF16: 10.9 | AG16: 1.3 | AH16: 0.2 | AI16: 1.7 | AJ16: 0.1 | AK16: 0.2 | AM16: 65.4 | AO16: 0.7 | AR16: 0.1 | AU16: 0.1 | AV16: 0.5 | AX16: 0.4 | AY16: 0.1 | AZ16: 0.3 | BC16: 0.3 | BD16: 16.3 | BE16: 13.4 | BF16: 2.7 | BG16: 10.1 | BH16: 8.8 | BI16: 1.6 | BJ16: 0.3 | BK16: 0.7 | BM16: 1 | BP16: 8.5 | BQ16: 1453.3 | BS16: 47.7 | BT16: 150.1
A17: A01 | B17: Crop and animal production, hunting and related service activities | C17: MX | D17: 25.2 | E17: 0.3 | H17: 209.8 | I17: 2.3 | K17: 0.1 | N17: 4 | O17: 0.3 | P17: 2.1 | Y17: 0.2 | AA17: 0.2 | AF17: 0.8 | AG17: 0.1 | AI17: 0.1 | AM17: 6.5 | BD17: 1.6 | BE17: 0.8 | BF17: 0.2 | BG17: 0.7 | BH17: 0.8 | BI17: 0.1 | BM17: 0.1 | BP17: 0.2 | BQ17: 136.9 | BS17: 4.6 | BT17: 15.3
A18: A01 | B18: Crop and animal production, hunting and related service activities | C18: AR | D18: 18.8 | E18: 0.2 | H18: 145.3 | I18: 2.4 | K18: 0.1 | N18: 3 | O18: 0.3 | P18: 2.3 | Y18: 0.1 | AA18: 0.5 | AD18: 0.1 | AF18: 1 | AG18: 0.2 | AM18: 3.5 | BD18: 0.7 | BE18: 0.5 | BF18: 0.2 | BG18: 0.4 | BH18: 0.4 | BP18: 0.2 | BQ18: 93.4 | BS18: 3.6 | BT18: 12.9
A19: A01 | B19: Crop and animal production, hunting and related service activities | C19: BR | D19: 293.9 | E19: 3.4 | H19: 2824.8 | I19: 42 | J19: 12.4 | K19: 16.8 | M19: 2.9 | N19: 44.9 | O19: 6.3 | P19: 29.7 | Q19: 0.2 | R19: 0.5 | S19: 0.1 | V19: 0.1 | W19: 0.4 | Y19: 2.5 | Z19: 0.1 | AA19: 2.4 | AC19: 0.9 | AD19: 2.2 | AF19: 13.5 | AG19: 2.1 | AH19: 0.3 | AI19: 1.2 | AJ19: 0.1 | AK19: 0.3 | AM19: 65.9 | AO19: 0.1 | AQ19: 0.1 | AU19: 0.3 | AV19: 0.8 | AW19: 0.1 | AX19: 0.5 | AY19: 0.1 | AZ19: 0.3 | BC19: 0.1 | BD19: 13.4 | BE19: 11.6 | BF19: 4 | BG19: 9.8 | BH19: 8 | BI19: 1.1 | BJ19: 0.5 | BK19: 0.5 | BM19: 1 | BP19: 5.7 | BQ19: 1740.8 | BS19: 69.8 | BT19: 212.2
A20: A01 | B20: Crop and animal production, hunting and related service activities | C20: CN | D20: 88.9 | E20: 0.8 | H20: 775.9 | I20: 13.6 | J20: 0.1 | K20: 0.4 | N20: 5.7 | O20: 2.4 | P20: 10.5 | Q20: 0.1 | Y20: 0.9 | AA20: 1.9 | AC20: 0.2 | AD20: 0.3 | AF20: 4.5 | AG20: 0.7 | AH20: 0.2 | AI20: 0.3 | AK20: 0.1 | AM20: 14.7 | AU20: 0.1 | AV20: 0.2 | AX20: 0.2 | AY20: 0.1 | AZ20: 0.1 | BC20: 0.1 | BD20: 4.7 | BE20: 3.1 | BF20: 0.9 | BG20: 2.5 | BH20: 2.1 | BI20: 0.3 | BJ20: 0.1 | BK20: 0.2 | BM20: 0.3 | BP20: 1.9 | BQ20: 474 | BS20: 15.9 | BT20: 77
A21: A01 | B21: Crop and animal production, hunting and related service activities | C21: JP | D21: 1.3 | H21: 10.5 | I21: 0.1 | N21: 0.1 | O21: 0.1 | P21: 0.1 | AF21: 0.1 | AM21: 0.6 | BD21: 0.1 | BE21: 0.1 | BG21: 0.1 | BH21: 0.1 | BP21: 0.1 | BQ21: 7 | BS21: 0.1 | BT21: 0.8
A22: A01 | B22: Crop and animal production, hunting and related service activities | C22: KR | D22: 0.9 | H22: 6.8 | N22: 0.1 | P22: 0.1 | AF22: 0.1 | AM22: 0.3 | BD22: 0.1 | BQ22: 4.9 | BS22: 0.1 | BT22: 0.4
A23: A01 | B23: Crop and animal production, hunting and related service activities | C23: IN | D23: 22.2 | E23: 0.3 | H23: 178.1 | I23: 2.9 | K23: 0.1 | N23: 1.7 | O23: 0.5 | P23: 2.5 | Y23: 0.2 | AA23: 0.4 | AD23: 0.1 | AF23: 1.2 | AG23: 0.2 | AI23: 0.1 | AM23: 4.7 | BD23: 1.5 | BE23: 1.1 | BF23: 0.2 | BG23: 0.7 | BH23: 0.6 | BI23: 0.1 | BK23: 0.1 | BM23: 0.1 | BP23: 0.5 | BQ23: 123.5 | BS23: 3 | BT23: 16.6
A24: A01 | B24: Crop and animal production, hunting and related service activities | C24: ID | D24: 61.4 | E24: 0.6 | H24: 331.1 | I24: 4 | J24: 0.1 | K24: 0.2 | N24: 8.6 | O24: 0.8 | P24: 11.9 | Q24: 0.1 | Y24: 0.2 | AA24: 1.9 | AC24: 0.1 | AD24: 0.2 | AF24: 4 | AG24: 0.9 | AH24: 0.1 | AI24: 0.1 | AM24: 9.3 | AO24: 0.4 | AU24: 0.1 | AV24: 0.1 | AX24: 0.1 | AZ24: 0.1 | BD24: 2.4 | BE24: 1.5 | BF24: 0.5 | BG24: 1.2 | BH24: 0.8 | BI24: 0.2 | BJ24: 0.1 | BK24: 0.1 | BM24: 0.1 | BP24: 0.2 | BQ24: 264.2 | BS24: 10.8 | BT24: 24.6
A25: A01 | B25: Crop and animal production, hunting and related service activities | C25: SA | D25: 0.5 | H25: 4.2 | N25: 0.1 | P25: 0.2 | AF25: 0.1 | AM25: 0.1 | BQ25: 3.1 | BS25: 0.1 | BT25: 0.2
A26: A01 | B26: Crop and animal production, hunting and related service activities | C26: AU | D26: 49 | E26: 0.9 | H26: 429.8 | I26: 4.4 | J26: 0.1 | K26: 0.1 | M26: 0.5 | N26: 2.2 | O26: 0.6 | P26: 4.4 | Q26: 0.1 | R26: 0.3 | S26: 0.1 | V26: 0.1 | W26: 0.1 | Y26: 0.3 | AA26: 1.2 | AD26: 0.1 | AF26: 1 | AG26: 0.2 | AH26: 0.2 | AI26: 1.1 | AJ26: 0.1 | AK26: 0.3 | AM26: 10.8 | AU26: 0.1 | AV26: 0.1 | AX26: 0.1 | AZ26: 0.1 | BD26: 4.4 | BE26: 4.2 | BF26: 0.5 | BG26: 2.1 | BH26: 1.9 | BI26: 0.4 | BK26: 0.2 | BM26: 0.3 | BP26: 0.1 | BQ26: 387.6 | BS26: 7.9 | BT26: 50.3
A27: A01 | B27: Crop and animal production, hunting and related service activities | C27: WRL_REST | D27: 2715.4 | E27: 23.2 | F27: 1 | G27: 0.7 | H27: 16581.6 | I27: 204.2 | J27: 3.7 | K27: 10.4 | L27: 0.3 | M27: 5.5 | N27: 247.4 | O27: 32.9 | P27: 250.3 | Q27: 3.1 | R27: 1.4 | S27: 1.8 | T27: 0.7 | U27: 1.9 | V27: 2.4 | W27: 3.5 | X27: 0.5 | Y27: 13.6 | Z27: 0.6 | AA27: 56.8 | AB27: 0.3 | AC27: 4.8 | AD27: 12.9 | AE27: 0.7 | AF27: 174 | AG27: 34.8 | AH27: 5.6 | AI27: 7.6 | AJ27: 0.9 | AK27: 3.2 | AL27: 0.1 | AM27: 396.3 | AN27: 0.3 | AO27: 1.2 | AP27: 0.3 | AQ27: 1.1 | AR27: 0.3 | AS27: 0.2 | AT27: 0.3 | AU27: 4.5 | AV27: 4.3 | AW27: 0.6 | AX27: 5.2 | AY27: 2.5 | AZ27: 2.8 | BA27: 1 | BB27: 0.5 | BC27: 1.7 | BD27: 115.2 | BE27: 73.4 | BF27: 23.3 | BG27: 66.5 | BH27: 48 | BI27: 8.1 | BJ27: 3.6 | BK27: 4 | BM27: 6.6 | BP27: 22.3 | BQ27: 13251.8 | BS27: 453 | BT27: 1493.3
A28: A02 | B28: Forestry and logging | C28: EU27 | D28: 610.4 | E28: 14855.5 | F28: 34.1 | G28: 61.4 | H28: 498.2 | I28: 14.8 | J28: 16420.1 | K28: 6302.8 | L28: 9.7 | M28: 9.2 | N28: 254.8 | O28: 13.6 | P28: 59.7 | Q28: 32.7 | R28: 29.8 | S28: 32.3 | T28: 10.6 | U28: 15.8 | V28: 22 | W28: 40.3 | X28: 7.4 | Y28: 799.8 | Z28: 5.4 | AA28: 1084 | AB28: 4.4 | AC28: 16.3 | AD28: 606.2 | AE28: 11.5 | AF28: 226.2 | AG28: 46.5 | AH28: 53.2 | AI28: 1.9 | AJ28: 3.4 | AK28: 25.9 | AL28: 1.7 | AM28: 75.1 | AN28: 2.6 | AO28: 4.6 | AP28: 3.7 | AQ28: 13.7 | AR28: 4.7 | AS28: 1.2 | AT28: 1.6 | AU28: 39.2 | AV28: 12.4 | AW28: 41.7 | AX28: 9.9 | AY28: 4.2 | AZ28: 5.4 | BA28: 3.8 | BB28: 2.2 | BC28: 2.3 | BD28: 135.4 | BE28: 231 | BF28: 25.8 | BG28: 39.7 | BH28: 14.2 | BI28: 23.7 | BJ28: 17.5 | BK28: 14.2 | BL28: 6.1 | BM28: 20.9 | BP28: 1215.7 | BQ28: 9779 | BR28: 7.9 | BS28: 443.1 | BT28: 5148.3
A29: A02 | B29: Forestry and logging | C29: NO | D29: 0.5 | E29: 42.2 | H29: 1.1 | J29: 126.1 | K29: 29.3 | N29: 1.1 | O29: 0.4 | P29: 0.2 | S29: 0.3 | Y29: 4.6 | AA29: 1.1 | AD29: 2 | AF29: 0.1 | AH29: 0.2 | AM29: 0.7 | AW29: 0.2 | BD29: 0.8 | BE29: 0.6 | BG29: 0.3 | BH29: 0.3 | BI29: 0.2 | BK29: 0.3 | BM29: 0.4 | BQ29: 32.2 | BT29: 3.6
A30: A02 | B30: Forestry and logging | C30: CH | D30: 0.3 | E30: 2.1 | H30: 2.1 | I30: 0.1 | J30: 32.8 | K30: 5.7 | N30: 1.8 | O30: 0.1 | P30: 0.2 | Q30: 0.1 | R30: 0.1 | S30: 0.1 | V30: 0.1 | W30: 0.1 | Y30: 0.7 | AA30: 1.1 | AD30: 0.7 | AF30: 0.5 | AG30: 0.1 | AH30: 0.1 | AJ30: 0.1 | AM30: 0.2 | AQ30: 0.1 | AW30: 0.1 | BD30: 0.3 | BE30: 0.4 | BG30: 0.1 | BH30: 0.1 | BI30: 0.1 | BJ30: 0.1 | BK30: 0.1 | BM30: 0.1 | BQ30: 16.9 | BS30: 0.1 | BT30: 2.5
A31: A02 | B31: Forestry and logging | C31: UK | D31: 1 | E31: 1.7 | H31: 0.5 | I31: 0.1 | J31: 11.3 | K31: 1.6 | N31: 0.3 | O31: 0.3 | P31: 0.2 | S31: 0.1 | T31: 0.1 | U31: 0.1 | V31: 0.1 | W31: 0.1 | Y31: 0.5 | AA31: 0.3 | AD31: 1.9 | AF31: 0.6 | AG31: 0.1 | AH31: 0.1 | AJ31: 0.4 | AM31: 0.1 | AN31: 0.1 | AO31: 0.1 | AQ31: 0.5 | AV31: 0.1 | BA31: 0.1 | BC31: 0.1 | BD31: 0.1 | BE31: 0.5 | BG31: 0.1 | BI31: 0.2 | BQ31: 6 | BS31: 0.2 | BT31: 0.7
A32: A02 | B32: Forestry and logging | C32: ME | J32: 0.4 | Y32: 0.2 | AD32: 0.3 | BQ32: 0.2 | BS32: 0.1 | BT32: 0.1
A33: A02 | B33: Forestry and logging | C33: MK | E33: 0.1 | J33: 0.8 | K33: 0.1 | BE33: 0.1 | BQ33: 0.2 | BS33: 0.2
A34: A02 | B34: Forestry and logging | C34: AL
A35: A02 | B35: Forestry and logging | C35: RS | E35: 0.3 | H35: 0.1 | J35: 1.9 | K35: 0.3 | N35: 0.1 | Y35: 0.2 | AA35: 0.1 | AD35: 0.1 | AF35: 0.1 | BE35: 0.1 | BQ35: 0.9 | BT35: 0.2
A36: A02 | B36: Forestry and logging | C36: TR | E36: 0.3 | H36: 0.1 | J36: 2.1 | K36: 0.3 | N36: 0.1 | Y36: 0.1 | AA36: 0.1 | AD36: 0.1 | BE36: 0.1 | BI36: 0.1 | BQ36: 1.2
A37: A02 | B37: Forestry and logging | C37: RU | D37: 0.6 | E37: 4.4 | G37: 0.1 | H37: 1.8 | I37: 0.1 | J37: 34.2 | K37: 22.7 | M37: 2.3 | N37: 0.6 | O37: 0.1 | P37: 1.4 | Q37: 0.2 | R37: 0.6 | S37: 0.3 | T37: 0.1 | U37: 0.1 | V37: 0.2 | W37: 0.2 | X37: 0.1 | Y37: 2.7 | Z37: 0.1 | AA37: 2.3 | AD37: 4.2 | AF37: 0.5 | AG37: 0.2 | AH37: 0.1 | AI37: 0.1 | AJ37: 0.1 | AK37: 0.2 | AM37: 0.2 | AQ37: 0.1 | AU37: 0.2 | AV37: 0.1 | AW37: 0.1 | BD37: 0.2 | BE37: 0.4 | BF37: 0.1 | BG37: 0.1 | BI37: 0.2 | BM37: 0.1 | BQ37: 8.3 | BS37: 0.6 | BT37: 3.7
A38: A02 | B38: Forestry and logging | C38: ZA | E38: 0.2 | J38: 2 | K38: 0.3 | P38: 0.1 | Y38: 0.1 | AA38: 0.1 | BE38: 0.2 | BI38: 0.1 | BQ38: 0.6 | BT38: -0.1
A39: A02 | B39: Forestry and logging | C39: CA | D39: 10.8 | E39: 0.7 | H39: 76.2 | I39: 1.9 | J39: 6.3 | K39: 0.6 | N39: 1.5 | O39: 0.6 | P39: 1.4 | S39: 0.1 | T39: 0.1 | V39: 0.1 | W39: 0.1 | Y39: 0.3 | AA39: 0.1 | AD39: 0.6 | AF39: 1.1 | AG39: 0.1 | AJ39: 0.1 | AK39: 0.1 | AM39: 1.5 | AN39: 0.1 | AQ39: 0.4 | AV39: 0.3 | AW39: 0.1 | AX39: 0.1 | BA39: 0.1 | BD39: 0.4 | BE39: 0.9 | BF39: 0.1 | BG39: 0.3 | BH39: 0.2 | BI39: 0.4 | BP39: 0.8 | BQ39: 45.6 | BS39: 2.2 | BT39: 9.2
A40: A02 | B40: Forestry and logging | C40: US | D40: 2.7 | E40: 4 | H40: 2.1 | J40: 49.8 | K40: 10.6 | N40: 1.8 | O40: 0.4 | P40: 0.5 | Q40: 0.1 | S40: 0.1 | Y40: 1.4 | AA40: 1 | AD40: 5.1 | AF40: 0.4 | AG40: 0.1 | AH40: 0.1 | AJ40: 0.2 | AM40: 0.2 | AW40: 0.1 | BD40: 0.4 | BE40: 1.6 | BG40: 0.1 | BH40: 0.1 | BI40: 0.8 | BK40: 0.1 | BM40: 0.1 | BQ40: 18.5 | BT40: 3.1
A41: A02 | B41: Forestry and logging | C41: MX | E41: 0.3 | J41: 3.1 | K41: 0.2 | P41: 0.1 | BE41: 0.5 | BI41: 0.3 | BQ41: 0.2 | BT41: -0.1
A42: A02 | B42: Forestry and logging | C42: AR | H42: 0.2 | J42: 0.7 | K42: 0.8 | N42: 0.1 | BQ42: 0.2
A43: A02 | B43: Forestry and logging | C43: BR | D43: 0.2 | E43: 0.6 | H43: 1.5 | J43: 87.1 | K43: 111.9 | M43: 0.1 | N43: 19.8 | P43: 0.1 | Y43: 2 | AA43: 0.3 | AD43: 0.5 | AF43: 0.3 | AG43: 1.2 | AJ43: 0.1 | AM43: 0.2 | BD43: 0.1 | BE43: 0.2 | BI43: 0.1 | BQ43: 6.2 | BT43: 0.4
A44: A02 | B44: Forestry and logging | C44: CN | D44: 0.2 | E44: 1.8 | H44: 0.3 | J44: 9.4 | K44: 1.8 | N44: 0.3 | P44: 0.1 | Y44: 0.5 | AA44: 0.4 | AD44: 0.4 | AF44: 0.1 | AJ44: 0.1 | AM44: 0.1 | BD44: 0.1 | BE44: 0.4 | BI44: 0.2 | BQ44: 6.1
A45: A02 | B45: Forestry and logging | C45: JP | E45: 0.2 | H45: 0.1 | J45: 1 | K45: 0.2 | Y45: 0.1 | AD45: 0.1 | BQ45: 0.7 | BT45: -0.1
A46: A02 | B46: Forestry and logging | C46: KR | D46: 0.2 | E46: 1.6 | H46: 0.3 | J46: 6.6 | K46: 1.3 | N46: 0.2 | P46: 0.1 | Y46: 0.4 | AA46: 0.4 | AD46: 0.4 | AF46: 0.1 | AJ46: 0.2 | AM46: 0.1 | BD46: 0.1 | BE46: 0.2 | BI46: 0.1 | BQ46: 4 | BT46: 0.6
A47: A02 | B47: Forestry and logging | C47: IN | D47: 0.9 | E47: 5.7 | H47: 1.2 | J47: 34 | K47: 5.5 | N47: 1 | O47: 0.1 | P47: 0.4 | S47: 0.1 | Y47: 1.9 | AA47: 1.5 | AD47: 1.5 | AF47: 0.2 | AJ47: 0.2 | AM47: 0.3 | AW47: 0.1 | BD47: 0.5 | BE47: 1.4 | BG47: 0.2 | BH47: 0.2 | BI47: 0.6 | BK47: 0.2 | BM47: 0.2 | BQ47: 21.9 | BT47: 3.2
A48: A02 | B48: Forestry and logging | C48: ID | E48: 0.2 | H48: 0.1 | J48: 2.1 | K48: 0.8 | N48: 0.1 | Y48: 0.1 | BQ48: 1.2 | BT48: 0.1
A49: A02 | B49: Forestry and logging | C49: SA
A50: A02 | B50: Forestry and logging | C50: AU | D50: 0.3 | E50: 0.6 | H50: 0.1 | J50: 4.6 | K50: 0.5 | N50: 0.1 | P50: 0.1 | Y50: 0.1 | AA50: 0.1 | AD50: 0.6 | BE50: 0.3 | BI50: 0.2 | BQ50: 1.6 | BT50: 0.4
A51: A02 | B51: Forestry and logging | C51: WRL_REST | D51: 3.6 | E51: 28.8 | G51: 0.4 | H51: 9.3 | I51: 0.1 | J51: 170.2 | K51: 40.6 | L51: 0.1 | M51: 0.1 | N51: 6.2 | O51: 0.7 | P51: 2.4 | Q51: 0.2 | R51: 0.3 | S51: 0.4 | T51: 0.1 | U51: 0.1 | V51: 0.1 | W51: 0.3 | X51: 0.1 | Y51: 8.5 | AA51: 4.2 | AB51: 0.1 | AC51: 0.1 | AD51: 8.2 | AF51: 1.4 | AG51: 0.6 | AH51: 0.4 | AI51: 0.1 | AJ51: 1.9 | AK51: 0.1 | AM51: 1.5 | AO51: 0.1 | AQ51: 0.2 | AR51: 0.1 | AU51: 0.1 | AV51: 0.2 | AW51: 0.5 | AX51: 0.1 | BD51: 1.5 | BE51: 8 | BF51: 0.2 | BG51: 1 | BH51: 0.4 | BI51: 3.3 | BJ51: 0.2 | BK51: 0.5 | BM51: 0.5 | BQ51: 131.7 | BS51: 0.4 | BT51: 30.4
A52: A03 | B52: Fishing and aquaculture | C52: EU27 | D52: 40 | E52: 2.2 | F52: 427.2 | G52: 0.8 | H52: 2985.3 | I52: 5.8 | J52: 1.8 | K52: 1.4 | L52: 0.5 | M52: 2 | N52: 19.4 | O52: 9 | P52: 1.6 | Q52: 1.5 | R52: 1 | S52: 2.5 | T52: 1 | U52: 1.4 | V52: 1.9 | W52: 1.8 | X52: 0.7 | Y52: 5.4 | Z52: 1.3 | AA52: 28.9 | AB52: 0.3 | AC52: 2.7 | AD52: 38.5 | AE52: 1 | AF52: 33.5 | AG52: 8.2 | AH52: 3.3 | AI52: 7.3 | AJ52: 0.9 | AK52: 5 | AL52: 0.2 | AM52: 1596.4 | AN52: 0.5 | AO52: 2.8 | AP52: 1.8 | AQ52: 4.9 | AR52: 1.8 | AS52: 0.8 | AT52: 0.5 | AU52: 3.4 | AV52: 3.9 | AW52: 1.9 | AX52: 1.7 | AY52: 0.9 | AZ52: 2.1 | BA52: 3.1 | BB52: 0.3 | BC52: 0.5 | BD52: 5.4 | BE52: 17.2 | BF52: 8.4 | BG52: 40.9 | BH52: 34.8 | BI52: 6.8 | BJ52: 9.2 | BK52: 32.2 | BL52: 0.1 | BM52: 1.2 | BP52: 18 | BQ52: 7586.4 | BR52: 2.3 | BS52: 75.6 | BT52: 176.6
A53: A03 | B53: Fishing and aquaculture | C53: NO | D53: 8.8 | E53: 0.8 | F53: 19.1 | G53: 0.2 | H53: 2722.8 | I53: 0.1 | J53: 0.2 | N53: 21.3 | O53: 57.5 | T53: 0.2 | V53: 0.1 | W53: 0.1 | Y53: 0.5 | AA53: 0.1 | AB53: 0.1 | AC53: 0.3 | AD53: 4.9 | AE53: 0.5 | AF53: 5.9 | AG53: 19.3 | AH53: 1.2 | AI53: 1.9 | AK53: 9.5 | AM53: 686.2 | AO53: 0.1 | AP53: 1.2 | AQ53: 6.8 | AR53: 0.6 | AS53: 0.8 | AT53: 0.3 | AU53: 2.2 | AV53: 8.9 | AW53: 2.3 | AX53: 1.9 | AY53: 0.8 | AZ53: 0.9 | BA53: 6.4 | BB53: 0.1 | BC53: 0.1 | BD53: 13.4 | BE53: 4.3 | BF53: 7.3 | BG53: 22 | BH53: 28.1 | BI53: 14.6 | BJ53: 12.5 | BK53: 1.8 | BM53: 0.2 | BQ53: 1820.4 | BS53: 3.6 | BT53: -32.5
A54: A03 | B54: Fishing and aquaculture | C54: CH | F54: 0.3 | H54: 7.2 | AM54: 2.5 | BG54: 0.2 | BH54: 0.2 | BQ54: 7.6 | BS54: 0.1 | BT54: -4.6
A55: A03 | B55: Fishing and aquaculture | C55: UK | D55: 0.3 | E55: 0.1 | F55: 6.1 | H55: 236.2 | I55: 0.6 | M55: 0.2 | N55: 1 | O55: 0.2 | R55: 0.1 | S55: 0.1 | T55: 0.1 | U55: 0.1 | V55: 0.1 | W55: 0.1 | Y55: 0.1 | AA55: 2.3 | AC55: 0.1 | AD55: 5 | AF55: 0.6 | AG55: 0.1 | AH55: 0.1 | AI55: 1.2 | AK55: 0.2 | AM55: 105.7 | AN55: 0.1 | AO55: 0.3 | AP55: 0.1 | AQ55: 0.2 | AV55: 0.1 | AX55: 0.1 | BC55: 0.1 | BD55: 0.2 | BE55: 0.1 | BG55: 1.1 | BH55: 0.9 | BI55: 0.2 | BJ55: 0.8 | BK55: 3 | BQ55: 204.1 | BS55: 1.2 | BT55: 3.3
A56: A03 | B56: Fishing and aquaculture | C56: ME
A57: A03 | B57: Fishing and aquaculture | C57: MK | H57: 0.1 | AM57: 0.1 | BQ57: 0.2
A58: A03 | B58: Fishing and aquaculture | C58: AL | H58: 2.6 | AF58: 0.1 | AM58: 0.2 | BQ58: 6.4 | BS58: 0.3 | BT58: -0.1
A59: A03 | B59: Fishing and aquaculture | C59: RS | H59: 0.4 | AM59: 0.2 | BQ59: 0.6 | BT59: -0.5
A60: A03 | B60: Fishing and aquaculture | C60: TR | F60: 1.7 | H60: 21.6 | Y60: 0.1 | AF60: 0.2 | AM60: 6.9 | BG60: 0.3 | BH60: 0.3 | BK60: 0.1 | BQ60: 78.8 | BS60: 1 | BT60: -2
A61: A03 | B61: Fishing and aquaculture | C61: RU | D61: 0.7 | F61: 0.4 | H61: 14.7 | I61: 0.1 | J61: 0.1 | K61: 0.1 | M61: 3.9 | N61: 1.5 | O61: 0.3 | P61: 0.1 | Q61: 0.1 | R61: 1 | S61: 0.2 | T61: 0.1 | U61: 0.1 | V61: 0.2 | W61: 0.1 | Y61: 0.1 | AA61: 0.6 | AC61: 0.1 | AD61: 0.3 | AF61: 0.8 | AG61: 0.3 | AH61: 0.4 | AI61: 2.6 | AJ61: 0.1 | AK61: 0.6 | AM61: 4.8 | AN61: 0.1 | AQ61: 0.2 | AV61: 0.1 | BA61: 0.1 | BD61: 0.1 | BE61: 0.1 | BF61: 0.1 | BG61: 0.5 | BH61: 0.3 | BI61: 0.1 | BK61: 0.1 | BQ61: 25.3 | BS61: 0.1 | BT61: 0.6
A62: A03 | B62: Fishing and aquaculture | C62: ZA | D62: 0.2 | H62: 3.4 | N62: 0.2 | O62: 0.1 | AF62: 0.1 | AM62: 0.9 | BG62: 0.1 | BH62: 0.1 | BQ62: 8.3 | BT62: -2
A63: A03 | B63: Fishing and aquaculture | C63: CA | F63: 0.3 | H63: 10.7 | AD63: 0.1 | AF63: 0.1 | AM63: 4.4 | BG63: 0.2 | BH63: 0.1 | BK63: 0.1 | BQ63: 29.1 | BS63: 0.4 | BT63: -0.7
A64: A03 | B64: Fishing and aquaculture | C64: US | D64: 0.4 | F64: 9.5 | H64: 177.3 | I64: 0.1 | N64: 0.4 | O64: 0.3 | Y64: 0.2 | AA64: 0.2 | AD64: 0.6 | AF64: 0.7 | AG64: 0.1 | AI64: 0.4 | AK64: 0.1 | AM64: 35.9 | AR64: 0.1 | AV64: 0.1 | BD64: 0.1 | BE64: 0.1 | BF64: 0.1 | BG64: 2.6 | BH64: 2.2 | BI64: 0.4 | BJ64: 0.1 | BK64: 0.3 | BQ64: 164.2 | BS64: 3.3 | BT64: 2.4
A65: A03 | B65: Fishing and aquaculture | C65: MX | H65: 0.6 | AM65: 0.2 | BQ65: 0.6 | BS65: 0.1 | BT65: -0.8
A66: A03 | B66: Fishing and aquaculture | C66: AR | D66: 0.1 | F66: 2.1 | H66: 47.8 | N66: 0.1 | AA66: 0.1 | AD66: 0.2 | AF66: 0.4 | AI66: 0.1 | AM66: 15.1 | BF66: 0.1 | BG66: 0.9 | BH66: 0.8 | BI66: 0.2 | BK66: 0.1 | BQ66: 60.6 | BS66: 0.1 | BT66: 1.8
A67: A03 | B67: Fishing and aquaculture | C67: BR | F67: 0.2 | H67: 5 | AM67: 1.6 | BG67: 0.1 | BH67: 0.1 | BQ67: 5.1
A68: A03 | B68: Fishing and aquaculture | C68: CN | F68: 0.8 | H68: 21.9 | N68: 0.1 | AD68: 0.1 | AF68: 0.1 | AM68: 6.4 | BG68: 0.4 | BH68: 0.3 | BI68: 0.1 | BK68: 0.1 | BQ68: 21.9 | BS68: 0.2 | BT68: -3
A69: A03 | B69: Fishing and aquaculture | C69: JP | F69: 0.1 | H69: 3.2 | AM69: 1 | BG69: 0.1 | BH69: 0.1 | BQ69: 3.1 | BT69: -6.4
A70: A03 | B70: Fishing and aquaculture | C70: KR | F70: 0.1 | H70: 3.5 | AM70: 0.9 | BG70: 0.1 | BH70: 0.1 | BQ70: 3.2 | BT70: -1.3
A71: A03 | B71: Fishing and aquaculture | C71: IN | F71: 1 | H71: 22.4 | N71: 0.1 | O71: 0.1 | AD71: 0.1 | AF71: 0.1 | AI71: 0.1 | AM71: 6.7 | BG71: 0.6 | BH71: 0.5 | BI71: 0.1 | BK71: 0.1 | BQ71: 20.1 | BS71: 0.1 | BT71: -0.1
A72: A03 | B72: Fishing and aquaculture | C72: ID | F72: 0.3 | H72: 9.6 | AA72: 0.1 | AD72: 0.1 | AM72: 3.8 | BG72: 0.2 | BH72: 0.1 | BK72: 0.1 | BQ72: 12.7 | BS72: 0.1 | BT72: -0.4
A73: A03 | B73: Fishing and aquaculture | C73: SA | F73: 0.1 | H73: 1 | AM73: 0.2 | BQ73: 0.9
A74: A03 | B74: Fishing and aquaculture | C74: AU | F74: 0.1 | H74: 2.9 | AM74: 0.7 | BG74: 0.1 | BH74: 0.1 | BQ74: 3 | BS74: 0.1 | BT74: -0.8
A75: A03 | B75: Fishing and aquaculture | C75: WRL_REST | D75: 1.4 | F75: 19.9 | H75: 230 | I75: 0.3 | M75: 0.3 | N75: 1.2 | O75: 0.4 | R75: 0.1 | T75: 0.1 | V75: 0.1 | W75: 0.1 | Y75: 0.2 | AA75: 0.5 | AC75: 0.1 | AD75: 1 | AF75: 1 | AG75: 0.2 | AH75: 0.1 | AI75: 0.4 | AJ75: 0.1 | AK75: 0.1 | AM75: 53.5 | AO75: 0.1 | AP75: 0.1 | AQ75: 0.3 | AR75: 0.1 | AV75: 0.3 | AW75: 0.1 | AX75: 0.1 | BA75: 0.2 | BD75: 0.1 | BE75: 0.3 | BF75: 0.2 | BG75: 2.7 | BH75: 2.7 | BI75: 0.4 | BJ75: 0.2 | BK75: 0.7 | BM75: 0.1 | BQ75: 390.9 | BS75: 1.2 | BT75: -2.9
A76: B | B76: Mining and quarrying | C76: EU27 | D76: 983.2 | E76: 79.5 | F76: 46.3 | G76: 6092.1 | H76: 1375.6 | I76: 138.4 | J76: 116.5 | K76: 654.2 | L76: 51.5 | M76: 22698.5 | N76: 5494.9 | O76: 202.8 | P76: 446.1 | Q76: 10229.4 | R76: 10020.4 | S76: 2024.5 | T76: 172.5 | U76: 805.4 | V76: 810.1 | W76: 846.2 | X76: 194.2 | Y76: 531.2 | Z76: 182.5 | AA76: 15926.1 | AB76: 127.7 | AC76: 543.1 | AD76: 14358.9 | AE76: 90.3 | AF76: 911.6 | AG76: 295.6 | AH76: 437.5 | AI76: 55.3 | AJ76: 36.7 | AK76: 508.6 | AL76: 21.3 | AM76: 265.8 | AN76: 20.4 | AO76: 22.1 | AP76: 55.8 | AQ76: 165 | AR76: 58.1 | AS76: 15.4 | AT76: 35.8 | AU76: 509.2 | AV76: 355.5 | AW76: 244 | AX76: 82.1 | AY76: 34 | AZ76: 63.4 | BA76: 41.2 | BB76: 50.4 | BC76: 12.6 | BD76: 540.8 | BE76: 856.1 | BF76: 161.3 | BG76: 367.7 | BH76: 149.4 | BI76: 48 | BJ76: 71.7 | BK76: 78.9 | BL76: 6.9 | BM76: 70.2 | BP76: 353 | BQ76: 5107.9 | BR76: 4.8 | BS76: 2202.9 | BT76: 27.9
A77: B | B77: Mining and quarrying | C77: NO | D77: 338.3 | E77: 3.7 | F77: 1.6 | G77: 545.6 | H77: 885.1 | I77: 122.2 | J77: 19.6 | K77: 1039.8 | L77: 26.2 | M77: 68338.3 | N77: 6570.5 | O77: 102.8 | P77: 194.9 | Q77: 1797.6 | R77: 15209.8 | S77: 302 | T77: 38.6 | U77: 110.4 | V77: 390.5 | W77: 126.4 | X77: 66.9 | Y77: 362.8 | Z77: 38 | AA77: 17956 | AB77: 14.6 | AC77: 70.5 | AD77: 1716.9 | AE77: 15.3 | AF77: 550.4 | AG77: 131.9 | AH77: 185.9 | AI77: 97.9 | AJ77: 69.3 | AK77: 155.5 | AL77: 9.2 | AM77: 143.2 | AN77: 4.5 | AO77: 5 | AP77: 13.3 | AQ77: 26.8 | AR77: 6.3 | AS77: 1.5 | AT77: 3.8 | AU77: 68.6 | AV77: 231.1 | AW77: 50.6 | AX77: 12.5 | AY77: 2.3 | AZ77: 3.7 | BA77: 20.2 | BB77: 4.1 | BC77: 1.2 | BD77: 121.9 | BE77: 218 | BF77: 43.4 | BG77: 194.5 | BH77: 96.2 | BI77: 12 | BJ77: 15.3 | BK77: 13.3 | BL77: 0.9 | BM77: 35.7 | BP77: 61.3 | BQ77: 6424.8 | BS77: 133.2 | BT77: 4486.4
A78: B | B78: Mining and quarrying | C78: CH | M78: 5 | N78: 0.2 | Q78: 0.1 | R78: 0.9 | AA78: 3.1 | AD78: 0.1 | BQ78: 0.4 | BS78: 0.2 | BT78: -0.2
A79: B | B79: Mining and quarrying | C79: UK | D79: 125.2 | E79: 0.8 | F79: 0.3 | G79: 126.5 | H79: 293 | I79: 16 | J79: 7 | K79: 105.1 | L79: 2.2 | M79: 15927.2 | N79: 1330 | O79: 101.6 | P79: 27.7 | Q79: 416 | R79: 3487.7 | S79: 46.1 | T79: 17 | U79: 25.8 | V79: 102.6 | W79: 35.2 | X79: 21.9 | Y79: 162.2 | Z79: 8.3 | AA79: 5018.4 | AB79: 2.4 | AC79: 21.2 | AD79: 504.3 | AE79: 7.8 | AF79: 86.3 | AG79: 50.5 | AH79: 23.5 | AI79: 1.8 | AJ79: 2.9 | AK79: 23.2 | AL79: 3.7 | AM79: 37.3 | AN79: 6.4 | AO79: 2.7 | AP79: 11.1 | AQ79: 25.9 | AR79: 4.8 | AS79: 3.9 | AT79: 5.3 | AU79: 28.4 | AV79: 106.8 | AW79: 24.9 | AX79: 6 | AY79: 2.3 | AZ79: 2.1 | BA79: 6.9 | BB79: 2.2 | BC79: 1.7 | BD79: 44.2 | BE79: 80.1 | BF79: 15.7 | BG79: 52.1 | BH79: 33.2 | BI79: 5.5 | BJ79: 5.3 | BK79: 6 | BL79: 0.8 | BM79: 15.6 | BP79: 26.4 | BQ79: 1200.2 | BS79: 109.2 | BT79: 970
A80: B | B80: Mining and quarrying | C80: ME | G80: 0.1 | H80: 0.1 | K80: 0.2 | M80: 13.3 | N80: 0.5 | Q80: 0.7 | R80: 3.1 | AA80: 4.3 | AD80: 0.3 | BQ80: 0.1 | BS80: 0.1 | BT80: 0.3
A81: B | B81: Mining and quarrying | C81: MK | D81: 0.6 | G81: 0.2 | H81: 2.3 | I81: 0.4 | J81: 0.3 | K81: 1.4 | M81: 33.7 | N81: 7.1 | O81: 2.4 | P81: 0.3 | Q81: 6 | R81: 41.6 | S81: 0.9 | T81: 0.1 | U81: 0.6 | V81: 0.6 | W81: 0.5 | X81: 0.1 | Y81: 0.1 | AA81: 64.8 | AC81: 0.1 | AD81: 3 | AF81: 0.3 | AG81: 0.1 | AH81: 0.3 | AK81: 0.1 | AM81: 0.1 | AU81: 0.1 | AX81: 0.1 | BG81: 0.5 | BP81: 0.1 | BQ81: 2.1 | BS81: 0.5 | BT81: 29
A82: B | B82: Mining and quarrying | C82: AL | G82: 0.1 | H82: 0.3 | I82: 0.1 | K82: 0.2 | M82: 47.3 | N82: 0.8 | O82: 0.1 | P82: 0.1 | Q82: 2.7 | R82: 10.1 | S82: 0.1 | U82: 0.1 | V82: 0.1 | W82: 0.1 | X82: 0.1 | AA82: 15.6 | AD82: 0.7 | AF82: 0.2 | AH82: 0.1 | BE82: 0.1 | BG82: 0.1 | BQ82: 1.8 | BT82: 1.2
A83: B | B83: Mining and quarrying | C83: RS | D83: 0.3 | G83: 0.4 | H83: 1.1 | I83: 0.2 | J83: 0.1 | K83: 1.5 | M83: 78.5 | N83: 4.7 | O83: 1.3 | P83: 0.2 | Q83: 5.3 | R83: 28.7 | S83: 0.3 | T83: 0.2 | U83: 0.3 | V83: 0.3 | W83: 0.6 | Y83: 0.1 | AA83: 43.9 | AC83: 0.1 | AD83: 1.7 | AF83: 0.4 | AG83: 0.2 | AH83: 0.2 | AK83: 0.1 | AM83: 0.1 | AQ83: 0.3 | AV83: 0.2 | AW83: 0.1 | AX83: 0.9 | BE83: 0.1 | BF83: 0.1 | BG83: 0.2 | BP83: 0.3 | BQ83: 1.2 | BS83: 9.2 | BT83: 13.9
A84: B | B84: Mining and quarrying | C84: TR | D84: 1.8 | F84: 0.3 | G84: 3.7 | H84: 23.6 | I84: 1.2 | J84: 0.6 | K84: 3.9 | L84: 0.2 | M84: 1356 | N84: 24.6 | O84: 3.4 | P84: 1.6 | Q84: 40.2 | R84: 182.4 | S84: 2.7 | T84: 0.7 | U84: 1.7 | V84: 5.4 | W84: 2.7 | X84: 0.7 | Y84: 0.8 | Z84: 0.5 | AA84: 429.6 | AB84: 0.2 | AC84: 1 | AD84: 21.7 | AE84: 0.3 | AF84: 3.4 | AG84: 1.6 | AH84: 1.8 | AI84: 2.2 | AJ84: 0.2 | AK84: 4.2 | AL84: 0.1 | AM84: 1.3 | AN84: 0.1 | AO84: 0.1 | AP84: 0.2 | AQ84: 0.6 | AR84: 0.1 | AS84: 0.1 | AT84: 0.1 | AU84: 0.8 | AV84: 1.5 | AW84: 4.2 | AX84: 0.1 | AY84: 0.1 | AZ84: 0.1 | BA84: 0.2 | BC84: 0.1 | BD84: 0.8 | BE84: 1.9 | BF84: 0.3 | BG84: 2.3 | BH84: 0.8 | BI84: 0.1 | BJ84: 0.1 | BK84: 0.1 | BM84: 0.2 | BP84: 0.7 | BQ84: 44.4 | BS84: 4.1 | BT84: 100
A85: B | B85: Mining and quarrying | C85: RU | D85: 260.5 | E85: 8.2 | F85: 2.4 | G85: 154.7 | H85: 392.4 | I85: 66.1 | J85: 19.3 | K85: 253.2 | L85: 15.5 | M85: 20252.7 | N85: 2568.3 | O85: 84.2 | P85: 129 | Q85: 801.3 | R85: 4471.3 | S85: 172.1 | T85: 29.3 | U85: 83.2 | V85: 154.6 | W85: 81.8 | X85: 34.1 | Y85: 40.3 | Z85: 13.4 | AA85: 12196.6 | AB85: 11.2 | AC85: 38.6 | AD85: 557.7 | AE85: 24.5 | AF85: 262.3 | AG85: 91.2 | AH85: 331.1 | AI85: 300.8 | AJ85: 136.4 | AK85: 98.9 | AL85: 9.4 | AM85: 79.9 | AN85: 1.7 | AO85: 9.3 | AP85: 8.2 | AQ85: 13.9 | AR85: 5.1 | AS85: 3.7 | AT85: 2.4 | AU85: 22.8 | AV85: 120.1 | AW85: 32.2 | AX85: 8.2 | AY85: 3.2 | AZ85: 4.7 | BA85: 19.5 | BB85: 2.8 | BC85: 1.2 | BD85: 39.8 | BE85: 106.5 | BF85: 43.9 | BG85: 92.4 | BH85: 33.3 | BI85: 8.2 | BJ85: 10.6 | BK85: 9.7 | BL85: 1 | BM85: 11.5 | BP85: 17 | BQ85: 3839.6 | BS85: 22.1 | BT85: 3840.8
A86: B | B86: Mining and quarrying | C86: ZA | D86: 6.9 | E86: 0.1 | G86: 14.1 | H86: 39.6 | I86: 4.1 | J86: 1.6 | K86: 18.8 | L86: 0.9 | M86: 2412.6 | N86: 155.5 | O86: 9 | P86: 18.5 | Q86: 67.2 | R86: 1346.2 | S86: 320.4 | T86: 19.8 | U86: 104.2 | V86: 192.5 | W86: 151.5 | X86: 19.8 | Y86: 48.4 | Z86: 18.4 | AA86: 832.4 | AB86: 0.8 | AC86: 7.6 | AD86: 98 | AE86: 1.2 | AF86: 15.3 | AG86: 10.7 | AH86: 5.8 | AI86: 0.1 | AJ86: 0.2 | AK86: 5.1 | AL86: 0.5 | AM86: 3.2 | AN86: 0.1 | AO86: 0.3 | AP86: 0.7 | AQ86: 0.6 | AR86: 0.2 | AT86: 0.2 | AU86: 1.2 | AV86: 1.1 | AW86: 3.5 | AX86: 0.5 | AY86: 0.3 | AZ86: 0.2 | BA86: 0.4 | BB86: 0.1 | BD86: 4.4 | BE86: 13.5 | BF86: 1 | BG86: 12.1 | BH86: 6.4 | BI86: 0.6 | BJ86: 0.3 | BK86: 0.2 | BL86: 0.2 | BM86: 0.7 | BP86: 5.8 | BQ86: 323.4 | BS86: 19.1 | BT86: 205.4
A87: B | B87: Mining and quarrying | C87: CA | D87: 13.4 | E87: 0.2 | F87: 0.1 | G87: 11.4 | H87: 28.6 | I87: 3.6 | J87: 1.3 | K87: 20.4 | L87: 0.7 | M87: 2394.8 | N87: 193.3 | O87: 10.1 | P87: 19.1 | Q87: 71.3 | R87: 603.7 | S87: 34.2 | T87: 4.6 | U87: 11 | V87: 29.9 | W87: 16.3 | X87: 4.4 | Y87: 14 | Z87: 3.1 | AA87: 797.6 | AB87: 0.3 | AC87: 3 | AD87: 47.3 | AE87: 1.4 | AF87: 16 | AG87: 7.5 | AH87: 5.4 | AI87: 3 | AJ87: 3.5 | AK87: 3.5 | AL87: 0.7 | AM87: 4 | AN87: 1.5 | AO87: 0.8 | AP87: 1 | AQ87: 7.1 | AR87: 1.2 | AS87: 1 | AT87: 0.9 | AU87: 2.9 | AV87: 14.7 | AW87: 3.5 | AX87: 1.8 | AY87: 0.6 | AZ87: 0.6 | BA87: 2.4 | BB87: 0.5 | BC87: 0.6 | BD87: 7.2 | BE87: 10.7 | BF87: 1.6 | BG87: 10.4 | BH87: 5 | BI87: 1.1 | BJ87: 0.5 | BK87: 0.8 | BL87: 0.1 | BM87: 1.7 | BP87: 3.7 | BQ87: 185.9 | BS87: 11.2 | BT87: 186.8
A88: B | B88: Mining and quarrying | C88: US | D88: 184.8 | E88: 1.7 | F88: 3.1 | G88: 182.3 | H88: 311.7 | I88: 28.2 | J88: 5.7 | K88: 111.3 | L88: 6.1 | M88: 22867.6 | N88: 1326.1 | O88: 48.7 | P88: 41.4 | Q88: 596.2 | R88: 3324.7 | S88: 73.5 | T88: 15.1 | U88: 25.2 | V88: 90.9 | W88: 31.9 | X88: 33.5 | Y88: 26 | Z88: 9.2 | AA88: 9305.4 | AB88: 4 | AC88: 19.6 | AD88: 459.7 | AE88: 9.3 | AF88: 116.5 | AG88: 38.6 | AH88: 83.8 | AI88: 86.9 | AJ88: 52.9 | AK88: 48.7 | AL88: 5.3 | AM88: 61.5 | AN88: 8.7 | AO88: 1.7 | AP88: 5.2 | AQ88: 25.6 | AR88: 2.4 | AS88: 1.4 | AT88: 2.2 | AU88: 12.7 | AV88: 188.5 | AW88: 57.7 | AX88: 6.1 | AY88: 1.2 | AZ88: 1.5 | BA88: 8.2 | BB88: 2.5 | BC88: 0.4 | BD88: 33.1 | BE88: 75.2 | BF88: 20 | BG88: 54.4 | BH88: 32.4 | BI88: 4.9 | BJ88: 6.6 | BK88: 10.6 | BL88: 0.4 | BM88: 7 | BP88: 20.4 | BQ88: 1781.3 | BR88: 0.1 | BS88: 65.4 | BT88: 1115.3
A89: B | B89: Mining and quarrying | C89: MX | D89: 0.7 | G89: 3.4 | H89: 3.9 | I89: 0.8 | J89: 0.2 | K89: 2.8 | L89: 0.2 | M89: 1074.8 | N89: 17.8 | O89: 0.9 | P89: 0.5 | Q89: 52.7 | R89: 225.2 | S89: 1.2 | T89: 0.2 | U89: 0.4 | V89: 1.9 | W89: 0.7 | X89: 0.2 | Y89: 0.8 | Z89: 0.1 | AA89: 331 | AB89: 0.1 | AC89: 0.5 | AD89: 7.6 | AE89: 0.1 | AF89: 2.9 | AG89: 0.6 | AH89: 1 | AK89: 0.5 | AM89: 0.6 | AQ89: 0.1 | AU89: 0.2 | AV89: 0.2 | AW89: 0.1 | BD89: 0.2 | BE89: 1.6 | BF89: 0.2 | BG89: 1.1 | BH89: 0.4 | BJ89: 0.1 | BM89: 0.1 | BP89: 0.3 | BQ89: 36.3 | BS89: 0.3 | BT89: 24.6
A90: B | B90: Mining and quarrying | C90: AR | D90: 2.3 | G90: 1.7 | H90: 2.1 | I90: 0.3 | K90: 1 | L90: 0.1 | M90: 116.9 | N90: 11 | O90: 0.2 | P90: 0.1 | Q90: 2 | R90: 14.4 | S90: 0.5 | T90: 0.1 | U90: 0.1 | V90: 0.4 | W90: 0.2 | X90: 0.5 | Y90: 0.3 | AA90: 15.8 | AC90: 0.1 | AD90: 3.1 | AE90: 0.1 | AF90: 1.1 | AG90: 0.2 | AH90: 0.3 | AK90: 0.2 | AL90: 0.1 | AM90: 0.8 | AQ90: 0.1 | AU90: 0.2 | AV90: 3.3 | AW90: 0.6 | BD90: 0.2 | BE90: 0.5 | BF90: 0.3 | BG90: 0.4 | BH90: 0.3 | BI90: 0.1 | BJ90: 0.1 | BK90: 0.2 | BM90: 0.1 | BP90: 0.1 | BQ90: 15.9 | BS90: 0.7 | BT90: 2.8
A91: B | B91: Mining and quarrying | C91: BR | D91: 20.7 | E91: 0.1 | F91: 0.1 | G91: 28.7 | H91: 33.7 | I91: 3.8 | J91: 0.8 | K91: 22.5 | L91: 0.8 | M91: 4936.5 | N91: 175.3 | O91: 5.2 | P91: 3.9 | Q91: 147.4 | R91: 713.7 | S91: 12.2 | T91: 1.2 | U91: 4.4 | V91: 14.4 | W91: 4.5 | X91: 4.5 | Y91: 4.1 | Z91: 0.9 | AA91: 1577.8 | AB91: 0.6 | AC91: 2.2 | AD91: 63.5 | AE91: 0.8 | AF91: 13.6 | AG91: 4.9 | AH91: 4.6 | AI91: 0.2 | AJ91: 0.2 | AK91: 3.6 | AL91: 0.6 | AM91: 7.6 | AN91: 0.1 | AO91: 0.1 | AP91: 0.5 | AQ91: 0.3 | AR91: 0.3 | AS91: 0.2 | AT91: 0.2 | AU91: 2 | AV91: 24.6 | AW91: 4.8 | AX91: 0.6 | AY91: 0.1 | AZ91: 0.1 | BA91: 0.4 | BB91: 0.2 | BD91: 2.8 | BE91: 9.8 | BF91: 2.6 | BG91: 7.2 | BH91: 4.4 | BI91: 0.6 | BJ91: 0.8 | BK91: 1.3 | BM91: 0.9 | BP91: 2.6 | BQ91: 233 | BS91: 11.4 | BT91: 156.6
A92: B | B92: Mining and quarrying | C92: CN | D92: 1.1 | G92: 1.9 | H92: 3.8 | I92: 0.6 | J92: 0.1 | K92: 2.7 | L92: 0.2 | M92: 241.4 | N92: 13.8 | O92: 0.5 | P92: 0.6 | Q92: 10.8 | R92: 50 | S92: 1.2 | T92: 0.2 | U92: 0.5 | V92: 1.6 | W92: 0.5 | X92: 0.2 | Y92: 0.4 | Z92: 0.1 | AA92: 100.8 | AB92: 0.1 | AC92: 0.3 | AD92: 13.6 | AE92: 0.1 | AF92: 2.2 | AG92: 0.6 | AH92: 0.8 | AJ92: 0.3 | AK92: 0.6 | AM92: 0.7 | AP92: 0.1 | AQ92: 0.1 | AU92: 0.2 | AV92: 0.9 | AW92: 0.4 | AX92: 0.1 | BD92: 0.4 | BE92: 0.9 | BF92: 0.3 | BG92: 0.9 | BH92: 0.4 | BI92: 0.1 | BJ92: 0.1 | BK92: 0.1 | BM92: 0.1 | BP92: 0.3 | BQ92: 32.9 | BS92: 0.5 | BT92: 12.6
A93: B | B93: Mining and quarrying | C93: JP | D93: 0.2 | G93: 0.4 | H93: 0.3 | K93: 0.1 | M93: 45.4 | N93: 1.6 | O93: 0.1 | P93: 0.1 | Q93: 1.7 | R93: 7.5 | S93: 0.1 | U93: 0.1 | V93: 0.1 | W93: 0.1 | AA93: 17.1 | AD93: 0.6 | AF93: 0.1 | AG93: 0.1 | AH93: 0.1 | AV93: 0.1 | BE93: 0.1 | BG93: 0.1 | BQ93: 2.2 | BS93: 0.2 | BT93: 3.8
A94: B | B94: Mining and quarrying | C94: KR | H94: 0.1 | M94: 3.7 | N94: 0.3 | P94: 0.1 | Q94: 0.3 | R94: 0.6 | U94: 0.1 | V94: 0.1 | W94: 0.1 | AA94: 1.3 | AD94: 0.3 | AF94: 0.1 | AI94: 0.1 | AJ94: 0.1 | BQ94: 0.2 | BS94: 0.1 | BT94: -0.3
A95: B | B95: Mining and quarrying | C95: IN | D95: 0.3 | G95: 0.7 | H95: 2 | I95: 0.2 | K95: 0.9 | M95: 69 | N95: 5.7 | O95: 0.2 | P95: 0.2 | Q95: 2.5 | R95: 14.3 | S95: 0.3 | U95: 0.1 | V95: 0.3 | W95: 0.1 | X95: 0.1 | Y95: 0.3 | AA95: 32.3 | AC95: 0.1 | AD95: 1.7 | AF95: 0.6 | AG95: 0.1 | AH95: 0.3 | AK95: 0.3 | AM95: 0.2 | AU95: 0.1 | AV95: 0.3 | AW95: 0.3 | BD95: 0.1 | BE95: 0.2 | BF95: 0.1 | BG95: 0.2 | BH95: 0.1 | BQ95: 8.3 | BS95: 0.1 | BT95: 2.7
A96: B | B96: Mining and quarrying | C96: ID | D96: 3.8 | E96: 0.1 | F96: 0.1 | G96: 8.5 | H96: 14.9 | I96: 2.4 | J96: 0.7 | K96: 10 | L96: 0.5 | M96: 822 | N96: 45.5 | O96: 4.3 | P96: 2.3 | Q96: 42.7 | R96: 188.8 | S96: 5 | T96: 0.6 | U96: 2.5 | V96: 4.7 | W96: 1.8 | X96: 0.6 | Y96: 0.9 | Z96: 0.2 | AA96: 354.1 | AB96: 0.4 | AC96: 1.1 | AD96: 18.6 | AE96: 0.4 | AF96: 7.5 | AG96: 2.1 | AH96: 3.4 | AI96: 0.1 | AJ96: 0.1 | AK96: 2.1 | AL96: 0.1 | AM96: 2.5 | AP96: 0.2 | AQ96: 0.1 | AR96: 0.1 | AU96: 0.6 | AV96: 2.2 | AW96: 1.6 | AX96: 0.3 | BD96: 0.6 | BE96: 2.3 | BF96: 1.1 | BG96: 3 | BH96: 0.9 | BI96: 0.2 | BJ96: 0.3 | BK96: 0.2 | BM96: 0.4 | BP96: 0.6 | BQ96: 96.2 | BS96: 0.3 | BT96: 60
A97: B | B97: Mining and quarrying | C97: SA | D97: 104.1 | E97: 1.3 | F97: 0.3 | G97: 158.2 | H97: 115.5 | I97: 21.9 | J97: 2.7 | K97: 68.1 | L97: 5 | M97: 13344.7 | N97: 766.1 | O97: 12.6 | P97: 19.1 | Q97: 368.1 | R97: 1526.8 | S97: 51.2 | T97: 4 | U97: 25.5 | V97: 33 | W97: 14.5 | X97: 16.9 | Y97: 8.3 | Z97: 3.7 | AA97: 4056.3 | AB97: 3 | AC97: 10.4 | AD97: 241.2 | AE97: 3.5 | AF97: 75.7 | AG97: 12.5 | AH97: 37.2 | AI97: 0.1 | AJ97: 0.7 | AK97: 14.9 | AL97: 1.8 | AM97: 35.8 | AN97: 0.1 | AO97: 0.3 | AP97: 1.8 | AQ97: 1.3 | AR97: 1.4 | AS97: 0.4 | AT97: 0.6 | AU97: 5.6 | AV97: 95 | AW97: 16.7 | AX97: 3.1 | AY97: 0.3 | AZ97: 0.6 | BA97: 2.3 | BB97: 1 | BC97: 0.1 | BD97: 20.6 | BE97: 29.8 | BF97: 11.2 | BG97: 23.8 | BH97: 12.3 | BI97: 2.3 | BJ97: 3.4 | BK97: 5.3 | BL97: 0.1 | BM97: 3.2 | BP97: 4.7 | BQ97: 1124.6 | BS97: 12.4 | BT97: 409.3
A98: B | B98: Mining and quarrying | C98: AU | D98: 8.4 | E98: 0.3 | F98: 0.1 | G98: 23.9 | H98: 27.4 | I98: 3.1 | J98: 0.5 | K98: 26.4 | L98: 0.7 | M98: 2879.8 | N98: 165.2 | O98: 3 | P98: 6.6 | Q98: 83.1 | R98: 598 | S98: 11.6 | T98: 1.6 | U98: 6.2 | V98: 21.7 | W98: 4.8 | X98: 1.7 | Y98: 4.5 | Z98: 1.1 | AA98: 1132.6 | AB98: 0.7 | AC98: 2.1 | AD98: 45.6 | AE98: 0.6 | AF98: 11.9 | AG98: 8.6 | AH98: 4.2 | AI98: 2.6 | AJ98: 0.3 | AK98: 4.2 | AL98: 0.5 | AM98: 3.9 | AN98: 0.3 | AO98: 0.2 | AP98: 0.3 | AQ98: 1 | AR98: 0.2 | AS98: 0.1 | AT98: 0.1 | AU98: 1.2 | AV98: 4 | AW98: 2 | AX98: 0.5 | AY98: 0.1 | AZ98: 0.1 | BA98: 0.1 | BB98: 0.1 | BD98: 2.9 | BE98: 10.6 | BF98: 1.8 | BG98: 8.7 | BH98: 4.9 | BI98: 0.5 | BJ98: 0.5 | BK98: 0.4 | BM98: 0.9 | BP98: 4 | BQ98: 248.4 | BS98: 1.9 | BT98: 204.2
A99: B | B99: Mining and quarrying | C99: WRL_REST | D99: 744.9 | E99: 3.2 | F99: 7 | G99: 755 | H99: 2112.1 | I99: 449.2 | J99: 63 | K99: 1437.6 | L99: 114.4 | M99: 139180.8 | N99: 7377.2 | O99: 351.2 | P99: 300.2 | Q99: 4919.1 | R99: 22424.4 | S99: 744.2 | T99: 85.8 | U99: 212.7 | V99: 645.9 | W99: 303.7 | X99: 143.8 | Y99: 210.8 | Z99: 42.6 | AA99: 51623.9 | AB99: 58.5 | AC99: 149.5 | AD99: 2249.7 | AE99: 44.2 | AF99: 1694 | AG99: 226 | AH99: 599.4 | AI99: 7.8 | AJ99: 22.8 | AK99: 339.1 | AL99: 16.8 | AM99: 459.6 | AN99: 2.5 | AO99: 5.7 | AP99: 32.5 | AQ99: 29.7 | AR99: 25 | AS99: 3.6 | AT99: 7.5 | AU99: 89.5 | AV99: 607.1 | AW99: 164.4 | AX99: 36.1 | AY99: 2.9 | AZ99: 10 | BA99: 11.3 | BB99: 8.3 | BC99: 2.5 | BD99: 132.7 | BE99: 375.7 | BF99: 160.6 | BG99: 492.9 | BH99: 153.4 | BI99: 23.3 | BJ99: 47 | BK99: 34.8 | BL99: 2.5 | BM99: 53.7 | BP99: 68.9 | BQ99: 19945.4 | BS99: 399.2 | BT99: 6436.6
A100: C10-12 | B100: Manufacture of food products | C100: EU27 | D100: 56635.5 | E100: 169.1 | F100: 618.4 | G100: 278.8 | H100: 222061.1 | I100: 1992.5 | J100: 395.3 | K100: 991.5 | L100: 155.4 | M100: 1167.4 | N100: 11852.3 | O100: 3460.5 | P100: 1431.4 | Q100: 780.5 | R100: 1190 | S100: 851.7 | T100: 654.6 | U100: 647 | V100: 1065.1 | W100: 1283 | X100: 328.4 | Y100: 1031.4 | Z100: 374.5 | AA100: 2066.7 | AB100: 128 | AC100: 1026.4 | AD100: 3539.1 | AE100: 754.4 | AF100: 14268 | AG100: 7131.7 | AH100: 1785.9 | AI100: 772.7 | AJ100: 479.5 | AK100: 1374.8 | AL100: 157.1 | AM100: 105908.1 | AN100: 445.2 | AO100: 584.3 | AP100: 655.5 | AQ100: 2007.1 | AR100: 516.8 | AS100: 229.6 | AT100: 334.8 | AU100: 1169.6 | AV100: 2498.9 | AW100: 754.8 | AX100: 915.2 | AY100: 549.8 | AZ100: 656.7 | BA100: 846.4 | BB100: 253.5 | BC100: 373.8 | BD100: 2085.2 | BE100: 6521 | BF100: 5787 | BG100: 12764.3 | BH100: 8145.5 | BI100: 959 | BJ100: 2495 | BK100: 1331.6 | BL100: 97 | BM100: 478.9 | BP100: 1968.2 | BQ100: 590479.6 | BR100: 237.5 | BS100: 4054.8 | BT100: 31041.5
...

Sheet FIGARO exports raw
A1: FIGARO raw extra-EU exports — EU-27 exports by supplying industry × destination partner, € million, split into deliveries to the partners' intermediate use and to their final demand (figaro-global-flows.json, same naio_10_fcp_ii4 extract). The IO model sheet derives each industry's total extra-EU exports from the two 2023 blocks by formula.
A3: 2023 · deliveries to partners' intermediate use
A4: Industry | B4: Label | C4: NO | D4: CH | E4: UK | F4: ME | G4: MK | H4: AL | I4: RS | J4: TR | K4: RU | L4: ZA | M4: CA | N4: US | O4: MX | P4: AR | Q4: BR | R4: CN | S4: JP | T4: KR | U4: IN | V4: ID | W4: SA | X4: AU | Y4: WRL_REST
A5: A01 | B5: Crop and animal production, hunting and related service activities | C5: 506.3 | D5: 1801 | E5: 1179 | F5: 14.9 | G5: 22.2 | H5: 28.1 | I5: 180.8 | J5: 969.1 | K5: 442.1 | L5: 183.8 | M5: 251.1 | N5: 773.8 | O5: 142.4 | P5: 18.9 | Q5: 190.7 | R5: 1464.7 | S5: 255.3 | T5: 353.9 | U5: 144.3 | V5: 127.9 | W5: 225.7 | X5: 95.9 | Y5: 8466.2
A6: A02 | B6: Forestry and logging | C6: 41.1 | D6: 79.6 | E6: 137.5 | F6: 0.4 | G6: 0.7 | H6: 0.5 | I6: 7.1 | J6: 32.3 | K6: 10 | L6: 3.1 | M6: 15.2 | N6: 178.1 | O6: 14.1 | P6: 1.9 | Q6: 7.9 | R6: 1364.1 | S6: 15.8 | T6: 20.2 | U6: 20.9 | V6: 5.6 | W6: 15.7 | X6: 7.3 | Y6: 327.9
A7: A03 | B7: Fishing and aquaculture | C7: 39.4 | D7: 45.2 | E7: 15.6 | F7: 0.5 | G7: 1.3 | H7: 1 | I7: 7.6 | J7: 3.1 | K7: 12.9 | L7: 0.8 | M7: 21.3 | N7: 159.4 | O7: 0.3 | P7: 0.3 | Q7: 1.3 | R7: 46.6 | S7: 31.3 | T7: 6 | U7: 3.9 | V7: 0.5 | W7: 0.5 | X7: 5 | Y7: 175.4
A8: B | B8: Mining and quarrying | C8: 534.4 | D8: 381.6 | E8: 365.7 | F8: 1.3 | G8: 20.5 | H8: 3.9 | I8: 135.3 | J8: 755.9 | K8: 82.5 | L8: 72.4 | M8: 298.6 | N8: 463.8 | O8: 74.3 | P8: 8.7 | Q8: 40.5 | R8: 1161.4 | S8: 53.7 | T8: 95.5 | U8: 216.8 | V8: 11.4 | W8: 76.9 | X8: 79.3 | Y8: 2726
A9: C10-12 | B9: Manufacture of food products | C9: 1918.9 | D9: 4189.2 | E9: 5400.8 | F9: 51.2 | G9: 67.4 | H9: 74.4 | I9: 404.7 | J9: 2179.8 | K9: 832.9 | L9: 310.2 | M9: 1610.3 | N9: 8562.6 | O9: 435.1 | P9: 51.7 | Q9: 617.8 | R9: 5728.9 | S9: 2884.6 | T9: 2151.7 | U9: 404.1 | V9: 215.7 | W9: 590.2 | X9: 1296.8 | Y9: 19629.2
A10: C13-15 | B10: Manufacture of textiles, wearing apparel, leather and related products | C10: 164.6 | D10: 1606.6 | E10: 291.3 | F10: 5.1 | G10: 74.5 | H10: 40 | I10: 148.6 | J10: 1181.9 | K10: 125.6 | L10: 34.6 | M10: 350.3 | N10: 917.9 | O10: 424.2 | P10: 24.3 | Q10: 89.7 | R10: 8378.1 | S10: 1502.7 | T10: 1543.9 | U10: 234 | V10: 128.5 | W10: 128.3 | X10: 223.1 | Y10: 9423.6
A11: C16 | B11: Manufacture of wood and of products of wood and cork, except furniture | C11: 1734.3 | D11: 1693 | E11: 2794.6 | F11: 18.5 | G11: 20.4 | H11: 32.3 | I11: 223.4 | J11: 441 | K11: 440.5 | L11: 60.4 | M11: 402.9 | N11: 3017.3 | O11: 251.4 | P11: 59.7 | Q11: 130.7 | R11: 2256.2 | S11: 917.3 | T11: 353.4 | U11: 442.3 | V11: 52.4 | W11: 347 | X11: 396.7 | Y11: 5542.6
A12: C17 | B12: Manufacture of paper and paper products | C12: 1048.7 | D12: 2738.2 | E12: 3231.6 | F12: 13.2 | G12: 52.4 | H12: 52.7 | I12: 530.1 | J12: 2904.1 | K12: 657.9 | L12: 290 | M12: 487 | N12: 3859.9 | O12: 603.3 | P12: 78.7 | Q12: 330.5 | R12: 5001 | S12: 464.5 | T12: 354.3 | U12: 1167.6 | V12: 302.4 | W12: 140.5 | X12: 336.7 | Y12: 9676.6
A13: C18 | B13: Printing and reproduction of recorded media | C13: 109.4 | D13: 277 | E13: 496.1 | F13: 1.4 | G13: 4.4 | H13: 7.9 | I13: 34.3 | J13: 115.3 | K13: 105 | L13: 16 | M13: 75.2 | N13: 461.5 | O13: 61.8 | P13: 9.4 | Q13: 70 | R13: 230.7 | S13: 88.5 | T13: 69.4 | U13: 109.8 | V13: 14.5 | W13: 32.5 | X13: 52.9 | Y13: 960.1
A14: C19 | B14: Manufacture of coke and refined petroleum products | C14: 5032.4 | D14: 2655.1 | E14: 2611.7 | F14: 101.9 | G14: 472 | H14: 78.5 | I14: 511.8 | J14: 2124.5 | K14: 567 | L14: 608.1 | M14: 1516.8 | N14: 10094.1 | O14: 475.2 | P14: 313.1 | Q14: 1368.7 | R14: 2311.1 | S14: 578.6 | T14: 1053.6 | U14: 911 | V14: 124.5 | W14: 1291.4 | X14: 241.2 | Y14: 36553.9
A15: C20 | B15: Manufacture of chemicals and chemical products | C15: 2001.4 | D15: 8340.6 | E15: 9099.1 | F15: 22.5 | G15: 312.8 | H15: 72.9 | I15: 1203.3 | J15: 10616.6 | K15: 2831.2 | L15: 1468 | M15: 2890.2 | N15: 23339.6 | O15: 2873.5 | P15: 727.5 | Q15: 3658.6 | R15: 21243.7 | S15: 4038.4 | T15: 3748.3 | U15: 5069.3 | V15: 908.9 | W15: 1421.6 | X15: 1114.3 | Y15: 43487.9
A16: C21 | B16: Manufacture of basic pharmaceutical products and pharmaceutical prepa… | C16: 972.8 | D16: 16434.8 | E16: 5166.1 | F16: 12.6 | G16: 35.7 | H16: 20.3 | I16: 329.2 | J16: 876.8 | K16: 2133.4 | L16: 190.3 | M16: 4489.4 | N16: 32554.9 | O16: 868.5 | P16: 178 | Q16: 744.1 | R16: 4181.2 | S16: 1414 | T16: 2092.2 | U16: 1217.8 | V16: 149.4 | W16: 209.2 | X16: 500.5 | Y16: 11415.9
... A60: Q86 | B60: Human health activities | C60: 34.2 | D60: 176.4 | E60: 200.3 | F60: 2.9 | G60: 0.7 | H60: 0.2 | I60: 11.4 | J60: 28.6 | K60: 14.7 | L60: 6 | M60: 32.4 | N60: 99.8 | O60: 9.4 | P60: 2.1 | Q60: 15.9 | R60: 67.8 | S60: 13.2 | T60: 21.6 | U60: 17.7 | V60: 1.9 | W60: 4.3 | X60: 8.2 | Y60: 161.9
A61: Q87_88 | B61: Residential care activities and social work activities without accomm… | C61: 10.6 | D61: 17.9 | E61: 36 | G61: 0.1 | H61: 0.1 | I61: 0.9 | J61: 5 | K61: 4.4 | L61: 1.1 | M61: 6.6 | N61: 45.7 | O61: 4.5 | P61: 0.7 | Q61: 3.7 | R61: 22.7 | S61: 4.3 | T61: 6.2 | U61: 5.3 | V61: 0.9 | W61: 1.6 | X61: 3.5 | Y61: 58.4
A62: R90-92 | B62: Creative, arts and entertainment activities | C62: 30.2 | D62: 120.8 | E62: 182.2 | F62: 1.3 | G62: 1.5 | H62: 0.3 | I62: 10.1 | J62: 19.9 | K62: 25.4 | L62: 8.1 | M62: 165.4 | N62: 931.1 | O62: 29.3 | P62: 5.7 | Q62: 27.2 | R62: 60 | S62: 41.7 | T62: 30.5 | U62: 50.3 | V62: 4.1 | W62: 14 | X62: 16.5 | Y62: 476.7
A63: R93 | B63: Sports activities and amusement and recreation activities | C63: 12.8 | D63: 39.8 | E63: 96 | F63: 1 | G63: 0.6 | H63: 0.5 | I63: 5.3 | J63: 15.1 | K63: 14.6 | L63: 1.5 | M63: 16.6 | N63: 134.1 | O63: 7.7 | P63: 2.5 | Q63: 10.3 | R63: 30.4 | S63: 11 | T63: 10 | U63: 15 | V63: 1.9 | W63: 6.6 | X63: 7.9 | Y63: 115.8
A64: S94 | B64: Activities of membership organisations | C64: 14.1 | D64: 48 | E64: 75.9 | F64: 0.3 | G64: 0.4 | H64: 0.2 | I64: 4.8 | J64: 15.3 | K64: 8.5 | L64: 2.8 | M64: 10.3 | N64: 98.4 | O64: 12.9 | P64: 4.1 | Q64: 10.2 | R64: 21.5 | S64: 9.7 | T64: 10.1 | U64: 11.2 | V64: 1.5 | W64: 2.6 | X64: 4.4 | Y64: 100
A65: S95 | B65: Repair of computers and personal and household goods | C65: 7.3 | D65: 15.7 | E65: 53.2 | F65: 0.1 | G65: 0.1 | H65: 0.2 | I65: 1.5 | J65: 10.2 | K65: 10.3 | L65: 1.3 | M65: 10.3 | N65: 138 | O65: 4.6 | P65: 1.2 | Q65: 6.2 | R65: 22.9 | S65: 3.3 | T65: 11.1 | U65: 4.6 | V65: 0.7 | W65: 1.4 | X65: 2.5 | Y65: 49.2
A66: S96 | B66: Other personal service activities | C66: 6.9 | D66: 16.1 | E66: 137 | F66: 0.5 | G66: 1.2 | H66: 0.1 | I66: 3.8 | J66: 19.8 | K66: 25.4 | L66: 1 | M66: 39.3 | N66: 251.3 | O66: 3.5 | P66: 2.3 | Q66: 18.7 | R66: 23.2 | S66: 5.8 | T66: 5.7 | U66: 5.9 | V66: 0.7 | W66: 1.9 | X66: 2.8 | Y66: 56
A67: T | B67: Activities of households as employers | J67: 0.1 | N67: 0.2 | R67: 0.1 | Y67: 0.8
A68: U | B68: Activities of extraterritorial organisations and bodies
A71: 2023 · deliveries to partners' final demand
A72: Industry | B72: Label | C72: NO | D72: CH | E72: UK | F72: ME | G72: MK | H72: AL | I72: RS | J72: TR | K72: RU | L72: ZA | M72: CA | N72: US | O72: MX | P72: AR | Q72: BR | R72: CN | S72: JP | T72: KR | U72: IN | V72: ID | W72: SA | X72: AU | Y72: WRL_REST
A73: A01 | B73: Crop and animal production, hunting and related service activities | C73: 447.9 | D73: 845.4 | E73: 6174.6 | F73: 27.1 | G73: 19.9 | H73: 55 | I73: 231.4 | J73: 99.5 | K73: 385.4 | L73: 132.3 | M73: 258.3 | N73: 1349.3 | O73: 77.6 | P73: 11.5 | Q73: 92 | R73: 1156.7 | S73: 226.1 | T73: 117.2 | U73: 137.8 | V73: 130 | W73: 825.6 | X73: 81.2 | Y73: 9205.5
A74: A02 | B74: Forestry and logging | C74: 16.5 | D74: 16.8 | E74: 7.2 | F74: 0.1 | G74: 2 | H74: 0.3 | I74: 0.5 | J74: 2 | K74: 17.2 | L74: 2.1 | M74: 0.6 | N74: 4.2 | O74: 4.3 | P74: 1.6 | Q74: 3.5 | R74: 15.9 | S74: 11.8 | T74: 1.3 | U74: 14 | V74: 1.2 | W74: 2.2 | X74: 2 | Y74: 134.5
A75: A03 | B75: Fishing and aquaculture | C75: -17.1 | D75: 58.5 | E75: 87.4 | F75: 2.5 | G75: 1.1 | H75: 7.4 | I75: 5.3 | J75: 3.3 | K75: 4.4 | L75: 2.4 | M75: 12 | N75: 53.8 | O75: 7.8 | P75: 0.6 | Q75: 4.7 | R75: 57.5 | S75: 13.2 | T75: 1 | U75: 7.7 | V75: 2.2 | W75: 18.4 | X75: 5.6 | Y75: 290.1
A76: B | B76: Mining and quarrying | C76: -80.4 | D76: 72.7 | E76: 30.9 | F76: 0.2 | G76: 5.5 | H76: 0.4 | I76: 1.4 | J76: -7.7 | K76: 37.7 | L76: -3.5 | M76: 40.2 | N76: 38.7 | O76: 10.3 | P76: 1 | Q76: -19.6 | R76: 40.3 | S76: 10.7 | T76: 3.8 | U76: 5.8 | V76: 2.7 | W76: 16.8 | X76: 16 | Y76: 254.6
A77: C10-12 | B77: Manufacture of food products | C77: 1952.3 | D77: 4537.7 | E77: 32322.5 | F77: 210.5 | G77: 273.4 | H77: 453.1 | I77: 1268.3 | J77: 679.6 | K77: 1303.7 | L77: 1052.7 | M77: 2642.9 | N77: 15535.7 | O77: 989.7 | P77: 138.1 | Q77: 1201.3 | R77: 10606.3 | S77: 4120.3 | T77: 1413.4 | U77: 1057.4 | V77: 642.4 | W77: 2876.5 | X77: 1785.2 | Y77: 35160
A78: C13-15 | B78: Manufacture of textiles, wearing apparel, leather and related products | C78: 223.8 | D78: 1776.5 | E78: 4648.2 | F78: 22.3 | G78: 59.1 | H78: 325.5 | I78: 389.2 | J78: 649.5 | K78: 570.1 | L78: 165.4 | M78: 1043.2 | N78: 6864.7 | O78: 427 | P78: 35.1 | Q78: 187.5 | R78: 2649.3 | S78: 1228 | T78: 1551.7 | U78: 238.6 | V78: 67.6 | W78: 296.2 | X78: 536.1 | Y78: 10983.5
A79: C16 | B79: Manufacture of wood and of products of wood and cork, except furniture | C79: -86.2 | D79: 263.7 | E79: 966.4 | F79: 3.6 | G79: 23.5 | H79: 8.4 | I79: 10.4 | J79: 55.9 | K79: 118.1 | L79: 18.8 | M79: 66.9 | N79: 766.8 | O79: 66.3 | P79: 5.5 | Q79: 14.5 | R79: 288.4 | S79: 86.3 | T79: 46.5 | U79: 76.2 | V79: 14.9 | W79: 132.3 | X79: 49.1 | Y79: 2770
A80: C17 | B80: Manufacture of paper and paper products | C80: -18.6 | D80: 248.7 | E80: 2570.2 | F80: 7.6 | G80: 4.9 | H80: 30.1 | I80: 33.5 | J80: -318.6 | K80: 169.6 | L80: 102.9 | M80: 147.8 | N80: 570.9 | O80: 197.1 | P80: 46.1 | Q80: 57.4 | R80: 320.1 | S80: 67.7 | T80: 33.8 | U80: 69.9 | V80: 67.1 | W80: 362.1 | X80: 170.4 | Y80: 4278.7
A81: C18 | B81: Printing and reproduction of recorded media | C81: -433.1 | D81: 210.5 | E81: 195.5 | F81: 0.7 | G81: 0.5 | H81: 2 | I81: 3.2 | J81: 0.6 | K81: 20 | L81: 7.3 | M81: 17.3 | N81: 272.7 | O81: 38.7 | P81: 7 | Q81: -192.1 | R81: 238.1 | S81: 45.6 | T81: 17.4 | U81: 25.2 | V81: 13.8 | W81: 48.7 | X81: 26.9 | Y81: 737.5
A82: C19 | B82: Manufacture of coke and refined petroleum products | C82: 400.5 | D82: 5160.8 | E82: 5171.3 | F82: 67.6 | G82: 113.8 | H82: 50 | I82: 46.8 | J82: 298.2 | K82: 63.3 | L82: 192 | M82: 504.1 | N82: 2035.7 | O82: 211.3 | P82: 308.5 | Q82: 615 | R82: 336.5 | S82: 283.3 | T82: 53.2 | U82: 256.6 | V82: 29.4 | W82: 540.1 | X82: 124.6 | Y82: 19165.8
A83: C20 | B83: Manufacture of chemicals and chemical products | C83: 911.1 | D83: 1081.8 | E83: 5740.3 | F83: 51.3 | G83: 153.5 | H83: 139.9 | I83: 439.9 | J83: 607 | K83: 724.6 | L83: 386.4 | M83: 624.8 | N83: 7700 | O83: 1007.1 | P83: 232.9 | Q83: 977.3 | R83: 2641.4 | S83: 1334.4 | T83: 470 | U83: 539.3 | V83: 262.4 | W83: 803.4 | X83: 877.7 | Y83: 13051.2
A84: C21 | B84: Manufacture of basic pharmaceutical products and pharmaceutical prepa… | C84: 459.6 | D84: 1061.5 | E84: 4721 | F84: 39.8 | G84: 59.4 | H84: 50.6 | I84: 328.6 | J84: 1549.3 | K84: 1388.9 | L84: 473.8 | M84: 1777.4 | N84: 37903.6 | O84: 1828.6 | P84: 527.9 | Q84: 2422.9 | R84: 18675.8 | S84: 7547 | T84: 325.9 | U84: 411.9 | V84: 303.8 | W84: 2792.7 | X84: 2252.2 | Y84: 20172.9
... A134: S96 | B134: Other personal service activities | C134: 20.6 | D134: 363.2 | E134: 15.8 | F134: 0.1 | G134: 0.3 | H134: 0.9 | I134: 0.7 | J134: -2 | K134: 3.9 | L134: 8.8 | M134: 2 | N134: 33.7 | O134: 37.2 | P134: 0.6 | Q134: 3 | R134: 67 | S134: 54.7 | T134: 40.3 | U134: 30.8 | V134: 14.4 | W134: 8.1 | X134: 16.8 | Y134: 349.8
A135: T | B135: Activities of households as employers | E135: 0.2 | R135: 0.1 | Y135: 1.3
A136: U | B136: Activities of extraterritorial organisations and bodies
A139: 2022 · deliveries to partners' intermediate use
A140: Industry | B140: Label | C140: NO | D140: CH | E140: UK | F140: ME | G140: MK | H140: AL | I140: RS | J140: TR | K140: RU | L140: ZA | M140: CA | N140: US | O140: MX | P140: AR | Q140: BR | R140: CN | S140: JP | T140: KR | U140: IN | V140: ID | W140: SA | X140: AU | Y140: WRL_REST
A141: A01 | B141: Crop and animal production, hunting and related service activities | C141: 553.9 | D141: 1579 | E141: 1204.9 | F141: 10.5 | G141: 24.3 | H141: 36.8 | I141: 152.2 | J141: 855.5 | K141: 346.3 | L141: 108.4 | M141: 251.3 | N141: 797.2 | O141: 160.5 | P141: 22 | Q141: 166.6 | R141: 1013.8 | S141: 288.3 | T141: 272.7 | U141: 144.6 | V141: 90.2 | W141: 234.1 | X141: 87.7 | Y141: 9422.1
A142: A02 | B142: Forestry and logging | C142: 53.6 | D142: 57.2 | E142: 105.3 | F142: 0.3 | G142: 0.5 | H142: 0.8 | I142: 6.2 | J142: 24.6 | K142: 10.9 | L142: 2.1 | M142: 13.9 | N142: 167.7 | O142: 9.7 | P142: 1.7 | Q142: 6 | R142: 1630.7 | S142: 17.2 | T142: 24.7 | U142: 20.7 | V142: 7.6 | W142: 14.2 | X142: 7.2 | Y142: 365.5
A143: A03 | B143: Fishing and aquaculture | C143: 40.2 | D143: 37.5 | E143: 17.3 | F143: 0.3 | G143: 1.8 | H143: 1.6 | I143: 5.1 | J143: 3.5 | K143: 13.3 | L143: 0.9 | M143: 20.5 | N143: 123 | O143: 0.3 | P143: 0.4 | Q143: 1.4 | R143: 35.9 | S143: 16.1 | T143: 6.1 | U143: 4.5 | V143: 0.5 | W143: 0.6 | X143: 5.9 | Y143: 155.5
A144: B | B144: Mining and quarrying | C144: 665.9 | D144: 606.8 | E144: 336.8 | F144: 1.1 | G144: 8.8 | H144: 3.2 | I144: 221.6 | J144: 1078.9 | K144: 91.5 | L144: 20 | M144: 228.2 | N144: 585 | O144: 58.9 | P144: 10.8 | Q144: 56.6 | R144: 1649.3 | S144: 58.4 | T144: 83.2 | U144: 692.1 | V144: 8.3 | W144: 250.7 | X144: 75.3 | Y144: 2609.2
A145: C10-12 | B145: Manufacture of food products | C145: 2023.8 | D145: 3731.9 | E145: 5279.2 | F145: 35.8 | G145: 67.4 | H145: 75.8 | I145: 362.2 | J145: 1748.2 | K145: 972.1 | L145: 298.8 | M145: 1698.3 | N145: 8894.3 | O145: 430.2 | P145: 57.1 | Q145: 601.6 | R145: 5461.3 | S145: 3428 | T145: 2246.7 | U145: 367.3 | V145: 225 | W145: 584.2 | X145: 1328.8 | Y145: 19350.7
A146: C13-15 | B146: Manufacture of textiles, wearing apparel, leather and related products | C146: 172 | D146: 1431.3 | E146: 293 | F146: 4.1 | G146: 76 | H146: 49.8 | I146: 137.9 | J146: 1051.2 | K146: 239.4 | L146: 33.2 | M146: 367.6 | N146: 967.1 | O146: 456 | P146: 21.8 | Q146: 93.5 | R146: 7659.2 | S146: 1448 | T146: 1805.7 | U146: 222.6 | V146: 138.1 | W146: 145.2 | X146: 215.4 | Y146: 9017.5
A147: C16 | B147: Manufacture of wood and of products of wood and cork, except furniture | C147: 1931.8 | D147: 1560.2 | E147: 2671.9 | F147: 14.6 | G147: 17.8 | H147: 38.3 | I147: 216.7 | J147: 334.4 | K147: 328.9 | L147: 63.1 | M147: 389.9 | N147: 3341.3 | O147: 218.1 | P147: 61.1 | Q147: 110.4 | R147: 2000.3 | S147: 1954.7 | T147: 305.7 | U147: 356.2 | V147: 48 | W147: 384.1 | X147: 562.6 | Y147: 5240.3
A148: C17 | B148: Manufacture of paper and paper products | C148: 1114.1 | D148: 2497.4 | E148: 3315.5 | F148: 10.3 | G148: 62.8 | H148: 61.4 | I148: 554.6 | J148: 2568.4 | K148: 559.1 | L148: 311 | M148: 488.6 | N148: 4222.3 | O148: 714.5 | P148: 84.4 | Q148: 322.8 | R148: 3967.5 | S148: 485.9 | T148: 392.4 | U148: 1139.9 | V148: 268.3 | W148: 147.5 | X148: 334.5 | Y148: 9932.9
A149: C18 | B149: Printing and reproduction of recorded media | C149: 143.4 | D149: 250.5 | E149: 459.1 | F149: 1.1 | G149: 5 | H149: 9.3 | I149: 31.8 | J149: 97.3 | K149: 79.6 | L149: 16.6 | M149: 70.7 | N149: 436.9 | O149: 56.7 | P149: 9.2 | Q149: 62.4 | R149: 187.9 | S149: 91.6 | T149: 68.9 | U149: 108.1 | V149: 13.3 | W149: 29.3 | X149: 38.6 | Y149: 914.2
A150: C19 | B150: Manufacture of coke and refined petroleum products | C150: 6420.6 | D150: 2557.6 | E150: 3119.6 | F150: 146.7 | G150: 777.5 | H150: 98.1 | I150: 527.5 | J150: 2868.7 | K150: 557.1 | L150: 590.9 | M150: 1759.6 | N150: 10453.8 | O150: 1283.2 | P150: 390.1 | Q150: 1004.3 | R150: 2270.5 | S150: 675.5 | T150: 1292 | U150: 1649.9 | V150: 85.3 | W150: 1083.4 | X150: 173.1 | Y150: 38374.6
A151: C20 | B151: Manufacture of chemicals and chemical products | C151: 2159.8 | D151: 8221.3 | E151: 9303.9 | F151: 17 | G151: 235.5 | H151: 84.9 | I151: 1222.1 | J151: 10523.6 | K151: 2805.9 | L151: 1490.6 | M151: 3097.5 | N151: 25141.4 | O151: 2736.1 | P151: 799 | Q151: 3950.6 | R151: 21845.9 | S151: 4246.8 | T151: 4079.1 | U151: 5254 | V151: 873.3 | W151: 1333.5 | X151: 1094.2 | Y151: 45621.6
A152: C21 | B152: Manufacture of basic pharmaceutical products and pharmaceutical prepa… | C152: 1115.7 | D152: 14608.7 | E152: 5532.9 | F152: 9.7 | G152: 35.2 | H152: 19.6 | I152: 344.1 | J152: 913.6 | K152: 1788.2 | L152: 206.4 | M152: 4342.8 | N152: 37607.1 | O152: 865 | P152: 175.1 | Q152: 654.1 | R152: 4059.8 | S152: 1966.6 | T152: 2457.8 | U152: 1170.9 | V152: 144.6 | W152: 211.9 | X152: 568.8 | Y152: 11657.9
... A196: Q86 | B196: Human health activities | C196: 37 | D196: 150.6 | E196: 204.4 | F196: 2.7 | G196: 0.6 | H196: 0.2 | I196: 10.9 | J196: 22.7 | K196: 15.7 | L196: 5.2 | M196: 37.7 | N196: 95.8 | O196: 7.5 | P196: 1.9 | Q196: 16.8 | R196: 59.4 | S196: 13.9 | T196: 21.1 | U196: 15.9 | V196: 1.7 | W196: 4.1 | X196: 7.3 | Y196: 146.5
A197: Q87_88 | B197: Residential care activities and social work activities without accomm… | C197: 12.6 | D197: 15.7 | E197: 43.8 | G197: 0.1 | H197: 0.1 | I197: 0.8 | J197: 4.1 | K197: 4 | L197: 1 | M197: 6 | N197: 41.6 | O197: 3.9 | P197: 0.7 | Q197: 3.2 | R197: 20.3 | S197: 4.8 | T197: 6.5 | U197: 4.6 | V197: 0.8 | W197: 1.5 | X197: 2.9 | Y197: 52.8
A198: R90-92 | B198: Creative, arts and entertainment activities | C198: 32.4 | D198: 119.4 | E198: 188.2 | F198: 1 | G198: 1.5 | H198: 0.4 | I198: 9.8 | J198: 19.5 | K198: 23.5 | L198: 6.2 | M198: 197.4 | N198: 966.5 | O198: 27.6 | P198: 5.6 | Q198: 25.5 | R198: 52.7 | S198: 36.5 | T198: 35.5 | U198: 36.6 | V198: 3.2 | W198: 12.1 | X198: 12.9 | Y198: 421.1
A199: R93 | B199: Sports activities and amusement and recreation activities | C199: 12.9 | D199: 36.9 | E199: 95.9 | F199: 1 | G199: 0.5 | H199: 0.3 | I199: 4.9 | J199: 13.7 | K199: 15.6 | L199: 1.5 | M199: 15.9 | N199: 130.7 | O199: 6.9 | P199: 2.3 | Q199: 9.9 | R199: 26.9 | S199: 12.4 | T199: 9.7 | U199: 12 | V199: 1.7 | W199: 5.7 | X199: 5.6 | Y199: 107.6
A200: S94 | B200: Activities of membership organisations | C200: 14.3 | D200: 45.1 | E200: 83.8 | F200: 0.2 | G200: 0.3 | H200: 0.3 | I200: 4 | J200: 14.6 | K200: 10.5 | L200: 2.5 | M200: 10.9 | N200: 97.7 | O200: 11.6 | P200: 4.3 | Q200: 11 | R200: 20.9 | S200: 9.2 | T200: 10.7 | U200: 10.8 | V200: 1.5 | W200: 2.4 | X200: 3.7 | Y200: 98.1
A201: S95 | B201: Repair of computers and personal and household goods | C201: 7.6 | D201: 13.7 | E201: 57.3 | F201: 0.1 | G201: 0.4 | H201: 0.2 | I201: 2.9 | J201: 7 | K201: 11.9 | L201: 1.2 | M201: 9.2 | N201: 136.8 | O201: 3.6 | P201: 0.9 | Q201: 4.9 | R201: 21 | S201: 3.2 | T201: 10.5 | U201: 3.7 | V201: 0.6 | W201: 1.4 | X201: 2.2 | Y201: 47.6
A202: S96 | B202: Other personal service activities | C202: 6.8 | D202: 13.9 | E202: 146.8 | F202: 0.6 | G202: 1 | H202: 0.2 | I202: 3.8 | J202: 19.8 | K202: 26.9 | L202: 0.9 | M202: 49.5 | N202: 280.3 | O202: 3.2 | P202: 2.7 | Q202: 15 | R202: 19.4 | S202: 5.4 | T202: 6.1 | U202: 4.9 | V202: 0.7 | W202: 1.7 | X202: 2.1 | Y202: 50.5
A203: T | B203: Activities of households as employers | J203: 0.2 | N203: 0.3 | R203: 0.1 | T203: 0.1 | Y203: 0.7
A204: U | B204: Activities of extraterritorial organisations and bodies
A207: 2022 · deliveries to partners' final demand
A208: Industry | B208: Label | C208: NO | D208: CH | E208: UK | F208: ME | G208: MK | H208: AL | I208: RS | J208: TR | K208: RU | L208: ZA | M208: CA | N208: US | O208: MX | P208: AR | Q208: BR | R208: CN | S208: JP | T208: KR | U208: IN | V208: ID | W208: SA | X208: AU | Y208: WRL_REST
A209: A01 | B209: Crop and animal production, hunting and related service activities | C209: 461.4 | D209: 749.6 | E209: 6311.3 | F209: 20.3 | G209: 25 | H209: 67.4 | I209: 217 | J209: 96.1 | K209: 132.7 | L209: 89.4 | M209: 254.6 | N209: 1595.7 | O209: 91.9 | P209: 10.1 | Q209: 90.8 | R209: 878 | S209: 284.7 | T209: 111.9 | U209: 151.2 | V209: 99.8 | W209: 762.1 | X209: 81.8 | Y209: 10836.9
A210: A02 | B210: Forestry and logging | C210: 20.2 | D210: 12.3 | E210: 7.7 | F210: 0.1 | G210: 1.7 | H210: 0.4 | I210: 0.5 | J210: 1.7 | K210: 7.5 | L210: 1.4 | M210: 0.8 | N210: 5.3 | O210: 3.8 | P210: 1.3 | Q210: 3.5 | R210: 18.7 | S210: 10.1 | T210: 2 | U210: 15.9 | V210: 1.5 | W210: 2 | X210: 1.7 | Y210: 148.9
A211: A03 | B211: Fishing and aquaculture | C211: -10.5 | D211: 48.8 | E211: 96.1 | F211: 1.8 | G211: 1.3 | H211: 11.8 | I211: 4.2 | J211: 4.7 | K211: 2.3 | L211: 2.5 | M211: 12.7 | N211: 52.3 | O211: 7.9 | P211: 0.6 | Q211: 5 | R211: 46 | S211: 8.7 | T211: 5 | U211: 10.6 | V211: 2.2 | W211: 14.9 | X211: 6.9 | Y211: 272.4
A212: B | B212: Mining and quarrying | C212: -168.4 | D212: 117.2 | E212: 37.2 | G212: 3.4 | H212: 1 | I212: 1.6 | J212: 19.6 | K212: 28.4 | L212: -1.8 | M212: 50.3 | N212: 50.4 | O212: 11.8 | P212: 0.2 | Q212: -16.1 | R212: 71 | S212: 14.4 | T212: 5.4 | U212: 11.2 | V212: 2.8 | W212: 28.5 | X212: 16.2 | Y212: 306.9
A213: C10-12 | B213: Manufacture of food products | C213: 1884.8 | D213: 4112.2 | E213: 31769.9 | F213: 173.9 | G213: 308.5 | H213: 432.5 | I213: 1264.6 | J213: 671 | K213: 630.7 | L213: 1055.8 | M213: 2813.1 | N213: 17775.2 | O213: 1120.4 | P213: 136 | Q213: 1245.3 | R213: 10328.3 | S213: 5358.6 | T213: 1671.9 | U213: 1126.8 | V213: 712.4 | W213: 2490.5 | X213: 1875.2 | Y213: 36725.9
A214: C13-15 | B214: Manufacture of textiles, wearing apparel, leather and related products | C214: 244 | D214: 1554 | E214: 5015.4 | F214: 20.3 | G214: 69.3 | H214: 333.1 | I214: 367.2 | J214: 659.4 | K214: 430.7 | L214: 154.1 | M214: 1069.2 | N214: 7592.6 | O214: 527.4 | P214: 29.7 | Q214: 213.7 | R214: 2252.7 | S214: 1206.4 | T214: 1908.8 | U214: 256.3 | V214: 75 | W214: 275.9 | X214: 516.1 | Y214: 10435.8
A215: C16 | B215: Manufacture of wood and of products of wood and cork, except furniture | C215: -121.7 | D215: 239.6 | E215: 1045.9 | F215: 3 | G215: 34.8 | H215: 8.4 | I215: 10.7 | J215: 56 | K215: 54.9 | L215: 19.3 | M215: 76.6 | N215: 872.1 | O215: 68.1 | P215: 4.4 | Q215: 22.2 | R215: 258 | S215: 119.6 | T215: 59.5 | U215: 81.4 | V215: 14.4 | W215: 139.4 | X215: 57.4 | Y215: 2750.9
A216: C17 | B216: Manufacture of paper and paper products | C216: -32.6 | D216: 226.7 | E216: 2908.5 | F216: 6.8 | G216: 6.8 | H216: 34 | I216: 37 | J216: -2.8 | K216: 54.6 | L216: 116.4 | M216: 152.7 | N216: 772.2 | O216: 270.7 | P216: 45.7 | Q216: 73.5 | R216: 259.7 | S216: 74.6 | T216: 40.2 | U216: 80.3 | V216: 63 | W216: 318.9 | X216: 169.4 | Y216: 4554
A217: C18 | B217: Printing and reproduction of recorded media | C217: -755.2 | D217: 190 | E217: 201.2 | F217: 0.5 | G217: 0.7 | H217: 2 | I217: 3.3 | J217: 12.6 | K217: 9.8 | L217: 7.6 | M217: 17.3 | N217: 311.1 | O217: 40.4 | P217: 6.2 | Q217: -71.7 | R217: 201.8 | S217: 45.3 | T217: 18.7 | U217: 27.7 | V217: 12.6 | W217: 38.6 | X217: 20.4 | Y217: 723.7
A218: C19 | B218: Manufacture of coke and refined petroleum products | C218: 542.1 | D218: 4821 | E218: 6274 | F218: 114.8 | G218: 234.2 | H218: 54.6 | I218: 69.8 | J218: 492.3 | K218: 23.9 | L218: 194.4 | M218: 626.8 | N218: 2185.9 | O218: 749.6 | P218: 350.9 | Q218: 546.9 | R218: 338 | S218: 413.9 | T218: 80.5 | U218: 636.7 | V218: 24.9 | W218: 370.4 | X218: 96.5 | Y218: 21829.6
A219: C20 | B219: Manufacture of chemicals and chemical products | C219: 1013.6 | D219: 1061.5 | E219: 7102.2 | F219: 44.8 | G219: 207.7 | H219: 139.2 | I219: 480.7 | J219: 903.2 | K219: 272.2 | L219: 419 | M219: 761.2 | N219: 9126.1 | O219: 1128.2 | P219: 257.7 | Q219: 1359 | R219: 2804.7 | S219: 1885.7 | T219: 592.9 | U219: 698.5 | V219: 281 | W219: 672 | X219: 972.8 | Y219: 14148.2
A220: C21 | B220: Manufacture of basic pharmaceutical products and pharmaceutical prepa… | C220: 483.1 | D220: 943.9 | E220: 5596.5 | F220: 37.1 | G220: 65.8 | H220: 46.1 | I220: 413 | J220: 1661 | K220: 507 | L220: 544.5 | M220: 1912.2 | N220: 40577.4 | O220: 1464.2 | P220: 513 | Q220: 2293.8 | R220: 17186.6 | S220: 10950.2 | T220: 451.3 | U220: 465.6 | V220: 306.8 | W220: 2490.9 | X220: 2563 | Y220: 21637.2
A221: C22 | B221: Manufacture of rubber and plastic products | C221: 187.4 | D221: 330.6 | E221: 2823.6 | F221: 9.1 | G221: 38.5 | H221: 49.1 | I221: 69 | J221: 653.4 | K221: 154.6 | L221: 270.9 | M221: 383.7 | N221: 4340.4 | O221: 598.7 | P221: 33.9 | Q221: 186.5 | R221: 444 | S221: 201.4 | T221: 118.7 | U221: 444 | V221: 114.4 | W221: 173.7 | X221: 266.3 | Y221: 3747.5
A222: C23 | B222: Manufacture of other non-metallic mineral products | C222: -80.2 | D222: 144 | E222: 1874.1 | F222: 5.2 | G222: 78.7 | H222: 10.8 | I222: 22.3 | J222: 166.6 | K222: 56.3 | L222: 48.3 | M222: 189 | N222: 1875.2 | O222: 80.9 | P222: 11.4 | Q222: 46.7 | R222: 156.6 | S222: 97.7 | T222: 43.8 | U222: 29.3 | V222: 18.9 | W222: 382.6 | X222: 51.6 | Y222: 2183.3
A223: C24 | B223: Manufacture of basic metals | C223: -156.5 | D223: 181.1 | E223: 339.2 | F223: 6.2 | G223: 88.7 | H223: 31.2 | I223: 47.5 | J223: 103.5 | K223: 80.8 | L223: 13.4 | M223: 1978.3 | N223: 739 | O223: 109.2 | P223: 13.8 | Q223: 50.3 | R223: 358.1 | S223: 193.7 | T223: 64.5 | U223: 61.6 | V223: 16.6 | W223: 80.4 | X223: 41.4 | Y223: 821.4
A224: C25 | B224: Manufacture of fabricated metal products, except machinery and equipm… | C224: 423.9 | D224: 469 | E224: 3329.9 | F224: 20.8 | G224: 29.9 | H224: 103.3 | I224: 370.6 | J224: 1483.6 | K224: 739 | L224: 123.4 | M224: 638.7 | N224: 5424.7 | O224: 637.4 | P224: 85.2 | Q224: 491.3 | R224: 1989.3 | S224: 367.9 | T224: 479.2 | U224: 212.7 | V224: 137.3 | W224: 1027.9 | X224: 274.6 | Y224: 7773.7
... A270: S96 | B270: Other personal service activities | C270: 23.4 | D270: 375.5 | E270: 16.5 | F270: 0.1 | G270: 0.3 | H270: 0.9 | I270: 0.7 | J270: -0.5 | K270: 3.1 | L270: 9 | M270: 2 | N270: 37.3 | O270: 39.9 | P270: 0.6 | Q270: 3.1 | R270: 65.7 | S270: 69.4 | T270: 52.3 | U270: 32.5 | V270: 15.8 | W270: 7.4 | X270: 14.7 | Y270: 372.9
A271: T | B271: Activities of households as employers | E271: 0.2 | N271: 0.1 | R271: 0.1 | Y271: 1.2
A272: U | B272: Activities of extraterritorial organisations and bodies

Sheet IO model
A1: IO model — per-industry accounts, 2023, € million, EU-27 as one economy. Output, value added and intermediate totals are formulas over the Z sheets (themselves derived from the FIGARO raw sheet); extra-EU exports are formulas over the FIGARO exports raw sheet. The residual column checks column-based against row-based output — keep it near zero.
A2: Code | B2: Industry | C2: NACE section | D2: Total output x (col sum incl. VA) | E2: Intermediate inputs (all origins) | F2: Value added + taxes + adj. | G2: of which: compensation (D1) | H2: of which: operating surplus (B2A3G) | I2: of which: taxes less subsidies | J2: VA coefficient v = VA/x | K2: Domestic deliveries to EU intermediate use (row sum) | L2: Domestic deliveries to EU final demand (row sum) | M2: Extra-EU exports (interm. + final) | N2: Row-based output | O2: Residual (row − col, % of x)
A3: A01 | B3: Crop and animal production, hunting and related service activities | C3: A | D3: =SUM('Z total'!C3:C72) -> 572833.5 | E3: =SUM('Z total'!C3:C66) -> 319526.2 | F3: =SUM('Z domestic'!C67:C72) -> 253307.3 | G3: ='Z domestic'!C68 -> 55795.8 | H3: ='Z domestic'!C67 -> 230146.4 | I3: ='Z domestic'!C69+'Z domestic'!C70 -> -32634.9 | J3: =IF(D3=0,0,F3/D3) -> 0.44220057 | K3: =SUM('Z domestic'!C3:BN3) -> 372979.2 | L3: =SUM('Z domestic'!BO3:BS3) -> 159932.7 | M3: =SUM('FIGARO exports raw'!C5:Y5)+SUM('FIGARO exports raw'!C73:Y73) -> 39925.4 | N3: =K3+L3+M3 -> 572837.3 | O3: =IF(D3=0,0,100*(N3-D3)/D3) -> 0.00066336902
A4: A02 | B4: Forestry and logging | C4: A | D4: =SUM('Z total'!D3:D72) -> 62450.1 | E4: =SUM('Z total'!D3:D66) -> 31369.5 | F4: =SUM('Z domestic'!D67:D72) -> 31080.6 | G4: ='Z domestic'!D68 -> 9168.9 | H4: ='Z domestic'!D67 -> 21434.6 | I4: ='Z domestic'!D69+'Z domestic'!D70 -> 477.1 | J4: =IF(D4=0,0,F4/D4) -> 0.49768695 | K4: =SUM('Z domestic'!C4:BN4) -> 45185.4 | L4: =SUM('Z domestic'!BO4:BS4) -> 14701.1 | M4: =SUM('FIGARO exports raw'!C6:Y6)+SUM('FIGARO exports raw'!C74:Y74) -> 2568.8 | N4: =K4+L4+M4 -> 62455.3 | O4: =IF(D4=0,0,100*(N4-D4)/D4) -> 0.008326648
A5: A03 | B5: Fishing and aquaculture | C5: A | D5: =SUM('Z total'!E3:E72) -> 14733.9 | E5: =SUM('Z total'!E3:E66) -> 7802.7 | F5: =SUM('Z domestic'!E67:E72) -> 6931.2 | G5: ='Z domestic'!E68 -> 2540 | H5: ='Z domestic'!E67 -> 4307.4 | I5: ='Z domestic'!E69+'Z domestic'!E70 -> 83.8 | J5: =IF(D5=0,0,F5/D5) -> 0.47042535 | K5: =SUM('Z domestic'!C5:BN5) -> 5664.9 | L5: =SUM('Z domestic'!BO5:BS5) -> 7865 | M5: =SUM('FIGARO exports raw'!C7:Y7)+SUM('FIGARO exports raw'!C75:Y75) -> 1209 | N5: =K5+L5+M5 -> 14738.9 | O5: =IF(D5=0,0,100*(N5-D5)/D5) -> 0.033935346
A6: B | B6: Mining and quarrying | C6: B | D6: =SUM('Z total'!F3:F72) -> 108915.4 | E6: =SUM('Z total'!F3:F66) -> 48798.7 | F6: =SUM('Z domestic'!F67:F72) -> 60116.7 | G6: ='Z domestic'!F68 -> 19451.9 | H6: ='Z domestic'!F67 -> 38968.7 | I6: ='Z domestic'!F69+'Z domestic'!F70 -> 1696.1 | J6: =IF(D6=0,0,F6/D6) -> 0.55195776 | K6: =SUM('Z domestic'!C6:BN6) -> 96253.7 | L6: =SUM('Z domestic'!BO6:BS6) -> 4526.1 | M6: =SUM('FIGARO exports raw'!C8:Y8)+SUM('FIGARO exports raw'!C76:Y76) -> 8138.9 | N6: =K6+L6+M6 -> 108918.7 | O6: =IF(D6=0,0,100*(N6-D6)/D6) -> 0.0030298746
A7: C10-12 | B7: Manufacture of food products | C7: C | D7: =SUM('Z total'!G3:G72) -> 1359072 | E7: =SUM('Z total'!G3:G66) -> 1052883.1 | F7: =SUM('Z domestic'!G67:G72) -> 306188.9 | G7: ='Z domestic'!G68 -> 163173.1 | H7: ='Z domestic'!G67 -> 132312.7 | I7: ='Z domestic'!G69+'Z domestic'!G70 -> 10703.1 | J7: =IF(D7=0,0,F7/D7) -> 0.22529263 | K7: =SUM('Z domestic'!C7:BN7) -> 519427 | L7: =SUM('Z domestic'!BO7:BS7) -> 657815 | M7: =SUM('FIGARO exports raw'!C9:Y9)+SUM('FIGARO exports raw'!C77:Y77) -> 181831.2 | N7: =K7+L7+M7 -> 1359073.2 | O7: =IF(D7=0,0,100*(N7-D7)/D7) -> 8.8295543e-05
A8: C13-15 | B8: Manufacture of textiles, wearing apparel, leather and related products | C8: C | D8: =SUM('Z total'!H3:H72) -> 227703.6 | E8: =SUM('Z total'!H3:H66) -> 149210.7 | F8: =SUM('Z domestic'!H67:H72) -> 78492.9 | G8: ='Z domestic'!H68 -> 44207.4 | H8: ='Z domestic'!H67 -> 32088.6 | I8: ='Z domestic'!H69+'Z domestic'!H70 -> 2196.9 | J8: =IF(D8=0,0,F8/D8) -> 0.34471524 | K8: =SUM('Z domestic'!C8:BN8) -> 84304 | L8: =SUM('Z domestic'!BO8:BS8) -> 81422.3 | M8: =SUM('FIGARO exports raw'!C10:Y10)+SUM('FIGARO exports raw'!C78:Y78) -> 61979.5 | N8: =K8+L8+M8 -> 227705.8 | O8: =IF(D8=0,0,100*(N8-D8)/D8) -> 0.0009661683
A9: C16 | B9: Manufacture of wood and of products of wood and cork, except furniture | C9: C | D9: =SUM('Z total'!I3:I72) -> 176754.9 | E9: =SUM('Z total'!I3:I66) -> 122288.7 | F9: =SUM('Z domestic'!I67:I72) -> 54466.2 | G9: ='Z domestic'!I68 -> 27376.6 | H9: ='Z domestic'!I67 -> 25626.3 | I9: ='Z domestic'!I69+'Z domestic'!I70 -> 1463.3 | J9: =IF(D9=0,0,F9/D9) -> 0.30814535 | K9: =SUM('Z domestic'!C9:BN9) -> 122659.7 | L9: =SUM('Z domestic'!BO9:BS9) -> 26702.6 | M9: =SUM('FIGARO exports raw'!C11:Y11)+SUM('FIGARO exports raw'!C79:Y79) -> 27394.6 | N9: =K9+L9+M9 -> 176756.9 | O9: =IF(D9=0,0,100*(N9-D9)/D9) -> 0.0011315104
A10: C17 | B10: Manufacture of paper and paper products | C10: C | D10: =SUM('Z total'!J3:J72) -> 223049.7 | E10: =SUM('Z total'!J3:J66) -> 166729.2 | F10: =SUM('Z domestic'!J67:J72) -> 56320.5 | G10: ='Z domestic'!J68 -> 28810.8 | H10: ='Z domestic'!J67 -> 25312.8 | I10: ='Z domestic'!J69+'Z domestic'!J70 -> 2196.9 | J10: =IF(D10=0,0,F10/D10) -> 0.25250202 | K10: =SUM('Z domestic'!C10:BN10) -> 148174.8 | L10: =SUM('Z domestic'!BO10:BS10) -> 31336.6 | M10: =SUM('FIGARO exports raw'!C12:Y12)+SUM('FIGARO exports raw'!C80:Y80) -> 43541.3 | N10: =K10+L10+M10 -> 223052.7 | O10: =IF(D10=0,0,100*(N10-D10)/D10) -> 0.0013449917
A11: C18 | B11: Printing and reproduction of recorded media | C11: C | D11: =SUM('Z total'!K3:K72) -> 70340.1 | E11: =SUM('Z total'!K3:K66) -> 43673.2 | F11: =SUM('Z domestic'!K67:K72) -> 26666.9 | G11: ='Z domestic'!K68 -> 16842.9 | H11: ='Z domestic'!K67 -> 9276.4 | I11: ='Z domestic'!K69+'Z domestic'!K70 -> 547.6 | J11: =IF(D11=0,0,F11/D11) -> 0.37911376 | K11: =SUM('Z domestic'!C11:BN11) -> 60115.1 | L11: =SUM('Z domestic'!BO11:BS11) -> 5521 | M11: =SUM('FIGARO exports raw'!C13:Y13)+SUM('FIGARO exports raw'!C81:Y81) -> 4707.1 | N11: =K11+L11+M11 -> 70343.2 | O11: =IF(D11=0,0,100*(N11-D11)/D11) -> 0.0044071589
A12: C19 | B12: Manufacture of coke and refined petroleum products | C12: C | D12: =SUM('Z total'!L3:L72) -> 544426.3 | E12: =SUM('Z total'!L3:L66) -> 477132 | F12: =SUM('Z domestic'!L67:L72) -> 67294.3 | G12: ='Z domestic'!L68 -> 9163.1 | H12: ='Z domestic'!L67 -> 47156.4 | I12: ='Z domestic'!L69+'Z domestic'!L70 -> 10974.8 | J12: =IF(D12=0,0,F12/D12) -> 0.12360589 | K12: =SUM('Z domestic'!C12:BN12) -> 296602.4 | L12: =SUM('Z domestic'!BO12:BS12) -> 140201.9 | M12: =SUM('FIGARO exports raw'!C14:Y14)+SUM('FIGARO exports raw'!C82:Y82) -> 107624.6 | N12: =K12+L12+M12 -> 544428.9 | O12: =IF(D12=0,0,100*(N12-D12)/D12) -> 0.00047756694
A13: C20 | B13: Manufacture of chemicals and chemical products | C13: C | D13: =SUM('Z total'!M3:M72) -> 634576.5 | E13: =SUM('Z total'!M3:M66) -> 483601.4 | F13: =SUM('Z domestic'!M67:M72) -> 150975.1 | G13: ='Z domestic'!M68 -> 78035.1 | H13: ='Z domestic'!M67 -> 65780.2 | I13: ='Z domestic'!M69+'Z domestic'!M70 -> 7159.8 | J13: =IF(D13=0,0,F13/D13) -> 0.23791474 | K13: =SUM('Z domestic'!C13:BN13) -> 368913.8 | L13: =SUM('Z domestic'!BO13:BS13) -> 74416.2 | M13: =SUM('FIGARO exports raw'!C15:Y15)+SUM('FIGARO exports raw'!C83:Y83) -> 191247.9 | N13: =K13+L13+M13 -> 634577.9 | O13: =IF(D13=0,0,100*(N13-D13)/D13) -> 0.00022061958
A14: C21 | B14: Manufacture of basic pharmaceutical products and pharmaceutical prepa… | C14: C | D14: =SUM('Z total'!N3:N72) -> 371583.4 | E14: =SUM('Z total'!N3:N66) -> 193451.5 | F14: =SUM('Z domestic'!N67:N72) -> 178131.9 | G14: ='Z domestic'!N68 -> 43594.6 | H14: ='Z domestic'!N67 -> 131798.9 | I14: ='Z domestic'!N69+'Z domestic'!N70 -> 2738.4 | J14: =IF(D14=0,0,F14/D14) -> 0.47938605 | K14: =SUM('Z domestic'!C14:BN14) -> 96843.4 | L14: =SUM('Z domestic'!BO14:BS14) -> 81480 | M14: =SUM('FIGARO exports raw'!C16:Y16)+SUM('FIGARO exports raw'!C84:Y84) -> 193262.2 | N14: =K14+L14+M14 -> 371585.6 | O14: =IF(D14=0,0,100*(N14-D14)/D14) -> 0.00059206089
A15: C22 | B15: Manufacture of rubber and plastic products | C15: C | D15: =SUM('Z total'!O3:O72) -> 356785.9 | E15: =SUM('Z total'!O3:O66) -> 245442.6 | F15: =SUM('Z domestic'!O67:O72) -> 111343.3 | G15: ='Z domestic'!O68 -> 66784.9 | H15: ='Z domestic'!O67 -> 41902.2 | I15: ='Z domestic'!O69+'Z domestic'!O70 -> 2656.2 | J15: =IF(D15=0,0,F15/D15) -> 0.31207315 | K15: =SUM('Z domestic'!C15:BN15) -> 254363.5 | L15: =SUM('Z domestic'!BO15:BS15) -> 37196 | M15: =SUM('FIGARO exports raw'!C17:Y17)+SUM('FIGARO exports raw'!C85:Y85) -> 65228.8 | N15: =K15+L15+M15 -> 356788.3 | O15: =IF(D15=0,0,100*(N15-D15)/D15) -> 0.00067267232
A16: C23 | B16: Manufacture of other non-metallic mineral products | C16: C | D16: =SUM('Z total'!P3:P72) -> 265794.4 | E16: =SUM('Z total'!P3:P66) -> 177680.3 | F16: =SUM('Z domestic'!P67:P72) -> 88114.1 | G16: ='Z domestic'!P68 -> 48639 | H16: ='Z domestic'!P67 -> 34716.6 | I16: ='Z domestic'!P69+'Z domestic'!P70 -> 4758.5 | J16: =IF(D16=0,0,F16/D16) -> 0.33151225 | K16: =SUM('Z domestic'!C16:BN16) -> 208910.1 | L16: =SUM('Z domestic'!BO16:BS16) -> 24210.5 | M16: =SUM('FIGARO exports raw'!C18:Y18)+SUM('FIGARO exports raw'!C86:Y86) -> 32676 | N16: =K16+L16+M16 -> 265796.6 | O16: =IF(D16=0,0,100*(N16-D16)/D16) -> 0.00082770743
A17: C24 | B17: Manufacture of basic metals | C17: C | D17: =SUM('Z total'!Q3:Q72) -> 503364 | E17: =SUM('Z total'!Q3:Q66) -> 414830.1 | F17: =SUM('Z domestic'!Q67:Q72) -> 88533.9 | G17: ='Z domestic'!Q68 -> 47120.7 | H17: ='Z domestic'!Q67 -> 37886.3 | I17: ='Z domestic'!Q69+'Z domestic'!Q70 -> 3526.9 | J17: =IF(D17=0,0,F17/D17) -> 0.17588445 | K17: =SUM('Z domestic'!C17:BN17) -> 399656.4 | L17: =SUM('Z domestic'!BO17:BS17) -> 16903.6 | M17: =SUM('FIGARO exports raw'!C19:Y19)+SUM('FIGARO exports raw'!C87:Y87) -> 86804.3 | N17: =K17+L17+M17 -> 503364.3 | O17: =IF(D17=0,0,100*(N17-D17)/D17) -> 5.9599018e-05
A18: C25 | B18: Manufacture of fabricated metal products, except machinery and equipm… | C18: C | D18: =SUM('Z total'!R3:R72) -> 625037.3 | E18: =SUM('Z total'!R3:R66) -> 404113.8 | F18: =SUM('Z domestic'!R67:R72) -> 220923.5 | G18: ='Z domestic'!R68 -> 141421.8 | H18: ='Z domestic'!R67 -> 74974.8 | I18: ='Z domestic'!R69+'Z domestic'!R70 -> 4526.9 | J18: =IF(D18=0,0,F18/D18) -> 0.35345651 | K18: =SUM('Z domestic'!C18:BN18) -> 447842.3 | L18: =SUM('Z domestic'!BO18:BS18) -> 100232.8 | M18: =SUM('FIGARO exports raw'!C20:Y20)+SUM('FIGARO exports raw'!C88:Y88) -> 76962.9 | N18: =K18+L18+M18 -> 625038 | O18: =IF(D18=0,0,100*(N18-D18)/D18) -> 0.00011199332
A19: C26 | B19: Manufacture of computer, electronic and optical products | C19: C | D19: =SUM('Z total'!S3:S72) -> 391662.1 | E19: =SUM('Z total'!S3:S66) -> 207468.5 | F19: =SUM('Z domestic'!S67:S72) -> 184193.6 | G19: ='Z domestic'!S68 -> 64081 | H19: ='Z domestic'!S67 -> 118454.5 | I19: ='Z domestic'!S69+'Z domestic'!S70 -> 1658.1 | J19: =IF(D19=0,0,F19/D19) -> 0.47028702 | K19: =SUM('Z domestic'!C19:BN19) -> 120127.5 | L19: =SUM('Z domestic'!BO19:BS19) -> 125647.3 | M19: =SUM('FIGARO exports raw'!C21:Y21)+SUM('FIGARO exports raw'!C89:Y89) -> 145889.1 | N19: =K19+L19+M19 -> 391663.9 | O19: =IF(D19=0,0,100*(N19-D19)/D19) -> 0.00045957983
A20: C27 | B20: Manufacture of electrical equipment | C20: C | D20: =SUM('Z total'!T3:T72) -> 385310.9 | E20: =SUM('Z total'!T3:T66) -> 264642.1 | F20: =SUM('Z domestic'!T67:T72) -> 120668.8 | G20: ='Z domestic'!T68 -> 75910 | H20: ='Z domestic'!T67 -> 42546.6 | I20: ='Z domestic'!T69+'Z domestic'!T70 -> 2212.2 | J20: =IF(D20=0,0,F20/D20) -> 0.31317256 | K20: =SUM('Z domestic'!C20:BN20) -> 182112.6 | L20: =SUM('Z domestic'!BO20:BS20) -> 100135.2 | M20: =SUM('FIGARO exports raw'!C22:Y22)+SUM('FIGARO exports raw'!C90:Y90) -> 103065.7 | N20: =K20+L20+M20 -> 385313.5 | O20: =IF(D20=0,0,100*(N20-D20)/D20) -> 0.00067477977
A21: C28 | B21: Manufacture of machinery and equipment n.e.c. | C21: C | D21: =SUM('Z total'!U3:U72) -> 790221.4 | E21: =SUM('Z total'!U3:U66) -> 513768.4 | F21: =SUM('Z domestic'!U67:U72) -> 276453 | G21: ='Z domestic'!U68 -> 170726.5 | H21: ='Z domestic'!U67 -> 102190.3 | I21: ='Z domestic'!U69+'Z domestic'!U70 -> 3536.2 | J21: =IF(D21=0,0,F21/D21) -> 0.34984246 | K21: =SUM('Z domestic'!C21:BN21) -> 284924.5 | L21: =SUM('Z domestic'!BO21:BS21) -> 244544.1 | M21: =SUM('FIGARO exports raw'!C23:Y23)+SUM('FIGARO exports raw'!C91:Y91) -> 260755 | N21: =K21+L21+M21 -> 790223.6 | O21: =IF(D21=0,0,100*(N21-D21)/D21) -> 0.00027840299
A22: C29 | B22: Manufacture of motor vehicles, trailers and semi-trailers | C22: C | D22: =SUM('Z total'!V3:V72) -> 1078372.9 | E22: =SUM('Z total'!V3:V66) -> 801327.4 | F22: =SUM('Z domestic'!V67:V72) -> 277045.5 | G22: ='Z domestic'!V68 -> 134665.4 | H22: ='Z domestic'!V67 -> 137475.3 | I22: ='Z domestic'!V69+'Z domestic'!V70 -> 4904.8 | J22: =IF(D22=0,0,F22/D22) -> 0.25691067 | K22: =SUM('Z domestic'!C22:BN22) -> 386551.1 | L22: =SUM('Z domestic'!BO22:BS22) -> 436878.2 | M22: =SUM('FIGARO exports raw'!C24:Y24)+SUM('FIGARO exports raw'!C92:Y92) -> 254945.3 | N22: =K22+L22+M22 -> 1078374.6 | O22: =IF(D22=0,0,100*(N22-D22)/D22) -> 0.00015764491
A23: C30 | B23: Manufacture of other transport equipment | C23: C | D23: =SUM('Z total'!W3:W72) -> 272900.4 | E23: =SUM('Z total'!W3:W66) -> 202628.8 | F23: =SUM('Z domestic'!W67:W72) -> 70271.6 | G23: ='Z domestic'!W68 -> 40847.3 | H23: ='Z domestic'!W67 -> 28397.8 | I23: ='Z domestic'!W69+'Z domestic'!W70 -> 1026.5 | J23: =IF(D23=0,0,F23/D23) -> 0.25749907 | K23: =SUM('Z domestic'!C23:BN23) -> 88880.1 | L23: =SUM('Z domestic'!BO23:BS23) -> 80285.3 | M23: =SUM('FIGARO exports raw'!C25:Y25)+SUM('FIGARO exports raw'!C93:Y93) -> 103737.4 | N23: =K23+L23+M23 -> 272902.8 | O23: =IF(D23=0,0,100*(N23-D23)/D23) -> 0.00087944173
A24: C31_32 | B24: Manufacture of furniture | C24: C | D24: =SUM('Z total'!X3:X72) -> 279984.2 | E24: =SUM('Z total'!X3:X66) -> 168919.5 | F24: =SUM('Z domestic'!X67:X72) -> 111064.7 | G24: ='Z domestic'!X68 -> 62954.8 | H24: ='Z domestic'!X67 -> 45579.9 | I24: ='Z domestic'!X69+'Z domestic'!X70 -> 2530 | J24: =IF(D24=0,0,F24/D24) -> 0.39668203 | K24: =SUM('Z domestic'!C24:BN24) -> 78346 | L24: =SUM('Z domestic'!BO24:BS24) -> 122498 | M24: =SUM('FIGARO exports raw'!C26:Y26)+SUM('FIGARO exports raw'!C94:Y94) -> 79142.8 | N24: =K24+L24+M24 -> 279986.8 | O24: =IF(D24=0,0,100*(N24-D24)/D24) -> 0.00092862383
A25: C33 | B25: Repair and installation of machinery and equipment | C25: C | D25: =SUM('Z total'!Y3:Y72) -> 246618.3 | E25: =SUM('Z total'!Y3:Y66) -> 143866.7 | F25: =SUM('Z domestic'!Y67:Y72) -> 102751.6 | G25: ='Z domestic'!Y68 -> 70079.3 | H25: ='Z domestic'!Y67 -> 30311.2 | I25: ='Z domestic'!Y69+'Z domestic'!Y70 -> 2361.1 | J25: =IF(D25=0,0,F25/D25) -> 0.41664224 | K25: =SUM('Z domestic'!C25:BN25) -> 146177.9 | L25: =SUM('Z domestic'!BO25:BS25) -> 78981 | M25: =SUM('FIGARO exports raw'!C27:Y27)+SUM('FIGARO exports raw'!C95:Y95) -> 21463 | N25: =K25+L25+M25 -> 246621.9 | O25: =IF(D25=0,0,100*(N25-D25)/D25) -> 0.0014597457
A26: D35 | B26: Electricity, gas, steam and air conditioning supply | C26: D | D26: =SUM('Z total'!Z3:Z72) -> 1119921.9 | E26: =SUM('Z total'!Z3:Z66) -> 691913.4 | F26: =SUM('Z domestic'!Z67:Z72) -> 428008.5 | G26: ='Z domestic'!Z68 -> 83268.5 | H26: ='Z domestic'!Z67 -> 335246.8 | I26: ='Z domestic'!Z69+'Z domestic'!Z70 -> 9493.2 | J26: =IF(D26=0,0,F26/D26) -> 0.3821771 | K26: =SUM('Z domestic'!C26:BN26) -> 777332.7 | L26: =SUM('Z domestic'!BO26:BS26) -> 323697.1 | M26: =SUM('FIGARO exports raw'!C28:Y28)+SUM('FIGARO exports raw'!C96:Y96) -> 18893.1 | N26: =K26+L26+M26 -> 1119922.9 | O26: =IF(D26=0,0,100*(N26-D26)/D26) -> 8.9291941e-05
A27: E36 | B27: Water collection, treatment and supply | C27: E | D27: =SUM('Z total'!AA3:AA72) -> 70152.3 | E27: =SUM('Z total'!AA3:AA66) -> 37053.9 | F27: =SUM('Z domestic'!AA67:AA72) -> 33098.4 | G27: ='Z domestic'!AA68 -> 14135.1 | H27: ='Z domestic'!AA67 -> 17647.3 | I27: ='Z domestic'!AA69+'Z domestic'!AA70 -> 1316 | J27: =IF(D27=0,0,F27/D27) -> 0.47180777 | K27: =SUM('Z domestic'!C27:BN27) -> 38601.9 | L27: =SUM('Z domestic'!BO27:BS27) -> 30653.5 | M27: =SUM('FIGARO exports raw'!C29:Y29)+SUM('FIGARO exports raw'!C97:Y97) -> 903 | N27: =K27+L27+M27 -> 70158.4 | O27: =IF(D27=0,0,100*(N27-D27)/D27) -> 0.0086953671
A28: E37-39 | B28: Sewerage, waste management, remediation activities | C28: E | D28: =SUM('Z total'!AB3:AB72) -> 290682.8 | E28: =SUM('Z total'!AB3:AB66) -> 173759.7 | F28: =SUM('Z domestic'!AB67:AB72) -> 116923.1 | G28: ='Z domestic'!AB68 -> 49814.9 | H28: ='Z domestic'!AB67 -> 61027.4 | I28: ='Z domestic'!AB69+'Z domestic'!AB70 -> 6080.8 | J28: =IF(D28=0,0,F28/D28) -> 0.40223605 | K28: =SUM('Z domestic'!C28:BN28) -> 206551.4 | L28: =SUM('Z domestic'!BO28:BS28) -> 70411.1 | M28: =SUM('FIGARO exports raw'!C30:Y30)+SUM('FIGARO exports raw'!C98:Y98) -> 13724.1 | N28: =K28+L28+M28 -> 290686.6 | O28: =IF(D28=0,0,100*(N28-D28)/D28) -> 0.0013072669
A29: F | B29: Construction | C29: F | D29: =SUM('Z total'!AC3:AC72) -> 2425374.1 | E29: =SUM('Z total'!AC3:AC66) -> 1534257.9 | F29: =SUM('Z domestic'!AC67:AC72) -> 891116.2 | G29: ='Z domestic'!AC68 -> 460011.2 | H29: ='Z domestic'!AC67 -> 398479.8 | I29: ='Z domestic'!AC69+'Z domestic'!AC70 -> 32625.2 | J29: =IF(D29=0,0,F29/D29) -> 0.36741392 | K29: =SUM('Z domestic'!C29:BN29) -> 865624.3 | L29: =SUM('Z domestic'!BO29:BS29) -> 1542497.9 | M29: =SUM('FIGARO exports raw'!C31:Y31)+SUM('FIGARO exports raw'!C99:Y99) -> 17254.1 | N29: =K29+L29+M29 -> 2425376.3 | O29: =IF(D29=0,0,100*(N29-D29)/D29) -> 9.0707656e-05
A30: G45 | B30: Wholesale and retail trade and repair of motor vehicles and motorcycl… | C30: G | D30: =SUM('Z total'!AD3:AD72) -> 406251.7 | E30: =SUM('Z total'!AD3:AD66) -> 193393.6 | F30: =SUM('Z domestic'!AD67:AD72) -> 212858.1 | G30: ='Z domestic'!AD68 -> 116614.7 | H30: ='Z domestic'!AD67 -> 87315.4 | I30: ='Z domestic'!AD69+'Z domestic'!AD70 -> 8928 | J30: =IF(D30=0,0,F30/D30) -> 0.52395621 | K30: =SUM('Z domestic'!C30:BN30) -> 192521.4 | L30: =SUM('Z domestic'!BO30:BS30) -> 183729 | M30: =SUM('FIGARO exports raw'!C32:Y32)+SUM('FIGARO exports raw'!C100:Y100) -> 30001.8 | N30: =K30+L30+M30 -> 406252.2 | O30: =IF(D30=0,0,100*(N30-D30)/D30) -> 0.00012307641
A31: G46 | B31: Wholesale trade, except of motor vehicles and motorcycles | C31: G | D31: =SUM('Z total'!AE3:AE72) -> 1762441.2 | E31: =SUM('Z total'!AE3:AE66) -> 851246.1 | F31: =SUM('Z domestic'!AE67:AE72) -> 911195.1 | G31: ='Z domestic'!AE68 -> 439785 | H31: ='Z domestic'!AE67 -> 472646.7 | I31: ='Z domestic'!AE69+'Z domestic'!AE70 -> -1236.6 | J31: =IF(D31=0,0,F31/D31) -> 0.51700738 | K31: =SUM('Z domestic'!C31:BN31) -> 996108.9 | L31: =SUM('Z domestic'!BO31:BS31) -> 474083.7 | M31: =SUM('FIGARO exports raw'!C33:Y33)+SUM('FIGARO exports raw'!C101:Y101) -> 292249.6 | N31: =K31+L31+M31 -> 1762442.2 | O31: =IF(D31=0,0,100*(N31-D31)/D31) -> 5.6739482e-05
A32: G47 | B32: Retail trade, except of motor vehicles and motorcycles | C32: G | D32: =SUM('Z total'!AF3:AF72) -> 1120894.3 | E32: =SUM('Z total'!AF3:AF66) -> 474326.2 | F32: =SUM('Z domestic'!AF67:AF72) -> 646568.1 | G32: ='Z domestic'!AF68 -> 388581.7 | H32: ='Z domestic'!AF67 -> 220766.7 | I32: ='Z domestic'!AF69+'Z domestic'!AF70 -> 37219.7 | J32: =IF(D32=0,0,F32/D32) -> 0.57683236 | K32: =SUM('Z domestic'!C32:BN32) -> 285475.8 | L32: =SUM('Z domestic'!BO32:BS32) -> 783414.7 | M32: =SUM('FIGARO exports raw'!C34:Y34)+SUM('FIGARO exports raw'!C102:Y102) -> 52006.2 | N32: =K32+L32+M32 -> 1120896.7 | O32: =IF(D32=0,0,100*(N32-D32)/D32) -> 0.00021411475
A33: H49 | B33: Land transport and transport via pipelines | C33: H | D33: =SUM('Z total'!AG3:AG72) -> 772155.4 | E33: =SUM('Z total'!AG3:AG66) -> 438948.7 | F33: =SUM('Z domestic'!AG67:AG72) -> 333206.7 | G33: ='Z domestic'!AG68 -> 198638.5 | H33: ='Z domestic'!AG67 -> 113506.3 | I33: ='Z domestic'!AG69+'Z domestic'!AG70 -> 21061.9 | J33: =IF(D33=0,0,F33/D33) -> 0.43152803 | K33: =SUM('Z domestic'!C33:BN33) -> 499948.6 | L33: =SUM('Z domestic'!BO33:BS33) -> 181732.5 | M33: =SUM('FIGARO exports raw'!C35:Y35)+SUM('FIGARO exports raw'!C103:Y103) -> 90476.8 | N33: =K33+L33+M33 -> 772157.9 | O33: =IF(D33=0,0,100*(N33-D33)/D33) -> 0.00032376902
A34: H50 | B34: Water transport | C34: H | D34: =SUM('Z total'!AH3:AH72) -> 233049.9 | E34: =SUM('Z total'!AH3:AH66) -> 157351.3 | F34: =SUM('Z domestic'!AH67:AH72) -> 75698.6 | G34: ='Z domestic'!AH68 -> 13497.9 | H34: ='Z domestic'!AH67 -> 59586.5 | I34: ='Z domestic'!AH69+'Z domestic'!AH70 -> 2614.2 | J34: =IF(D34=0,0,F34/D34) -> 0.32481713 | K34: =SUM('Z domestic'!C34:BN34) -> 68262.6 | L34: =SUM('Z domestic'!BO34:BS34) -> 18075.9 | M34: =SUM('FIGARO exports raw'!C36:Y36)+SUM('FIGARO exports raw'!C104:Y104) -> 146714.8 | N34: =K34+L34+M34 -> 233053.3 | O34: =IF(D34=0,0,100*(N34-D34)/D34) -> 0.001458915
A35: H51 | B35: Air transport | C35: H | D35: =SUM('Z total'!AI3:AI72) -> 158054.5 | E35: =SUM('Z total'!AI3:AI66) -> 120519.2 | F35: =SUM('Z domestic'!AI67:AI72) -> 37535.3 | G35: ='Z domestic'!AI68 -> 20724.1 | H35: ='Z domestic'!AI67 -> 11937.6 | I35: ='Z domestic'!AI69+'Z domestic'!AI70 -> 4873.6 | J35: =IF(D35=0,0,F35/D35) -> 0.23748327 | K35: =SUM('Z domestic'!C35:BN35) -> 63872.9 | L35: =SUM('Z domestic'!BO35:BS35) -> 37607.2 | M35: =SUM('FIGARO exports raw'!C37:Y37)+SUM('FIGARO exports raw'!C105:Y105) -> 56577.4 | N35: =K35+L35+M35 -> 158057.5 | O35: =IF(D35=0,0,100*(N35-D35)/D35) -> 0.0018980795
A36: H52 | B36: Warehousing and support activities for transportation | C36: H | D36: =SUM('Z total'!AJ3:AJ72) -> 718849.6 | E36: =SUM('Z total'!AJ3:AJ66) -> 435604.8 | F36: =SUM('Z domestic'!AJ67:AJ72) -> 283244.8 | G36: ='Z domestic'!AJ68 -> 146271 | H36: ='Z domestic'!AJ67 -> 123878.1 | I36: ='Z domestic'!AJ69+'Z domestic'!AJ70 -> 13095.7 | J36: =IF(D36=0,0,F36/D36) -> 0.39402512 | K36: =SUM('Z domestic'!C36:BN36) -> 538062.4 | L36: =SUM('Z domestic'!BO36:BS36) -> 112296.4 | M36: =SUM('FIGARO exports raw'!C38:Y38)+SUM('FIGARO exports raw'!C106:Y106) -> 68493 | N36: =K36+L36+M36 -> 718851.8 | O36: =IF(D36=0,0,100*(N36-D36)/D36) -> 0.00030604455
A37: H53 | B37: Postal and courier activities | C37: H | D37: =SUM('Z total'!AK3:AK72) -> 144461.5 | E37: =SUM('Z total'!AK3:AK66) -> 84940.1 | F37: =SUM('Z domestic'!AK67:AK72) -> 59521.4 | G37: ='Z domestic'!AK68 -> 47483.1 | H37: ='Z domestic'!AK67 -> 8280.7 | I37: ='Z domestic'!AK69+'Z domestic'!AK70 -> 3757.6 | J37: =IF(D37=0,0,F37/D37) -> 0.41202258 | K37: =SUM('Z domestic'!C37:BN37) -> 117864.7 | L37: =SUM('Z domestic'!BO37:BS37) -> 10994.5 | M37: =SUM('FIGARO exports raw'!C39:Y39)+SUM('FIGARO exports raw'!C107:Y107) -> 15603.9 | N37: =K37+L37+M37 -> 144463.1 | O37: =IF(D37=0,0,100*(N37-D37)/D37) -> 0.0011075615
A38: I | B38: Accommodation and food service activities | C38: I | D38: =SUM('Z total'!AL3:AL72) -> 887630.1 | E38: =SUM('Z total'!AL3:AL66) -> 454090.5 | F38: =SUM('Z domestic'!AL67:AL72) -> 433539.6 | G38: ='Z domestic'!AL68 -> 237266.2 | H38: ='Z domestic'!AL67 -> 178636.3 | I38: ='Z domestic'!AL69+'Z domestic'!AL70 -> 17637.1 | J38: =IF(D38=0,0,F38/D38) -> 0.48842373 | K38: =SUM('Z domestic'!C38:BN38) -> 190230.5 | L38: =SUM('Z domestic'!BO38:BS38) -> 690002.8 | M38: =SUM('FIGARO exports raw'!C40:Y40)+SUM('FIGARO exports raw'!C108:Y108) -> 7397.1 | N38: =K38+L38+M38 -> 887630.4 | O38: =IF(D38=0,0,100*(N38-D38)/D38) -> 3.3797862e-05
A39: J58 | B39: Publishing activities | C39: J | D39: =SUM('Z total'!AM3:AM72) -> 221296.2 | E39: =SUM('Z total'!AM3:AM66) -> 113680.5 | F39: =SUM('Z domestic'!AM67:AM72) -> 107615.7 | G39: ='Z domestic'!AM68 -> 41434.8 | H39: ='Z domestic'!AM67 -> 64425.8 | I39: ='Z domestic'!AM69+'Z domestic'!AM70 -> 1755.1 | J39: =IF(D39=0,0,F39/D39) -> 0.4862971 | K39: =SUM('Z domestic'!C39:BN39) -> 81317.7 | L39: =SUM('Z domestic'!BO39:BS39) -> 64189.7 | M39: =SUM('FIGARO exports raw'!C41:Y41)+SUM('FIGARO exports raw'!C109:Y109) -> 75790.9 | N39: =K39+L39+M39 -> 221298.3 | O39: =IF(D39=0,0,100*(N39-D39)/D39) -> 0.00094895439
A40: J59_60 | B40: Motion picture, video, television programme production | C40: J | D40: =SUM('Z total'!AN3:AN72) -> 172578.4 | E40: =SUM('Z total'!AN3:AN66) -> 104188 | F40: =SUM('Z domestic'!AN67:AN72) -> 68390.4 | G40: ='Z domestic'!AN68 -> 36394.6 | H40: ='Z domestic'!AN67 -> 31726.2 | I40: ='Z domestic'!AN69+'Z domestic'!AN70 -> 269.6 | J40: =IF(D40=0,0,F40/D40) -> 0.39628598 | K40: =SUM('Z domestic'!C40:BN40) -> 90153.8 | L40: =SUM('Z domestic'!BO40:BS40) -> 69162.8 | M40: =SUM('FIGARO exports raw'!C42:Y42)+SUM('FIGARO exports raw'!C110:Y110) -> 13264.6 | N40: =K40+L40+M40 -> 172581.2 | O40: =IF(D40=0,0,100*(N40-D40)/D40) -> 0.001622451
A41: J61 | B41: Telecommunications | C41: J | D41: =SUM('Z total'!AO3:AO72) -> 344352.8 | E41: =SUM('Z total'!AO3:AO66) -> 207040.6 | F41: =SUM('Z domestic'!AO67:AO72) -> 137312.2 | G41: ='Z domestic'!AO68 -> 46778.1 | H41: ='Z domestic'!AO67 -> 86386.5 | I41: ='Z domestic'!AO69+'Z domestic'!AO70 -> 4147.6 | J41: =IF(D41=0,0,F41/D41) -> 0.39875442 | K41: =SUM('Z domestic'!C41:BN41) -> 189742.5 | L41: =SUM('Z domestic'!BO41:BS41) -> 135689.1 | M41: =SUM('FIGARO exports raw'!C43:Y43)+SUM('FIGARO exports raw'!C111:Y111) -> 18924.1 | N41: =K41+L41+M41 -> 344355.7 | O41: =IF(D41=0,0,100*(N41-D41)/D41) -> 0.00084215955
A42: J62_63 | B42: Computer programming, consultancy, and information service activities | C42: J | D42: =SUM('Z total'!AP3:AP72) -> 1102310.4 | E42: =SUM('Z total'!AP3:AP66) -> 584342.9 | F42: =SUM('Z domestic'!AP67:AP72) -> 517967.5 | G42: ='Z domestic'!AP68 -> 326346.8 | H42: ='Z domestic'!AP67 -> 181778.8 | I42: ='Z domestic'!AP69+'Z domestic'!AP70 -> 9841.9 | J42: =IF(D42=0,0,F42/D42) -> 0.4698926 | K42: =SUM('Z domestic'!C42:BN42) -> 610947.7 | L42: =SUM('Z domestic'!BO42:BS42) -> 298455.8 | M42: =SUM('FIGARO exports raw'!C44:Y44)+SUM('FIGARO exports raw'!C112:Y112) -> 192909 | N42: =K42+L42+M42 -> 1102312.5 | O42: =IF(D42=0,0,100*(N42-D42)/D42) -> 0.00019050895
A43: K64 | B43: Financial service activities, except insurance and pension funding | C43: K | D43: =SUM('Z total'!AQ3:AQ72) -> 834445.7 | E43: =SUM('Z total'!AQ3:AQ66) -> 369420.1 | F43: =SUM('Z domestic'!AQ67:AQ72) -> 465025.6 | G43: ='Z domestic'!AQ68 -> 202559.6 | H43: ='Z domestic'!AQ67 -> 207063.7 | I43: ='Z domestic'!AQ69+'Z domestic'!AQ70 -> 55402.3 | J43: =IF(D43=0,0,F43/D43) -> 0.55728683 | K43: =SUM('Z domestic'!C43:BN43) -> 556009.9 | L43: =SUM('Z domestic'!BO43:BS43) -> 181816.6 | M43: =SUM('FIGARO exports raw'!C45:Y45)+SUM('FIGARO exports raw'!C113:Y113) -> 96621 | N43: =K43+L43+M43 -> 834447.5 | O43: =IF(D43=0,0,100*(N43-D43)/D43) -> 0.00021571206
A44: K65 | B44: Insurance, reinsurance and pension funding, except compulsory social … | C44: K | D44: =SUM('Z total'!AR3:AR72) -> 401186.1 | E44: =SUM('Z total'!AR3:AR66) -> 249794.6 | F44: =SUM('Z domestic'!AR67:AR72) -> 151391.5 | G44: ='Z domestic'!AR68 -> 52745.7 | H44: ='Z domestic'!AR67 -> 77592.6 | I44: ='Z domestic'!AR69+'Z domestic'!AR70 -> 21053.2 | J44: =IF(D44=0,0,F44/D44) -> 0.37735978 | K44: =SUM('Z domestic'!C44:BN44) -> 134929.8 | L44: =SUM('Z domestic'!BO44:BS44) -> 229409.1 | M44: =SUM('FIGARO exports raw'!C46:Y46)+SUM('FIGARO exports raw'!C114:Y114) -> 36852.2 | N44: =K44+L44+M44 -> 401191.1 | O44: =IF(D44=0,0,100*(N44-D44)/D44) -> 0.0012463044
A45: K66 | B45: Activities auxiliary to financial services and insurance activities | C45: K | D45: =SUM('Z total'!AS3:AS72) -> 311317 | E45: =SUM('Z total'!AS3:AS66) -> 171183.5 | F45: =SUM('Z domestic'!AS67:AS72) -> 140133.5 | G45: ='Z domestic'!AS68 -> 75668.7 | H45: ='Z domestic'!AS67 -> 50830.9 | I45: ='Z domestic'!AS69+'Z domestic'!AS70 -> 13633.9 | J45: =IF(D45=0,0,F45/D45) -> 0.45013122 | K45: =SUM('Z domestic'!C45:BN45) -> 264405.7 | L45: =SUM('Z domestic'!BO45:BS45) -> 26570.1 | M45: =SUM('FIGARO exports raw'!C47:Y47)+SUM('FIGARO exports raw'!C115:Y115) -> 20344.5 | N45: =K45+L45+M45 -> 311320.3 | O45: =IF(D45=0,0,100*(N45-D45)/D45) -> 0.0010600128
A46: L | B46: Real estate activities | C46: L | D46: =SUM('Z total'!AT3:AT72) -> 2108661.6 | E46: =SUM('Z total'!AT3:AT66) -> 409097.3 | F46: =SUM('Z domestic'!AT67:AT72) -> 1699564.3 | G46: ='Z domestic'!AT68 -> 84237 | H46: ='Z domestic'!AT67 -> 1495163.6 | I46: ='Z domestic'!AT69+'Z domestic'!AT70 -> 120163.7 | J46: =IF(D46=0,0,F46/D46) -> 0.80599196 | K46: =SUM('Z domestic'!C46:BN46) -> 584277.7 | L46: =SUM('Z domestic'!BO46:BS46) -> 1519413.6 | M46: =SUM('FIGARO exports raw'!C48:Y48)+SUM('FIGARO exports raw'!C116:Y116) -> 4973 | N46: =K46+L46+M46 -> 2108664.3 | O46: =IF(D46=0,0,100*(N46-D46)/D46) -> 0.0001280433
A47: M69_70 | B47: Legal and accounting activities | C47: M | D47: =SUM('Z total'!AU3:AU72) -> 1133952.2 | E47: =SUM('Z total'!AU3:AU66) -> 567754.8 | F47: =SUM('Z domestic'!AU67:AU72) -> 566197.4 | G47: ='Z domestic'!AU68 -> 339931.2 | H47: ='Z domestic'!AU67 -> 210975.3 | I47: ='Z domestic'!AU69+'Z domestic'!AU70 -> 15290.9 | J47: =IF(D47=0,0,F47/D47) -> 0.49931329 | K47: =SUM('Z domestic'!C47:BN47) -> 944038.6 | L47: =SUM('Z domestic'!BO47:BS47) -> 86348 | M47: =SUM('FIGARO exports raw'!C49:Y49)+SUM('FIGARO exports raw'!C117:Y117) -> 103566.6 | N47: =K47+L47+M47 -> 1133953.2 | O47: =IF(D47=0,0,100*(N47-D47)/D47) -> 8.8187139e-05
A48: M71 | B48: Architectural and engineering activities | C48: M | D48: =SUM('Z total'!AV3:AV72) -> 448418.2 | E48: =SUM('Z total'!AV3:AV66) -> 219118.8 | F48: =SUM('Z domestic'!AV67:AV72) -> 229299.4 | G48: ='Z domestic'!AV68 -> 140991.6 | H48: ='Z domestic'!AV67 -> 83826.4 | I48: ='Z domestic'!AV69+'Z domestic'!AV70 -> 4481.4 | J48: =IF(D48=0,0,F48/D48) -> 0.51135168 | K48: =SUM('Z domestic'!C48:BN48) -> 299321.2 | L48: =SUM('Z domestic'!BO48:BS48) -> 117489 | M48: =SUM('FIGARO exports raw'!C50:Y50)+SUM('FIGARO exports raw'!C118:Y118) -> 31612 | N48: =K48+L48+M48 -> 448422.2 | O48: =IF(D48=0,0,100*(N48-D48)/D48) -> 0.00089202445
A49: M72 | B49: Scientific research and development | C49: M | D49: =SUM('Z total'!AW3:AW72) -> 245570.9 | E49: =SUM('Z total'!AW3:AW66) -> 84179.5 | F49: =SUM('Z domestic'!AW67:AW72) -> 161391.4 | G49: ='Z domestic'!AW68 -> 80574.1 | H49: ='Z domestic'!AW67 -> 81112.1 | I49: ='Z domestic'!AW69+'Z domestic'!AW70 -> -294.8 | J49: =IF(D49=0,0,F49/D49) -> 0.65720898 | K49: =SUM('Z domestic'!C49:BN49) -> 42695.1 | L49: =SUM('Z domestic'!BO49:BS49) -> 180853.1 | M49: =SUM('FIGARO exports raw'!C51:Y51)+SUM('FIGARO exports raw'!C119:Y119) -> 22025.5 | N49: =K49+L49+M49 -> 245573.7 | O49: =IF(D49=0,0,100*(N49-D49)/D49) -> 0.0011402002
A50: M73 | B50: Advertising and market research | C50: M | D50: =SUM('Z total'!AX3:AX72) -> 172665.5 | E50: =SUM('Z total'!AX3:AX66) -> 106165 | F50: =SUM('Z domestic'!AX67:AX72) -> 66500.5 | G50: ='Z domestic'!AX68 -> 40093.7 | H50: ='Z domestic'!AX67 -> 25001.2 | I50: ='Z domestic'!AX69+'Z domestic'!AX70 -> 1405.6 | J50: =IF(D50=0,0,F50/D50) -> 0.38514063 | K50: =SUM('Z domestic'!C50:BN50) -> 147545 | L50: =SUM('Z domestic'!BO50:BS50) -> 3195.3 | M50: =SUM('FIGARO exports raw'!C52:Y52)+SUM('FIGARO exports raw'!C120:Y120) -> 21928.6 | N50: =K50+L50+M50 -> 172668.9 | O50: =IF(D50=0,0,100*(N50-D50)/D50) -> 0.0019691253
A51: M74_75 | B51: Other professional, scientific and technical activities | C51: M | D51: =SUM('Z total'!AY3:AY72) -> 162735.4 | E51: =SUM('Z total'!AY3:AY66) -> 79484.4 | F51: =SUM('Z domestic'!AY67:AY72) -> 83251 | G51: ='Z domestic'!AY68 -> 34556.9 | H51: ='Z domestic'!AY67 -> 47044.1 | I51: ='Z domestic'!AY69+'Z domestic'!AY70 -> 1650 | J51: =IF(D51=0,0,F51/D51) -> 0.51157277 | K51: =SUM('Z domestic'!C51:BN51) -> 126011.8 | L51: =SUM('Z domestic'!BO51:BS51) -> 27555.4 | M51: =SUM('FIGARO exports raw'!C53:Y53)+SUM('FIGARO exports raw'!C121:Y121) -> 9171.5 | N51: =K51+L51+M51 -> 162738.7 | O51: =IF(D51=0,0,100*(N51-D51)/D51) -> 0.0020278317
A52: N77 | B52: Rental and leasing activities | C52: N | D52: =SUM('Z total'!AZ3:AZ72) -> 368437.2 | E52: =SUM('Z total'!AZ3:AZ66) -> 171113.4 | F52: =SUM('Z domestic'!AZ67:AZ72) -> 197323.8 | G52: ='Z domestic'!AZ68 -> 33083.2 | H52: ='Z domestic'!AZ67 -> 159246.6 | I52: ='Z domestic'!AZ69+'Z domestic'!AZ70 -> 4994 | J52: =IF(D52=0,0,F52/D52) -> 0.5355697 | K52: =SUM('Z domestic'!C52:BN52) -> 293578.6 | L52: =SUM('Z domestic'!BO52:BS52) -> 37001.4 | M52: =SUM('FIGARO exports raw'!C54:Y54)+SUM('FIGARO exports raw'!C122:Y122) -> 37859.3 | N52: =K52+L52+M52 -> 368439.3 | O52: =IF(D52=0,0,100*(N52-D52)/D52) -> 0.00056997502
A53: N78 | B53: Employment activities | C53: N | D53: =SUM('Z total'!BA3:BA72) -> 232880.9 | E53: =SUM('Z total'!BA3:BA66) -> 54045 | F53: =SUM('Z domestic'!BA67:BA72) -> 178835.9 | G53: ='Z domestic'!BA68 -> 165308.9 | H53: ='Z domestic'!BA67 -> 11516.8 | I53: ='Z domestic'!BA69+'Z domestic'!BA70 -> 2010.2 | J53: =IF(D53=0,0,F53/D53) -> 0.76792858 | K53: =SUM('Z domestic'!C53:BN53) -> 220778.7 | L53: =SUM('Z domestic'!BO53:BS53) -> 7545.2 | M53: =SUM('FIGARO exports raw'!C55:Y55)+SUM('FIGARO exports raw'!C123:Y123) -> 4561.8 | N53: =K53+L53+M53 -> 232885.7 | O53: =IF(D53=0,0,100*(N53-D53)/D53) -> 0.0020611394
